Workbook

Sheet START HERE
A1: PCI AI — PROJECT CONTROLS INSTITUTE | EMPLOYEE EXECUTION TRACKER
A2: Read this page first. It takes 5 minutes and explains exactly how to use every tab.
A4: 1. HOW THIS WORKS — employees fill in ONE sheet
A5: EVERY DAY -> DAILY ENTRY tab | B5: This is the only sheet you must fill in. One row for each thing you did: the date, your name, which platform, what kind of work, how many, how long it took and a link that proves it. Six of the ten columns are dropdowns, so most of a row is clicking, not typing.
A6: Log as you go, not at 5pm | B6: Add the row when you finish the task. Ten rows a day is normal. If you did nothing on a platform, there is simply no row for it.
A7: ALSO, if you do LinkedIn outreach | B7: The LinkedIn Outreach tab holds one row per PERSON you contact - name, company, the message you sent, and what they replied. This cannot be collapsed into daily totals, because acceptance and reply rates need to be tracked per person.
A8: Everything else fills itself in | B8: Platform Progress, Who Did What, Team Scorecard, Weekly Review, Dashboard and Summary all calculate from what you enter. You never type a number twice. The Daily Summary tab is optional.
A9: BEFORE YOU START -> Platform Setup tab | B9: Work through the account list and follow the setup steps written in each row. Mark Status = Complete only when the profile is fully filled in with logo, bio, link and 2FA.
A10: BEFORE YOU WRITE -> Publishing Plan tab | B10: The ten publishing platforms, ranked, with the rule for each one. Read the rule before you publish anywhere.
A11: BEFORE YOU MESSAGE -> Message Bank tab | B11: Never write outreach from scratch. Copy the approved message and replace every [bracket] with real details from the person's profile.
A12: EVERY FRIDAY -> Weekly Review tab | B12: Write your wins, misses and next week's focus. The numbers are already there. Use the dropdown in cell B2 to see just your own week.
A13: REFERENCE -> How-To Guides, LinkedIn Playbook, Benchmarks | B13: Read these when you start a platform for the first time or when you want to know what good looks like.
A14: FOR THE MANAGER -> Dashboard, Team Scorecard, Platform Progress, Who Did What | B14: Four read-only pages. Nobody types in them.
A15: Master Tasks tab | B15: The full workstream list with an Owner column. Update Status and Progress when a task moves.
A17: 2. YOUR SETTINGS — fill in the yellow cells once
A18: Employee name
A19: Manager / reviewer
A20: Programme start date (a Monday) | B20: 2026-08-17
A21: Working days per week | B21: 5
A23: 3. DAILY TARGETS — agreed with your manager (blue = you may change with approval)
A24: Activity | B24: Target per day | C24: Target per week (auto)
A25: Sales Navigator leads researched | B25: 30 | C25: =B25*'START HERE'!$B$21 -> 150
A26: Connection requests sent | B26: 20 | C26: =B26*'START HERE'!$B$21 -> 100
A27: First messages sent (accepted connections) | B27: 15 | C27: =B27*'START HERE'!$B$21 -> 75
A28: Follow-up messages sent | B28: 10 | C28: =B28*'START HERE'!$B$21 -> 50
A29: Posts published (all platforms) | B29: 2 | C29: =B29*'START HERE'!$B$21 -> 10
A30: Community answers / comments (Quora, Reddit, Groups) | B30: 3 | C30: =B30*'START HERE'!$B$21 -> 15
A31: Partnership / PR contacts approached | B31: 5 | C31: =B31*'START HERE'!$B$21 -> 25
A32: Meaningful engagements (likes + comments on others) | B32: 15 | C32: =B32*'START HERE'!$B$21 -> 75
A34: 4. GOLDEN RULES — these protect PCI's reputation. Breaking them is a serious issue.
A35: 1. Be honest. Never tell anyone they have been awarded, approved or guaranteed an honorary certification. You are inviting them to be considered and sharing the criteria — nothing more.
A36: 2. Never invent facts about PCI — numbers of members, accreditations, recognition or partnerships. If you are unsure, ask your manager before you send.
A37: 3. Personalise every message. Read the profile first and reference something real (their role, employer, project type or years of experience).
A38: 4. Keep outreach messages under 300 characters and connection notes under 200 characters.
A39: 5. No bulk sending, no automation tools, no bots, no scraping. LinkedIn restricts accounts for this and it destroys reply rates.
A40: 6. Respect limits: stop at the daily target. If LinkedIn shows a warning, stop for the day and tell your manager.
A41: 7. If someone says no or asks you to stop, thank them politely and never contact them again. Mark Outcome = Declined.
A42: 8. Answer the question first, promote PCI second. On Quora, Reddit and groups a useful answer with no link beats a link with no value.
A43: 9. Never post PCI passwords in this file — only the reference name from the password manager. Turn on 2FA everywhere.
A44: 10. Log everything the same day. Evidence (a URL or screenshot link) is what makes the work count.
A46: 5. COLOUR LEGEND
A47: Yellow cell | B47: You type here.
A48: White cell | B48: Calculated or reference — do not type over it.
A49: Grey / blue header | B49: Structure — do not rename, the Dashboard depends on these names.
A50: Green | B50: Good / on target.
A51: Red | B51: Attention needed / over limit.
A53: 6. TEAM ROSTER — type each marketing team member's name here, exactly as they will type it in the log tabs
A54: Slot | B54: Employee name (this becomes the dropdown in every log tab)
A55: 1 | B55: Employee 1
A56: 2
A57: 3
A58: 4
A59: 5
A60: 6
A61: 7
A62: 8
A63: 9
A64: 10
A66: Names must match exactly between this list and the log tabs, otherwise the Team Scorecard will show zero for that person. Use the dropdown in the log tabs rather than typing names by hand.
A68: 7. BRAND / PRODUCT THIS PLAN COVERS
A69: Brand / product | B69: PCI - Project Controls Institute
A70: If the team runs both brands, add a Brand column to the log tabs or keep a separate copy of this file per brand - mixing two audiences in one outreach log makes the acceptance and reply rates meaningless, because they will be measuring two different markets.
A72: 8. WHERE EACH PART OF THE GROWTH PLAN LIVES
A73: Executive dashboard / management summary | B73: Dashboard, Summary
A74: Employee scorecard and grading | B74: Employee Score, Team Scorecard
A75: Master growth plan | B75: Master Tasks
A76: Daily execution | B76: DAILY ENTRY
A77: LinkedIn Sales Navigator + honorary certification pipeline | B77: LinkedIn Outreach, LinkedIn Playbook, Message Bank
A78: Enterprise / employer, university, association and influencer pipelines | B78: Partnership Pipeline
A79: Funnel and lead scoring | B79: LinkedIn Outreach (columns Y-AC), Partnership Pipeline, Dashboard section 7
A80: Social media, content factory, Medium / Quora / Reddit, YouTube | B80: Content Calendar, Publishing Plan, Platform Setup, Platform Progress
A81: SEO and content clusters | B81: SEO Clusters
A82: PR, media, podcasts, webinars and events | B82: Partnership Pipeline, Community & PR, Platform Setup
A83: Reviews and reputation | B83: Platform Setup (directory rows), QA & Compliance
A84: Platform accounts | B84: Platform Setup, Platform Progress
... A90: Lists and controls | B90: Lists, Benchmarks

Sheet DAILY ENTRY
A1: DAILY ENTRY — this is the only sheet you need to fill in
A2: One row for each thing you did, on each platform, each day. Six of the ten columns are dropdowns. Everything else in this workbook fills itself in from here.
A3: Date | B3: Your name | C3: Platform | D3: What kind of work | E3: What exactly did you do? | F3: How many | G3: Minutes spent | H3: Link / proof | I3: Result | J3: Notes or blocker
A4: 46251 | B4: Employee 1 | C4: LinkedIn Sales Navigator | D4: Lead researched (Sales Navigator) | E4: Built a list of project controls managers in the UK rail sector | F4: 30 | G4: 60 | H4: [Sales Nav list link] | I4: Done | J4: EXAMPLE ROW - delete these three before you start
A5: 46251 | B5: Employee 1 | C5: LinkedIn | D5: Connection request sent | E5: Sent connection requests with a personal line from each profile | F5: 20 | G5: 45 | H5: logged in LinkedIn Outreach tab | I5: Done | J5: EXAMPLE ROW
A6: 46251 | B6: Employee 1 | C6: Medium | D6: Post / content published | E6: Published the article on cost control mistakes, canonical set to our site | F6: 1 | G6: 90 | H6: [article URL] | I6: Done | J6: EXAMPLE ROW

Sheet LinkedIn Outreach
A1: LINKEDIN + SALES NAVIGATOR OUTREACH LOG — one row per person
A2: Log every lead the same day. Row 4 is a worked example - your data starts on row 5. Column Q counts your message characters and turns red above 300.
A3: Date | B3: Employee | C3: Lead name | D3: LinkedIn / Sales Nav URL | E3: Company | F3: Job title | G3: Country | H3: Lead segment | I3: Sales Nav list | J3: Years exp. | K3: Qualified? | L3: Personal line used (from their profile) | M3: Connection sent? | N3: Accepted? | O3: Template used | P3: Message sent (paste the final text) | Q3: Chars | R3: Message sent? | S3: Outcome | T3: Reply summary | U3: Follow-up due | V3: Follow-ups sent | W3: Next action | X3: Notes | Y3: ICP fit (1-5) | Z3: Intent signals (1-5) | AA3: Lead score (auto) | AB3: Priority band | AC3: Funnel stage (auto)
A4: 46251 | B4: [Your name] | C4: A. Sample (example row - delete) | D4: https://www.linkedin.com/in/example | E4: Example Engineering Ltd | F4: Project Controls Manager | G4: United Kingdom | H4: Project Controls Lead | I4: PC Managers - UK | J4: 14 | K4: =IF(J4="","",IF(J4>=8,"Yes","Check")) -> Yes | L4: Led cost control on the [X] rail upgrade - mentioned it in her post last week | M4: Yes | N4: Yes | O4: M2 First Message | P4: Thanks for connecting, Anna. PCI recognises senior project controls practitioners through an honorary certification, assessed on experience and contribution rather than an exam. With 14 years at Example Engineering you may qualify. May I send you the criteria? No cost to review. - Sam | Q4: =IF(P4="","",LEN(P4)) -> 285 | R4: Yes | S4: Info Requested | T4: Asked for the criteria document and fee position | U4: =IF(OR(R4<>"Yes",A4=""),"",A4+4) -> 46255 | V4: 0 | W4: Send criteria pack, then diarise day 4 follow-up | X4: EXAMPLE ROW - shows the level of detail expected. Delete before use. | AA4: =IF(AND($Y4="",$Z4=""),"",ROUND(IFERROR(VALUE(LEFT($Y4,1)),0)*12+IFERROR(VALUE(LEFT($Z4,1)),0)*8,0)) | AB4: =IF($AA4="","",IF($AA4>=80,"A - call first",IF($AA4>=60,"B - worth pursuing",IF($AA4>=40,"C - nurture","D - do not spend time here")))) | AC4: =IF($C4="","",IF($S4="Converted","7 Certification / Enterprise opportunity",IF($S4="Application Started","7 Certification / Enterprise opportunity",IF($S4="Meeting Booked","6 Meeting / Application",IF(OR($S4="Interested",$S4="Info Requested"),"5 Interested",IF(OR($S4="Declined",$S4="Not Relevant"),"0 Closed - no",IF($R4="Yes","4 Contacted",IF($N4="Yes","2 Engaged",IF($M4="Yes","1 Awareness",IF($AA4>=60,"3 Qualified","1 Awareness")))))))))) -> 5 Interested
K5: =IF(J5="","",IF(J5>=8,"Yes","Check")) | Q5: =IF(P5="","",LEN(P5)) | U5: =IF(OR(R5<>"Yes",A5=""),"",A5+4) | AA5: =IF(AND($Y5="",$Z5=""),"",ROUND(IFERROR(VALUE(LEFT($Y5,1)),0)*12+IFERROR(VALUE(LEFT($Z5,1)),0)*8,0)) | AB5: =IF($AA5="","",IF($AA5>=80,"A - call first",IF($AA5>=60,"B - worth pursuing",IF($AA5>=40,"C - nurture","D - do not spend time here")))) | AC5: =IF($C5="","",IF($S5="Converted","7 Certification / Enterprise opportunity",IF($S5="Application Started","7 Certification / Enterprise opportunity",IF($S5="Meeting Booked","6 Meeting / Application",IF(OR($S5="Interested",$S5="Info Requested"),"5 Interested",IF(OR($S5="Declined",$S5="Not Relevant"),"0 Closed - no",IF($R5="Yes","4 Contacted",IF($N5="Yes","2 Engaged",IF($M5="Yes","1 Awareness",IF($AA5>=60,"3 Qualified","1 Awareness"))))))))))
K6: =IF(J6="","",IF(J6>=8,"Yes","Check")) | Q6: =IF(P6="","",LEN(P6)) | U6: =IF(OR(R6<>"Yes",A6=""),"",A6+4) | AA6: =IF(AND($Y6="",$Z6=""),"",ROUND(IFERROR(VALUE(LEFT($Y6,1)),0)*12+IFERROR(VALUE(LEFT($Z6,1)),0)*8,0)) | AB6: =IF($AA6="","",IF($AA6>=80,"A - call first",IF($AA6>=60,"B - worth pursuing",IF($AA6>=40,"C - nurture","D - do not spend time here")))) | AC6: =IF($C6="","",IF($S6="Converted","7 Certification / Enterprise opportunity",IF($S6="Application Started","7 Certification / Enterprise opportunity",IF($S6="Meeting Booked","6 Meeting / Application",IF(OR($S6="Interested",$S6="Info Requested"),"5 Interested",IF(OR($S6="Declined",$S6="Not Relevant"),"0 Closed - no",IF($R6="Yes","4 Contacted",IF($N6="Yes","2 Engaged",IF($M6="Yes","1 Awareness",IF($AA6>=60,"3 Qualified","1 Awareness"))))))))))
K7: =IF(J7="","",IF(J7>=8,"Yes","Check")) | Q7: =IF(P7="","",LEN(P7)) | U7: =IF(OR(R7<>"Yes",A7=""),"",A7+4) | AA7: =IF(AND($Y7="",$Z7=""),"",ROUND(IFERROR(VALUE(LEFT($Y7,1)),0)*12+IFERROR(VALUE(LEFT($Z7,1)),0)*8,0)) | AB7: =IF($AA7="","",IF($AA7>=80,"A - call first",IF($AA7>=60,"B - worth pursuing",IF($AA7>=40,"C - nurture","D - do not spend time here")))) | AC7: =IF($C7="","",IF($S7="Converted","7 Certification / Enterprise opportunity",IF($S7="Application Started","7 Certification / Enterprise opportunity",IF($S7="Meeting Booked","6 Meeting / Application",IF(OR($S7="Interested",$S7="Info Requested"),"5 Interested",IF(OR($S7="Declined",$S7="Not Relevant"),"0 Closed - no",IF($R7="Yes","4 Contacted",IF($N7="Yes","2 Engaged",IF($M7="Yes","1 Awareness",IF($AA7>=60,"3 Qualified","1 Awareness"))))))))))
K8: =IF(J8="","",IF(J8>=8,"Yes","Check")) | Q8: =IF(P8="","",LEN(P8)) | U8: =IF(OR(R8<>"Yes",A8=""),"",A8+4) | AA8: =IF(AND($Y8="",$Z8=""),"",ROUND(IFERROR(VALUE(LEFT($Y8,1)),0)*12+IFERROR(VALUE(LEFT($Z8,1)),0)*8,0)) | AB8: =IF($AA8="","",IF($AA8>=80,"A - call first",IF($AA8>=60,"B - worth pursuing",IF($AA8>=40,"C - nurture","D - do not spend time here")))) | AC8: =IF($C8="","",IF($S8="Converted","7 Certification / Enterprise opportunity",IF($S8="Application Started","7 Certification / Enterprise opportunity",IF($S8="Meeting Booked","6 Meeting / Application",IF(OR($S8="Interested",$S8="Info Requested"),"5 Interested",IF(OR($S8="Declined",$S8="Not Relevant"),"0 Closed - no",IF($R8="Yes","4 Contacted",IF($N8="Yes","2 Engaged",IF($M8="Yes","1 Awareness",IF($AA8>=60,"3 Qualified","1 Awareness"))))))))))
K9: =IF(J9="","",IF(J9>=8,"Yes","Check")) | Q9: =IF(P9="","",LEN(P9)) | U9: =IF(OR(R9<>"Yes",A9=""),"",A9+4) | AA9: =IF(AND($Y9="",$Z9=""),"",ROUND(IFERROR(VALUE(LEFT($Y9,1)),0)*12+IFERROR(VALUE(LEFT($Z9,1)),0)*8,0)) | AB9: =IF($AA9="","",IF($AA9>=80,"A - call first",IF($AA9>=60,"B - worth pursuing",IF($AA9>=40,"C - nurture","D - do not spend time here")))) | AC9: =IF($C9="","",IF($S9="Converted","7 Certification / Enterprise opportunity",IF($S9="Application Started","7 Certification / Enterprise opportunity",IF($S9="Meeting Booked","6 Meeting / Application",IF(OR($S9="Interested",$S9="Info Requested"),"5 Interested",IF(OR($S9="Declined",$S9="Not Relevant"),"0 Closed - no",IF($R9="Yes","4 Contacted",IF($N9="Yes","2 Engaged",IF($M9="Yes","1 Awareness",IF($AA9>=60,"3 Qualified","1 Awareness"))))))))))
K10: =IF(J10="","",IF(J10>=8,"Yes","Check")) | Q10: =IF(P10="","",LEN(P10)) | U10: =IF(OR(R10<>"Yes",A10=""),"",A10+4) | AA10: =IF(AND($Y10="",$Z10=""),"",ROUND(IFERROR(VALUE(LEFT($Y10,1)),0)*12+IFERROR(VALUE(LEFT($Z10,1)),0)*8,0)) | AB10: =IF($AA10="","",IF($AA10>=80,"A - call first",IF($AA10>=60,"B - worth pursuing",IF($AA10>=40,"C - nurture","D - do not spend time here")))) | AC10: =IF($C10="","",IF($S10="Converted","7 Certification / Enterprise opportunity",IF($S10="Application Started","7 Certification / Enterprise opportunity",IF($S10="Meeting Booked","6 Meeting / Application",IF(OR($S10="Interested",$S10="Info Requested"),"5 Interested",IF(OR($S10="Declined",$S10="Not Relevant"),"0 Closed - no",IF($R10="Yes","4 Contacted",IF($N10="Yes","2 Engaged",IF($M10="Yes","1 Awareness",IF($AA10>=60,"3 Qualified","1 Awareness"))))))))))
K11: =IF(J11="","",IF(J11>=8,"Yes","Check")) | Q11: =IF(P11="","",LEN(P11)) | U11: =IF(OR(R11<>"Yes",A11=""),"",A11+4) | AA11: =IF(AND($Y11="",$Z11=""),"",ROUND(IFERROR(VALUE(LEFT($Y11,1)),0)*12+IFERROR(VALUE(LEFT($Z11,1)),0)*8,0)) | AB11: =IF($AA11="","",IF($AA11>=80,"A - call first",IF($AA11>=60,"B - worth pursuing",IF($AA11>=40,"C - nurture","D - do not spend time here")))) | AC11: =IF($C11="","",IF($S11="Converted","7 Certification / Enterprise opportunity",IF($S11="Application Started","7 Certification / Enterprise opportunity",IF($S11="Meeting Booked","6 Meeting / Application",IF(OR($S11="Interested",$S11="Info Requested"),"5 Interested",IF(OR($S11="Declined",$S11="Not Relevant"),"0 Closed - no",IF($R11="Yes","4 Contacted",IF($N11="Yes","2 Engaged",IF($M11="Yes","1 Awareness",IF($AA11>=60,"3 Qualified","1 Awareness"))))))))))
K12: =IF(J12="","",IF(J12>=8,"Yes","Check")) | Q12: =IF(P12="","",LEN(P12)) | U12: =IF(OR(R12<>"Yes",A12=""),"",A12+4) | AA12: =IF(AND($Y12="",$Z12=""),"",ROUND(IFERROR(VALUE(LEFT($Y12,1)),0)*12+IFERROR(VALUE(LEFT($Z12,1)),0)*8,0)) | AB12: =IF($AA12="","",IF($AA12>=80,"A - call first",IF($AA12>=60,"B - worth pursuing",IF($AA12>=40,"C - nurture","D - do not spend time here")))) | AC12: =IF($C12="","",IF($S12="Converted","7 Certification / Enterprise opportunity",IF($S12="Application Started","7 Certification / Enterprise opportunity",IF($S12="Meeting Booked","6 Meeting / Application",IF(OR($S12="Interested",$S12="Info Requested"),"5 Interested",IF(OR($S12="Declined",$S12="Not Relevant"),"0 Closed - no",IF($R12="Yes","4 Contacted",IF($N12="Yes","2 Engaged",IF($M12="Yes","1 Awareness",IF($AA12>=60,"3 Qualified","1 Awareness"))))))))))
K13: =IF(J13="","",IF(J13>=8,"Yes","Check")) | Q13: =IF(P13="","",LEN(P13)) | U13: =IF(OR(R13<>"Yes",A13=""),"",A13+4) | AA13: =IF(AND($Y13="",$Z13=""),"",ROUND(IFERROR(VALUE(LEFT($Y13,1)),0)*12+IFERROR(VALUE(LEFT($Z13,1)),0)*8,0)) | AB13: =IF($AA13="","",IF($AA13>=80,"A - call first",IF($AA13>=60,"B - worth pursuing",IF($AA13>=40,"C - nurture","D - do not spend time here")))) | AC13: =IF($C13="","",IF($S13="Converted","7 Certification / Enterprise opportunity",IF($S13="Application Started","7 Certification / Enterprise opportunity",IF($S13="Meeting Booked","6 Meeting / Application",IF(OR($S13="Interested",$S13="Info Requested"),"5 Interested",IF(OR($S13="Declined",$S13="Not Relevant"),"0 Closed - no",IF($R13="Yes","4 Contacted",IF($N13="Yes","2 Engaged",IF($M13="Yes","1 Awareness",IF($AA13>=60,"3 Qualified","1 Awareness"))))))))))
K14: =IF(J14="","",IF(J14>=8,"Yes","Check")) | Q14: =IF(P14="","",LEN(P14)) | U14: =IF(OR(R14<>"Yes",A14=""),"",A14+4) | AA14: =IF(AND($Y14="",$Z14=""),"",ROUND(IFERROR(VALUE(LEFT($Y14,1)),0)*12+IFERROR(VALUE(LEFT($Z14,1)),0)*8,0)) | AB14: =IF($AA14="","",IF($AA14>=80,"A - call first",IF($AA14>=60,"B - worth pursuing",IF($AA14>=40,"C - nurture","D - do not spend time here")))) | AC14: =IF($C14="","",IF($S14="Converted","7 Certification / Enterprise opportunity",IF($S14="Application Started","7 Certification / Enterprise opportunity",IF($S14="Meeting Booked","6 Meeting / Application",IF(OR($S14="Interested",$S14="Info Requested"),"5 Interested",IF(OR($S14="Declined",$S14="Not Relevant"),"0 Closed - no",IF($R14="Yes","4 Contacted",IF($N14="Yes","2 Engaged",IF($M14="Yes","1 Awareness",IF($AA14>=60,"3 Qualified","1 Awareness"))))))))))
K15: =IF(J15="","",IF(J15>=8,"Yes","Check")) | Q15: =IF(P15="","",LEN(P15)) | U15: =IF(OR(R15<>"Yes",A15=""),"",A15+4) | AA15: =IF(AND($Y15="",$Z15=""),"",ROUND(IFERROR(VALUE(LEFT($Y15,1)),0)*12+IFERROR(VALUE(LEFT($Z15,1)),0)*8,0)) | AB15: =IF($AA15="","",IF($AA15>=80,"A - call first",IF($AA15>=60,"B - worth pursuing",IF($AA15>=40,"C - nurture","D - do not spend time here")))) | AC15: =IF($C15="","",IF($S15="Converted","7 Certification / Enterprise opportunity",IF($S15="Application Started","7 Certification / Enterprise opportunity",IF($S15="Meeting Booked","6 Meeting / Application",IF(OR($S15="Interested",$S15="Info Requested"),"5 Interested",IF(OR($S15="Declined",$S15="Not Relevant"),"0 Closed - no",IF($R15="Yes","4 Contacted",IF($N15="Yes","2 Engaged",IF($M15="Yes","1 Awareness",IF($AA15>=60,"3 Qualified","1 Awareness"))))))))))
K16: =IF(J16="","",IF(J16>=8,"Yes","Check")) | Q16: =IF(P16="","",LEN(P16)) | U16: =IF(OR(R16<>"Yes",A16=""),"",A16+4) | AA16: =IF(AND($Y16="",$Z16=""),"",ROUND(IFERROR(VALUE(LEFT($Y16,1)),0)*12+IFERROR(VALUE(LEFT($Z16,1)),0)*8,0)) | AB16: =IF($AA16="","",IF($AA16>=80,"A - call first",IF($AA16>=60,"B - worth pursuing",IF($AA16>=40,"C - nurture","D - do not spend time here")))) | AC16: =IF($C16="","",IF($S16="Converted","7 Certification / Enterprise opportunity",IF($S16="Application Started","7 Certification / Enterprise opportunity",IF($S16="Meeting Booked","6 Meeting / Application",IF(OR($S16="Interested",$S16="Info Requested"),"5 Interested",IF(OR($S16="Declined",$S16="Not Relevant"),"0 Closed - no",IF($R16="Yes","4 Contacted",IF($N16="Yes","2 Engaged",IF($M16="Yes","1 Awareness",IF($AA16>=60,"3 Qualified","1 Awareness"))))))))))
... K1203: =IF(J1203="","",IF(J1203>=8,"Yes","Check")) | Q1203: =IF(P1203="","",LEN(P1203)) | U1203: =IF(OR(R1203<>"Yes",A1203=""),"",A1203+4) | AA1203: =IF(AND($Y1203="",$Z1203=""),"",ROUND(IFERROR(VALUE(LEFT($Y1203,1)),0)*12+IFERROR(VALUE(LEFT($Z1203,1)),0)*8,0)) | AB1203: =IF($AA1203="","",IF($AA1203>=80,"A - call first",IF($AA1203>=60,"B - worth pursuing",IF($AA1203>=40,"C - nurture","D - do not spend time here")))) | AC1203: =IF($C1203="","",IF($S1203="Converted","7 Certification / Enterprise opportunity",IF($S1203="Application Started","7 Certification / Enterprise opportunity",IF($S1203="Meeting Booked","6 Meeting / Application",IF(OR($S1203="Interested",$S1203="Info Requested"),"5 Interested",IF(OR($S1203="Declined",$S1203="Not Relevant"),"0 Closed - no",IF($R1203="Yes","4 Contacted",IF($N1203="Yes","2 Engaged",IF($M1203="Yes","1 Awareness",IF($AA1203>=60,"3 Qualified","1 Awareness"))))))))))

Sheet Partnership Pipeline
A1: PARTNERSHIP PIPELINE — employers, universities, associations, influencers, media
A2: One row per organisation. A single association or employer partnership is worth hundreds of individual messages, so these get scored and staged like deals.
A3: Date opened | B3: Owner | C3: Organisation | D3: Type | E3: Country | F3: Contact name | G3: Contact role | H3: LinkedIn / URL | I3: Why them (the fit) | J3: ICP fit (1-5) | K3: Intent signals (1-5) | L3: Score (auto) | M3: Band (auto) | N3: Stage | O3: Potential value | P3: What they get | Q3: Last contact | R3: Next step | S3: Next step due | T3: Status | U3: Notes
A4: 46251 | B4: Employee 1 | C4: Example Rail Group | D4: Enterprise / Employer | E4: United Kingdom | F4: A. Sample | G4: Head of PMO | H4: [LinkedIn URL] | I4: 300+ project controls staff, no internal credentialing route, actively hiring planners | J4: 5 - excellent | K4: 3 - average | L4: =IF(AND($J4="",$K4=""),"",ROUND(IFERROR(VALUE(LEFT($J4,1)),0)*12+IFERROR(VALUE(LEFT($K4,1)),0)*8,0)) -> 84 | M4: =IF($L4="","",IF($L4>=80,"A - pursue now",IF($L4>=60,"B - worth pursuing",IF($L4>=40,"C - nurture","D - park it")))) -> A - pursue now | N4: 4 Contacted | O4: High | P4: A benchmarked capability picture of their project controls team | Q4: 46251 | R4: Send the one-page overview and propose a 20-minute call | S4: 46255 | T4: In Progress | U4: EXAMPLE ROW - delete before use
L5: =IF(AND($J5="",$K5=""),"",ROUND(IFERROR(VALUE(LEFT($J5,1)),0)*12+IFERROR(VALUE(LEFT($K5,1)),0)*8,0)) | M5: =IF($L5="","",IF($L5>=80,"A - pursue now",IF($L5>=60,"B - worth pursuing",IF($L5>=40,"C - nurture","D - park it"))))
L6: =IF(AND($J6="",$K6=""),"",ROUND(IFERROR(VALUE(LEFT($J6,1)),0)*12+IFERROR(VALUE(LEFT($K6,1)),0)*8,0)) | M6: =IF($L6="","",IF($L6>=80,"A - pursue now",IF($L6>=60,"B - worth pursuing",IF($L6>=40,"C - nurture","D - park it"))))
L7: =IF(AND($J7="",$K7=""),"",ROUND(IFERROR(VALUE(LEFT($J7,1)),0)*12+IFERROR(VALUE(LEFT($K7,1)),0)*8,0)) | M7: =IF($L7="","",IF($L7>=80,"A - pursue now",IF($L7>=60,"B - worth pursuing",IF($L7>=40,"C - nurture","D - park it"))))
L8: =IF(AND($J8="",$K8=""),"",ROUND(IFERROR(VALUE(LEFT($J8,1)),0)*12+IFERROR(VALUE(LEFT($K8,1)),0)*8,0)) | M8: =IF($L8="","",IF($L8>=80,"A - pursue now",IF($L8>=60,"B - worth pursuing",IF($L8>=40,"C - nurture","D - park it"))))
L9: =IF(AND($J9="",$K9=""),"",ROUND(IFERROR(VALUE(LEFT($J9,1)),0)*12+IFERROR(VALUE(LEFT($K9,1)),0)*8,0)) | M9: =IF($L9="","",IF($L9>=80,"A - pursue now",IF($L9>=60,"B - worth pursuing",IF($L9>=40,"C - nurture","D - park it"))))
L10: =IF(AND($J10="",$K10=""),"",ROUND(IFERROR(VALUE(LEFT($J10,1)),0)*12+IFERROR(VALUE(LEFT($K10,1)),0)*8,0)) | M10: =IF($L10="","",IF($L10>=80,"A - pursue now",IF($L10>=60,"B - worth pursuing",IF($L10>=40,"C - nurture","D - park it"))))
L11: =IF(AND($J11="",$K11=""),"",ROUND(IFERROR(VALUE(LEFT($J11,1)),0)*12+IFERROR(VALUE(LEFT($K11,1)),0)*8,0)) | M11: =IF($L11="","",IF($L11>=80,"A - pursue now",IF($L11>=60,"B - worth pursuing",IF($L11>=40,"C - nurture","D - park it"))))
L12: =IF(AND($J12="",$K12=""),"",ROUND(IFERROR(VALUE(LEFT($J12,1)),0)*12+IFERROR(VALUE(LEFT($K12,1)),0)*8,0)) | M12: =IF($L12="","",IF($L12>=80,"A - pursue now",IF($L12>=60,"B - worth pursuing",IF($L12>=40,"C - nurture","D - park it"))))
L13: =IF(AND($J13="",$K13=""),"",ROUND(IFERROR(VALUE(LEFT($J13,1)),0)*12+IFERROR(VALUE(LEFT($K13,1)),0)*8,0)) | M13: =IF($L13="","",IF($L13>=80,"A - pursue now",IF($L13>=60,"B - worth pursuing",IF($L13>=40,"C - nurture","D - park it"))))
L14: =IF(AND($J14="",$K14=""),"",ROUND(IFERROR(VALUE(LEFT($J14,1)),0)*12+IFERROR(VALUE(LEFT($K14,1)),0)*8,0)) | M14: =IF($L14="","",IF($L14>=80,"A - pursue now",IF($L14>=60,"B - worth pursuing",IF($L14>=40,"C - nurture","D - park it"))))
L15: =IF(AND($J15="",$K15=""),"",ROUND(IFERROR(VALUE(LEFT($J15,1)),0)*12+IFERROR(VALUE(LEFT($K15,1)),0)*8,0)) | M15: =IF($L15="","",IF($L15>=80,"A - pursue now",IF($L15>=60,"B - worth pursuing",IF($L15>=40,"C - nurture","D - park it"))))
L16: =IF(AND($J16="",$K16=""),"",ROUND(IFERROR(VALUE(LEFT($J16,1)),0)*12+IFERROR(VALUE(LEFT($K16,1)),0)*8,0)) | M16: =IF($L16="","",IF($L16>=80,"A - pursue now",IF($L16>=60,"B - worth pursuing",IF($L16>=40,"C - nurture","D - park it"))))
... L403: =IF(AND($J403="",$K403=""),"",ROUND(IFERROR(VALUE(LEFT($J403,1)),0)*12+IFERROR(VALUE(LEFT($K403,1)),0)*8,0)) | M403: =IF($L403="","",IF($L403>=80,"A - pursue now",IF($L403>=60,"B - worth pursuing",IF($L403>=40,"C - nurture","D - park it"))))

Sheet Dashboard
A1: PCI AI — EXECUTION DASHBOARD
A2: Nothing is typed on this page. Every figure updates from the other tabs. Press Ctrl+Shift+F9 if a figure looks stale. | H2: Chart data (do not delete)
A4: 1. TASK EXECUTION (from Master Tasks) | H4: Not Started | I4: =COUNTIF('Master Tasks'!$J$4:$J$66,H4) -> 63
A5: Metric | B5: Value | C5: Target / benchmark | D5: Status | E5: What it tells management | H5: In Progress | I5: =COUNTIF('Master Tasks'!$J$4:$J$66,H5) -> 0
A6: Total tasks in the plan | B6: =COUNTA('Master Tasks'!$A$4:$A$66) -> 63 | C6: 63 | E6: Size of the agreed workload. | H6: Waiting | I6: =COUNTIF('Master Tasks'!$J$4:$J$66,H6) -> 0
A7: Complete | B7: =COUNTIF('Master Tasks'!$J$4:$J$66,"Complete") -> 0 | E7: Finished and evidenced. | H7: Blocked | I7: =COUNTIF('Master Tasks'!$J$4:$J$66,H7) -> 0
A8: In progress | B8: =COUNTIF('Master Tasks'!$J$4:$J$66,"In Progress") -> 0 | E8: Being actively worked on. | H8: Complete | I8: =COUNTIF('Master Tasks'!$J$4:$J$66,H8) -> 0
A9: Waiting / paused | B9: =COUNTIF('Master Tasks'!$J$4:$J$66,"Waiting")+COUNTIF('Master Tasks'!$J$4:$J$66,"Paused") -> 0 | E9: Held up but not blocked. | H9: Paused | I9: =COUNTIF('Master Tasks'!$J$4:$J$66,H9) -> 0
A10: Blocked - needs management help | B10: =COUNTIF('Master Tasks'!$J$4:$J$66,"Blocked") -> 0 | C10: 0 | E10: Anything above zero needs a decision from the manager this week.
A11: Not started | B11: =COUNTIF('Master Tasks'!$J$4:$J$66,"Not Started") -> 63 | E11: Not yet begun.
A12: Task completion rate | B12: =IFERROR(COUNTIF('Master Tasks'!$J$4:$J$66,"Complete")/COUNTA('Master Tasks'!$A$4:$A$66),0) -> 0 | C12: 100% | E12: Share of the plan finished. | H12: Not Started | I12: =COUNTIF('Platform Setup'!$J$4:$J$49,H12) -> 46
A13: Average progress across all tasks | B13: =IFERROR(AVERAGE('Master Tasks'!$K$4:$K$66),0) -> 0 | C13: 100% | E13: Weighted sense of momentum, including part-finished work. | H13: In Progress | I13: =COUNTIF('Platform Setup'!$J$4:$J$49,H13) -> 0
H14: Waiting | I14: =COUNTIF('Platform Setup'!$J$4:$J$49,H14) -> 0
A15: 2. PLATFORM PRESENCE (from Platform Setup) | H15: Blocked | I15: =COUNTIF('Platform Setup'!$J$4:$J$49,H15) -> 0
A16: Metric | B16: Value | C16: Target / benchmark | D16: Status | E16: What it tells management | H16: Complete | I16: =COUNTIF('Platform Setup'!$J$4:$J$49,H16) -> 0
A17: Platforms in scope | B17: =COUNTA('Platform Setup'!$B$4:$B$49) -> 46 | C17: 46 | E17: Every channel PCI should exist on. | H17: Paused | I17: =COUNTIF('Platform Setup'!$J$4:$J$49,H17) -> 0
A18: Accounts live and complete | B18: =COUNTIF('Platform Setup'!$J$4:$J$49,"Complete") -> 0 | E18: Fully branded, filled in and 2FA enabled.
A19: In progress | B19: =COUNTIF('Platform Setup'!$J$4:$J$49,"In Progress") -> 0 | E19: Created but not finished.
A20: Not started | B20: =COUNTIF('Platform Setup'!$J$4:$J$49,"Not Started") -> 46 | C20: 0 | E20: Still no PCI presence.
A21: Platform coverage | B21: =IFERROR(COUNTIF('Platform Setup'!$J$4:$J$49,"Complete")/COUNTA('Platform Setup'!$B$4:$B$49),0) -> 0 | C21: 100% | E21: The headline 'are we everywhere yet' number.
A22: Live accounts without 2FA | B22: =COUNTIFS('Platform Setup'!$I$4:$I$49,"No",'Platform Setup'!$J$4:$J$49,"<>Not Started") -> 0 | C22: 0 | E22: Security risk - every live account must have 2FA.
A24: 3. LINKEDIN OUTREACH FUNNEL (from LinkedIn Outreach)
A25: Metric | B25: Value | C25: Target / benchmark | D25: Status | E25: What it tells management
A26: Leads researched and logged | B26: =COUNTA('LinkedIn Outreach'!$C$5:$C$1203) -> 0 | E26: Top of the funnel.
A27: Connection requests sent | B27: =COUNTIF('LinkedIn Outreach'!$M$5:$M$1203,"Yes") -> 0 | E27: Invitations sent with a personalised note.
A28: Connections accepted | B28: =COUNTIF('LinkedIn Outreach'!$N$5:$N$1203,"Yes") -> 0 | E28: Accepted invitations.
A29: Acceptance rate | B29: =IFERROR(COUNTIF('LinkedIn Outreach'!$N$5:$N$1203,"Yes")/COUNTIF('LinkedIn Outreach'!$M$5:$M$1203,"Yes"),0) -> 0 | C29: 30-45% | E29: 2026 industry average is 27-30%. Below 20% means fix the targeting, profile or note before sending more.
A30: Honorary certification messages sent | B30: =COUNTIF('LinkedIn Outreach'!$R$5:$R$1203,"Yes") -> 0 | E30: The 300-character message actually delivered.
A31: Positive replies (interested / info requested) | B31: =COUNTIF('LinkedIn Outreach'!$S$5:$S$1203,"Interested")+COUNTIF('LinkedIn Outreach'!$S$5:$S$1203,"Info Requested") -> 0 | E31: Real interest created.
A32: Reply rate on messages sent | B32: =IFERROR((COUNTIF('LinkedIn Outreach'!$S$5:$S$1203,"Interested")+COUNTIF('LinkedIn Outreach'!$S$5:$S$1203,"Info Requested")+COUNTIF('LinkedIn Outreach'!$S$5:$S$1203,"Meeting Booked")+COUNTIF('LinkedIn Outreach'!$S$5:$S$1203,"Converted"))/COUNTIF('LinkedIn Outreach'!$R$5:$R$1203,"Yes"),0) -> 0 | C32: 15%+ | E32: 2026 average for post-connection messages is about 10%. 15%+ is strong.
A33: Meetings / calls booked | B33: =COUNTIF('LinkedIn Outreach'!$S$5:$S$1203,"Meeting Booked") -> 0 | E33: Conversations that management can join.
A34: Applications started / converted | B34: =COUNTIF('LinkedIn Outreach'!$S$5:$S$1203,"Application Started")+COUNTIF('LinkedIn Outreach'!$S$5:$S$1203,"Converted") -> 0 | E34: The outcome that matters commercially.
A35: Declined - do not contact again | B35: =COUNTIF('LinkedIn Outreach'!$S$5:$S$1203,"Declined") -> 0 | E35: Must never be messaged again.
A36: Messages over the 300-character limit | B36: =COUNTIF('LinkedIn Outreach'!$Q$5:$Q$1203,">300") -> 0 | C36: 0 | E36: Anything above zero means the limit was broken - check the message text.
A37: Follow-ups due today or earlier | B37: =COUNTIFS('LinkedIn Outreach'!$U$5:$U$1203,"<="&TODAY(),'LinkedIn Outreach'!$U$5:$U$1203,">0",'LinkedIn Outreach'!$S$5:$S$1203,"Awaiting Reply") -> 0 | C37: 0 | E37: Work waiting to be done today.
A39: 4. ACTIVITY VERSUS DAILY TARGET (from Daily Log)
A40: Activity | B40: Actual to date | C40: Expected to date | D40: Attainment | E40: Notes
A41: Days with activity logged | B41: =SUMPRODUCT(('DAILY ENTRY'!$A$7:$A$1203<>"")/COUNTIFS('DAILY ENTRY'!$A$7:$A$1203,'DAILY ENTRY'!$A$7:$A$1203&"")) -> 0 | E41: Counted from the DAILY ENTRY tab. The expected figures below are this number multiplied by the daily target on START HERE.
A42: Sales Navigator leads researched | B42: =SUMIFS('DAILY ENTRY'!$F$7:$F$1203,'DAILY ENTRY'!$D$7:$D$1203,"Lead researched (Sales Navigator)") -> 0 | C42: ='START HERE'!$B$25*$B$41 -> 0 | D42: =IFERROR(B42/C42,0) -> 0 | E42: =IF(C42=0,"No days logged yet",IF(D42>=1,"On target",IF(D42>=0.8,"Slightly behind - recoverable this week","Behind target - discuss in the weekly review"))) -> No days logged yet
A43: Connection requests sent | B43: =SUMIFS('DAILY ENTRY'!$F$7:$F$1203,'DAILY ENTRY'!$D$7:$D$1203,"Connection request sent") -> 0 | C43: ='START HERE'!$B$26*$B$41 -> 0 | D43: =IFERROR(B43/C43,0) -> 0 | E43: =IF(C43=0,"No days logged yet",IF(D43>=1,"On target",IF(D43>=0.8,"Slightly behind - recoverable this week","Behind target - discuss in the weekly review"))) -> No days logged yet
A44: First messages sent | B44: =SUMIFS('DAILY ENTRY'!$F$7:$F$1203,'DAILY ENTRY'!$D$7:$D$1203,"First message sent") -> 0 | C44: ='START HERE'!$B$27*$B$41 -> 0 | D44: =IFERROR(B44/C44,0) -> 0 | E44: =IF(C44=0,"No days logged yet",IF(D44>=1,"On target",IF(D44>=0.8,"Slightly behind - recoverable this week","Behind target - discuss in the weekly review"))) -> No days logged yet
A45: Follow-up messages sent | B45: =SUMIFS('DAILY ENTRY'!$F$7:$F$1203,'DAILY ENTRY'!$D$7:$D$1203,"Follow-up message sent") -> 0 | C45: ='START HERE'!$B$28*$B$41 -> 0 | D45: =IFERROR(B45/C45,0) -> 0 | E45: =IF(C45=0,"No days logged yet",IF(D45>=1,"On target",IF(D45>=0.8,"Slightly behind - recoverable this week","Behind target - discuss in the weekly review"))) -> No days logged yet
A46: Posts published | B46: =SUMIFS('DAILY ENTRY'!$F$7:$F$1203,'DAILY ENTRY'!$D$7:$D$1203,"Post / content published") -> 0 | C46: ='START HERE'!$B$29*$B$41 -> 0 | D46: =IFERROR(B46/C46,0) -> 0 | E46: =IF(C46=0,"No days logged yet",IF(D46>=1,"On target",IF(D46>=0.8,"Slightly behind - recoverable this week","Behind target - discuss in the weekly review"))) -> No days logged yet
A47: Community answers / comments | B47: =SUMIFS('DAILY ENTRY'!$F$7:$F$1203,'DAILY ENTRY'!$D$7:$D$1203,"Community answer or comment") -> 0 | C47: ='START HERE'!$B$30*$B$41 -> 0 | D47: =IFERROR(B47/C47,0) -> 0 | E47: =IF(C47=0,"No days logged yet",IF(D47>=1,"On target",IF(D47>=0.8,"Slightly behind - recoverable this week","Behind target - discuss in the weekly review"))) -> No days logged yet
A48: Partnership / PR contacts | B48: =SUMIFS('DAILY ENTRY'!$F$7:$F$1203,'DAILY ENTRY'!$D$7:$D$1203,"Partnership / PR contact") -> 0 | C48: ='START HERE'!$B$31*$B$41 -> 0 | D48: =IFERROR(B48/C48,0) -> 0 | E48: =IF(C48=0,"No days logged yet",IF(D48>=1,"On target",IF(D48>=0.8,"Slightly behind - recoverable this week","Behind target - discuss in the weekly review"))) -> No days logged yet
A49: Engagements on other people's posts | B49: =SUMIFS('DAILY ENTRY'!$F$7:$F$1203,'DAILY ENTRY'!$D$7:$D$1203,"Engagement (commented on someone else)") -> 0 | C49: ='START HERE'!$B$32*$B$41 -> 0 | D49: =IFERROR(B49/C49,0) -> 0 | E49: =IF(C49=0,"No days logged yet",IF(D49>=1,"On target",IF(D49>=0.8,"Slightly behind - recoverable this week","Behind target - discuss in the weekly review"))) -> No days logged yet
A51: 5. CONTENT AND COMMUNITY OUTPUT (from Content Calendar and Community & PR)
A52: Metric | B52: Value | C52: Target / benchmark | D52: Status | E52: What it tells management
A53: Content items planned | B53: =COUNTA('Content Calendar'!$E$5:$E$403) -> 0 | E53: Everything in the calendar.
A54: Content published | B54: =COUNTIF('Content Calendar'!$J$5:$J$403,"Published")+COUNTIF('Content Calendar'!$J$5:$J$403,"Repurposed") -> 0 | E54: Actually live.
A55: Total impressions | B55: =SUM('Content Calendar'!$M$5:$M$403) -> 0 | E55: Reach across all platforms.
A56: Total engagements | B56: =SUM('Content Calendar'!$N$5:$N$403) -> 0 | E56: Comments, likes and shares earned.
A57: Engagement rate | B57: =IFERROR(SUM('Content Calendar'!$N$5:$N$403)/SUM('Content Calendar'!$M$5:$M$403),0) -> 0 | C57: 2%+ | E57: Whether the content is landing with the right people.
A58: Clicks to PCI | B58: =SUM('Content Calendar'!$O$5:$O$403) -> 0 | E58: Traffic the content sent to PCI.
A59: Leads from content | B59: =SUM('Content Calendar'!$P$5:$P$403) -> 0 | E59: Enquiries attributable to content.
A60: Community and PR actions logged | B60: =COUNTA('Community & PR'!$C$5:$C$403) -> 0 | E60: Quora, Reddit, groups, associations, universities, employers and media.
A61: Partnership meetings booked | B61: =COUNTIF('Community & PR'!$N$5:$N$403,"Meeting Booked") -> 0 | E61: Partnership pipeline.
A63: 6. BY AREA — where the work stands
A64: Area | B64: Tasks | C64: Complete | D64: Completion | E64: Platforms live in this area
A65: LinkedIn | B65: =COUNTIF('Master Tasks'!$B$4:$B$66,$A65) -> 12 | C65: =COUNTIFS('Master Tasks'!$B$4:$B$66,$A65,'Master Tasks'!$J$4:$J$66,"Complete") -> 0 | D65: =IFERROR(C65/B65,0) -> 0 | E65: =COUNTIFS('Platform Setup'!$C$4:$C$49,$A65,'Platform Setup'!$J$4:$J$49,"Complete")&" of "&COUNTIF('Platform Setup'!$C$4:$C$49,$A65) -> 0 of 3
A66: Social Media | B66: =COUNTIF('Master Tasks'!$B$4:$B$66,$A66) -> 12 | C66: =COUNTIFS('Master Tasks'!$B$4:$B$66,$A66,'Master Tasks'!$J$4:$J$66,"Complete") -> 0 | D66: =IFERROR(C66/B66,0) -> 0 | E66: =COUNTIFS('Platform Setup'!$C$4:$C$49,$A66,'Platform Setup'!$J$4:$J$49,"Complete")&" of "&COUNTIF('Platform Setup'!$C$4:$C$49,$A66) -> 0 of 10
A67: Publishing | B67: =COUNTIF('Master Tasks'!$B$4:$B$66,$A67) -> 12 | C67: =COUNTIFS('Master Tasks'!$B$4:$B$66,$A67,'Master Tasks'!$J$4:$J$66,"Complete") -> 0 | D67: =IFERROR(C67/B67,0) -> 0 | E67: =COUNTIFS('Platform Setup'!$C$4:$C$49,$A67,'Platform Setup'!$J$4:$J$49,"Complete")&" of "&COUNTIF('Platform Setup'!$C$4:$C$49,$A67) -> 0 of 11
A68: Community | B68: =COUNTIF('Master Tasks'!$B$4:$B$66,$A68) -> 4 | C68: =COUNTIFS('Master Tasks'!$B$4:$B$66,$A68,'Master Tasks'!$J$4:$J$66,"Complete") -> 0 | D68: =IFERROR(C68/B68,0) -> 0 | E68: =COUNTIFS('Platform Setup'!$C$4:$C$49,$A68,'Platform Setup'!$J$4:$J$49,"Complete")&" of "&COUNTIF('Platform Setup'!$C$4:$C$49,$A68) -> 0 of 7
A69: Directory/Review | B69: =COUNTIF('Master Tasks'!$B$4:$B$66,$A69) -> 7 | C69: =COUNTIFS('Master Tasks'!$B$4:$B$66,$A69,'Master Tasks'!$J$4:$J$66,"Complete") -> 0 | D69: =IFERROR(C69/B69,0) -> 0 | E69: =COUNTIFS('Platform Setup'!$C$4:$C$49,$A69,'Platform Setup'!$J$4:$J$49,"Complete")&" of "&COUNTIF('Platform Setup'!$C$4:$C$49,$A69) -> 0 of 7
A70: Partnership/PR | B70: =COUNTIF('Master Tasks'!$B$4:$B$66,$A70) -> 7 | C70: =COUNTIFS('Master Tasks'!$B$4:$B$66,$A70,'Master Tasks'!$J$4:$J$66,"Complete") -> 0 | D70: =IFERROR(C70/B70,0) -> 0 | E70: =COUNTIFS('Platform Setup'!$C$4:$C$49,$A70,'Platform Setup'!$J$4:$J$49,"Complete")&" of "&COUNTIF('Platform Setup'!$C$4:$C$49,$A70) -> 0 of 0
A71: Events | B71: =COUNTIF('Master Tasks'!$B$4:$B$66,$A71) -> 5 | C71: =COUNTIFS('Master Tasks'!$B$4:$B$66,$A71,'Master Tasks'!$J$4:$J$66,"Complete") -> 0 | D71: =IFERROR(C71/B71,0) -> 0 | E71: =COUNTIFS('Platform Setup'!$C$4:$C$49,$A71,'Platform Setup'!$J$4:$J$49,"Complete")&" of "&COUNTIF('Platform Setup'!$C$4:$C$49,$A71) -> 0 of 5
A72: Analytics | B72: =COUNTIF('Master Tasks'!$B$4:$B$66,$A72) -> 4 | C72: =COUNTIFS('Master Tasks'!$B$4:$B$66,$A72,'Master Tasks'!$J$4:$J$66,"Complete") -> 0 | D72: =IFERROR(C72/B72,0) -> 0 | E72: =COUNTIFS('Platform Setup'!$C$4:$C$49,$A72,'Platform Setup'!$J$4:$J$49,"Complete")&" of "&COUNTIF('Platform Setup'!$C$4:$C$49,$A72) -> 0 of 3
A74: MANAGER RULE: activity only counts when it is logged with evidence. If a lead has no URL, a post has no published link or an account has no profile URL, treat it as not done. Read the Weekly Review tab alongside this page - a good week is a rising acceptance and reply rate, not a bigger number of messages.
A76: 7. FUNNEL — where every contact currently sits
A77: Stage | B77: LinkedIn leads | C77: Partnerships | D77: Total | E77: What it tells you
A78: 1 Awareness | B78: =COUNTIF('LinkedIn Outreach'!$AC$5:$AC$1203,$A78) -> 0 | C78: =COUNTIF('Partnership Pipeline'!$N$5:$N$403,$A78) -> 0 | D78: =B78+C78 -> 0 | E78: Contacted but no response yet.
A79: 2 Engaged | B79: =COUNTIF('LinkedIn Outreach'!$AC$5:$AC$1203,$A79) -> 0 | C79: =COUNTIF('Partnership Pipeline'!$N$5:$N$403,$A79) -> 0 | D79: =B79+C79 -> 0 | E79: They accepted - the relationship exists.
A80: 3 Qualified | B80: =COUNTIF('LinkedIn Outreach'!$AC$5:$AC$1203,$A80) -> 0 | C80: =COUNTIF('Partnership Pipeline'!$N$5:$N$403,$A80) -> 0 | D80: =B80+C80 -> 0 | E80: Scored as a genuine fit but not yet approached.
A81: 4 Contacted | B81: =COUNTIF('LinkedIn Outreach'!$AC$5:$AC$1203,$A81) -> 0 | C81: =COUNTIF('Partnership Pipeline'!$N$5:$N$403,$A81) -> 0 | D81: =B81+C81 -> 0 | E81: The substantive message has been sent.
A82: 5 Interested | B82: =COUNTIF('LinkedIn Outreach'!$AC$5:$AC$1203,$A82) -> 0 | C82: =COUNTIF('Partnership Pipeline'!$N$5:$N$403,$A82) -> 0 | D82: =B82+C82 -> 0 | E82: They replied positively or asked for the criteria.
A83: 6 Meeting / Application | B83: =COUNTIF('LinkedIn Outreach'!$AC$5:$AC$1203,$A83) -> 0 | C83: =COUNTIF('Partnership Pipeline'!$N$5:$N$403,$A83) -> 0 | D83: =B83+C83 -> 0 | E83: A real conversation is booked.
A84: 7 Certification / Enterprise opportunity | B84: =COUNTIF('LinkedIn Outreach'!$AC$5:$AC$1203,$A84) -> 0 | C84: =COUNTIF('Partnership Pipeline'!$N$5:$N$403,$A84) -> 0 | D84: =B84+C84 -> 0 | E84: The outcome that matters commercially.
A85: 0 Closed - no | B85: =COUNTIF('LinkedIn Outreach'!$AC$5:$AC$1203,$A85) -> 0 | C85: =COUNTIF('Partnership Pipeline'!$N$5:$N$403,$A85) -> 0 | D85: =B85+C85 -> 0 | E85: Declined or not relevant. Never contact again.
A86: Stages are derived automatically from what has been logged - nobody moves a card by hand, so the funnel cannot be inflated. A healthy funnel narrows steadily. A funnel that is wide at Awareness and empty at Interested means the message is wrong, not that more volume is needed.

Sheet Employee Score
A1: EMPLOYEE SCORE — scored on outcomes, not on how many messages were sent
A2: Every component rewards qualified prospects, acceptance, replies, meetings and conversions. Volume is only a gate: it can cap the score, it can never raise it.
A3: Employee | B3: Lead quality (15) | C3: Acceptance rate (20) | D3: Reply rate (20) | E3: Positive replies (10) | F3: Meetings & applications (20) | G3: Downstream results (10) | H3: Compliance (5) | I3: TOTAL / 100 | J3: Grade | K3: Activity gate | L3: What to fix first
A4: =IF('START HERE'!$B$55="","",'START HERE'!$B$55) -> Employee 1 | B4: =IF($A4="","",ROUND(IFERROR(AVERAGEIFS('LinkedIn Outreach'!$AA$5:$AA$1203,'LinkedIn Outreach'!$B$5:$B$1203,$A4,'LinkedIn Outreach'!$AA$5:$AA$1203,">0"),0)/100*15,1)) -> 0 | C4: =IF($A4="","",ROUND(MIN(1,IFERROR('Team Scorecard'!F4/0.3,0))*20,1)) -> 0 | D4: =IF($A4="","",ROUND(MIN(1,IFERROR('Team Scorecard'!I4/0.15,0))*20,1)) -> 0 | E4: =IF($A4="","",ROUND(MIN(1,IFERROR('Team Scorecard'!H4/MAX(1,'Team Scorecard'!G4)/0.2,0))*10,1)) -> 0 | F4: =IF($A4="","",ROUND(MIN(1,(COUNTIFS('LinkedIn Outreach'!$B$5:$B$1203,$A4,'LinkedIn Outreach'!$AC$5:$AC$1203,"6 Meeting / Application")+COUNTIFS('LinkedIn Outreach'!$B$5:$B$1203,$A4,'LinkedIn Outreach'!$AC$5:$AC$1203,"7 Certification / Enterprise opportunity"))/5)*20,1)) -> 0 | G4: =IF($A4="","",ROUND(MIN(1,COUNTIFS('LinkedIn Outreach'!$B$5:$B$1203,$A4,'LinkedIn Outreach'!$AC$5:$AC$1203,"7 Certification / Enterprise opportunity")/3)*10,1)) -> 0 | H4: =IF($A4="","",MAX(0,5-'Team Scorecard'!O4*2.5)) -> 5 | I4: =IF($A4="","",ROUND(SUM(B4:H4),1)) -> 5 | J4: =IF($A4="","",IF(I4>=80,"A - excellent",IF(I4>=65,"B - solid",IF(I4>=50,"C - needs coaching",IF(I4>=30,"D - at risk","E - not working"))))) -> E - not working | K4: =IF($A4="","",IF('Team Scorecard'!B4=0,"No activity logged",IF('Team Scorecard'!D4<20,"Too little data to score fairly yet","Enough data"))) -> No activity logged | L4: =IF($A4="","",IF(H4<5,"Compliance first: messages were sent over the 300-character limit.",IF(C4<10,"Targeting: acceptance is well below benchmark. Fix who is being approached and the personal line.",IF(D4<10,"Message quality: people accept but do not reply. Rewrite the opening message.",IF(F4<10,"Conversion: replies are not turning into meetings. Work on the ask and the follow-through.",IF(B4<8,"Lead quality: the prospects being researched score low on fit. Tighten the Sales Navigator filters.","Nothing structural - keep going and raise the volume gradually.")))))) -> Targeting: acceptance is well below benchmark. Fix who is being approached and the personal line.
A5: =IF('START HERE'!$B$56="","",'START HERE'!$B$56) | B5: =IF($A5="","",ROUND(IFERROR(AVERAGEIFS('LinkedIn Outreach'!$AA$5:$AA$1203,'LinkedIn Outreach'!$B$5:$B$1203,$A5,'LinkedIn Outreach'!$AA$5:$AA$1203,">0"),0)/100*15,1)) | C5: =IF($A5="","",ROUND(MIN(1,IFERROR('Team Scorecard'!F5/0.3,0))*20,1)) | D5: =IF($A5="","",ROUND(MIN(1,IFERROR('Team Scorecard'!I5/0.15,0))*20,1)) | E5: =IF($A5="","",ROUND(MIN(1,IFERROR('Team Scorecard'!H5/MAX(1,'Team Scorecard'!G5)/0.2,0))*10,1)) | F5: =IF($A5="","",ROUND(MIN(1,(COUNTIFS('LinkedIn Outreach'!$B$5:$B$1203,$A5,'LinkedIn Outreach'!$AC$5:$AC$1203,"6 Meeting / Application")+COUNTIFS('LinkedIn Outreach'!$B$5:$B$1203,$A5,'LinkedIn Outreach'!$AC$5:$AC$1203,"7 Certification / Enterprise opportunity"))/5)*20,1)) | G5: =IF($A5="","",ROUND(MIN(1,COUNTIFS('LinkedIn Outreach'!$B$5:$B$1203,$A5,'LinkedIn Outreach'!$AC$5:$AC$1203,"7 Certification / Enterprise opportunity")/3)*10,1)) | H5: =IF($A5="","",MAX(0,5-'Team Scorecard'!O5*2.5)) | I5: =IF($A5="","",ROUND(SUM(B5:H5),1)) | J5: =IF($A5="","",IF(I5>=80,"A - excellent",IF(I5>=65,"B - solid",IF(I5>=50,"C - needs coaching",IF(I5>=30,"D - at risk","E - not working"))))) | K5: =IF($A5="","",IF('Team Scorecard'!B5=0,"No activity logged",IF('Team Scorecard'!D5<20,"Too little data to score fairly yet","Enough data"))) | L5: =IF($A5="","",IF(H5<5,"Compliance first: messages were sent over the 300-character limit.",IF(C5<10,"Targeting: acceptance is well below benchmark. Fix who is being approached and the personal line.",IF(D5<10,"Message quality: people accept but do not reply. Rewrite the opening message.",IF(F5<10,"Conversion: replies are not turning into meetings. Work on the ask and the follow-through.",IF(B5<8,"Lead quality: the prospects being researched score low on fit. Tighten the Sales Navigator filters.","Nothing structural - keep going and raise the volume gradually."))))))
A6: =IF('START HERE'!$B$57="","",'START HERE'!$B$57) | B6: =IF($A6="","",ROUND(IFERROR(AVERAGEIFS('LinkedIn Outreach'!$AA$5:$AA$1203,'LinkedIn Outreach'!$B$5:$B$1203,$A6,'LinkedIn Outreach'!$AA$5:$AA$1203,">0"),0)/100*15,1)) | C6: =IF($A6="","",ROUND(MIN(1,IFERROR('Team Scorecard'!F6/0.3,0))*20,1)) | D6: =IF($A6="","",ROUND(MIN(1,IFERROR('Team Scorecard'!I6/0.15,0))*20,1)) | E6: =IF($A6="","",ROUND(MIN(1,IFERROR('Team Scorecard'!H6/MAX(1,'Team Scorecard'!G6)/0.2,0))*10,1)) | F6: =IF($A6="","",ROUND(MIN(1,(COUNTIFS('LinkedIn Outreach'!$B$5:$B$1203,$A6,'LinkedIn Outreach'!$AC$5:$AC$1203,"6 Meeting / Application")+COUNTIFS('LinkedIn Outreach'!$B$5:$B$1203,$A6,'LinkedIn Outreach'!$AC$5:$AC$1203,"7 Certification / Enterprise opportunity"))/5)*20,1)) | G6: =IF($A6="","",ROUND(MIN(1,COUNTIFS('LinkedIn Outreach'!$B$5:$B$1203,$A6,'LinkedIn Outreach'!$AC$5:$AC$1203,"7 Certification / Enterprise opportunity")/3)*10,1)) | H6: =IF($A6="","",MAX(0,5-'Team Scorecard'!O6*2.5)) | I6: =IF($A6="","",ROUND(SUM(B6:H6),1)) | J6: =IF($A6="","",IF(I6>=80,"A - excellent",IF(I6>=65,"B - solid",IF(I6>=50,"C - needs coaching",IF(I6>=30,"D - at risk","E - not working"))))) | K6: =IF($A6="","",IF('Team Scorecard'!B6=0,"No activity logged",IF('Team Scorecard'!D6<20,"Too little data to score fairly yet","Enough data"))) | L6: =IF($A6="","",IF(H6<5,"Compliance first: messages were sent over the 300-character limit.",IF(C6<10,"Targeting: acceptance is well below benchmark. Fix who is being approached and the personal line.",IF(D6<10,"Message quality: people accept but do not reply. Rewrite the opening message.",IF(F6<10,"Conversion: replies are not turning into meetings. Work on the ask and the follow-through.",IF(B6<8,"Lead quality: the prospects being researched score low on fit. Tighten the Sales Navigator filters.","Nothing structural - keep going and raise the volume gradually."))))))
A7: =IF('START HERE'!$B$58="","",'START HERE'!$B$58) | B7: =IF($A7="","",ROUND(IFERROR(AVERAGEIFS('LinkedIn Outreach'!$AA$5:$AA$1203,'LinkedIn Outreach'!$B$5:$B$1203,$A7,'LinkedIn Outreach'!$AA$5:$AA$1203,">0"),0)/100*15,1)) | C7: =IF($A7="","",ROUND(MIN(1,IFERROR('Team Scorecard'!F7/0.3,0))*20,1)) | D7: =IF($A7="","",ROUND(MIN(1,IFERROR('Team Scorecard'!I7/0.15,0))*20,1)) | E7: =IF($A7="","",ROUND(MIN(1,IFERROR('Team Scorecard'!H7/MAX(1,'Team Scorecard'!G7)/0.2,0))*10,1)) | F7: =IF($A7="","",ROUND(MIN(1,(COUNTIFS('LinkedIn Outreach'!$B$5:$B$1203,$A7,'LinkedIn Outreach'!$AC$5:$AC$1203,"6 Meeting / Application")+COUNTIFS('LinkedIn Outreach'!$B$5:$B$1203,$A7,'LinkedIn Outreach'!$AC$5:$AC$1203,"7 Certification / Enterprise opportunity"))/5)*20,1)) | G7: =IF($A7="","",ROUND(MIN(1,COUNTIFS('LinkedIn Outreach'!$B$5:$B$1203,$A7,'LinkedIn Outreach'!$AC$5:$AC$1203,"7 Certification / Enterprise opportunity")/3)*10,1)) | H7: =IF($A7="","",MAX(0,5-'Team Scorecard'!O7*2.5)) | I7: =IF($A7="","",ROUND(SUM(B7:H7),1)) | J7: =IF($A7="","",IF(I7>=80,"A - excellent",IF(I7>=65,"B - solid",IF(I7>=50,"C - needs coaching",IF(I7>=30,"D - at risk","E - not working"))))) | K7: =IF($A7="","",IF('Team Scorecard'!B7=0,"No activity logged",IF('Team Scorecard'!D7<20,"Too little data to score fairly yet","Enough data"))) | L7: =IF($A7="","",IF(H7<5,"Compliance first: messages were sent over the 300-character limit.",IF(C7<10,"Targeting: acceptance is well below benchmark. Fix who is being approached and the personal line.",IF(D7<10,"Message quality: people accept but do not reply. Rewrite the opening message.",IF(F7<10,"Conversion: replies are not turning into meetings. Work on the ask and the follow-through.",IF(B7<8,"Lead quality: the prospects being researched score low on fit. Tighten the Sales Navigator filters.","Nothing structural - keep going and raise the volume gradually."))))))
A8: =IF('START HERE'!$B$59="","",'START HERE'!$B$59) | B8: =IF($A8="","",ROUND(IFERROR(AVERAGEIFS('LinkedIn Outreach'!$AA$5:$AA$1203,'LinkedIn Outreach'!$B$5:$B$1203,$A8,'LinkedIn Outreach'!$AA$5:$AA$1203,">0"),0)/100*15,1)) | C8: =IF($A8="","",ROUND(MIN(1,IFERROR('Team Scorecard'!F8/0.3,0))*20,1)) | D8: =IF($A8="","",ROUND(MIN(1,IFERROR('Team Scorecard'!I8/0.15,0))*20,1)) | E8: =IF($A8="","",ROUND(MIN(1,IFERROR('Team Scorecard'!H8/MAX(1,'Team Scorecard'!G8)/0.2,0))*10,1)) | F8: =IF($A8="","",ROUND(MIN(1,(COUNTIFS('LinkedIn Outreach'!$B$5:$B$1203,$A8,'LinkedIn Outreach'!$AC$5:$AC$1203,"6 Meeting / Application")+COUNTIFS('LinkedIn Outreach'!$B$5:$B$1203,$A8,'LinkedIn Outreach'!$AC$5:$AC$1203,"7 Certification / Enterprise opportunity"))/5)*20,1)) | G8: =IF($A8="","",ROUND(MIN(1,COUNTIFS('LinkedIn Outreach'!$B$5:$B$1203,$A8,'LinkedIn Outreach'!$AC$5:$AC$1203,"7 Certification / Enterprise opportunity")/3)*10,1)) | H8: =IF($A8="","",MAX(0,5-'Team Scorecard'!O8*2.5)) | I8: =IF($A8="","",ROUND(SUM(B8:H8),1)) | J8: =IF($A8="","",IF(I8>=80,"A - excellent",IF(I8>=65,"B - solid",IF(I8>=50,"C - needs coaching",IF(I8>=30,"D - at risk","E - not working"))))) | K8: =IF($A8="","",IF('Team Scorecard'!B8=0,"No activity logged",IF('Team Scorecard'!D8<20,"Too little data to score fairly yet","Enough data"))) | L8: =IF($A8="","",IF(H8<5,"Compliance first: messages were sent over the 300-character limit.",IF(C8<10,"Targeting: acceptance is well below benchmark. Fix who is being approached and the personal line.",IF(D8<10,"Message quality: people accept but do not reply. Rewrite the opening message.",IF(F8<10,"Conversion: replies are not turning into meetings. Work on the ask and the follow-through.",IF(B8<8,"Lead quality: the prospects being researched score low on fit. Tighten the Sales Navigator filters.","Nothing structural - keep going and raise the volume gradually."))))))
A9: =IF('START HERE'!$B$60="","",'START HERE'!$B$60) | B9: =IF($A9="","",ROUND(IFERROR(AVERAGEIFS('LinkedIn Outreach'!$AA$5:$AA$1203,'LinkedIn Outreach'!$B$5:$B$1203,$A9,'LinkedIn Outreach'!$AA$5:$AA$1203,">0"),0)/100*15,1)) | C9: =IF($A9="","",ROUND(MIN(1,IFERROR('Team Scorecard'!F9/0.3,0))*20,1)) | D9: =IF($A9="","",ROUND(MIN(1,IFERROR('Team Scorecard'!I9/0.15,0))*20,1)) | E9: =IF($A9="","",ROUND(MIN(1,IFERROR('Team Scorecard'!H9/MAX(1,'Team Scorecard'!G9)/0.2,0))*10,1)) | F9: =IF($A9="","",ROUND(MIN(1,(COUNTIFS('LinkedIn Outreach'!$B$5:$B$1203,$A9,'LinkedIn Outreach'!$AC$5:$AC$1203,"6 Meeting / Application")+COUNTIFS('LinkedIn Outreach'!$B$5:$B$1203,$A9,'LinkedIn Outreach'!$AC$5:$AC$1203,"7 Certification / Enterprise opportunity"))/5)*20,1)) | G9: =IF($A9="","",ROUND(MIN(1,COUNTIFS('LinkedIn Outreach'!$B$5:$B$1203,$A9,'LinkedIn Outreach'!$AC$5:$AC$1203,"7 Certification / Enterprise opportunity")/3)*10,1)) | H9: =IF($A9="","",MAX(0,5-'Team Scorecard'!O9*2.5)) | I9: =IF($A9="","",ROUND(SUM(B9:H9),1)) | J9: =IF($A9="","",IF(I9>=80,"A - excellent",IF(I9>=65,"B - solid",IF(I9>=50,"C - needs coaching",IF(I9>=30,"D - at risk","E - not working"))))) | K9: =IF($A9="","",IF('Team Scorecard'!B9=0,"No activity logged",IF('Team Scorecard'!D9<20,"Too little data to score fairly yet","Enough data"))) | L9: =IF($A9="","",IF(H9<5,"Compliance first: messages were sent over the 300-character limit.",IF(C9<10,"Targeting: acceptance is well below benchmark. Fix who is being approached and the personal line.",IF(D9<10,"Message quality: people accept but do not reply. Rewrite the opening message.",IF(F9<10,"Conversion: replies are not turning into meetings. Work on the ask and the follow-through.",IF(B9<8,"Lead quality: the prospects being researched score low on fit. Tighten the Sales Navigator filters.","Nothing structural - keep going and raise the volume gradually."))))))
A10: =IF('START HERE'!$B$61="","",'START HERE'!$B$61) | B10: =IF($A10="","",ROUND(IFERROR(AVERAGEIFS('LinkedIn Outreach'!$AA$5:$AA$1203,'LinkedIn Outreach'!$B$5:$B$1203,$A10,'LinkedIn Outreach'!$AA$5:$AA$1203,">0"),0)/100*15,1)) | C10: =IF($A10="","",ROUND(MIN(1,IFERROR('Team Scorecard'!F10/0.3,0))*20,1)) | D10: =IF($A10="","",ROUND(MIN(1,IFERROR('Team Scorecard'!I10/0.15,0))*20,1)) | E10: =IF($A10="","",ROUND(MIN(1,IFERROR('Team Scorecard'!H10/MAX(1,'Team Scorecard'!G10)/0.2,0))*10,1)) | F10: =IF($A10="","",ROUND(MIN(1,(COUNTIFS('LinkedIn Outreach'!$B$5:$B$1203,$A10,'LinkedIn Outreach'!$AC$5:$AC$1203,"6 Meeting / Application")+COUNTIFS('LinkedIn Outreach'!$B$5:$B$1203,$A10,'LinkedIn Outreach'!$AC$5:$AC$1203,"7 Certification / Enterprise opportunity"))/5)*20,1)) | G10: =IF($A10="","",ROUND(MIN(1,COUNTIFS('LinkedIn Outreach'!$B$5:$B$1203,$A10,'LinkedIn Outreach'!$AC$5:$AC$1203,"7 Certification / Enterprise opportunity")/3)*10,1)) | H10: =IF($A10="","",MAX(0,5-'Team Scorecard'!O10*2.5)) | I10: =IF($A10="","",ROUND(SUM(B10:H10),1)) | J10: =IF($A10="","",IF(I10>=80,"A - excellent",IF(I10>=65,"B - solid",IF(I10>=50,"C - needs coaching",IF(I10>=30,"D - at risk","E - not working"))))) | K10: =IF($A10="","",IF('Team Scorecard'!B10=0,"No activity logged",IF('Team Scorecard'!D10<20,"Too little data to score fairly yet","Enough data"))) | L10: =IF($A10="","",IF(H10<5,"Compliance first: messages were sent over the 300-character limit.",IF(C10<10,"Targeting: acceptance is well below benchmark. Fix who is being approached and the personal line.",IF(D10<10,"Message quality: people accept but do not reply. Rewrite the opening message.",IF(F10<10,"Conversion: replies are not turning into meetings. Work on the ask and the follow-through.",IF(B10<8,"Lead quality: the prospects being researched score low on fit. Tighten the Sales Navigator filters.","Nothing structural - keep going and raise the volume gradually."))))))
A11: =IF('START HERE'!$B$62="","",'START HERE'!$B$62) | B11: =IF($A11="","",ROUND(IFERROR(AVERAGEIFS('LinkedIn Outreach'!$AA$5:$AA$1203,'LinkedIn Outreach'!$B$5:$B$1203,$A11,'LinkedIn Outreach'!$AA$5:$AA$1203,">0"),0)/100*15,1)) | C11: =IF($A11="","",ROUND(MIN(1,IFERROR('Team Scorecard'!F11/0.3,0))*20,1)) | D11: =IF($A11="","",ROUND(MIN(1,IFERROR('Team Scorecard'!I11/0.15,0))*20,1)) | E11: =IF($A11="","",ROUND(MIN(1,IFERROR('Team Scorecard'!H11/MAX(1,'Team Scorecard'!G11)/0.2,0))*10,1)) | F11: =IF($A11="","",ROUND(MIN(1,(COUNTIFS('LinkedIn Outreach'!$B$5:$B$1203,$A11,'LinkedIn Outreach'!$AC$5:$AC$1203,"6 Meeting / Application")+COUNTIFS('LinkedIn Outreach'!$B$5:$B$1203,$A11,'LinkedIn Outreach'!$AC$5:$AC$1203,"7 Certification / Enterprise opportunity"))/5)*20,1)) | G11: =IF($A11="","",ROUND(MIN(1,COUNTIFS('LinkedIn Outreach'!$B$5:$B$1203,$A11,'LinkedIn Outreach'!$AC$5:$AC$1203,"7 Certification / Enterprise opportunity")/3)*10,1)) | H11: =IF($A11="","",MAX(0,5-'Team Scorecard'!O11*2.5)) | I11: =IF($A11="","",ROUND(SUM(B11:H11),1)) | J11: =IF($A11="","",IF(I11>=80,"A - excellent",IF(I11>=65,"B - solid",IF(I11>=50,"C - needs coaching",IF(I11>=30,"D - at risk","E - not working"))))) | K11: =IF($A11="","",IF('Team Scorecard'!B11=0,"No activity logged",IF('Team Scorecard'!D11<20,"Too little data to score fairly yet","Enough data"))) | L11: =IF($A11="","",IF(H11<5,"Compliance first: messages were sent over the 300-character limit.",IF(C11<10,"Targeting: acceptance is well below benchmark. Fix who is being approached and the personal line.",IF(D11<10,"Message quality: people accept but do not reply. Rewrite the opening message.",IF(F11<10,"Conversion: replies are not turning into meetings. Work on the ask and the follow-through.",IF(B11<8,"Lead quality: the prospects being researched score low on fit. Tighten the Sales Navigator filters.","Nothing structural - keep going and raise the volume gradually."))))))
A12: =IF('START HERE'!$B$63="","",'START HERE'!$B$63) | B12: =IF($A12="","",ROUND(IFERROR(AVERAGEIFS('LinkedIn Outreach'!$AA$5:$AA$1203,'LinkedIn Outreach'!$B$5:$B$1203,$A12,'LinkedIn Outreach'!$AA$5:$AA$1203,">0"),0)/100*15,1)) | C12: =IF($A12="","",ROUND(MIN(1,IFERROR('Team Scorecard'!F12/0.3,0))*20,1)) | D12: =IF($A12="","",ROUND(MIN(1,IFERROR('Team Scorecard'!I12/0.15,0))*20,1)) | E12: =IF($A12="","",ROUND(MIN(1,IFERROR('Team Scorecard'!H12/MAX(1,'Team Scorecard'!G12)/0.2,0))*10,1)) | F12: =IF($A12="","",ROUND(MIN(1,(COUNTIFS('LinkedIn Outreach'!$B$5:$B$1203,$A12,'LinkedIn Outreach'!$AC$5:$AC$1203,"6 Meeting / Application")+COUNTIFS('LinkedIn Outreach'!$B$5:$B$1203,$A12,'LinkedIn Outreach'!$AC$5:$AC$1203,"7 Certification / Enterprise opportunity"))/5)*20,1)) | G12: =IF($A12="","",ROUND(MIN(1,COUNTIFS('LinkedIn Outreach'!$B$5:$B$1203,$A12,'LinkedIn Outreach'!$AC$5:$AC$1203,"7 Certification / Enterprise opportunity")/3)*10,1)) | H12: =IF($A12="","",MAX(0,5-'Team Scorecard'!O12*2.5)) | I12: =IF($A12="","",ROUND(SUM(B12:H12),1)) | J12: =IF($A12="","",IF(I12>=80,"A - excellent",IF(I12>=65,"B - solid",IF(I12>=50,"C - needs coaching",IF(I12>=30,"D - at risk","E - not working"))))) | K12: =IF($A12="","",IF('Team Scorecard'!B12=0,"No activity logged",IF('Team Scorecard'!D12<20,"Too little data to score fairly yet","Enough data"))) | L12: =IF($A12="","",IF(H12<5,"Compliance first: messages were sent over the 300-character limit.",IF(C12<10,"Targeting: acceptance is well below benchmark. Fix who is being approached and the personal line.",IF(D12<10,"Message quality: people accept but do not reply. Rewrite the opening message.",IF(F12<10,"Conversion: replies are not turning into meetings. Work on the ask and the follow-through.",IF(B12<8,"Lead quality: the prospects being researched score low on fit. Tighten the Sales Navigator filters.","Nothing structural - keep going and raise the volume gradually."))))))
A13: =IF('START HERE'!$B$64="","",'START HERE'!$B$64) | B13: =IF($A13="","",ROUND(IFERROR(AVERAGEIFS('LinkedIn Outreach'!$AA$5:$AA$1203,'LinkedIn Outreach'!$B$5:$B$1203,$A13,'LinkedIn Outreach'!$AA$5:$AA$1203,">0"),0)/100*15,1)) | C13: =IF($A13="","",ROUND(MIN(1,IFERROR('Team Scorecard'!F13/0.3,0))*20,1)) | D13: =IF($A13="","",ROUND(MIN(1,IFERROR('Team Scorecard'!I13/0.15,0))*20,1)) | E13: =IF($A13="","",ROUND(MIN(1,IFERROR('Team Scorecard'!H13/MAX(1,'Team Scorecard'!G13)/0.2,0))*10,1)) | F13: =IF($A13="","",ROUND(MIN(1,(COUNTIFS('LinkedIn Outreach'!$B$5:$B$1203,$A13,'LinkedIn Outreach'!$AC$5:$AC$1203,"6 Meeting / Application")+COUNTIFS('LinkedIn Outreach'!$B$5:$B$1203,$A13,'LinkedIn Outreach'!$AC$5:$AC$1203,"7 Certification / Enterprise opportunity"))/5)*20,1)) | G13: =IF($A13="","",ROUND(MIN(1,COUNTIFS('LinkedIn Outreach'!$B$5:$B$1203,$A13,'LinkedIn Outreach'!$AC$5:$AC$1203,"7 Certification / Enterprise opportunity")/3)*10,1)) | H13: =IF($A13="","",MAX(0,5-'Team Scorecard'!O13*2.5)) | I13: =IF($A13="","",ROUND(SUM(B13:H13),1)) | J13: =IF($A13="","",IF(I13>=80,"A - excellent",IF(I13>=65,"B - solid",IF(I13>=50,"C - needs coaching",IF(I13>=30,"D - at risk","E - not working"))))) | K13: =IF($A13="","",IF('Team Scorecard'!B13=0,"No activity logged",IF('Team Scorecard'!D13<20,"Too little data to score fairly yet","Enough data"))) | L13: =IF($A13="","",IF(H13<5,"Compliance first: messages were sent over the 300-character limit.",IF(C13<10,"Targeting: acceptance is well below benchmark. Fix who is being approached and the personal line.",IF(D13<10,"Message quality: people accept but do not reply. Rewrite the opening message.",IF(F13<10,"Conversion: replies are not turning into meetings. Work on the ask and the follow-through.",IF(B13<8,"Lead quality: the prospects being researched score low on fit. Tighten the Sales Navigator filters.","Nothing structural - keep going and raise the volume gradually."))))))
A15: HOW THE SCORE IS BUILT - and why there is no 'messages sent' component. Lead quality 15, acceptance rate 20, reply rate 20, positive replies 10, meetings and applications 20, downstream conversions 10, compliance 5. Acceptance is scored against the 30% benchmark and reply rate against 15%, both from the Benchmarks tab. Sending more messages cannot raise any of these; sending worse messages to worse-fitting people lowers almost all of them. The Activity gate column exists so that nobody is graded on twenty data points - below 20 connection requests it says so instead of pretending the score is meaningful.

Sheet Team Scorecard
A1: TEAM SCORECARD — one row per employee, updates itself
A2: This is the page to use for one-to-ones and appraisals. Names come from the roster on START HERE; figures come from the log tabs.
A3: Employee | B3: Days logged | C3: Leads researched | D3: Connections sent | E3: Accepted | F3: Acceptance % | G3: Messages sent | H3: Positive replies | I3: Reply % | J3: Meetings booked | K3: Posts published | L3: Community actions | M3: Partner / PR contacts | N3: Engagements | O3: Msgs over 300 chars | P3: Blocked items | Q3: Verdict | R3: Tasks owned | S3: Tasks complete | T3: Task completion | U3: Platforms owned live | V3: Content published
A4: =IF('START HERE'!$B$55="","",'START HERE'!$B$55) -> Employee 1 | B4: =IF($A4="","",IFERROR(SUMPRODUCT(('DAILY ENTRY'!$B$7:$B$1203=$A4)*('DAILY ENTRY'!$A$7:$A$1203<>"")/COUNTIFS('DAILY ENTRY'!$A$7:$A$1203,'DAILY ENTRY'!$A$7:$A$1203&"",'DAILY ENTRY'!$B$7:$B$1203,'DAILY ENTRY'!$B$7:$B$1203&"")),0)) -> 0 | C4: =IF($A4="","",SUMIFS('DAILY ENTRY'!$F$7:$F$1203,'DAILY ENTRY'!$D$7:$D$1203,"Lead researched (Sales Navigator)",'DAILY ENTRY'!$B$7:$B$1203,$A4)) -> 0 | D4: =IF($A4="","",COUNTIFS('LinkedIn Outreach'!$B$5:$B$1203,$A4,'LinkedIn Outreach'!$M$5:$M$1203,"Yes")) -> 0 | E4: =IF($A4="","",COUNTIFS('LinkedIn Outreach'!$B$5:$B$1203,$A4,'LinkedIn Outreach'!$N$5:$N$1203,"Yes")) -> 0 | F4: =IF($A4="","",IFERROR(E4/D4,"")) | G4: =IF($A4="","",COUNTIFS('LinkedIn Outreach'!$B$5:$B$1203,$A4,'LinkedIn Outreach'!$R$5:$R$1203,"Yes")) -> 0 | H4: =IF($A4="","",COUNTIFS('LinkedIn Outreach'!$B$5:$B$1203,$A4,'LinkedIn Outreach'!$S$5:$S$1203,"Interested")+COUNTIFS('LinkedIn Outreach'!$B$5:$B$1203,$A4,'LinkedIn Outreach'!$S$5:$S$1203,"Info Requested")+COUNTIFS('LinkedIn Outreach'!$B$5:$B$1203,$A4,'LinkedIn Outreach'!$S$5:$S$1203,"Meeting Booked")+COUNTIFS('LinkedIn Outreach'!$B$5:$B$1203,$A4,'LinkedIn Outreach'!$S$5:$S$1203,"Converted")) -> 0 | I4: =IF($A4="","",IFERROR(H4/G4,"")) | J4: =IF($A4="","",COUNTIFS('LinkedIn Outreach'!$B$5:$B$1203,$A4,'LinkedIn Outreach'!$S$5:$S$1203,"Meeting Booked")) -> 0 | K4: =IF($A4="","",SUMIFS('DAILY ENTRY'!$F$7:$F$1203,'DAILY ENTRY'!$D$7:$D$1203,"Post / content published",'DAILY ENTRY'!$B$7:$B$1203,$A4)) -> 0 | L4: =IF($A4="","",SUMIFS('DAILY ENTRY'!$F$7:$F$1203,'DAILY ENTRY'!$D$7:$D$1203,"Community answer or comment",'DAILY ENTRY'!$B$7:$B$1203,$A4)) -> 0 | M4: =IF($A4="","",SUMIFS('DAILY ENTRY'!$F$7:$F$1203,'DAILY ENTRY'!$D$7:$D$1203,"Partnership / PR contact",'DAILY ENTRY'!$B$7:$B$1203,$A4)) -> 0 | N4: =IF($A4="","",SUMIFS('DAILY ENTRY'!$F$7:$F$1203,'DAILY ENTRY'!$D$7:$D$1203,"Engagement (commented on someone else)",'DAILY ENTRY'!$B$7:$B$1203,$A4)) -> 0 | O4: =IF($A4="","",COUNTIFS('LinkedIn Outreach'!$B$5:$B$1203,$A4,'LinkedIn Outreach'!$Q$5:$Q$1203,">300")) -> 0 | P4: =IF($A4="","",COUNTIFS('DAILY ENTRY'!$B$7:$B$1203,$A4,'DAILY ENTRY'!$I$7:$I$1203,"Blocked")) -> 0 | Q4: =IF($A4="","",IF(AND(B4=0,D4=0),"No activity logged yet",IF(O4>0,"BREACH: sent messages over the 300-character limit - review the message text",IF(AND(D4>=20,F4<0.2),"Acceptance below 20% - fix targeting or the connection note before sending more",IF(AND(G4>=20,I4<0.1),"Reply rate below the 10% average - the message needs rewriting, not more volume",IF(AND(F4>=0.3,I4>=0.15),"Strong: both acceptance and reply rate are above benchmark",IF(AND(B4>0,D4=0),"Logging daily work but no LinkedIn outreach recorded","Within normal range - compare against the Benchmarks tab"))))))) -> No activity logged yet | R4: =IF($A4="","",COUNTIF('Master Tasks'!$I$4:$I$66,$A4)) -> 0 | S4: =IF($A4="","",COUNTIFS('Master Tasks'!$I$4:$I$66,$A4,'Master Tasks'!$J$4:$J$66,"Complete")) -> 0 | T4: =IF($A4="","",IFERROR(S4/R4,"")) | U4: =IF($A4="","",COUNTIFS('Platform Setup'!$M$4:$M$49,$A4,'Platform Setup'!$J$4:$J$49,"Complete")) -> 0 | V4: =IF($A4="","",COUNTIFS('Content Calendar'!$B$5:$B$403,$A4,'Content Calendar'!$J$5:$J$403,"Published")+COUNTIFS('Content Calendar'!$B$5:$B$403,$A4,'Content Calendar'!$J$5:$J$403,"Repurposed")) -> 0
A5: =IF('START HERE'!$B$56="","",'START HERE'!$B$56) | B5: =IF($A5="","",IFERROR(SUMPRODUCT(('DAILY ENTRY'!$B$7:$B$1203=$A5)*('DAILY ENTRY'!$A$7:$A$1203<>"")/COUNTIFS('DAILY ENTRY'!$A$7:$A$1203,'DAILY ENTRY'!$A$7:$A$1203&"",'DAILY ENTRY'!$B$7:$B$1203,'DAILY ENTRY'!$B$7:$B$1203&"")),0)) | C5: =IF($A5="","",SUMIFS('DAILY ENTRY'!$F$7:$F$1203,'DAILY ENTRY'!$D$7:$D$1203,"Lead researched (Sales Navigator)",'DAILY ENTRY'!$B$7:$B$1203,$A5)) | D5: =IF($A5="","",COUNTIFS('LinkedIn Outreach'!$B$5:$B$1203,$A5,'LinkedIn Outreach'!$M$5:$M$1203,"Yes")) | E5: =IF($A5="","",COUNTIFS('LinkedIn Outreach'!$B$5:$B$1203,$A5,'LinkedIn Outreach'!$N$5:$N$1203,"Yes")) | F5: =IF($A5="","",IFERROR(E5/D5,"")) | G5: =IF($A5="","",COUNTIFS('LinkedIn Outreach'!$B$5:$B$1203,$A5,'LinkedIn Outreach'!$R$5:$R$1203,"Yes")) | H5: =IF($A5="","",COUNTIFS('LinkedIn Outreach'!$B$5:$B$1203,$A5,'LinkedIn Outreach'!$S$5:$S$1203,"Interested")+COUNTIFS('LinkedIn Outreach'!$B$5:$B$1203,$A5,'LinkedIn Outreach'!$S$5:$S$1203,"Info Requested")+COUNTIFS('LinkedIn Outreach'!$B$5:$B$1203,$A5,'LinkedIn Outreach'!$S$5:$S$1203,"Meeting Booked")+COUNTIFS('LinkedIn Outreach'!$B$5:$B$1203,$A5,'LinkedIn Outreach'!$S$5:$S$1203,"Converted")) | I5: =IF($A5="","",IFERROR(H5/G5,"")) | J5: =IF($A5="","",COUNTIFS('LinkedIn Outreach'!$B$5:$B$1203,$A5,'LinkedIn Outreach'!$S$5:$S$1203,"Meeting Booked")) | K5: =IF($A5="","",SUMIFS('DAILY ENTRY'!$F$7:$F$1203,'DAILY ENTRY'!$D$7:$D$1203,"Post / content published",'DAILY ENTRY'!$B$7:$B$1203,$A5)) | L5: =IF($A5="","",SUMIFS('DAILY ENTRY'!$F$7:$F$1203,'DAILY ENTRY'!$D$7:$D$1203,"Community answer or comment",'DAILY ENTRY'!$B$7:$B$1203,$A5)) | M5: =IF($A5="","",SUMIFS('DAILY ENTRY'!$F$7:$F$1203,'DAILY ENTRY'!$D$7:$D$1203,"Partnership / PR contact",'DAILY ENTRY'!$B$7:$B$1203,$A5)) | N5: =IF($A5="","",SUMIFS('DAILY ENTRY'!$F$7:$F$1203,'DAILY ENTRY'!$D$7:$D$1203,"Engagement (commented on someone else)",'DAILY ENTRY'!$B$7:$B$1203,$A5)) | O5: =IF($A5="","",COUNTIFS('LinkedIn Outreach'!$B$5:$B$1203,$A5,'LinkedIn Outreach'!$Q$5:$Q$1203,">300")) | P5: =IF($A5="","",COUNTIFS('DAILY ENTRY'!$B$7:$B$1203,$A5,'DAILY ENTRY'!$I$7:$I$1203,"Blocked")) | Q5: =IF($A5="","",IF(AND(B5=0,D5=0),"No activity logged yet",IF(O5>0,"BREACH: sent messages over the 300-character limit - review the message text",IF(AND(D5>=20,F5<0.2),"Acceptance below 20% - fix targeting or the connection note before sending more",IF(AND(G5>=20,I5<0.1),"Reply rate below the 10% average - the message needs rewriting, not more volume",IF(AND(F5>=0.3,I5>=0.15),"Strong: both acceptance and reply rate are above benchmark",IF(AND(B5>0,D5=0),"Logging daily work but no LinkedIn outreach recorded","Within normal range - compare against the Benchmarks tab"))))))) | R5: =IF($A5="","",COUNTIF('Master Tasks'!$I$4:$I$66,$A5)) | S5: =IF($A5="","",COUNTIFS('Master Tasks'!$I$4:$I$66,$A5,'Master Tasks'!$J$4:$J$66,"Complete")) | T5: =IF($A5="","",IFERROR(S5/R5,"")) | U5: =IF($A5="","",COUNTIFS('Platform Setup'!$M$4:$M$49,$A5,'Platform Setup'!$J$4:$J$49,"Complete")) | V5: =IF($A5="","",COUNTIFS('Content Calendar'!$B$5:$B$403,$A5,'Content Calendar'!$J$5:$J$403,"Published")+COUNTIFS('Content Calendar'!$B$5:$B$403,$A5,'Content Calendar'!$J$5:$J$403,"Repurposed"))
A6: =IF('START HERE'!$B$57="","",'START HERE'!$B$57) | B6: =IF($A6="","",IFERROR(SUMPRODUCT(('DAILY ENTRY'!$B$7:$B$1203=$A6)*('DAILY ENTRY'!$A$7:$A$1203<>"")/COUNTIFS('DAILY ENTRY'!$A$7:$A$1203,'DAILY ENTRY'!$A$7:$A$1203&"",'DAILY ENTRY'!$B$7:$B$1203,'DAILY ENTRY'!$B$7:$B$1203&"")),0)) | C6: =IF($A6="","",SUMIFS('DAILY ENTRY'!$F$7:$F$1203,'DAILY ENTRY'!$D$7:$D$1203,"Lead researched (Sales Navigator)",'DAILY ENTRY'!$B$7:$B$1203,$A6)) | D6: =IF($A6="","",COUNTIFS('LinkedIn Outreach'!$B$5:$B$1203,$A6,'LinkedIn Outreach'!$M$5:$M$1203,"Yes")) | E6: =IF($A6="","",COUNTIFS('LinkedIn Outreach'!$B$5:$B$1203,$A6,'LinkedIn Outreach'!$N$5:$N$1203,"Yes")) | F6: =IF($A6="","",IFERROR(E6/D6,"")) | G6: =IF($A6="","",COUNTIFS('LinkedIn Outreach'!$B$5:$B$1203,$A6,'LinkedIn Outreach'!$R$5:$R$1203,"Yes")) | H6: =IF($A6="","",COUNTIFS('LinkedIn Outreach'!$B$5:$B$1203,$A6,'LinkedIn Outreach'!$S$5:$S$1203,"Interested")+COUNTIFS('LinkedIn Outreach'!$B$5:$B$1203,$A6,'LinkedIn Outreach'!$S$5:$S$1203,"Info Requested")+COUNTIFS('LinkedIn Outreach'!$B$5:$B$1203,$A6,'LinkedIn Outreach'!$S$5:$S$1203,"Meeting Booked")+COUNTIFS('LinkedIn Outreach'!$B$5:$B$1203,$A6,'LinkedIn Outreach'!$S$5:$S$1203,"Converted")) | I6: =IF($A6="","",IFERROR(H6/G6,"")) | J6: =IF($A6="","",COUNTIFS('LinkedIn Outreach'!$B$5:$B$1203,$A6,'LinkedIn Outreach'!$S$5:$S$1203,"Meeting Booked")) | K6: =IF($A6="","",SUMIFS('DAILY ENTRY'!$F$7:$F$1203,'DAILY ENTRY'!$D$7:$D$1203,"Post / content published",'DAILY ENTRY'!$B$7:$B$1203,$A6)) | L6: =IF($A6="","",SUMIFS('DAILY ENTRY'!$F$7:$F$1203,'DAILY ENTRY'!$D$7:$D$1203,"Community answer or comment",'DAILY ENTRY'!$B$7:$B$1203,$A6)) | M6: =IF($A6="","",SUMIFS('DAILY ENTRY'!$F$7:$F$1203,'DAILY ENTRY'!$D$7:$D$1203,"Partnership / PR contact",'DAILY ENTRY'!$B$7:$B$1203,$A6)) | N6: =IF($A6="","",SUMIFS('DAILY ENTRY'!$F$7:$F$1203,'DAILY ENTRY'!$D$7:$D$1203,"Engagement (commented on someone else)",'DAILY ENTRY'!$B$7:$B$1203,$A6)) | O6: =IF($A6="","",COUNTIFS('LinkedIn Outreach'!$B$5:$B$1203,$A6,'LinkedIn Outreach'!$Q$5:$Q$1203,">300")) | P6: =IF($A6="","",COUNTIFS('DAILY ENTRY'!$B$7:$B$1203,$A6,'DAILY ENTRY'!$I$7:$I$1203,"Blocked")) | Q6: =IF($A6="","",IF(AND(B6=0,D6=0),"No activity logged yet",IF(O6>0,"BREACH: sent messages over the 300-character limit - review the message text",IF(AND(D6>=20,F6<0.2),"Acceptance below 20% - fix targeting or the connection note before sending more",IF(AND(G6>=20,I6<0.1),"Reply rate below the 10% average - the message needs rewriting, not more volume",IF(AND(F6>=0.3,I6>=0.15),"Strong: both acceptance and reply rate are above benchmark",IF(AND(B6>0,D6=0),"Logging daily work but no LinkedIn outreach recorded","Within normal range - compare against the Benchmarks tab"))))))) | R6: =IF($A6="","",COUNTIF('Master Tasks'!$I$4:$I$66,$A6)) | S6: =IF($A6="","",COUNTIFS('Master Tasks'!$I$4:$I$66,$A6,'Master Tasks'!$J$4:$J$66,"Complete")) | T6: =IF($A6="","",IFERROR(S6/R6,"")) | U6: =IF($A6="","",COUNTIFS('Platform Setup'!$M$4:$M$49,$A6,'Platform Setup'!$J$4:$J$49,"Complete")) | V6: =IF($A6="","",COUNTIFS('Content Calendar'!$B$5:$B$403,$A6,'Content Calendar'!$J$5:$J$403,"Published")+COUNTIFS('Content Calendar'!$B$5:$B$403,$A6,'Content Calendar'!$J$5:$J$403,"Repurposed"))
A7: =IF('START HERE'!$B$58="","",'START HERE'!$B$58) | B7: =IF($A7="","",IFERROR(SUMPRODUCT(('DAILY ENTRY'!$B$7:$B$1203=$A7)*('DAILY ENTRY'!$A$7:$A$1203<>"")/COUNTIFS('DAILY ENTRY'!$A$7:$A$1203,'DAILY ENTRY'!$A$7:$A$1203&"",'DAILY ENTRY'!$B$7:$B$1203,'DAILY ENTRY'!$B$7:$B$1203&"")),0)) | C7: =IF($A7="","",SUMIFS('DAILY ENTRY'!$F$7:$F$1203,'DAILY ENTRY'!$D$7:$D$1203,"Lead researched (Sales Navigator)",'DAILY ENTRY'!$B$7:$B$1203,$A7)) | D7: =IF($A7="","",COUNTIFS('LinkedIn Outreach'!$B$5:$B$1203,$A7,'LinkedIn Outreach'!$M$5:$M$1203,"Yes")) | E7: =IF($A7="","",COUNTIFS('LinkedIn Outreach'!$B$5:$B$1203,$A7,'LinkedIn Outreach'!$N$5:$N$1203,"Yes")) | F7: =IF($A7="","",IFERROR(E7/D7,"")) | G7: =IF($A7="","",COUNTIFS('LinkedIn Outreach'!$B$5:$B$1203,$A7,'LinkedIn Outreach'!$R$5:$R$1203,"Yes")) | H7: =IF($A7="","",COUNTIFS('LinkedIn Outreach'!$B$5:$B$1203,$A7,'LinkedIn Outreach'!$S$5:$S$1203,"Interested")+COUNTIFS('LinkedIn Outreach'!$B$5:$B$1203,$A7,'LinkedIn Outreach'!$S$5:$S$1203,"Info Requested")+COUNTIFS('LinkedIn Outreach'!$B$5:$B$1203,$A7,'LinkedIn Outreach'!$S$5:$S$1203,"Meeting Booked")+COUNTIFS('LinkedIn Outreach'!$B$5:$B$1203,$A7,'LinkedIn Outreach'!$S$5:$S$1203,"Converted")) | I7: =IF($A7="","",IFERROR(H7/G7,"")) | J7: =IF($A7="","",COUNTIFS('LinkedIn Outreach'!$B$5:$B$1203,$A7,'LinkedIn Outreach'!$S$5:$S$1203,"Meeting Booked")) | K7: =IF($A7="","",SUMIFS('DAILY ENTRY'!$F$7:$F$1203,'DAILY ENTRY'!$D$7:$D$1203,"Post / content published",'DAILY ENTRY'!$B$7:$B$1203,$A7)) | L7: =IF($A7="","",SUMIFS('DAILY ENTRY'!$F$7:$F$1203,'DAILY ENTRY'!$D$7:$D$1203,"Community answer or comment",'DAILY ENTRY'!$B$7:$B$1203,$A7)) | M7: =IF($A7="","",SUMIFS('DAILY ENTRY'!$F$7:$F$1203,'DAILY ENTRY'!$D$7:$D$1203,"Partnership / PR contact",'DAILY ENTRY'!$B$7:$B$1203,$A7)) | N7: =IF($A7="","",SUMIFS('DAILY ENTRY'!$F$7:$F$1203,'DAILY ENTRY'!$D$7:$D$1203,"Engagement (commented on someone else)",'DAILY ENTRY'!$B$7:$B$1203,$A7)) | O7: =IF($A7="","",COUNTIFS('LinkedIn Outreach'!$B$5:$B$1203,$A7,'LinkedIn Outreach'!$Q$5:$Q$1203,">300")) | P7: =IF($A7="","",COUNTIFS('DAILY ENTRY'!$B$7:$B$1203,$A7,'DAILY ENTRY'!$I$7:$I$1203,"Blocked")) | Q7: =IF($A7="","",IF(AND(B7=0,D7=0),"No activity logged yet",IF(O7>0,"BREACH: sent messages over the 300-character limit - review the message text",IF(AND(D7>=20,F7<0.2),"Acceptance below 20% - fix targeting or the connection note before sending more",IF(AND(G7>=20,I7<0.1),"Reply rate below the 10% average - the message needs rewriting, not more volume",IF(AND(F7>=0.3,I7>=0.15),"Strong: both acceptance and reply rate are above benchmark",IF(AND(B7>0,D7=0),"Logging daily work but no LinkedIn outreach recorded","Within normal range - compare against the Benchmarks tab"))))))) | R7: =IF($A7="","",COUNTIF('Master Tasks'!$I$4:$I$66,$A7)) | S7: =IF($A7="","",COUNTIFS('Master Tasks'!$I$4:$I$66,$A7,'Master Tasks'!$J$4:$J$66,"Complete")) | T7: =IF($A7="","",IFERROR(S7/R7,"")) | U7: =IF($A7="","",COUNTIFS('Platform Setup'!$M$4:$M$49,$A7,'Platform Setup'!$J$4:$J$49,"Complete")) | V7: =IF($A7="","",COUNTIFS('Content Calendar'!$B$5:$B$403,$A7,'Content Calendar'!$J$5:$J$403,"Published")+COUNTIFS('Content Calendar'!$B$5:$B$403,$A7,'Content Calendar'!$J$5:$J$403,"Repurposed"))
A8: =IF('START HERE'!$B$59="","",'START HERE'!$B$59) | B8: =IF($A8="","",IFERROR(SUMPRODUCT(('DAILY ENTRY'!$B$7:$B$1203=$A8)*('DAILY ENTRY'!$A$7:$A$1203<>"")/COUNTIFS('DAILY ENTRY'!$A$7:$A$1203,'DAILY ENTRY'!$A$7:$A$1203&"",'DAILY ENTRY'!$B$7:$B$1203,'DAILY ENTRY'!$B$7:$B$1203&"")),0)) | C8: =IF($A8="","",SUMIFS('DAILY ENTRY'!$F$7:$F$1203,'DAILY ENTRY'!$D$7:$D$1203,"Lead researched (Sales Navigator)",'DAILY ENTRY'!$B$7:$B$1203,$A8)) | D8: =IF($A8="","",COUNTIFS('LinkedIn Outreach'!$B$5:$B$1203,$A8,'LinkedIn Outreach'!$M$5:$M$1203,"Yes")) | E8: =IF($A8="","",COUNTIFS('LinkedIn Outreach'!$B$5:$B$1203,$A8,'LinkedIn Outreach'!$N$5:$N$1203,"Yes")) | F8: =IF($A8="","",IFERROR(E8/D8,"")) | G8: =IF($A8="","",COUNTIFS('LinkedIn Outreach'!$B$5:$B$1203,$A8,'LinkedIn Outreach'!$R$5:$R$1203,"Yes")) | H8: =IF($A8="","",COUNTIFS('LinkedIn Outreach'!$B$5:$B$1203,$A8,'LinkedIn Outreach'!$S$5:$S$1203,"Interested")+COUNTIFS('LinkedIn Outreach'!$B$5:$B$1203,$A8,'LinkedIn Outreach'!$S$5:$S$1203,"Info Requested")+COUNTIFS('LinkedIn Outreach'!$B$5:$B$1203,$A8,'LinkedIn Outreach'!$S$5:$S$1203,"Meeting Booked")+COUNTIFS('LinkedIn Outreach'!$B$5:$B$1203,$A8,'LinkedIn Outreach'!$S$5:$S$1203,"Converted")) | I8: =IF($A8="","",IFERROR(H8/G8,"")) | J8: =IF($A8="","",COUNTIFS('LinkedIn Outreach'!$B$5:$B$1203,$A8,'LinkedIn Outreach'!$S$5:$S$1203,"Meeting Booked")) | K8: =IF($A8="","",SUMIFS('DAILY ENTRY'!$F$7:$F$1203,'DAILY ENTRY'!$D$7:$D$1203,"Post / content published",'DAILY ENTRY'!$B$7:$B$1203,$A8)) | L8: =IF($A8="","",SUMIFS('DAILY ENTRY'!$F$7:$F$1203,'DAILY ENTRY'!$D$7:$D$1203,"Community answer or comment",'DAILY ENTRY'!$B$7:$B$1203,$A8)) | M8: =IF($A8="","",SUMIFS('DAILY ENTRY'!$F$7:$F$1203,'DAILY ENTRY'!$D$7:$D$1203,"Partnership / PR contact",'DAILY ENTRY'!$B$7:$B$1203,$A8)) | N8: =IF($A8="","",SUMIFS('DAILY ENTRY'!$F$7:$F$1203,'DAILY ENTRY'!$D$7:$D$1203,"Engagement (commented on someone else)",'DAILY ENTRY'!$B$7:$B$1203,$A8)) | O8: =IF($A8="","",COUNTIFS('LinkedIn Outreach'!$B$5:$B$1203,$A8,'LinkedIn Outreach'!$Q$5:$Q$1203,">300")) | P8: =IF($A8="","",COUNTIFS('DAILY ENTRY'!$B$7:$B$1203,$A8,'DAILY ENTRY'!$I$7:$I$1203,"Blocked")) | Q8: =IF($A8="","",IF(AND(B8=0,D8=0),"No activity logged yet",IF(O8>0,"BREACH: sent messages over the 300-character limit - review the message text",IF(AND(D8>=20,F8<0.2),"Acceptance below 20% - fix targeting or the connection note before sending more",IF(AND(G8>=20,I8<0.1),"Reply rate below the 10% average - the message needs rewriting, not more volume",IF(AND(F8>=0.3,I8>=0.15),"Strong: both acceptance and reply rate are above benchmark",IF(AND(B8>0,D8=0),"Logging daily work but no LinkedIn outreach recorded","Within normal range - compare against the Benchmarks tab"))))))) | R8: =IF($A8="","",COUNTIF('Master Tasks'!$I$4:$I$66,$A8)) | S8: =IF($A8="","",COUNTIFS('Master Tasks'!$I$4:$I$66,$A8,'Master Tasks'!$J$4:$J$66,"Complete")) | T8: =IF($A8="","",IFERROR(S8/R8,"")) | U8: =IF($A8="","",COUNTIFS('Platform Setup'!$M$4:$M$49,$A8,'Platform Setup'!$J$4:$J$49,"Complete")) | V8: =IF($A8="","",COUNTIFS('Content Calendar'!$B$5:$B$403,$A8,'Content Calendar'!$J$5:$J$403,"Published")+COUNTIFS('Content Calendar'!$B$5:$B$403,$A8,'Content Calendar'!$J$5:$J$403,"Repurposed"))
A9: =IF('START HERE'!$B$60="","",'START HERE'!$B$60) | B9: =IF($A9="","",IFERROR(SUMPRODUCT(('DAILY ENTRY'!$B$7:$B$1203=$A9)*('DAILY ENTRY'!$A$7:$A$1203<>"")/COUNTIFS('DAILY ENTRY'!$A$7:$A$1203,'DAILY ENTRY'!$A$7:$A$1203&"",'DAILY ENTRY'!$B$7:$B$1203,'DAILY ENTRY'!$B$7:$B$1203&"")),0)) | C9: =IF($A9="","",SUMIFS('DAILY ENTRY'!$F$7:$F$1203,'DAILY ENTRY'!$D$7:$D$1203,"Lead researched (Sales Navigator)",'DAILY ENTRY'!$B$7:$B$1203,$A9)) | D9: =IF($A9="","",COUNTIFS('LinkedIn Outreach'!$B$5:$B$1203,$A9,'LinkedIn Outreach'!$M$5:$M$1203,"Yes")) | E9: =IF($A9="","",COUNTIFS('LinkedIn Outreach'!$B$5:$B$1203,$A9,'LinkedIn Outreach'!$N$5:$N$1203,"Yes")) | F9: =IF($A9="","",IFERROR(E9/D9,"")) | G9: =IF($A9="","",COUNTIFS('LinkedIn Outreach'!$B$5:$B$1203,$A9,'LinkedIn Outreach'!$R$5:$R$1203,"Yes")) | H9: =IF($A9="","",COUNTIFS('LinkedIn Outreach'!$B$5:$B$1203,$A9,'LinkedIn Outreach'!$S$5:$S$1203,"Interested")+COUNTIFS('LinkedIn Outreach'!$B$5:$B$1203,$A9,'LinkedIn Outreach'!$S$5:$S$1203,"Info Requested")+COUNTIFS('LinkedIn Outreach'!$B$5:$B$1203,$A9,'LinkedIn Outreach'!$S$5:$S$1203,"Meeting Booked")+COUNTIFS('LinkedIn Outreach'!$B$5:$B$1203,$A9,'LinkedIn Outreach'!$S$5:$S$1203,"Converted")) | I9: =IF($A9="","",IFERROR(H9/G9,"")) | J9: =IF($A9="","",COUNTIFS('LinkedIn Outreach'!$B$5:$B$1203,$A9,'LinkedIn Outreach'!$S$5:$S$1203,"Meeting Booked")) | K9: =IF($A9="","",SUMIFS('DAILY ENTRY'!$F$7:$F$1203,'DAILY ENTRY'!$D$7:$D$1203,"Post / content published",'DAILY ENTRY'!$B$7:$B$1203,$A9)) | L9: =IF($A9="","",SUMIFS('DAILY ENTRY'!$F$7:$F$1203,'DAILY ENTRY'!$D$7:$D$1203,"Community answer or comment",'DAILY ENTRY'!$B$7:$B$1203,$A9)) | M9: =IF($A9="","",SUMIFS('DAILY ENTRY'!$F$7:$F$1203,'DAILY ENTRY'!$D$7:$D$1203,"Partnership / PR contact",'DAILY ENTRY'!$B$7:$B$1203,$A9)) | N9: =IF($A9="","",SUMIFS('DAILY ENTRY'!$F$7:$F$1203,'DAILY ENTRY'!$D$7:$D$1203,"Engagement (commented on someone else)",'DAILY ENTRY'!$B$7:$B$1203,$A9)) | O9: =IF($A9="","",COUNTIFS('LinkedIn Outreach'!$B$5:$B$1203,$A9,'LinkedIn Outreach'!$Q$5:$Q$1203,">300")) | P9: =IF($A9="","",COUNTIFS('DAILY ENTRY'!$B$7:$B$1203,$A9,'DAILY ENTRY'!$I$7:$I$1203,"Blocked")) | Q9: =IF($A9="","",IF(AND(B9=0,D9=0),"No activity logged yet",IF(O9>0,"BREACH: sent messages over the 300-character limit - review the message text",IF(AND(D9>=20,F9<0.2),"Acceptance below 20% - fix targeting or the connection note before sending more",IF(AND(G9>=20,I9<0.1),"Reply rate below the 10% average - the message needs rewriting, not more volume",IF(AND(F9>=0.3,I9>=0.15),"Strong: both acceptance and reply rate are above benchmark",IF(AND(B9>0,D9=0),"Logging daily work but no LinkedIn outreach recorded","Within normal range - compare against the Benchmarks tab"))))))) | R9: =IF($A9="","",COUNTIF('Master Tasks'!$I$4:$I$66,$A9)) | S9: =IF($A9="","",COUNTIFS('Master Tasks'!$I$4:$I$66,$A9,'Master Tasks'!$J$4:$J$66,"Complete")) | T9: =IF($A9="","",IFERROR(S9/R9,"")) | U9: =IF($A9="","",COUNTIFS('Platform Setup'!$M$4:$M$49,$A9,'Platform Setup'!$J$4:$J$49,"Complete")) | V9: =IF($A9="","",COUNTIFS('Content Calendar'!$B$5:$B$403,$A9,'Content Calendar'!$J$5:$J$403,"Published")+COUNTIFS('Content Calendar'!$B$5:$B$403,$A9,'Content Calendar'!$J$5:$J$403,"Repurposed"))
A10: =IF('START HERE'!$B$61="","",'START HERE'!$B$61) | B10: =IF($A10="","",IFERROR(SUMPRODUCT(('DAILY ENTRY'!$B$7:$B$1203=$A10)*('DAILY ENTRY'!$A$7:$A$1203<>"")/COUNTIFS('DAILY ENTRY'!$A$7:$A$1203,'DAILY ENTRY'!$A$7:$A$1203&"",'DAILY ENTRY'!$B$7:$B$1203,'DAILY ENTRY'!$B$7:$B$1203&"")),0)) | C10: =IF($A10="","",SUMIFS('DAILY ENTRY'!$F$7:$F$1203,'DAILY ENTRY'!$D$7:$D$1203,"Lead researched (Sales Navigator)",'DAILY ENTRY'!$B$7:$B$1203,$A10)) | D10: =IF($A10="","",COUNTIFS('LinkedIn Outreach'!$B$5:$B$1203,$A10,'LinkedIn Outreach'!$M$5:$M$1203,"Yes")) | E10: =IF($A10="","",COUNTIFS('LinkedIn Outreach'!$B$5:$B$1203,$A10,'LinkedIn Outreach'!$N$5:$N$1203,"Yes")) | F10: =IF($A10="","",IFERROR(E10/D10,"")) | G10: =IF($A10="","",COUNTIFS('LinkedIn Outreach'!$B$5:$B$1203,$A10,'LinkedIn Outreach'!$R$5:$R$1203,"Yes")) | H10: =IF($A10="","",COUNTIFS('LinkedIn Outreach'!$B$5:$B$1203,$A10,'LinkedIn Outreach'!$S$5:$S$1203,"Interested")+COUNTIFS('LinkedIn Outreach'!$B$5:$B$1203,$A10,'LinkedIn Outreach'!$S$5:$S$1203,"Info Requested")+COUNTIFS('LinkedIn Outreach'!$B$5:$B$1203,$A10,'LinkedIn Outreach'!$S$5:$S$1203,"Meeting Booked")+COUNTIFS('LinkedIn Outreach'!$B$5:$B$1203,$A10,'LinkedIn Outreach'!$S$5:$S$1203,"Converted")) | I10: =IF($A10="","",IFERROR(H10/G10,"")) | J10: =IF($A10="","",COUNTIFS('LinkedIn Outreach'!$B$5:$B$1203,$A10,'LinkedIn Outreach'!$S$5:$S$1203,"Meeting Booked")) | K10: =IF($A10="","",SUMIFS('DAILY ENTRY'!$F$7:$F$1203,'DAILY ENTRY'!$D$7:$D$1203,"Post / content published",'DAILY ENTRY'!$B$7:$B$1203,$A10)) | L10: =IF($A10="","",SUMIFS('DAILY ENTRY'!$F$7:$F$1203,'DAILY ENTRY'!$D$7:$D$1203,"Community answer or comment",'DAILY ENTRY'!$B$7:$B$1203,$A10)) | M10: =IF($A10="","",SUMIFS('DAILY ENTRY'!$F$7:$F$1203,'DAILY ENTRY'!$D$7:$D$1203,"Partnership / PR contact",'DAILY ENTRY'!$B$7:$B$1203,$A10)) | N10: =IF($A10="","",SUMIFS('DAILY ENTRY'!$F$7:$F$1203,'DAILY ENTRY'!$D$7:$D$1203,"Engagement (commented on someone else)",'DAILY ENTRY'!$B$7:$B$1203,$A10)) | O10: =IF($A10="","",COUNTIFS('LinkedIn Outreach'!$B$5:$B$1203,$A10,'LinkedIn Outreach'!$Q$5:$Q$1203,">300")) | P10: =IF($A10="","",COUNTIFS('DAILY ENTRY'!$B$7:$B$1203,$A10,'DAILY ENTRY'!$I$7:$I$1203,"Blocked")) | Q10: =IF($A10="","",IF(AND(B10=0,D10=0),"No activity logged yet",IF(O10>0,"BREACH: sent messages over the 300-character limit - review the message text",IF(AND(D10>=20,F10<0.2),"Acceptance below 20% - fix targeting or the connection note before sending more",IF(AND(G10>=20,I10<0.1),"Reply rate below the 10% average - the message needs rewriting, not more volume",IF(AND(F10>=0.3,I10>=0.15),"Strong: both acceptance and reply rate are above benchmark",IF(AND(B10>0,D10=0),"Logging daily work but no LinkedIn outreach recorded","Within normal range - compare against the Benchmarks tab"))))))) | R10: =IF($A10="","",COUNTIF('Master Tasks'!$I$4:$I$66,$A10)) | S10: =IF($A10="","",COUNTIFS('Master Tasks'!$I$4:$I$66,$A10,'Master Tasks'!$J$4:$J$66,"Complete")) | T10: =IF($A10="","",IFERROR(S10/R10,"")) | U10: =IF($A10="","",COUNTIFS('Platform Setup'!$M$4:$M$49,$A10,'Platform Setup'!$J$4:$J$49,"Complete")) | V10: =IF($A10="","",COUNTIFS('Content Calendar'!$B$5:$B$403,$A10,'Content Calendar'!$J$5:$J$403,"Published")+COUNTIFS('Content Calendar'!$B$5:$B$403,$A10,'Content Calendar'!$J$5:$J$403,"Repurposed"))
A11: =IF('START HERE'!$B$62="","",'START HERE'!$B$62) | B11: =IF($A11="","",IFERROR(SUMPRODUCT(('DAILY ENTRY'!$B$7:$B$1203=$A11)*('DAILY ENTRY'!$A$7:$A$1203<>"")/COUNTIFS('DAILY ENTRY'!$A$7:$A$1203,'DAILY ENTRY'!$A$7:$A$1203&"",'DAILY ENTRY'!$B$7:$B$1203,'DAILY ENTRY'!$B$7:$B$1203&"")),0)) | C11: =IF($A11="","",SUMIFS('DAILY ENTRY'!$F$7:$F$1203,'DAILY ENTRY'!$D$7:$D$1203,"Lead researched (Sales Navigator)",'DAILY ENTRY'!$B$7:$B$1203,$A11)) | D11: =IF($A11="","",COUNTIFS('LinkedIn Outreach'!$B$5:$B$1203,$A11,'LinkedIn Outreach'!$M$5:$M$1203,"Yes")) | E11: =IF($A11="","",COUNTIFS('LinkedIn Outreach'!$B$5:$B$1203,$A11,'LinkedIn Outreach'!$N$5:$N$1203,"Yes")) | F11: =IF($A11="","",IFERROR(E11/D11,"")) | G11: =IF($A11="","",COUNTIFS('LinkedIn Outreach'!$B$5:$B$1203,$A11,'LinkedIn Outreach'!$R$5:$R$1203,"Yes")) | H11: =IF($A11="","",COUNTIFS('LinkedIn Outreach'!$B$5:$B$1203,$A11,'LinkedIn Outreach'!$S$5:$S$1203,"Interested")+COUNTIFS('LinkedIn Outreach'!$B$5:$B$1203,$A11,'LinkedIn Outreach'!$S$5:$S$1203,"Info Requested")+COUNTIFS('LinkedIn Outreach'!$B$5:$B$1203,$A11,'LinkedIn Outreach'!$S$5:$S$1203,"Meeting Booked")+COUNTIFS('LinkedIn Outreach'!$B$5:$B$1203,$A11,'LinkedIn Outreach'!$S$5:$S$1203,"Converted")) | I11: =IF($A11="","",IFERROR(H11/G11,"")) | J11: =IF($A11="","",COUNTIFS('LinkedIn Outreach'!$B$5:$B$1203,$A11,'LinkedIn Outreach'!$S$5:$S$1203,"Meeting Booked")) | K11: =IF($A11="","",SUMIFS('DAILY ENTRY'!$F$7:$F$1203,'DAILY ENTRY'!$D$7:$D$1203,"Post / content published",'DAILY ENTRY'!$B$7:$B$1203,$A11)) | L11: =IF($A11="","",SUMIFS('DAILY ENTRY'!$F$7:$F$1203,'DAILY ENTRY'!$D$7:$D$1203,"Community answer or comment",'DAILY ENTRY'!$B$7:$B$1203,$A11)) | M11: =IF($A11="","",SUMIFS('DAILY ENTRY'!$F$7:$F$1203,'DAILY ENTRY'!$D$7:$D$1203,"Partnership / PR contact",'DAILY ENTRY'!$B$7:$B$1203,$A11)) | N11: =IF($A11="","",SUMIFS('DAILY ENTRY'!$F$7:$F$1203,'DAILY ENTRY'!$D$7:$D$1203,"Engagement (commented on someone else)",'DAILY ENTRY'!$B$7:$B$1203,$A11)) | O11: =IF($A11="","",COUNTIFS('LinkedIn Outreach'!$B$5:$B$1203,$A11,'LinkedIn Outreach'!$Q$5:$Q$1203,">300")) | P11: =IF($A11="","",COUNTIFS('DAILY ENTRY'!$B$7:$B$1203,$A11,'DAILY ENTRY'!$I$7:$I$1203,"Blocked")) | Q11: =IF($A11="","",IF(AND(B11=0,D11=0),"No activity logged yet",IF(O11>0,"BREACH: sent messages over the 300-character limit - review the message text",IF(AND(D11>=20,F11<0.2),"Acceptance below 20% - fix targeting or the connection note before sending more",IF(AND(G11>=20,I11<0.1),"Reply rate below the 10% average - the message needs rewriting, not more volume",IF(AND(F11>=0.3,I11>=0.15),"Strong: both acceptance and reply rate are above benchmark",IF(AND(B11>0,D11=0),"Logging daily work but no LinkedIn outreach recorded","Within normal range - compare against the Benchmarks tab"))))))) | R11: =IF($A11="","",COUNTIF('Master Tasks'!$I$4:$I$66,$A11)) | S11: =IF($A11="","",COUNTIFS('Master Tasks'!$I$4:$I$66,$A11,'Master Tasks'!$J$4:$J$66,"Complete")) | T11: =IF($A11="","",IFERROR(S11/R11,"")) | U11: =IF($A11="","",COUNTIFS('Platform Setup'!$M$4:$M$49,$A11,'Platform Setup'!$J$4:$J$49,"Complete")) | V11: =IF($A11="","",COUNTIFS('Content Calendar'!$B$5:$B$403,$A11,'Content Calendar'!$J$5:$J$403,"Published")+COUNTIFS('Content Calendar'!$B$5:$B$403,$A11,'Content Calendar'!$J$5:$J$403,"Repurposed"))
A12: =IF('START HERE'!$B$63="","",'START HERE'!$B$63) | B12: =IF($A12="","",IFERROR(SUMPRODUCT(('DAILY ENTRY'!$B$7:$B$1203=$A12)*('DAILY ENTRY'!$A$7:$A$1203<>"")/COUNTIFS('DAILY ENTRY'!$A$7:$A$1203,'DAILY ENTRY'!$A$7:$A$1203&"",'DAILY ENTRY'!$B$7:$B$1203,'DAILY ENTRY'!$B$7:$B$1203&"")),0)) | C12: =IF($A12="","",SUMIFS('DAILY ENTRY'!$F$7:$F$1203,'DAILY ENTRY'!$D$7:$D$1203,"Lead researched (Sales Navigator)",'DAILY ENTRY'!$B$7:$B$1203,$A12)) | D12: =IF($A12="","",COUNTIFS('LinkedIn Outreach'!$B$5:$B$1203,$A12,'LinkedIn Outreach'!$M$5:$M$1203,"Yes")) | E12: =IF($A12="","",COUNTIFS('LinkedIn Outreach'!$B$5:$B$1203,$A12,'LinkedIn Outreach'!$N$5:$N$1203,"Yes")) | F12: =IF($A12="","",IFERROR(E12/D12,"")) | G12: =IF($A12="","",COUNTIFS('LinkedIn Outreach'!$B$5:$B$1203,$A12,'LinkedIn Outreach'!$R$5:$R$1203,"Yes")) | H12: =IF($A12="","",COUNTIFS('LinkedIn Outreach'!$B$5:$B$1203,$A12,'LinkedIn Outreach'!$S$5:$S$1203,"Interested")+COUNTIFS('LinkedIn Outreach'!$B$5:$B$1203,$A12,'LinkedIn Outreach'!$S$5:$S$1203,"Info Requested")+COUNTIFS('LinkedIn Outreach'!$B$5:$B$1203,$A12,'LinkedIn Outreach'!$S$5:$S$1203,"Meeting Booked")+COUNTIFS('LinkedIn Outreach'!$B$5:$B$1203,$A12,'LinkedIn Outreach'!$S$5:$S$1203,"Converted")) | I12: =IF($A12="","",IFERROR(H12/G12,"")) | J12: =IF($A12="","",COUNTIFS('LinkedIn Outreach'!$B$5:$B$1203,$A12,'LinkedIn Outreach'!$S$5:$S$1203,"Meeting Booked")) | K12: =IF($A12="","",SUMIFS('DAILY ENTRY'!$F$7:$F$1203,'DAILY ENTRY'!$D$7:$D$1203,"Post / content published",'DAILY ENTRY'!$B$7:$B$1203,$A12)) | L12: =IF($A12="","",SUMIFS('DAILY ENTRY'!$F$7:$F$1203,'DAILY ENTRY'!$D$7:$D$1203,"Community answer or comment",'DAILY ENTRY'!$B$7:$B$1203,$A12)) | M12: =IF($A12="","",SUMIFS('DAILY ENTRY'!$F$7:$F$1203,'DAILY ENTRY'!$D$7:$D$1203,"Partnership / PR contact",'DAILY ENTRY'!$B$7:$B$1203,$A12)) | N12: =IF($A12="","",SUMIFS('DAILY ENTRY'!$F$7:$F$1203,'DAILY ENTRY'!$D$7:$D$1203,"Engagement (commented on someone else)",'DAILY ENTRY'!$B$7:$B$1203,$A12)) | O12: =IF($A12="","",COUNTIFS('LinkedIn Outreach'!$B$5:$B$1203,$A12,'LinkedIn Outreach'!$Q$5:$Q$1203,">300")) | P12: =IF($A12="","",COUNTIFS('DAILY ENTRY'!$B$7:$B$1203,$A12,'DAILY ENTRY'!$I$7:$I$1203,"Blocked")) | Q12: =IF($A12="","",IF(AND(B12=0,D12=0),"No activity logged yet",IF(O12>0,"BREACH: sent messages over the 300-character limit - review the message text",IF(AND(D12>=20,F12<0.2),"Acceptance below 20% - fix targeting or the connection note before sending more",IF(AND(G12>=20,I12<0.1),"Reply rate below the 10% average - the message needs rewriting, not more volume",IF(AND(F12>=0.3,I12>=0.15),"Strong: both acceptance and reply rate are above benchmark",IF(AND(B12>0,D12=0),"Logging daily work but no LinkedIn outreach recorded","Within normal range - compare against the Benchmarks tab"))))))) | R12: =IF($A12="","",COUNTIF('Master Tasks'!$I$4:$I$66,$A12)) | S12: =IF($A12="","",COUNTIFS('Master Tasks'!$I$4:$I$66,$A12,'Master Tasks'!$J$4:$J$66,"Complete")) | T12: =IF($A12="","",IFERROR(S12/R12,"")) | U12: =IF($A12="","",COUNTIFS('Platform Setup'!$M$4:$M$49,$A12,'Platform Setup'!$J$4:$J$49,"Complete")) | V12: =IF($A12="","",COUNTIFS('Content Calendar'!$B$5:$B$403,$A12,'Content Calendar'!$J$5:$J$403,"Published")+COUNTIFS('Content Calendar'!$B$5:$B$403,$A12,'Content Calendar'!$J$5:$J$403,"Repurposed"))
A13: =IF('START HERE'!$B$64="","",'START HERE'!$B$64) | B13: =IF($A13="","",IFERROR(SUMPRODUCT(('DAILY ENTRY'!$B$7:$B$1203=$A13)*('DAILY ENTRY'!$A$7:$A$1203<>"")/COUNTIFS('DAILY ENTRY'!$A$7:$A$1203,'DAILY ENTRY'!$A$7:$A$1203&"",'DAILY ENTRY'!$B$7:$B$1203,'DAILY ENTRY'!$B$7:$B$1203&"")),0)) | C13: =IF($A13="","",SUMIFS('DAILY ENTRY'!$F$7:$F$1203,'DAILY ENTRY'!$D$7:$D$1203,"Lead researched (Sales Navigator)",'DAILY ENTRY'!$B$7:$B$1203,$A13)) | D13: =IF($A13="","",COUNTIFS('LinkedIn Outreach'!$B$5:$B$1203,$A13,'LinkedIn Outreach'!$M$5:$M$1203,"Yes")) | E13: =IF($A13="","",COUNTIFS('LinkedIn Outreach'!$B$5:$B$1203,$A13,'LinkedIn Outreach'!$N$5:$N$1203,"Yes")) | F13: =IF($A13="","",IFERROR(E13/D13,"")) | G13: =IF($A13="","",COUNTIFS('LinkedIn Outreach'!$B$5:$B$1203,$A13,'LinkedIn Outreach'!$R$5:$R$1203,"Yes")) | H13: =IF($A13="","",COUNTIFS('LinkedIn Outreach'!$B$5:$B$1203,$A13,'LinkedIn Outreach'!$S$5:$S$1203,"Interested")+COUNTIFS('LinkedIn Outreach'!$B$5:$B$1203,$A13,'LinkedIn Outreach'!$S$5:$S$1203,"Info Requested")+COUNTIFS('LinkedIn Outreach'!$B$5:$B$1203,$A13,'LinkedIn Outreach'!$S$5:$S$1203,"Meeting Booked")+COUNTIFS('LinkedIn Outreach'!$B$5:$B$1203,$A13,'LinkedIn Outreach'!$S$5:$S$1203,"Converted")) | I13: =IF($A13="","",IFERROR(H13/G13,"")) | J13: =IF($A13="","",COUNTIFS('LinkedIn Outreach'!$B$5:$B$1203,$A13,'LinkedIn Outreach'!$S$5:$S$1203,"Meeting Booked")) | K13: =IF($A13="","",SUMIFS('DAILY ENTRY'!$F$7:$F$1203,'DAILY ENTRY'!$D$7:$D$1203,"Post / content published",'DAILY ENTRY'!$B$7:$B$1203,$A13)) | L13: =IF($A13="","",SUMIFS('DAILY ENTRY'!$F$7:$F$1203,'DAILY ENTRY'!$D$7:$D$1203,"Community answer or comment",'DAILY ENTRY'!$B$7:$B$1203,$A13)) | M13: =IF($A13="","",SUMIFS('DAILY ENTRY'!$F$7:$F$1203,'DAILY ENTRY'!$D$7:$D$1203,"Partnership / PR contact",'DAILY ENTRY'!$B$7:$B$1203,$A13)) | N13: =IF($A13="","",SUMIFS('DAILY ENTRY'!$F$7:$F$1203,'DAILY ENTRY'!$D$7:$D$1203,"Engagement (commented on someone else)",'DAILY ENTRY'!$B$7:$B$1203,$A13)) | O13: =IF($A13="","",COUNTIFS('LinkedIn Outreach'!$B$5:$B$1203,$A13,'LinkedIn Outreach'!$Q$5:$Q$1203,">300")) | P13: =IF($A13="","",COUNTIFS('DAILY ENTRY'!$B$7:$B$1203,$A13,'DAILY ENTRY'!$I$7:$I$1203,"Blocked")) | Q13: =IF($A13="","",IF(AND(B13=0,D13=0),"No activity logged yet",IF(O13>0,"BREACH: sent messages over the 300-character limit - review the message text",IF(AND(D13>=20,F13<0.2),"Acceptance below 20% - fix targeting or the connection note before sending more",IF(AND(G13>=20,I13<0.1),"Reply rate below the 10% average - the message needs rewriting, not more volume",IF(AND(F13>=0.3,I13>=0.15),"Strong: both acceptance and reply rate are above benchmark",IF(AND(B13>0,D13=0),"Logging daily work but no LinkedIn outreach recorded","Within normal range - compare against the Benchmarks tab"))))))) | R13: =IF($A13="","",COUNTIF('Master Tasks'!$I$4:$I$66,$A13)) | S13: =IF($A13="","",COUNTIFS('Master Tasks'!$I$4:$I$66,$A13,'Master Tasks'!$J$4:$J$66,"Complete")) | T13: =IF($A13="","",IFERROR(S13/R13,"")) | U13: =IF($A13="","",COUNTIFS('Platform Setup'!$M$4:$M$49,$A13,'Platform Setup'!$J$4:$J$49,"Complete")) | V13: =IF($A13="","",COUNTIFS('Content Calendar'!$B$5:$B$403,$A13,'Content Calendar'!$J$5:$J$403,"Published")+COUNTIFS('Content Calendar'!$B$5:$B$403,$A13,'Content Calendar'!$J$5:$J$403,"Repurposed"))
A14: TEAM TOTAL | B14: =SUM(B4:B13) -> 0 | C14: =SUM(C4:C13) -> 0 | D14: =SUM(D4:D13) -> 0 | E14: =SUM(E4:E13) -> 0 | F14: =IFERROR(E14/D14,"") | G14: =SUM(G4:G13) -> 0 | H14: =SUM(H4:H13) -> 0 | I14: =IFERROR(H14/G14,"") | J14: =SUM(J4:J13) -> 0 | K14: =SUM(K4:K13) -> 0 | L14: =SUM(L4:L13) -> 0 | M14: =SUM(M4:M13) -> 0 | N14: =SUM(N4:N13) -> 0 | O14: =SUM(O4:O13) -> 0 | P14: =SUM(P4:P13) -> 0 | Q14: Compare individuals against the team total, not against each other's raw volume. | R14: =SUM(R4:R13) -> 0 | S14: =SUM(S4:S13) -> 0 | T14: =IFERROR(S14/R14,"") | U14: =SUM(U4:U13) -> 0 | V14: =SUM(V4:V13) -> 0
A16: HOW TO USE THIS FOR AN APPRAISAL: read the rates before the volumes. A person sending 500 requests at 12% acceptance is doing more damage than a person sending 150 at 38% - the first is burning the audience and risking the account. Rank the team on acceptance %, reply % and meetings booked; use volume only to check the daily targets were met.

Sheet Platform Progress
A1: PLATFORM PROGRESS — every platform, updated automatically
A2: Nothing is typed here. It reads the DAILY ENTRY tab and the Platform Setup tab. This is the fastest way to see which platforms are being neglected.
A3: Platform | B3: Area | C3: Setup status | D3: Entries logged | E3: Total activity | F3: Minutes spent | G3: Last worked on | H3: Days since | I3: Who worked on it last | J3: Blocked items | K3: Attention
A4: ='Platform Setup'!$B$4 -> LinkedIn Company Page | B4: ='Platform Setup'!$C$4 -> LinkedIn | C4: ='Platform Setup'!$J$4 -> Not Started | D4: =COUNTIF('DAILY ENTRY'!$C$7:$C$1203,$A4) -> 0 | E4: =SUMIF('DAILY ENTRY'!$C$7:$C$1203,$A4,'DAILY ENTRY'!$F$7:$F$1203) -> 0 | F4: =SUMIF('DAILY ENTRY'!$C$7:$C$1203,$A4,'DAILY ENTRY'!$G$7:$G$1203) -> 0 | G4: =IFERROR(SUMPRODUCT(MAX(('DAILY ENTRY'!$C$7:$C$1203=$A4)*'DAILY ENTRY'!$A$7:$A$1203)),"") -> 0 | H4: =IF(G4="","",TODAY()-G4) -> 46251 | I4: =IFERROR(INDEX('DAILY ENTRY'!$B$7:$B$1203,SUMPRODUCT(MATCH(SUMPRODUCT(MAX(('DAILY ENTRY'!$C$7:$C$1203=$A4)*'DAILY ENTRY'!$A$7:$A$1203)),('DAILY ENTRY'!$C$7:$C$1203=$A4)*'DAILY ENTRY'!$A$7:$A$1203,0))),"") -> 0 | J4: =COUNTIFS('DAILY ENTRY'!$C$7:$C$1203,$A4,'DAILY ENTRY'!$I$7:$I$1203,"Blocked") -> 0 | K4: =IF($C4="Complete",IF(D4=0,"Account is live but nothing has been done on it yet",IF(H4>14,"Live but untouched for over two weeks","Active")),IF($C4="Not Started","Not set up yet","Setup in progress")) -> Not set up yet
A5: ='Platform Setup'!$B$5 -> LinkedIn Personal Profile | B5: ='Platform Setup'!$C$5 -> LinkedIn | C5: ='Platform Setup'!$J$5 -> Not Started | D5: =COUNTIF('DAILY ENTRY'!$C$7:$C$1203,$A5) -> 0 | E5: =SUMIF('DAILY ENTRY'!$C$7:$C$1203,$A5,'DAILY ENTRY'!$F$7:$F$1203) -> 0 | F5: =SUMIF('DAILY ENTRY'!$C$7:$C$1203,$A5,'DAILY ENTRY'!$G$7:$G$1203) -> 0 | G5: =IFERROR(SUMPRODUCT(MAX(('DAILY ENTRY'!$C$7:$C$1203=$A5)*'DAILY ENTRY'!$A$7:$A$1203)),"") -> 0 | H5: =IF(G5="","",TODAY()-G5) -> 46251 | I5: =IFERROR(INDEX('DAILY ENTRY'!$B$7:$B$1203,SUMPRODUCT(MATCH(SUMPRODUCT(MAX(('DAILY ENTRY'!$C$7:$C$1203=$A5)*'DAILY ENTRY'!$A$7:$A$1203)),('DAILY ENTRY'!$C$7:$C$1203=$A5)*'DAILY ENTRY'!$A$7:$A$1203,0))),"") -> 0 | J5: =COUNTIFS('DAILY ENTRY'!$C$7:$C$1203,$A5,'DAILY ENTRY'!$I$7:$I$1203,"Blocked") -> 0 | K5: =IF($C5="Complete",IF(D5=0,"Account is live but nothing has been done on it yet",IF(H5>14,"Live but untouched for over two weeks","Active")),IF($C5="Not Started","Not set up yet","Setup in progress")) -> Not set up yet
A6: ='Platform Setup'!$B$6 -> LinkedIn Sales Navigator | B6: ='Platform Setup'!$C$6 -> LinkedIn | C6: ='Platform Setup'!$J$6 -> Not Started | D6: =COUNTIF('DAILY ENTRY'!$C$7:$C$1203,$A6) -> 0 | E6: =SUMIF('DAILY ENTRY'!$C$7:$C$1203,$A6,'DAILY ENTRY'!$F$7:$F$1203) -> 0 | F6: =SUMIF('DAILY ENTRY'!$C$7:$C$1203,$A6,'DAILY ENTRY'!$G$7:$G$1203) -> 0 | G6: =IFERROR(SUMPRODUCT(MAX(('DAILY ENTRY'!$C$7:$C$1203=$A6)*'DAILY ENTRY'!$A$7:$A$1203)),"") -> 0 | H6: =IF(G6="","",TODAY()-G6) -> 46251 | I6: =IFERROR(INDEX('DAILY ENTRY'!$B$7:$B$1203,SUMPRODUCT(MATCH(SUMPRODUCT(MAX(('DAILY ENTRY'!$C$7:$C$1203=$A6)*'DAILY ENTRY'!$A$7:$A$1203)),('DAILY ENTRY'!$C$7:$C$1203=$A6)*'DAILY ENTRY'!$A$7:$A$1203,0))),"") -> 0 | J6: =COUNTIFS('DAILY ENTRY'!$C$7:$C$1203,$A6,'DAILY ENTRY'!$I$7:$I$1203,"Blocked") -> 0 | K6: =IF($C6="Complete",IF(D6=0,"Account is live but nothing has been done on it yet",IF(H6>14,"Live but untouched for over two weeks","Active")),IF($C6="Not Started","Not set up yet","Setup in progress")) -> Not set up yet
A7: ='Platform Setup'!$B$7 -> LinkedIn Newsletter | B7: ='Platform Setup'!$C$7 -> Publishing | C7: ='Platform Setup'!$J$7 -> Not Started | D7: =COUNTIF('DAILY ENTRY'!$C$7:$C$1203,$A7) -> 0 | E7: =SUMIF('DAILY ENTRY'!$C$7:$C$1203,$A7,'DAILY ENTRY'!$F$7:$F$1203) -> 0 | F7: =SUMIF('DAILY ENTRY'!$C$7:$C$1203,$A7,'DAILY ENTRY'!$G$7:$G$1203) -> 0 | G7: =IFERROR(SUMPRODUCT(MAX(('DAILY ENTRY'!$C$7:$C$1203=$A7)*'DAILY ENTRY'!$A$7:$A$1203)),"") -> 0 | H7: =IF(G7="","",TODAY()-G7) -> 46251 | I7: =IFERROR(INDEX('DAILY ENTRY'!$B$7:$B$1203,SUMPRODUCT(MATCH(SUMPRODUCT(MAX(('DAILY ENTRY'!$C$7:$C$1203=$A7)*'DAILY ENTRY'!$A$7:$A$1203)),('DAILY ENTRY'!$C$7:$C$1203=$A7)*'DAILY ENTRY'!$A$7:$A$1203,0))),"") -> 0 | J7: =COUNTIFS('DAILY ENTRY'!$C$7:$C$1203,$A7,'DAILY ENTRY'!$I$7:$I$1203,"Blocked") -> 0 | K7: =IF($C7="Complete",IF(D7=0,"Account is live but nothing has been done on it yet",IF(H7>14,"Live but untouched for over two weeks","Active")),IF($C7="Not Started","Not set up yet","Setup in progress")) -> Not set up yet
A8: ='Platform Setup'!$B$8 -> LinkedIn Groups | B8: ='Platform Setup'!$C$8 -> Community | C8: ='Platform Setup'!$J$8 -> Not Started | D8: =COUNTIF('DAILY ENTRY'!$C$7:$C$1203,$A8) -> 0 | E8: =SUMIF('DAILY ENTRY'!$C$7:$C$1203,$A8,'DAILY ENTRY'!$F$7:$F$1203) -> 0 | F8: =SUMIF('DAILY ENTRY'!$C$7:$C$1203,$A8,'DAILY ENTRY'!$G$7:$G$1203) -> 0 | G8: =IFERROR(SUMPRODUCT(MAX(('DAILY ENTRY'!$C$7:$C$1203=$A8)*'DAILY ENTRY'!$A$7:$A$1203)),"") -> 0 | H8: =IF(G8="","",TODAY()-G8) -> 46251 | I8: =IFERROR(INDEX('DAILY ENTRY'!$B$7:$B$1203,SUMPRODUCT(MATCH(SUMPRODUCT(MAX(('DAILY ENTRY'!$C$7:$C$1203=$A8)*'DAILY ENTRY'!$A$7:$A$1203)),('DAILY ENTRY'!$C$7:$C$1203=$A8)*'DAILY ENTRY'!$A$7:$A$1203,0))),"") -> 0 | J8: =COUNTIFS('DAILY ENTRY'!$C$7:$C$1203,$A8,'DAILY ENTRY'!$I$7:$I$1203,"Blocked") -> 0 | K8: =IF($C8="Complete",IF(D8=0,"Account is live but nothing has been done on it yet",IF(H8>14,"Live but untouched for over two weeks","Active")),IF($C8="Not Started","Not set up yet","Setup in progress")) -> Not set up yet
A9: ='Platform Setup'!$B$9 -> Facebook Page | B9: ='Platform Setup'!$C$9 -> Social Media | C9: ='Platform Setup'!$J$9 -> Not Started | D9: =COUNTIF('DAILY ENTRY'!$C$7:$C$1203,$A9) -> 0 | E9: =SUMIF('DAILY ENTRY'!$C$7:$C$1203,$A9,'DAILY ENTRY'!$F$7:$F$1203) -> 0 | F9: =SUMIF('DAILY ENTRY'!$C$7:$C$1203,$A9,'DAILY ENTRY'!$G$7:$G$1203) -> 0 | G9: =IFERROR(SUMPRODUCT(MAX(('DAILY ENTRY'!$C$7:$C$1203=$A9)*'DAILY ENTRY'!$A$7:$A$1203)),"") -> 0 | H9: =IF(G9="","",TODAY()-G9) -> 46251 | I9: =IFERROR(INDEX('DAILY ENTRY'!$B$7:$B$1203,SUMPRODUCT(MATCH(SUMPRODUCT(MAX(('DAILY ENTRY'!$C$7:$C$1203=$A9)*'DAILY ENTRY'!$A$7:$A$1203)),('DAILY ENTRY'!$C$7:$C$1203=$A9)*'DAILY ENTRY'!$A$7:$A$1203,0))),"") -> 0 | J9: =COUNTIFS('DAILY ENTRY'!$C$7:$C$1203,$A9,'DAILY ENTRY'!$I$7:$I$1203,"Blocked") -> 0 | K9: =IF($C9="Complete",IF(D9=0,"Account is live but nothing has been done on it yet",IF(H9>14,"Live but untouched for over two weeks","Active")),IF($C9="Not Started","Not set up yet","Setup in progress")) -> Not set up yet
A10: ='Platform Setup'!$B$10 -> Facebook Groups | B10: ='Platform Setup'!$C$10 -> Community | C10: ='Platform Setup'!$J$10 -> Not Started | D10: =COUNTIF('DAILY ENTRY'!$C$7:$C$1203,$A10) -> 0 | E10: =SUMIF('DAILY ENTRY'!$C$7:$C$1203,$A10,'DAILY ENTRY'!$F$7:$F$1203) -> 0 | F10: =SUMIF('DAILY ENTRY'!$C$7:$C$1203,$A10,'DAILY ENTRY'!$G$7:$G$1203) -> 0 | G10: =IFERROR(SUMPRODUCT(MAX(('DAILY ENTRY'!$C$7:$C$1203=$A10)*'DAILY ENTRY'!$A$7:$A$1203)),"") -> 0 | H10: =IF(G10="","",TODAY()-G10) -> 46251 | I10: =IFERROR(INDEX('DAILY ENTRY'!$B$7:$B$1203,SUMPRODUCT(MATCH(SUMPRODUCT(MAX(('DAILY ENTRY'!$C$7:$C$1203=$A10)*'DAILY ENTRY'!$A$7:$A$1203)),('DAILY ENTRY'!$C$7:$C$1203=$A10)*'DAILY ENTRY'!$A$7:$A$1203,0))),"") -> 0 | J10: =COUNTIFS('DAILY ENTRY'!$C$7:$C$1203,$A10,'DAILY ENTRY'!$I$7:$I$1203,"Blocked") -> 0 | K10: =IF($C10="Complete",IF(D10=0,"Account is live but nothing has been done on it yet",IF(H10>14,"Live but untouched for over two weeks","Active")),IF($C10="Not Started","Not set up yet","Setup in progress")) -> Not set up yet
A11: ='Platform Setup'!$B$11 -> Instagram | B11: ='Platform Setup'!$C$11 -> Social Media | C11: ='Platform Setup'!$J$11 -> Not Started | D11: =COUNTIF('DAILY ENTRY'!$C$7:$C$1203,$A11) -> 0 | E11: =SUMIF('DAILY ENTRY'!$C$7:$C$1203,$A11,'DAILY ENTRY'!$F$7:$F$1203) -> 0 | F11: =SUMIF('DAILY ENTRY'!$C$7:$C$1203,$A11,'DAILY ENTRY'!$G$7:$G$1203) -> 0 | G11: =IFERROR(SUMPRODUCT(MAX(('DAILY ENTRY'!$C$7:$C$1203=$A11)*'DAILY ENTRY'!$A$7:$A$1203)),"") -> 0 | H11: =IF(G11="","",TODAY()-G11) -> 46251 | I11: =IFERROR(INDEX('DAILY ENTRY'!$B$7:$B$1203,SUMPRODUCT(MATCH(SUMPRODUCT(MAX(('DAILY ENTRY'!$C$7:$C$1203=$A11)*'DAILY ENTRY'!$A$7:$A$1203)),('DAILY ENTRY'!$C$7:$C$1203=$A11)*'DAILY ENTRY'!$A$7:$A$1203,0))),"") -> 0 | J11: =COUNTIFS('DAILY ENTRY'!$C$7:$C$1203,$A11,'DAILY ENTRY'!$I$7:$I$1203,"Blocked") -> 0 | K11: =IF($C11="Complete",IF(D11=0,"Account is live but nothing has been done on it yet",IF(H11>14,"Live but untouched for over two weeks","Active")),IF($C11="Not Started","Not set up yet","Setup in progress")) -> Not set up yet
A12: ='Platform Setup'!$B$12 -> X (Twitter) | B12: ='Platform Setup'!$C$12 -> Social Media | C12: ='Platform Setup'!$J$12 -> Not Started | D12: =COUNTIF('DAILY ENTRY'!$C$7:$C$1203,$A12) -> 0 | E12: =SUMIF('DAILY ENTRY'!$C$7:$C$1203,$A12,'DAILY ENTRY'!$F$7:$F$1203) -> 0 | F12: =SUMIF('DAILY ENTRY'!$C$7:$C$1203,$A12,'DAILY ENTRY'!$G$7:$G$1203) -> 0 | G12: =IFERROR(SUMPRODUCT(MAX(('DAILY ENTRY'!$C$7:$C$1203=$A12)*'DAILY ENTRY'!$A$7:$A$1203)),"") -> 0 | H12: =IF(G12="","",TODAY()-G12) -> 46251 | I12: =IFERROR(INDEX('DAILY ENTRY'!$B$7:$B$1203,SUMPRODUCT(MATCH(SUMPRODUCT(MAX(('DAILY ENTRY'!$C$7:$C$1203=$A12)*'DAILY ENTRY'!$A$7:$A$1203)),('DAILY ENTRY'!$C$7:$C$1203=$A12)*'DAILY ENTRY'!$A$7:$A$1203,0))),"") -> 0 | J12: =COUNTIFS('DAILY ENTRY'!$C$7:$C$1203,$A12,'DAILY ENTRY'!$I$7:$I$1203,"Blocked") -> 0 | K12: =IF($C12="Complete",IF(D12=0,"Account is live but nothing has been done on it yet",IF(H12>14,"Live but untouched for over two weeks","Active")),IF($C12="Not Started","Not set up yet","Setup in progress")) -> Not set up yet
A13: ='Platform Setup'!$B$13 -> Threads | B13: ='Platform Setup'!$C$13 -> Social Media | C13: ='Platform Setup'!$J$13 -> Not Started | D13: =COUNTIF('DAILY ENTRY'!$C$7:$C$1203,$A13) -> 0 | E13: =SUMIF('DAILY ENTRY'!$C$7:$C$1203,$A13,'DAILY ENTRY'!$F$7:$F$1203) -> 0 | F13: =SUMIF('DAILY ENTRY'!$C$7:$C$1203,$A13,'DAILY ENTRY'!$G$7:$G$1203) -> 0 | G13: =IFERROR(SUMPRODUCT(MAX(('DAILY ENTRY'!$C$7:$C$1203=$A13)*'DAILY ENTRY'!$A$7:$A$1203)),"") -> 0 | H13: =IF(G13="","",TODAY()-G13) -> 46251 | I13: =IFERROR(INDEX('DAILY ENTRY'!$B$7:$B$1203,SUMPRODUCT(MATCH(SUMPRODUCT(MAX(('DAILY ENTRY'!$C$7:$C$1203=$A13)*'DAILY ENTRY'!$A$7:$A$1203)),('DAILY ENTRY'!$C$7:$C$1203=$A13)*'DAILY ENTRY'!$A$7:$A$1203,0))),"") -> 0 | J13: =COUNTIFS('DAILY ENTRY'!$C$7:$C$1203,$A13,'DAILY ENTRY'!$I$7:$I$1203,"Blocked") -> 0 | K13: =IF($C13="Complete",IF(D13=0,"Account is live but nothing has been done on it yet",IF(H13>14,"Live but untouched for over two weeks","Active")),IF($C13="Not Started","Not set up yet","Setup in progress")) -> Not set up yet
A14: ='Platform Setup'!$B$14 -> TikTok | B14: ='Platform Setup'!$C$14 -> Social Media | C14: ='Platform Setup'!$J$14 -> Not Started | D14: =COUNTIF('DAILY ENTRY'!$C$7:$C$1203,$A14) -> 0 | E14: =SUMIF('DAILY ENTRY'!$C$7:$C$1203,$A14,'DAILY ENTRY'!$F$7:$F$1203) -> 0 | F14: =SUMIF('DAILY ENTRY'!$C$7:$C$1203,$A14,'DAILY ENTRY'!$G$7:$G$1203) -> 0 | G14: =IFERROR(SUMPRODUCT(MAX(('DAILY ENTRY'!$C$7:$C$1203=$A14)*'DAILY ENTRY'!$A$7:$A$1203)),"") -> 0 | H14: =IF(G14="","",TODAY()-G14) -> 46251 | I14: =IFERROR(INDEX('DAILY ENTRY'!$B$7:$B$1203,SUMPRODUCT(MATCH(SUMPRODUCT(MAX(('DAILY ENTRY'!$C$7:$C$1203=$A14)*'DAILY ENTRY'!$A$7:$A$1203)),('DAILY ENTRY'!$C$7:$C$1203=$A14)*'DAILY ENTRY'!$A$7:$A$1203,0))),"") -> 0 | J14: =COUNTIFS('DAILY ENTRY'!$C$7:$C$1203,$A14,'DAILY ENTRY'!$I$7:$I$1203,"Blocked") -> 0 | K14: =IF($C14="Complete",IF(D14=0,"Account is live but nothing has been done on it yet",IF(H14>14,"Live but untouched for over two weeks","Active")),IF($C14="Not Started","Not set up yet","Setup in progress")) -> Not set up yet
A15: ='Platform Setup'!$B$15 -> YouTube | B15: ='Platform Setup'!$C$15 -> Social Media | C15: ='Platform Setup'!$J$15 -> Not Started | D15: =COUNTIF('DAILY ENTRY'!$C$7:$C$1203,$A15) -> 0 | E15: =SUMIF('DAILY ENTRY'!$C$7:$C$1203,$A15,'DAILY ENTRY'!$F$7:$F$1203) -> 0 | F15: =SUMIF('DAILY ENTRY'!$C$7:$C$1203,$A15,'DAILY ENTRY'!$G$7:$G$1203) -> 0 | G15: =IFERROR(SUMPRODUCT(MAX(('DAILY ENTRY'!$C$7:$C$1203=$A15)*'DAILY ENTRY'!$A$7:$A$1203)),"") -> 0 | H15: =IF(G15="","",TODAY()-G15) -> 46251 | I15: =IFERROR(INDEX('DAILY ENTRY'!$B$7:$B$1203,SUMPRODUCT(MATCH(SUMPRODUCT(MAX(('DAILY ENTRY'!$C$7:$C$1203=$A15)*'DAILY ENTRY'!$A$7:$A$1203)),('DAILY ENTRY'!$C$7:$C$1203=$A15)*'DAILY ENTRY'!$A$7:$A$1203,0))),"") -> 0 | J15: =COUNTIFS('DAILY ENTRY'!$C$7:$C$1203,$A15,'DAILY ENTRY'!$I$7:$I$1203,"Blocked") -> 0 | K15: =IF($C15="Complete",IF(D15=0,"Account is live but nothing has been done on it yet",IF(H15>14,"Live but untouched for over two weeks","Active")),IF($C15="Not Started","Not set up yet","Setup in progress")) -> Not set up yet
A16: ='Platform Setup'!$B$16 -> YouTube Shorts | B16: ='Platform Setup'!$C$16 -> Social Media | C16: ='Platform Setup'!$J$16 -> Not Started | D16: =COUNTIF('DAILY ENTRY'!$C$7:$C$1203,$A16) -> 0 | E16: =SUMIF('DAILY ENTRY'!$C$7:$C$1203,$A16,'DAILY ENTRY'!$F$7:$F$1203) -> 0 | F16: =SUMIF('DAILY ENTRY'!$C$7:$C$1203,$A16,'DAILY ENTRY'!$G$7:$G$1203) -> 0 | G16: =IFERROR(SUMPRODUCT(MAX(('DAILY ENTRY'!$C$7:$C$1203=$A16)*'DAILY ENTRY'!$A$7:$A$1203)),"") -> 0 | H16: =IF(G16="","",TODAY()-G16) -> 46251 | I16: =IFERROR(INDEX('DAILY ENTRY'!$B$7:$B$1203,SUMPRODUCT(MATCH(SUMPRODUCT(MAX(('DAILY ENTRY'!$C$7:$C$1203=$A16)*'DAILY ENTRY'!$A$7:$A$1203)),('DAILY ENTRY'!$C$7:$C$1203=$A16)*'DAILY ENTRY'!$A$7:$A$1203,0))),"") -> 0 | J16: =COUNTIFS('DAILY ENTRY'!$C$7:$C$1203,$A16,'DAILY ENTRY'!$I$7:$I$1203,"Blocked") -> 0 | K16: =IF($C16="Complete",IF(D16=0,"Account is live but nothing has been done on it yet",IF(H16>14,"Live but untouched for over two weeks","Active")),IF($C16="Not Started","Not set up yet","Setup in progress")) -> Not set up yet
A17: ='Platform Setup'!$B$17 -> Pinterest | B17: ='Platform Setup'!$C$17 -> Social Media | C17: ='Platform Setup'!$J$17 -> Not Started | D17: =COUNTIF('DAILY ENTRY'!$C$7:$C$1203,$A17) -> 0 | E17: =SUMIF('DAILY ENTRY'!$C$7:$C$1203,$A17,'DAILY ENTRY'!$F$7:$F$1203) -> 0 | F17: =SUMIF('DAILY ENTRY'!$C$7:$C$1203,$A17,'DAILY ENTRY'!$G$7:$G$1203) -> 0 | G17: =IFERROR(SUMPRODUCT(MAX(('DAILY ENTRY'!$C$7:$C$1203=$A17)*'DAILY ENTRY'!$A$7:$A$1203)),"") -> 0 | H17: =IF(G17="","",TODAY()-G17) -> 46251 | I17: =IFERROR(INDEX('DAILY ENTRY'!$B$7:$B$1203,SUMPRODUCT(MATCH(SUMPRODUCT(MAX(('DAILY ENTRY'!$C$7:$C$1203=$A17)*'DAILY ENTRY'!$A$7:$A$1203)),('DAILY ENTRY'!$C$7:$C$1203=$A17)*'DAILY ENTRY'!$A$7:$A$1203,0))),"") -> 0 | J17: =COUNTIFS('DAILY ENTRY'!$C$7:$C$1203,$A17,'DAILY ENTRY'!$I$7:$I$1203,"Blocked") -> 0 | K17: =IF($C17="Complete",IF(D17=0,"Account is live but nothing has been done on it yet",IF(H17>14,"Live but untouched for over two weeks","Active")),IF($C17="Not Started","Not set up yet","Setup in progress")) -> Not set up yet
A18: ='Platform Setup'!$B$18 -> Medium | B18: ='Platform Setup'!$C$18 -> Publishing | C18: ='Platform Setup'!$J$18 -> Not Started | D18: =COUNTIF('DAILY ENTRY'!$C$7:$C$1203,$A18) -> 0 | E18: =SUMIF('DAILY ENTRY'!$C$7:$C$1203,$A18,'DAILY ENTRY'!$F$7:$F$1203) -> 0 | F18: =SUMIF('DAILY ENTRY'!$C$7:$C$1203,$A18,'DAILY ENTRY'!$G$7:$G$1203) -> 0 | G18: =IFERROR(SUMPRODUCT(MAX(('DAILY ENTRY'!$C$7:$C$1203=$A18)*'DAILY ENTRY'!$A$7:$A$1203)),"") -> 0 | H18: =IF(G18="","",TODAY()-G18) -> 46251 | I18: =IFERROR(INDEX('DAILY ENTRY'!$B$7:$B$1203,SUMPRODUCT(MATCH(SUMPRODUCT(MAX(('DAILY ENTRY'!$C$7:$C$1203=$A18)*'DAILY ENTRY'!$A$7:$A$1203)),('DAILY ENTRY'!$C$7:$C$1203=$A18)*'DAILY ENTRY'!$A$7:$A$1203,0))),"") -> 0 | J18: =COUNTIFS('DAILY ENTRY'!$C$7:$C$1203,$A18,'DAILY ENTRY'!$I$7:$I$1203,"Blocked") -> 0 | K18: =IF($C18="Complete",IF(D18=0,"Account is live but nothing has been done on it yet",IF(H18>14,"Live but untouched for over two weeks","Active")),IF($C18="Not Started","Not set up yet","Setup in progress")) -> Not set up yet
A19: ='Platform Setup'!$B$19 -> Substack | B19: ='Platform Setup'!$C$19 -> Publishing | C19: ='Platform Setup'!$J$19 -> Not Started | D19: =COUNTIF('DAILY ENTRY'!$C$7:$C$1203,$A19) -> 0 | E19: =SUMIF('DAILY ENTRY'!$C$7:$C$1203,$A19,'DAILY ENTRY'!$F$7:$F$1203) -> 0 | F19: =SUMIF('DAILY ENTRY'!$C$7:$C$1203,$A19,'DAILY ENTRY'!$G$7:$G$1203) -> 0 | G19: =IFERROR(SUMPRODUCT(MAX(('DAILY ENTRY'!$C$7:$C$1203=$A19)*'DAILY ENTRY'!$A$7:$A$1203)),"") -> 0 | H19: =IF(G19="","",TODAY()-G19) -> 46251 | I19: =IFERROR(INDEX('DAILY ENTRY'!$B$7:$B$1203,SUMPRODUCT(MATCH(SUMPRODUCT(MAX(('DAILY ENTRY'!$C$7:$C$1203=$A19)*'DAILY ENTRY'!$A$7:$A$1203)),('DAILY ENTRY'!$C$7:$C$1203=$A19)*'DAILY ENTRY'!$A$7:$A$1203,0))),"") -> 0 | J19: =COUNTIFS('DAILY ENTRY'!$C$7:$C$1203,$A19,'DAILY ENTRY'!$I$7:$I$1203,"Blocked") -> 0 | K19: =IF($C19="Complete",IF(D19=0,"Account is live but nothing has been done on it yet",IF(H19>14,"Live but untouched for over two weeks","Active")),IF($C19="Not Started","Not set up yet","Setup in progress")) -> Not set up yet
A20: ='Platform Setup'!$B$20 -> SlideShare | B20: ='Platform Setup'!$C$20 -> Publishing | C20: ='Platform Setup'!$J$20 -> Not Started | D20: =COUNTIF('DAILY ENTRY'!$C$7:$C$1203,$A20) -> 0 | E20: =SUMIF('DAILY ENTRY'!$C$7:$C$1203,$A20,'DAILY ENTRY'!$F$7:$F$1203) -> 0 | F20: =SUMIF('DAILY ENTRY'!$C$7:$C$1203,$A20,'DAILY ENTRY'!$G$7:$G$1203) -> 0 | G20: =IFERROR(SUMPRODUCT(MAX(('DAILY ENTRY'!$C$7:$C$1203=$A20)*'DAILY ENTRY'!$A$7:$A$1203)),"") -> 0 | H20: =IF(G20="","",TODAY()-G20) -> 46251 | I20: =IFERROR(INDEX('DAILY ENTRY'!$B$7:$B$1203,SUMPRODUCT(MATCH(SUMPRODUCT(MAX(('DAILY ENTRY'!$C$7:$C$1203=$A20)*'DAILY ENTRY'!$A$7:$A$1203)),('DAILY ENTRY'!$C$7:$C$1203=$A20)*'DAILY ENTRY'!$A$7:$A$1203,0))),"") -> 0 | J20: =COUNTIFS('DAILY ENTRY'!$C$7:$C$1203,$A20,'DAILY ENTRY'!$I$7:$I$1203,"Blocked") -> 0 | K20: =IF($C20="Complete",IF(D20=0,"Account is live but nothing has been done on it yet",IF(H20>14,"Live but untouched for over two weeks","Active")),IF($C20="Not Started","Not set up yet","Setup in progress")) -> Not set up yet
A21: ='Platform Setup'!$B$21 -> Tumblr | B21: ='Platform Setup'!$C$21 -> Publishing | C21: ='Platform Setup'!$J$21 -> Not Started | D21: =COUNTIF('DAILY ENTRY'!$C$7:$C$1203,$A21) -> 0 | E21: =SUMIF('DAILY ENTRY'!$C$7:$C$1203,$A21,'DAILY ENTRY'!$F$7:$F$1203) -> 0 | F21: =SUMIF('DAILY ENTRY'!$C$7:$C$1203,$A21,'DAILY ENTRY'!$G$7:$G$1203) -> 0 | G21: =IFERROR(SUMPRODUCT(MAX(('DAILY ENTRY'!$C$7:$C$1203=$A21)*'DAILY ENTRY'!$A$7:$A$1203)),"") -> 0 | H21: =IF(G21="","",TODAY()-G21) -> 46251 | I21: =IFERROR(INDEX('DAILY ENTRY'!$B$7:$B$1203,SUMPRODUCT(MATCH(SUMPRODUCT(MAX(('DAILY ENTRY'!$C$7:$C$1203=$A21)*'DAILY ENTRY'!$A$7:$A$1203)),('DAILY ENTRY'!$C$7:$C$1203=$A21)*'DAILY ENTRY'!$A$7:$A$1203,0))),"") -> 0 | J21: =COUNTIFS('DAILY ENTRY'!$C$7:$C$1203,$A21,'DAILY ENTRY'!$I$7:$I$1203,"Blocked") -> 0 | K21: =IF($C21="Complete",IF(D21=0,"Account is live but nothing has been done on it yet",IF(H21>14,"Live but untouched for over two weeks","Active")),IF($C21="Not Started","Not set up yet","Setup in progress")) -> Not set up yet
A22: ='Platform Setup'!$B$22 -> Quora | B22: ='Platform Setup'!$C$22 -> Community | C22: ='Platform Setup'!$J$22 -> Not Started | D22: =COUNTIF('DAILY ENTRY'!$C$7:$C$1203,$A22) -> 0 | E22: =SUMIF('DAILY ENTRY'!$C$7:$C$1203,$A22,'DAILY ENTRY'!$F$7:$F$1203) -> 0 | F22: =SUMIF('DAILY ENTRY'!$C$7:$C$1203,$A22,'DAILY ENTRY'!$G$7:$G$1203) -> 0 | G22: =IFERROR(SUMPRODUCT(MAX(('DAILY ENTRY'!$C$7:$C$1203=$A22)*'DAILY ENTRY'!$A$7:$A$1203)),"") -> 0 | H22: =IF(G22="","",TODAY()-G22) -> 46251 | I22: =IFERROR(INDEX('DAILY ENTRY'!$B$7:$B$1203,SUMPRODUCT(MATCH(SUMPRODUCT(MAX(('DAILY ENTRY'!$C$7:$C$1203=$A22)*'DAILY ENTRY'!$A$7:$A$1203)),('DAILY ENTRY'!$C$7:$C$1203=$A22)*'DAILY ENTRY'!$A$7:$A$1203,0))),"") -> 0 | J22: =COUNTIFS('DAILY ENTRY'!$C$7:$C$1203,$A22,'DAILY ENTRY'!$I$7:$I$1203,"Blocked") -> 0 | K22: =IF($C22="Complete",IF(D22=0,"Account is live but nothing has been done on it yet",IF(H22>14,"Live but untouched for over two weeks","Active")),IF($C22="Not Started","Not set up yet","Setup in progress")) -> Not set up yet
A23: ='Platform Setup'!$B$23 -> Reddit | B23: ='Platform Setup'!$C$23 -> Community | C23: ='Platform Setup'!$J$23 -> Not Started | D23: =COUNTIF('DAILY ENTRY'!$C$7:$C$1203,$A23) -> 0 | E23: =SUMIF('DAILY ENTRY'!$C$7:$C$1203,$A23,'DAILY ENTRY'!$F$7:$F$1203) -> 0 | F23: =SUMIF('DAILY ENTRY'!$C$7:$C$1203,$A23,'DAILY ENTRY'!$G$7:$G$1203) -> 0 | G23: =IFERROR(SUMPRODUCT(MAX(('DAILY ENTRY'!$C$7:$C$1203=$A23)*'DAILY ENTRY'!$A$7:$A$1203)),"") -> 0 | H23: =IF(G23="","",TODAY()-G23) -> 46251 | I23: =IFERROR(INDEX('DAILY ENTRY'!$B$7:$B$1203,SUMPRODUCT(MATCH(SUMPRODUCT(MAX(('DAILY ENTRY'!$C$7:$C$1203=$A23)*'DAILY ENTRY'!$A$7:$A$1203)),('DAILY ENTRY'!$C$7:$C$1203=$A23)*'DAILY ENTRY'!$A$7:$A$1203,0))),"") -> 0 | J23: =COUNTIFS('DAILY ENTRY'!$C$7:$C$1203,$A23,'DAILY ENTRY'!$I$7:$I$1203,"Blocked") -> 0 | K23: =IF($C23="Complete",IF(D23=0,"Account is live but nothing has been done on it yet",IF(H23>14,"Live but untouched for over two weeks","Active")),IF($C23="Not Started","Not set up yet","Setup in progress")) -> Not set up yet
A24: ='Platform Setup'!$B$24 -> Discord | B24: ='Platform Setup'!$C$24 -> Community | C24: ='Platform Setup'!$J$24 -> Not Started | D24: =COUNTIF('DAILY ENTRY'!$C$7:$C$1203,$A24) -> 0 | E24: =SUMIF('DAILY ENTRY'!$C$7:$C$1203,$A24,'DAILY ENTRY'!$F$7:$F$1203) -> 0 | F24: =SUMIF('DAILY ENTRY'!$C$7:$C$1203,$A24,'DAILY ENTRY'!$G$7:$G$1203) -> 0 | G24: =IFERROR(SUMPRODUCT(MAX(('DAILY ENTRY'!$C$7:$C$1203=$A24)*'DAILY ENTRY'!$A$7:$A$1203)),"") -> 0 | H24: =IF(G24="","",TODAY()-G24) -> 46251 | I24: =IFERROR(INDEX('DAILY ENTRY'!$B$7:$B$1203,SUMPRODUCT(MATCH(SUMPRODUCT(MAX(('DAILY ENTRY'!$C$7:$C$1203=$A24)*'DAILY ENTRY'!$A$7:$A$1203)),('DAILY ENTRY'!$C$7:$C$1203=$A24)*'DAILY ENTRY'!$A$7:$A$1203,0))),"") -> 0 | J24: =COUNTIFS('DAILY ENTRY'!$C$7:$C$1203,$A24,'DAILY ENTRY'!$I$7:$I$1203,"Blocked") -> 0 | K24: =IF($C24="Complete",IF(D24=0,"Account is live but nothing has been done on it yet",IF(H24>14,"Live but untouched for over two weeks","Active")),IF($C24="Not Started","Not set up yet","Setup in progress")) -> Not set up yet
A25: ='Platform Setup'!$B$25 -> Slack Communities | B25: ='Platform Setup'!$C$25 -> Community | C25: ='Platform Setup'!$J$25 -> Not Started | D25: =COUNTIF('DAILY ENTRY'!$C$7:$C$1203,$A25) -> 0 | E25: =SUMIF('DAILY ENTRY'!$C$7:$C$1203,$A25,'DAILY ENTRY'!$F$7:$F$1203) -> 0 | F25: =SUMIF('DAILY ENTRY'!$C$7:$C$1203,$A25,'DAILY ENTRY'!$G$7:$G$1203) -> 0 | G25: =IFERROR(SUMPRODUCT(MAX(('DAILY ENTRY'!$C$7:$C$1203=$A25)*'DAILY ENTRY'!$A$7:$A$1203)),"") -> 0 | H25: =IF(G25="","",TODAY()-G25) -> 46251 | I25: =IFERROR(INDEX('DAILY ENTRY'!$B$7:$B$1203,SUMPRODUCT(MATCH(SUMPRODUCT(MAX(('DAILY ENTRY'!$C$7:$C$1203=$A25)*'DAILY ENTRY'!$A$7:$A$1203)),('DAILY ENTRY'!$C$7:$C$1203=$A25)*'DAILY ENTRY'!$A$7:$A$1203,0))),"") -> 0 | J25: =COUNTIFS('DAILY ENTRY'!$C$7:$C$1203,$A25,'DAILY ENTRY'!$I$7:$I$1203,"Blocked") -> 0 | K25: =IF($C25="Complete",IF(D25=0,"Account is live but nothing has been done on it yet",IF(H25>14,"Live but untouched for over two weeks","Active")),IF($C25="Not Started","Not set up yet","Setup in progress")) -> Not set up yet
A26: ='Platform Setup'!$B$26 -> WhatsApp Channel | B26: ='Platform Setup'!$C$26 -> Social Media | C26: ='Platform Setup'!$J$26 -> Not Started | D26: =COUNTIF('DAILY ENTRY'!$C$7:$C$1203,$A26) -> 0 | E26: =SUMIF('DAILY ENTRY'!$C$7:$C$1203,$A26,'DAILY ENTRY'!$F$7:$F$1203) -> 0 | F26: =SUMIF('DAILY ENTRY'!$C$7:$C$1203,$A26,'DAILY ENTRY'!$G$7:$G$1203) -> 0 | G26: =IFERROR(SUMPRODUCT(MAX(('DAILY ENTRY'!$C$7:$C$1203=$A26)*'DAILY ENTRY'!$A$7:$A$1203)),"") -> 0 | H26: =IF(G26="","",TODAY()-G26) -> 46251 | I26: =IFERROR(INDEX('DAILY ENTRY'!$B$7:$B$1203,SUMPRODUCT(MATCH(SUMPRODUCT(MAX(('DAILY ENTRY'!$C$7:$C$1203=$A26)*'DAILY ENTRY'!$A$7:$A$1203)),('DAILY ENTRY'!$C$7:$C$1203=$A26)*'DAILY ENTRY'!$A$7:$A$1203,0))),"") -> 0 | J26: =COUNTIFS('DAILY ENTRY'!$C$7:$C$1203,$A26,'DAILY ENTRY'!$I$7:$I$1203,"Blocked") -> 0 | K26: =IF($C26="Complete",IF(D26=0,"Account is live but nothing has been done on it yet",IF(H26>14,"Live but untouched for over two weeks","Active")),IF($C26="Not Started","Not set up yet","Setup in progress")) -> Not set up yet
A27: ='Platform Setup'!$B$27 -> Telegram Channel | B27: ='Platform Setup'!$C$27 -> Social Media | C27: ='Platform Setup'!$J$27 -> Not Started | D27: =COUNTIF('DAILY ENTRY'!$C$7:$C$1203,$A27) -> 0 | E27: =SUMIF('DAILY ENTRY'!$C$7:$C$1203,$A27,'DAILY ENTRY'!$F$7:$F$1203) -> 0 | F27: =SUMIF('DAILY ENTRY'!$C$7:$C$1203,$A27,'DAILY ENTRY'!$G$7:$G$1203) -> 0 | G27: =IFERROR(SUMPRODUCT(MAX(('DAILY ENTRY'!$C$7:$C$1203=$A27)*'DAILY ENTRY'!$A$7:$A$1203)),"") -> 0 | H27: =IF(G27="","",TODAY()-G27) -> 46251 | I27: =IFERROR(INDEX('DAILY ENTRY'!$B$7:$B$1203,SUMPRODUCT(MATCH(SUMPRODUCT(MAX(('DAILY ENTRY'!$C$7:$C$1203=$A27)*'DAILY ENTRY'!$A$7:$A$1203)),('DAILY ENTRY'!$C$7:$C$1203=$A27)*'DAILY ENTRY'!$A$7:$A$1203,0))),"") -> 0 | J27: =COUNTIFS('DAILY ENTRY'!$C$7:$C$1203,$A27,'DAILY ENTRY'!$I$7:$I$1203,"Blocked") -> 0 | K27: =IF($C27="Complete",IF(D27=0,"Account is live but nothing has been done on it yet",IF(H27>14,"Live but untouched for over two weeks","Active")),IF($C27="Not Started","Not set up yet","Setup in progress")) -> Not set up yet
A28: ='Platform Setup'!$B$28 -> Google Business Profile | B28: ='Platform Setup'!$C$28 -> Directory/Review | C28: ='Platform Setup'!$J$28 -> Not Started | D28: =COUNTIF('DAILY ENTRY'!$C$7:$C$1203,$A28) -> 0 | E28: =SUMIF('DAILY ENTRY'!$C$7:$C$1203,$A28,'DAILY ENTRY'!$F$7:$F$1203) -> 0 | F28: =SUMIF('DAILY ENTRY'!$C$7:$C$1203,$A28,'DAILY ENTRY'!$G$7:$G$1203) -> 0 | G28: =IFERROR(SUMPRODUCT(MAX(('DAILY ENTRY'!$C$7:$C$1203=$A28)*'DAILY ENTRY'!$A$7:$A$1203)),"") -> 0 | H28: =IF(G28="","",TODAY()-G28) -> 46251 | I28: =IFERROR(INDEX('DAILY ENTRY'!$B$7:$B$1203,SUMPRODUCT(MATCH(SUMPRODUCT(MAX(('DAILY ENTRY'!$C$7:$C$1203=$A28)*'DAILY ENTRY'!$A$7:$A$1203)),('DAILY ENTRY'!$C$7:$C$1203=$A28)*'DAILY ENTRY'!$A$7:$A$1203,0))),"") -> 0 | J28: =COUNTIFS('DAILY ENTRY'!$C$7:$C$1203,$A28,'DAILY ENTRY'!$I$7:$I$1203,"Blocked") -> 0 | K28: =IF($C28="Complete",IF(D28=0,"Account is live but nothing has been done on it yet",IF(H28>14,"Live but untouched for over two weeks","Active")),IF($C28="Not Started","Not set up yet","Setup in progress")) -> Not set up yet
A29: ='Platform Setup'!$B$29 -> Bing Places | B29: ='Platform Setup'!$C$29 -> Directory/Review | C29: ='Platform Setup'!$J$29 -> Not Started | D29: =COUNTIF('DAILY ENTRY'!$C$7:$C$1203,$A29) -> 0 | E29: =SUMIF('DAILY ENTRY'!$C$7:$C$1203,$A29,'DAILY ENTRY'!$F$7:$F$1203) -> 0 | F29: =SUMIF('DAILY ENTRY'!$C$7:$C$1203,$A29,'DAILY ENTRY'!$G$7:$G$1203) -> 0 | G29: =IFERROR(SUMPRODUCT(MAX(('DAILY ENTRY'!$C$7:$C$1203=$A29)*'DAILY ENTRY'!$A$7:$A$1203)),"") -> 0 | H29: =IF(G29="","",TODAY()-G29) -> 46251 | I29: =IFERROR(INDEX('DAILY ENTRY'!$B$7:$B$1203,SUMPRODUCT(MATCH(SUMPRODUCT(MAX(('DAILY ENTRY'!$C$7:$C$1203=$A29)*'DAILY ENTRY'!$A$7:$A$1203)),('DAILY ENTRY'!$C$7:$C$1203=$A29)*'DAILY ENTRY'!$A$7:$A$1203,0))),"") -> 0 | J29: =COUNTIFS('DAILY ENTRY'!$C$7:$C$1203,$A29,'DAILY ENTRY'!$I$7:$I$1203,"Blocked") -> 0 | K29: =IF($C29="Complete",IF(D29=0,"Account is live but nothing has been done on it yet",IF(H29>14,"Live but untouched for over two weeks","Active")),IF($C29="Not Started","Not set up yet","Setup in progress")) -> Not set up yet
A30: ='Platform Setup'!$B$30 -> Trustpilot | B30: ='Platform Setup'!$C$30 -> Directory/Review | C30: ='Platform Setup'!$J$30 -> Not Started | D30: =COUNTIF('DAILY ENTRY'!$C$7:$C$1203,$A30) -> 0 | E30: =SUMIF('DAILY ENTRY'!$C$7:$C$1203,$A30,'DAILY ENTRY'!$F$7:$F$1203) -> 0 | F30: =SUMIF('DAILY ENTRY'!$C$7:$C$1203,$A30,'DAILY ENTRY'!$G$7:$G$1203) -> 0 | G30: =IFERROR(SUMPRODUCT(MAX(('DAILY ENTRY'!$C$7:$C$1203=$A30)*'DAILY ENTRY'!$A$7:$A$1203)),"") -> 0 | H30: =IF(G30="","",TODAY()-G30) -> 46251 | I30: =IFERROR(INDEX('DAILY ENTRY'!$B$7:$B$1203,SUMPRODUCT(MATCH(SUMPRODUCT(MAX(('DAILY ENTRY'!$C$7:$C$1203=$A30)*'DAILY ENTRY'!$A$7:$A$1203)),('DAILY ENTRY'!$C$7:$C$1203=$A30)*'DAILY ENTRY'!$A$7:$A$1203,0))),"") -> 0 | J30: =COUNTIFS('DAILY ENTRY'!$C$7:$C$1203,$A30,'DAILY ENTRY'!$I$7:$I$1203,"Blocked") -> 0 | K30: =IF($C30="Complete",IF(D30=0,"Account is live but nothing has been done on it yet",IF(H30>14,"Live but untouched for over two weeks","Active")),IF($C30="Not Started","Not set up yet","Setup in progress")) -> Not set up yet
A31: ='Platform Setup'!$B$31 -> Crunchbase | B31: ='Platform Setup'!$C$31 -> Directory/Review | C31: ='Platform Setup'!$J$31 -> Not Started | D31: =COUNTIF('DAILY ENTRY'!$C$7:$C$1203,$A31) -> 0 | E31: =SUMIF('DAILY ENTRY'!$C$7:$C$1203,$A31,'DAILY ENTRY'!$F$7:$F$1203) -> 0 | F31: =SUMIF('DAILY ENTRY'!$C$7:$C$1203,$A31,'DAILY ENTRY'!$G$7:$G$1203) -> 0 | G31: =IFERROR(SUMPRODUCT(MAX(('DAILY ENTRY'!$C$7:$C$1203=$A31)*'DAILY ENTRY'!$A$7:$A$1203)),"") -> 0 | H31: =IF(G31="","",TODAY()-G31) -> 46251 | I31: =IFERROR(INDEX('DAILY ENTRY'!$B$7:$B$1203,SUMPRODUCT(MATCH(SUMPRODUCT(MAX(('DAILY ENTRY'!$C$7:$C$1203=$A31)*'DAILY ENTRY'!$A$7:$A$1203)),('DAILY ENTRY'!$C$7:$C$1203=$A31)*'DAILY ENTRY'!$A$7:$A$1203,0))),"") -> 0 | J31: =COUNTIFS('DAILY ENTRY'!$C$7:$C$1203,$A31,'DAILY ENTRY'!$I$7:$I$1203,"Blocked") -> 0 | K31: =IF($C31="Complete",IF(D31=0,"Account is live but nothing has been done on it yet",IF(H31>14,"Live but untouched for over two weeks","Active")),IF($C31="Not Started","Not set up yet","Setup in progress")) -> Not set up yet
A32: ='Platform Setup'!$B$32 -> G2 | B32: ='Platform Setup'!$C$32 -> Directory/Review | C32: ='Platform Setup'!$J$32 -> Not Started | D32: =COUNTIF('DAILY ENTRY'!$C$7:$C$1203,$A32) -> 0 | E32: =SUMIF('DAILY ENTRY'!$C$7:$C$1203,$A32,'DAILY ENTRY'!$F$7:$F$1203) -> 0 | F32: =SUMIF('DAILY ENTRY'!$C$7:$C$1203,$A32,'DAILY ENTRY'!$G$7:$G$1203) -> 0 | G32: =IFERROR(SUMPRODUCT(MAX(('DAILY ENTRY'!$C$7:$C$1203=$A32)*'DAILY ENTRY'!$A$7:$A$1203)),"") -> 0 | H32: =IF(G32="","",TODAY()-G32) -> 46251 | I32: =IFERROR(INDEX('DAILY ENTRY'!$B$7:$B$1203,SUMPRODUCT(MATCH(SUMPRODUCT(MAX(('DAILY ENTRY'!$C$7:$C$1203=$A32)*'DAILY ENTRY'!$A$7:$A$1203)),('DAILY ENTRY'!$C$7:$C$1203=$A32)*'DAILY ENTRY'!$A$7:$A$1203,0))),"") -> 0 | J32: =COUNTIFS('DAILY ENTRY'!$C$7:$C$1203,$A32,'DAILY ENTRY'!$I$7:$I$1203,"Blocked") -> 0 | K32: =IF($C32="Complete",IF(D32=0,"Account is live but nothing has been done on it yet",IF(H32>14,"Live but untouched for over two weeks","Active")),IF($C32="Not Started","Not set up yet","Setup in progress")) -> Not set up yet
A33: ='Platform Setup'!$B$33 -> Capterra | B33: ='Platform Setup'!$C$33 -> Directory/Review | C33: ='Platform Setup'!$J$33 -> Not Started | D33: =COUNTIF('DAILY ENTRY'!$C$7:$C$1203,$A33) -> 0 | E33: =SUMIF('DAILY ENTRY'!$C$7:$C$1203,$A33,'DAILY ENTRY'!$F$7:$F$1203) -> 0 | F33: =SUMIF('DAILY ENTRY'!$C$7:$C$1203,$A33,'DAILY ENTRY'!$G$7:$G$1203) -> 0 | G33: =IFERROR(SUMPRODUCT(MAX(('DAILY ENTRY'!$C$7:$C$1203=$A33)*'DAILY ENTRY'!$A$7:$A$1203)),"") -> 0 | H33: =IF(G33="","",TODAY()-G33) -> 46251 | I33: =IFERROR(INDEX('DAILY ENTRY'!$B$7:$B$1203,SUMPRODUCT(MATCH(SUMPRODUCT(MAX(('DAILY ENTRY'!$C$7:$C$1203=$A33)*'DAILY ENTRY'!$A$7:$A$1203)),('DAILY ENTRY'!$C$7:$C$1203=$A33)*'DAILY ENTRY'!$A$7:$A$1203,0))),"") -> 0 | J33: =COUNTIFS('DAILY ENTRY'!$C$7:$C$1203,$A33,'DAILY ENTRY'!$I$7:$I$1203,"Blocked") -> 0 | K33: =IF($C33="Complete",IF(D33=0,"Account is live but nothing has been done on it yet",IF(H33>14,"Live but untouched for over two weeks","Active")),IF($C33="Not Started","Not set up yet","Setup in progress")) -> Not set up yet
A34: ='Platform Setup'!$B$34 -> Clutch | B34: ='Platform Setup'!$C$34 -> Directory/Review | C34: ='Platform Setup'!$J$34 -> Not Started | D34: =COUNTIF('DAILY ENTRY'!$C$7:$C$1203,$A34) -> 0 | E34: =SUMIF('DAILY ENTRY'!$C$7:$C$1203,$A34,'DAILY ENTRY'!$F$7:$F$1203) -> 0 | F34: =SUMIF('DAILY ENTRY'!$C$7:$C$1203,$A34,'DAILY ENTRY'!$G$7:$G$1203) -> 0 | G34: =IFERROR(SUMPRODUCT(MAX(('DAILY ENTRY'!$C$7:$C$1203=$A34)*'DAILY ENTRY'!$A$7:$A$1203)),"") -> 0 | H34: =IF(G34="","",TODAY()-G34) -> 46251 | I34: =IFERROR(INDEX('DAILY ENTRY'!$B$7:$B$1203,SUMPRODUCT(MATCH(SUMPRODUCT(MAX(('DAILY ENTRY'!$C$7:$C$1203=$A34)*'DAILY ENTRY'!$A$7:$A$1203)),('DAILY ENTRY'!$C$7:$C$1203=$A34)*'DAILY ENTRY'!$A$7:$A$1203,0))),"") -> 0 | J34: =COUNTIFS('DAILY ENTRY'!$C$7:$C$1203,$A34,'DAILY ENTRY'!$I$7:$I$1203,"Blocked") -> 0 | K34: =IF($C34="Complete",IF(D34=0,"Account is live but nothing has been done on it yet",IF(H34>14,"Live but untouched for over two weeks","Active")),IF($C34="Not Started","Not set up yet","Setup in progress")) -> Not set up yet
A35: ='Platform Setup'!$B$35 -> Eventbrite | B35: ='Platform Setup'!$C$35 -> Events | C35: ='Platform Setup'!$J$35 -> Not Started | D35: =COUNTIF('DAILY ENTRY'!$C$7:$C$1203,$A35) -> 0 | E35: =SUMIF('DAILY ENTRY'!$C$7:$C$1203,$A35,'DAILY ENTRY'!$F$7:$F$1203) -> 0 | F35: =SUMIF('DAILY ENTRY'!$C$7:$C$1203,$A35,'DAILY ENTRY'!$G$7:$G$1203) -> 0 | G35: =IFERROR(SUMPRODUCT(MAX(('DAILY ENTRY'!$C$7:$C$1203=$A35)*'DAILY ENTRY'!$A$7:$A$1203)),"") -> 0 | H35: =IF(G35="","",TODAY()-G35) -> 46251 | I35: =IFERROR(INDEX('DAILY ENTRY'!$B$7:$B$1203,SUMPRODUCT(MATCH(SUMPRODUCT(MAX(('DAILY ENTRY'!$C$7:$C$1203=$A35)*'DAILY ENTRY'!$A$7:$A$1203)),('DAILY ENTRY'!$C$7:$C$1203=$A35)*'DAILY ENTRY'!$A$7:$A$1203,0))),"") -> 0 | J35: =COUNTIFS('DAILY ENTRY'!$C$7:$C$1203,$A35,'DAILY ENTRY'!$I$7:$I$1203,"Blocked") -> 0 | K35: =IF($C35="Complete",IF(D35=0,"Account is live but nothing has been done on it yet",IF(H35>14,"Live but untouched for over two weeks","Active")),IF($C35="Not Started","Not set up yet","Setup in progress")) -> Not set up yet
A36: ='Platform Setup'!$B$36 -> Meetup | B36: ='Platform Setup'!$C$36 -> Events | C36: ='Platform Setup'!$J$36 -> Not Started | D36: =COUNTIF('DAILY ENTRY'!$C$7:$C$1203,$A36) -> 0 | E36: =SUMIF('DAILY ENTRY'!$C$7:$C$1203,$A36,'DAILY ENTRY'!$F$7:$F$1203) -> 0 | F36: =SUMIF('DAILY ENTRY'!$C$7:$C$1203,$A36,'DAILY ENTRY'!$G$7:$G$1203) -> 0 | G36: =IFERROR(SUMPRODUCT(MAX(('DAILY ENTRY'!$C$7:$C$1203=$A36)*'DAILY ENTRY'!$A$7:$A$1203)),"") -> 0 | H36: =IF(G36="","",TODAY()-G36) -> 46251 | I36: =IFERROR(INDEX('DAILY ENTRY'!$B$7:$B$1203,SUMPRODUCT(MATCH(SUMPRODUCT(MAX(('DAILY ENTRY'!$C$7:$C$1203=$A36)*'DAILY ENTRY'!$A$7:$A$1203)),('DAILY ENTRY'!$C$7:$C$1203=$A36)*'DAILY ENTRY'!$A$7:$A$1203,0))),"") -> 0 | J36: =COUNTIFS('DAILY ENTRY'!$C$7:$C$1203,$A36,'DAILY ENTRY'!$I$7:$I$1203,"Blocked") -> 0 | K36: =IF($C36="Complete",IF(D36=0,"Account is live but nothing has been done on it yet",IF(H36>14,"Live but untouched for over two weeks","Active")),IF($C36="Not Started","Not set up yet","Setup in progress")) -> Not set up yet
A37: ='Platform Setup'!$B$37 -> Luma | B37: ='Platform Setup'!$C$37 -> Events | C37: ='Platform Setup'!$J$37 -> Not Started | D37: =COUNTIF('DAILY ENTRY'!$C$7:$C$1203,$A37) -> 0 | E37: =SUMIF('DAILY ENTRY'!$C$7:$C$1203,$A37,'DAILY ENTRY'!$F$7:$F$1203) -> 0 | F37: =SUMIF('DAILY ENTRY'!$C$7:$C$1203,$A37,'DAILY ENTRY'!$G$7:$G$1203) -> 0 | G37: =IFERROR(SUMPRODUCT(MAX(('DAILY ENTRY'!$C$7:$C$1203=$A37)*'DAILY ENTRY'!$A$7:$A$1203)),"") -> 0 | H37: =IF(G37="","",TODAY()-G37) -> 46251 | I37: =IFERROR(INDEX('DAILY ENTRY'!$B$7:$B$1203,SUMPRODUCT(MATCH(SUMPRODUCT(MAX(('DAILY ENTRY'!$C$7:$C$1203=$A37)*'DAILY ENTRY'!$A$7:$A$1203)),('DAILY ENTRY'!$C$7:$C$1203=$A37)*'DAILY ENTRY'!$A$7:$A$1203,0))),"") -> 0 | J37: =COUNTIFS('DAILY ENTRY'!$C$7:$C$1203,$A37,'DAILY ENTRY'!$I$7:$I$1203,"Blocked") -> 0 | K37: =IF($C37="Complete",IF(D37=0,"Account is live but nothing has been done on it yet",IF(H37>14,"Live but untouched for over two weeks","Active")),IF($C37="Not Started","Not set up yet","Setup in progress")) -> Not set up yet
A38: ='Platform Setup'!$B$38 -> Spotify for Creators | B38: ='Platform Setup'!$C$38 -> Events | C38: ='Platform Setup'!$J$38 -> Not Started | D38: =COUNTIF('DAILY ENTRY'!$C$7:$C$1203,$A38) -> 0 | E38: =SUMIF('DAILY ENTRY'!$C$7:$C$1203,$A38,'DAILY ENTRY'!$F$7:$F$1203) -> 0 | F38: =SUMIF('DAILY ENTRY'!$C$7:$C$1203,$A38,'DAILY ENTRY'!$G$7:$G$1203) -> 0 | G38: =IFERROR(SUMPRODUCT(MAX(('DAILY ENTRY'!$C$7:$C$1203=$A38)*'DAILY ENTRY'!$A$7:$A$1203)),"") -> 0 | H38: =IF(G38="","",TODAY()-G38) -> 46251 | I38: =IFERROR(INDEX('DAILY ENTRY'!$B$7:$B$1203,SUMPRODUCT(MATCH(SUMPRODUCT(MAX(('DAILY ENTRY'!$C$7:$C$1203=$A38)*'DAILY ENTRY'!$A$7:$A$1203)),('DAILY ENTRY'!$C$7:$C$1203=$A38)*'DAILY ENTRY'!$A$7:$A$1203,0))),"") -> 0 | J38: =COUNTIFS('DAILY ENTRY'!$C$7:$C$1203,$A38,'DAILY ENTRY'!$I$7:$I$1203,"Blocked") -> 0 | K38: =IF($C38="Complete",IF(D38=0,"Account is live but nothing has been done on it yet",IF(H38>14,"Live but untouched for over two weeks","Active")),IF($C38="Not Started","Not set up yet","Setup in progress")) -> Not set up yet
A39: ='Platform Setup'!$B$39 -> Apple Podcasts | B39: ='Platform Setup'!$C$39 -> Events | C39: ='Platform Setup'!$J$39 -> Not Started | D39: =COUNTIF('DAILY ENTRY'!$C$7:$C$1203,$A39) -> 0 | E39: =SUMIF('DAILY ENTRY'!$C$7:$C$1203,$A39,'DAILY ENTRY'!$F$7:$F$1203) -> 0 | F39: =SUMIF('DAILY ENTRY'!$C$7:$C$1203,$A39,'DAILY ENTRY'!$G$7:$G$1203) -> 0 | G39: =IFERROR(SUMPRODUCT(MAX(('DAILY ENTRY'!$C$7:$C$1203=$A39)*'DAILY ENTRY'!$A$7:$A$1203)),"") -> 0 | H39: =IF(G39="","",TODAY()-G39) -> 46251 | I39: =IFERROR(INDEX('DAILY ENTRY'!$B$7:$B$1203,SUMPRODUCT(MATCH(SUMPRODUCT(MAX(('DAILY ENTRY'!$C$7:$C$1203=$A39)*'DAILY ENTRY'!$A$7:$A$1203)),('DAILY ENTRY'!$C$7:$C$1203=$A39)*'DAILY ENTRY'!$A$7:$A$1203,0))),"") -> 0 | J39: =COUNTIFS('DAILY ENTRY'!$C$7:$C$1203,$A39,'DAILY ENTRY'!$I$7:$I$1203,"Blocked") -> 0 | K39: =IF($C39="Complete",IF(D39=0,"Account is live but nothing has been done on it yet",IF(H39>14,"Live but untouched for over two weeks","Active")),IF($C39="Not Started","Not set up yet","Setup in progress")) -> Not set up yet
A40: ='Platform Setup'!$B$40 -> LinkedIn Articles | B40: ='Platform Setup'!$C$40 -> Publishing | C40: ='Platform Setup'!$J$40 -> Not Started | D40: =COUNTIF('DAILY ENTRY'!$C$7:$C$1203,$A40) -> 0 | E40: =SUMIF('DAILY ENTRY'!$C$7:$C$1203,$A40,'DAILY ENTRY'!$F$7:$F$1203) -> 0 | F40: =SUMIF('DAILY ENTRY'!$C$7:$C$1203,$A40,'DAILY ENTRY'!$G$7:$G$1203) -> 0 | G40: =IFERROR(SUMPRODUCT(MAX(('DAILY ENTRY'!$C$7:$C$1203=$A40)*'DAILY ENTRY'!$A$7:$A$1203)),"") -> 0 | H40: =IF(G40="","",TODAY()-G40) -> 46251 | I40: =IFERROR(INDEX('DAILY ENTRY'!$B$7:$B$1203,SUMPRODUCT(MATCH(SUMPRODUCT(MAX(('DAILY ENTRY'!$C$7:$C$1203=$A40)*'DAILY ENTRY'!$A$7:$A$1203)),('DAILY ENTRY'!$C$7:$C$1203=$A40)*'DAILY ENTRY'!$A$7:$A$1203,0))),"") -> 0 | J40: =COUNTIFS('DAILY ENTRY'!$C$7:$C$1203,$A40,'DAILY ENTRY'!$I$7:$I$1203,"Blocked") -> 0 | K40: =IF($C40="Complete",IF(D40=0,"Account is live but nothing has been done on it yet",IF(H40>14,"Live but untouched for over two weeks","Active")),IF($C40="Not Started","Not set up yet","Setup in progress")) -> Not set up yet
A41: ='Platform Setup'!$B$41 -> WordPress.com | B41: ='Platform Setup'!$C$41 -> Publishing | C41: ='Platform Setup'!$J$41 -> Not Started | D41: =COUNTIF('DAILY ENTRY'!$C$7:$C$1203,$A41) -> 0 | E41: =SUMIF('DAILY ENTRY'!$C$7:$C$1203,$A41,'DAILY ENTRY'!$F$7:$F$1203) -> 0 | F41: =SUMIF('DAILY ENTRY'!$C$7:$C$1203,$A41,'DAILY ENTRY'!$G$7:$G$1203) -> 0 | G41: =IFERROR(SUMPRODUCT(MAX(('DAILY ENTRY'!$C$7:$C$1203=$A41)*'DAILY ENTRY'!$A$7:$A$1203)),"") -> 0 | H41: =IF(G41="","",TODAY()-G41) -> 46251 | I41: =IFERROR(INDEX('DAILY ENTRY'!$B$7:$B$1203,SUMPRODUCT(MATCH(SUMPRODUCT(MAX(('DAILY ENTRY'!$C$7:$C$1203=$A41)*'DAILY ENTRY'!$A$7:$A$1203)),('DAILY ENTRY'!$C$7:$C$1203=$A41)*'DAILY ENTRY'!$A$7:$A$1203,0))),"") -> 0 | J41: =COUNTIFS('DAILY ENTRY'!$C$7:$C$1203,$A41,'DAILY ENTRY'!$I$7:$I$1203,"Blocked") -> 0 | K41: =IF($C41="Complete",IF(D41=0,"Account is live but nothing has been done on it yet",IF(H41>14,"Live but untouched for over two weeks","Active")),IF($C41="Not Started","Not set up yet","Setup in progress")) -> Not set up yet
A42: ='Platform Setup'!$B$42 -> Blogger | B42: ='Platform Setup'!$C$42 -> Publishing | C42: ='Platform Setup'!$J$42 -> Not Started | D42: =COUNTIF('DAILY ENTRY'!$C$7:$C$1203,$A42) -> 0 | E42: =SUMIF('DAILY ENTRY'!$C$7:$C$1203,$A42,'DAILY ENTRY'!$F$7:$F$1203) -> 0 | F42: =SUMIF('DAILY ENTRY'!$C$7:$C$1203,$A42,'DAILY ENTRY'!$G$7:$G$1203) -> 0 | G42: =IFERROR(SUMPRODUCT(MAX(('DAILY ENTRY'!$C$7:$C$1203=$A42)*'DAILY ENTRY'!$A$7:$A$1203)),"") -> 0 | H42: =IF(G42="","",TODAY()-G42) -> 46251 | I42: =IFERROR(INDEX('DAILY ENTRY'!$B$7:$B$1203,SUMPRODUCT(MATCH(SUMPRODUCT(MAX(('DAILY ENTRY'!$C$7:$C$1203=$A42)*'DAILY ENTRY'!$A$7:$A$1203)),('DAILY ENTRY'!$C$7:$C$1203=$A42)*'DAILY ENTRY'!$A$7:$A$1203,0))),"") -> 0 | J42: =COUNTIFS('DAILY ENTRY'!$C$7:$C$1203,$A42,'DAILY ENTRY'!$I$7:$I$1203,"Blocked") -> 0 | K42: =IF($C42="Complete",IF(D42=0,"Account is live but nothing has been done on it yet",IF(H42>14,"Live but untouched for over two weeks","Active")),IF($C42="Not Started","Not set up yet","Setup in progress")) -> Not set up yet
A43: ='Platform Setup'!$B$43 -> Quora Spaces | B43: ='Platform Setup'!$C$43 -> Community | C43: ='Platform Setup'!$J$43 -> Not Started | D43: =COUNTIF('DAILY ENTRY'!$C$7:$C$1203,$A43) -> 0 | E43: =SUMIF('DAILY ENTRY'!$C$7:$C$1203,$A43,'DAILY ENTRY'!$F$7:$F$1203) -> 0 | F43: =SUMIF('DAILY ENTRY'!$C$7:$C$1203,$A43,'DAILY ENTRY'!$G$7:$G$1203) -> 0 | G43: =IFERROR(SUMPRODUCT(MAX(('DAILY ENTRY'!$C$7:$C$1203=$A43)*'DAILY ENTRY'!$A$7:$A$1203)),"") -> 0 | H43: =IF(G43="","",TODAY()-G43) -> 46251 | I43: =IFERROR(INDEX('DAILY ENTRY'!$B$7:$B$1203,SUMPRODUCT(MATCH(SUMPRODUCT(MAX(('DAILY ENTRY'!$C$7:$C$1203=$A43)*'DAILY ENTRY'!$A$7:$A$1203)),('DAILY ENTRY'!$C$7:$C$1203=$A43)*'DAILY ENTRY'!$A$7:$A$1203,0))),"") -> 0 | J43: =COUNTIFS('DAILY ENTRY'!$C$7:$C$1203,$A43,'DAILY ENTRY'!$I$7:$I$1203,"Blocked") -> 0 | K43: =IF($C43="Complete",IF(D43=0,"Account is live but nothing has been done on it yet",IF(H43>14,"Live but untouched for over two weeks","Active")),IF($C43="Not Started","Not set up yet","Setup in progress")) -> Not set up yet
A44: ='Platform Setup'!$B$44 -> Vocal Media | B44: ='Platform Setup'!$C$44 -> Publishing | C44: ='Platform Setup'!$J$44 -> Not Started | D44: =COUNTIF('DAILY ENTRY'!$C$7:$C$1203,$A44) -> 0 | E44: =SUMIF('DAILY ENTRY'!$C$7:$C$1203,$A44,'DAILY ENTRY'!$F$7:$F$1203) -> 0 | F44: =SUMIF('DAILY ENTRY'!$C$7:$C$1203,$A44,'DAILY ENTRY'!$G$7:$G$1203) -> 0 | G44: =IFERROR(SUMPRODUCT(MAX(('DAILY ENTRY'!$C$7:$C$1203=$A44)*'DAILY ENTRY'!$A$7:$A$1203)),"") -> 0 | H44: =IF(G44="","",TODAY()-G44) -> 46251 | I44: =IFERROR(INDEX('DAILY ENTRY'!$B$7:$B$1203,SUMPRODUCT(MATCH(SUMPRODUCT(MAX(('DAILY ENTRY'!$C$7:$C$1203=$A44)*'DAILY ENTRY'!$A$7:$A$1203)),('DAILY ENTRY'!$C$7:$C$1203=$A44)*'DAILY ENTRY'!$A$7:$A$1203,0))),"") -> 0 | J44: =COUNTIFS('DAILY ENTRY'!$C$7:$C$1203,$A44,'DAILY ENTRY'!$I$7:$I$1203,"Blocked") -> 0 | K44: =IF($C44="Complete",IF(D44=0,"Account is live but nothing has been done on it yet",IF(H44>14,"Live but untouched for over two weeks","Active")),IF($C44="Not Started","Not set up yet","Setup in progress")) -> Not set up yet
A45: ='Platform Setup'!$B$45 -> DEV Community | B45: ='Platform Setup'!$C$45 -> Publishing | C45: ='Platform Setup'!$J$45 -> Not Started | D45: =COUNTIF('DAILY ENTRY'!$C$7:$C$1203,$A45) -> 0 | E45: =SUMIF('DAILY ENTRY'!$C$7:$C$1203,$A45,'DAILY ENTRY'!$F$7:$F$1203) -> 0 | F45: =SUMIF('DAILY ENTRY'!$C$7:$C$1203,$A45,'DAILY ENTRY'!$G$7:$G$1203) -> 0 | G45: =IFERROR(SUMPRODUCT(MAX(('DAILY ENTRY'!$C$7:$C$1203=$A45)*'DAILY ENTRY'!$A$7:$A$1203)),"") -> 0 | H45: =IF(G45="","",TODAY()-G45) -> 46251 | I45: =IFERROR(INDEX('DAILY ENTRY'!$B$7:$B$1203,SUMPRODUCT(MATCH(SUMPRODUCT(MAX(('DAILY ENTRY'!$C$7:$C$1203=$A45)*'DAILY ENTRY'!$A$7:$A$1203)),('DAILY ENTRY'!$C$7:$C$1203=$A45)*'DAILY ENTRY'!$A$7:$A$1203,0))),"") -> 0 | J45: =COUNTIFS('DAILY ENTRY'!$C$7:$C$1203,$A45,'DAILY ENTRY'!$I$7:$I$1203,"Blocked") -> 0 | K45: =IF($C45="Complete",IF(D45=0,"Account is live but nothing has been done on it yet",IF(H45>14,"Live but untouched for over two weeks","Active")),IF($C45="Not Started","Not set up yet","Setup in progress")) -> Not set up yet
A46: ='Platform Setup'!$B$46 -> Hashnode | B46: ='Platform Setup'!$C$46 -> Publishing | C46: ='Platform Setup'!$J$46 -> Not Started | D46: =COUNTIF('DAILY ENTRY'!$C$7:$C$1203,$A46) -> 0 | E46: =SUMIF('DAILY ENTRY'!$C$7:$C$1203,$A46,'DAILY ENTRY'!$F$7:$F$1203) -> 0 | F46: =SUMIF('DAILY ENTRY'!$C$7:$C$1203,$A46,'DAILY ENTRY'!$G$7:$G$1203) -> 0 | G46: =IFERROR(SUMPRODUCT(MAX(('DAILY ENTRY'!$C$7:$C$1203=$A46)*'DAILY ENTRY'!$A$7:$A$1203)),"") -> 0 | H46: =IF(G46="","",TODAY()-G46) -> 46251 | I46: =IFERROR(INDEX('DAILY ENTRY'!$B$7:$B$1203,SUMPRODUCT(MATCH(SUMPRODUCT(MAX(('DAILY ENTRY'!$C$7:$C$1203=$A46)*'DAILY ENTRY'!$A$7:$A$1203)),('DAILY ENTRY'!$C$7:$C$1203=$A46)*'DAILY ENTRY'!$A$7:$A$1203,0))),"") -> 0 | J46: =COUNTIFS('DAILY ENTRY'!$C$7:$C$1203,$A46,'DAILY ENTRY'!$I$7:$I$1203,"Blocked") -> 0 | K46: =IF($C46="Complete",IF(D46=0,"Account is live but nothing has been done on it yet",IF(H46>14,"Live but untouched for over two weeks","Active")),IF($C46="Not Started","Not set up yet","Setup in progress")) -> Not set up yet
A47: ='Platform Setup'!$B$47 -> Google Search Console | B47: ='Platform Setup'!$C$47 -> Analytics | C47: ='Platform Setup'!$J$47 -> Not Started | D47: =COUNTIF('DAILY ENTRY'!$C$7:$C$1203,$A47) -> 0 | E47: =SUMIF('DAILY ENTRY'!$C$7:$C$1203,$A47,'DAILY ENTRY'!$F$7:$F$1203) -> 0 | F47: =SUMIF('DAILY ENTRY'!$C$7:$C$1203,$A47,'DAILY ENTRY'!$G$7:$G$1203) -> 0 | G47: =IFERROR(SUMPRODUCT(MAX(('DAILY ENTRY'!$C$7:$C$1203=$A47)*'DAILY ENTRY'!$A$7:$A$1203)),"") -> 0 | H47: =IF(G47="","",TODAY()-G47) -> 46251 | I47: =IFERROR(INDEX('DAILY ENTRY'!$B$7:$B$1203,SUMPRODUCT(MATCH(SUMPRODUCT(MAX(('DAILY ENTRY'!$C$7:$C$1203=$A47)*'DAILY ENTRY'!$A$7:$A$1203)),('DAILY ENTRY'!$C$7:$C$1203=$A47)*'DAILY ENTRY'!$A$7:$A$1203,0))),"") -> 0 | J47: =COUNTIFS('DAILY ENTRY'!$C$7:$C$1203,$A47,'DAILY ENTRY'!$I$7:$I$1203,"Blocked") -> 0 | K47: =IF($C47="Complete",IF(D47=0,"Account is live but nothing has been done on it yet",IF(H47>14,"Live but untouched for over two weeks","Active")),IF($C47="Not Started","Not set up yet","Setup in progress")) -> Not set up yet
A48: ='Platform Setup'!$B$48 -> Google Analytics | B48: ='Platform Setup'!$C$48 -> Analytics | C48: ='Platform Setup'!$J$48 -> Not Started | D48: =COUNTIF('DAILY ENTRY'!$C$7:$C$1203,$A48) -> 0 | E48: =SUMIF('DAILY ENTRY'!$C$7:$C$1203,$A48,'DAILY ENTRY'!$F$7:$F$1203) -> 0 | F48: =SUMIF('DAILY ENTRY'!$C$7:$C$1203,$A48,'DAILY ENTRY'!$G$7:$G$1203) -> 0 | G48: =IFERROR(SUMPRODUCT(MAX(('DAILY ENTRY'!$C$7:$C$1203=$A48)*'DAILY ENTRY'!$A$7:$A$1203)),"") -> 0 | H48: =IF(G48="","",TODAY()-G48) -> 46251 | I48: =IFERROR(INDEX('DAILY ENTRY'!$B$7:$B$1203,SUMPRODUCT(MATCH(SUMPRODUCT(MAX(('DAILY ENTRY'!$C$7:$C$1203=$A48)*'DAILY ENTRY'!$A$7:$A$1203)),('DAILY ENTRY'!$C$7:$C$1203=$A48)*'DAILY ENTRY'!$A$7:$A$1203,0))),"") -> 0 | J48: =COUNTIFS('DAILY ENTRY'!$C$7:$C$1203,$A48,'DAILY ENTRY'!$I$7:$I$1203,"Blocked") -> 0 | K48: =IF($C48="Complete",IF(D48=0,"Account is live but nothing has been done on it yet",IF(H48>14,"Live but untouched for over two weeks","Active")),IF($C48="Not Started","Not set up yet","Setup in progress")) -> Not set up yet
A49: ='Platform Setup'!$B$49 -> Microsoft Clarity | B49: ='Platform Setup'!$C$49 -> Analytics | C49: ='Platform Setup'!$J$49 -> Not Started | D49: =COUNTIF('DAILY ENTRY'!$C$7:$C$1203,$A49) -> 0 | E49: =SUMIF('DAILY ENTRY'!$C$7:$C$1203,$A49,'DAILY ENTRY'!$F$7:$F$1203) -> 0 | F49: =SUMIF('DAILY ENTRY'!$C$7:$C$1203,$A49,'DAILY ENTRY'!$G$7:$G$1203) -> 0 | G49: =IFERROR(SUMPRODUCT(MAX(('DAILY ENTRY'!$C$7:$C$1203=$A49)*'DAILY ENTRY'!$A$7:$A$1203)),"") -> 0 | H49: =IF(G49="","",TODAY()-G49) -> 46251 | I49: =IFERROR(INDEX('DAILY ENTRY'!$B$7:$B$1203,SUMPRODUCT(MATCH(SUMPRODUCT(MAX(('DAILY ENTRY'!$C$7:$C$1203=$A49)*'DAILY ENTRY'!$A$7:$A$1203)),('DAILY ENTRY'!$C$7:$C$1203=$A49)*'DAILY ENTRY'!$A$7:$A$1203,0))),"") -> 0 | J49: =COUNTIFS('DAILY ENTRY'!$C$7:$C$1203,$A49,'DAILY ENTRY'!$I$7:$I$1203,"Blocked") -> 0 | K49: =IF($C49="Complete",IF(D49=0,"Account is live but nothing has been done on it yet",IF(H49>14,"Live but untouched for over two weeks","Active")),IF($C49="Not Started","Not set up yet","Setup in progress")) -> Not set up yet

Sheet Who Did What
A1: WHO DID WHAT — every platform against every team member
A2: Counts of logged activity from the DAILY ENTRY tab. Empty cells mean nobody has touched that platform.
A3: Platform | B3: =IF('START HERE'!$B$55="","(empty slot)",'START HERE'!$B$55) -> Employee 1 | C3: =IF('START HERE'!$B$56="","(empty slot)",'START HERE'!$B$56) -> (empty slot) | D3: =IF('START HERE'!$B$57="","(empty slot)",'START HERE'!$B$57) -> (empty slot) | E3: =IF('START HERE'!$B$58="","(empty slot)",'START HERE'!$B$58) -> (empty slot) | F3: =IF('START HERE'!$B$59="","(empty slot)",'START HERE'!$B$59) -> (empty slot) | G3: =IF('START HERE'!$B$60="","(empty slot)",'START HERE'!$B$60) -> (empty slot) | H3: =IF('START HERE'!$B$61="","(empty slot)",'START HERE'!$B$61) -> (empty slot) | I3: =IF('START HERE'!$B$62="","(empty slot)",'START HERE'!$B$62) -> (empty slot) | J3: =IF('START HERE'!$B$63="","(empty slot)",'START HERE'!$B$63) -> (empty slot) | K3: =IF('START HERE'!$B$64="","(empty slot)",'START HERE'!$B$64) -> (empty slot) | L3: Total
A4: ='Platform Setup'!$B$4 -> LinkedIn Company Page | B4: =IF(B$3="(empty slot)","",COUNTIFS('DAILY ENTRY'!$C$7:$C$1203,$A4,'DAILY ENTRY'!$B$7:$B$1203,B$3)) -> 0 | C4: =IF(C$3="(empty slot)","",COUNTIFS('DAILY ENTRY'!$C$7:$C$1203,$A4,'DAILY ENTRY'!$B$7:$B$1203,C$3)) | D4: =IF(D$3="(empty slot)","",COUNTIFS('DAILY ENTRY'!$C$7:$C$1203,$A4,'DAILY ENTRY'!$B$7:$B$1203,D$3)) | E4: =IF(E$3="(empty slot)","",COUNTIFS('DAILY ENTRY'!$C$7:$C$1203,$A4,'DAILY ENTRY'!$B$7:$B$1203,E$3)) | F4: =IF(F$3="(empty slot)","",COUNTIFS('DAILY ENTRY'!$C$7:$C$1203,$A4,'DAILY ENTRY'!$B$7:$B$1203,F$3)) | G4: =IF(G$3="(empty slot)","",COUNTIFS('DAILY ENTRY'!$C$7:$C$1203,$A4,'DAILY ENTRY'!$B$7:$B$1203,G$3)) | H4: =IF(H$3="(empty slot)","",COUNTIFS('DAILY ENTRY'!$C$7:$C$1203,$A4,'DAILY ENTRY'!$B$7:$B$1203,H$3)) | I4: =IF(I$3="(empty slot)","",COUNTIFS('DAILY ENTRY'!$C$7:$C$1203,$A4,'DAILY ENTRY'!$B$7:$B$1203,I$3)) | ... K4: =IF(K$3="(empty slot)","",COUNTIFS('DAILY ENTRY'!$C$7:$C$1203,$A4,'DAILY ENTRY'!$B$7:$B$1203,K$3)) | L4: =COUNTIF('DAILY ENTRY'!$C$7:$C$1203,$A4) -> 0
A5: ='Platform Setup'!$B$5 -> LinkedIn Personal Profile | B5: =IF(B$3="(empty slot)","",COUNTIFS('DAILY ENTRY'!$C$7:$C$1203,$A5,'DAILY ENTRY'!$B$7:$B$1203,B$3)) -> 0 | C5: =IF(C$3="(empty slot)","",COUNTIFS('DAILY ENTRY'!$C$7:$C$1203,$A5,'DAILY ENTRY'!$B$7:$B$1203,C$3)) | D5: =IF(D$3="(empty slot)","",COUNTIFS('DAILY ENTRY'!$C$7:$C$1203,$A5,'DAILY ENTRY'!$B$7:$B$1203,D$3)) | E5: =IF(E$3="(empty slot)","",COUNTIFS('DAILY ENTRY'!$C$7:$C$1203,$A5,'DAILY ENTRY'!$B$7:$B$1203,E$3)) | F5: =IF(F$3="(empty slot)","",COUNTIFS('DAILY ENTRY'!$C$7:$C$1203,$A5,'DAILY ENTRY'!$B$7:$B$1203,F$3)) | G5: =IF(G$3="(empty slot)","",COUNTIFS('DAILY ENTRY'!$C$7:$C$1203,$A5,'DAILY ENTRY'!$B$7:$B$1203,G$3)) | H5: =IF(H$3="(empty slot)","",COUNTIFS('DAILY ENTRY'!$C$7:$C$1203,$A5,'DAILY ENTRY'!$B$7:$B$1203,H$3)) | I5: =IF(I$3="(empty slot)","",COUNTIFS('DAILY ENTRY'!$C$7:$C$1203,$A5,'DAILY ENTRY'!$B$7:$B$1203,I$3)) | ... K5: =IF(K$3="(empty slot)","",COUNTIFS('DAILY ENTRY'!$C$7:$C$1203,$A5,'DAILY ENTRY'!$B$7:$B$1203,K$3)) | L5: =COUNTIF('DAILY ENTRY'!$C$7:$C$1203,$A5) -> 0
A6: ='Platform Setup'!$B$6 -> LinkedIn Sales Navigator | B6: =IF(B$3="(empty slot)","",COUNTIFS('DAILY ENTRY'!$C$7:$C$1203,$A6,'DAILY ENTRY'!$B$7:$B$1203,B$3)) -> 0 | C6: =IF(C$3="(empty slot)","",COUNTIFS('DAILY ENTRY'!$C$7:$C$1203,$A6,'DAILY ENTRY'!$B$7:$B$1203,C$3)) | D6: =IF(D$3="(empty slot)","",COUNTIFS('DAILY ENTRY'!$C$7:$C$1203,$A6,'DAILY ENTRY'!$B$7:$B$1203,D$3)) | E6: =IF(E$3="(empty slot)","",COUNTIFS('DAILY ENTRY'!$C$7:$C$1203,$A6,'DAILY ENTRY'!$B$7:$B$1203,E$3)) | F6: =IF(F$3="(empty slot)","",COUNTIFS('DAILY ENTRY'!$C$7:$C$1203,$A6,'DAILY ENTRY'!$B$7:$B$1203,F$3)) | G6: =IF(G$3="(empty slot)","",COUNTIFS('DAILY ENTRY'!$C$7:$C$1203,$A6,'DAILY ENTRY'!$B$7:$B$1203,G$3)) | H6: =IF(H$3="(empty slot)","",COUNTIFS('DAILY ENTRY'!$C$7:$C$1203,$A6,'DAILY ENTRY'!$B$7:$B$1203,H$3)) | I6: =IF(I$3="(empty slot)","",COUNTIFS('DAILY ENTRY'!$C$7:$C$1203,$A6,'DAILY ENTRY'!$B$7:$B$1203,I$3)) | ... K6: =IF(K$3="(empty slot)","",COUNTIFS('DAILY ENTRY'!$C$7:$C$1203,$A6,'DAILY ENTRY'!$B$7:$B$1203,K$3)) | L6: =COUNTIF('DAILY ENTRY'!$C$7:$C$1203,$A6) -> 0
A7: ='Platform Setup'!$B$7 -> LinkedIn Newsletter | B7: =IF(B$3="(empty slot)","",COUNTIFS('DAILY ENTRY'!$C$7:$C$1203,$A7,'DAILY ENTRY'!$B$7:$B$1203,B$3)) -> 0 | C7: =IF(C$3="(empty slot)","",COUNTIFS('DAILY ENTRY'!$C$7:$C$1203,$A7,'DAILY ENTRY'!$B$7:$B$1203,C$3)) | D7: =IF(D$3="(empty slot)","",COUNTIFS('DAILY ENTRY'!$C$7:$C$1203,$A7,'DAILY ENTRY'!$B$7:$B$1203,D$3)) | E7: =IF(E$3="(empty slot)","",COUNTIFS('DAILY ENTRY'!$C$7:$C$1203,$A7,'DAILY ENTRY'!$B$7:$B$1203,E$3)) | F7: =IF(F$3="(empty slot)","",COUNTIFS('DAILY ENTRY'!$C$7:$C$1203,$A7,'DAILY ENTRY'!$B$7:$B$1203,F$3)) | G7: =IF(G$3="(empty slot)","",COUNTIFS('DAILY ENTRY'!$C$7:$C$1203,$A7,'DAILY ENTRY'!$B$7:$B$1203,G$3)) | H7: =IF(H$3="(empty slot)","",COUNTIFS('DAILY ENTRY'!$C$7:$C$1203,$A7,'DAILY ENTRY'!$B$7:$B$1203,H$3)) | I7: =IF(I$3="(empty slot)","",COUNTIFS('DAILY ENTRY'!$C$7:$C$1203,$A7,'DAILY ENTRY'!$B$7:$B$1203,I$3)) | ... K7: =IF(K$3="(empty slot)","",COUNTIFS('DAILY ENTRY'!$C$7:$C$1203,$A7,'DAILY ENTRY'!$B$7:$B$1203,K$3)) | L7: =COUNTIF('DAILY ENTRY'!$C$7:$C$1203,$A7) -> 0
A8: ='Platform Setup'!$B$8 -> LinkedIn Groups | B8: =IF(B$3="(empty slot)","",COUNTIFS('DAILY ENTRY'!$C$7:$C$1203,$A8,'DAILY ENTRY'!$B$7:$B$1203,B$3)) -> 0 | C8: =IF(C$3="(empty slot)","",COUNTIFS('DAILY ENTRY'!$C$7:$C$1203,$A8,'DAILY ENTRY'!$B$7:$B$1203,C$3)) | D8: =IF(D$3="(empty slot)","",COUNTIFS('DAILY ENTRY'!$C$7:$C$1203,$A8,'DAILY ENTRY'!$B$7:$B$1203,D$3)) | E8: =IF(E$3="(empty slot)","",COUNTIFS('DAILY ENTRY'!$C$7:$C$1203,$A8,'DAILY ENTRY'!$B$7:$B$1203,E$3)) | F8: =IF(F$3="(empty slot)","",COUNTIFS('DAILY ENTRY'!$C$7:$C$1203,$A8,'DAILY ENTRY'!$B$7:$B$1203,F$3)) | G8: =IF(G$3="(empty slot)","",COUNTIFS('DAILY ENTRY'!$C$7:$C$1203,$A8,'DAILY ENTRY'!$B$7:$B$1203,G$3)) | H8: =IF(H$3="(empty slot)","",COUNTIFS('DAILY ENTRY'!$C$7:$C$1203,$A8,'DAILY ENTRY'!$B$7:$B$1203,H$3)) | I8: =IF(I$3="(empty slot)","",COUNTIFS('DAILY ENTRY'!$C$7:$C$1203,$A8,'DAILY ENTRY'!$B$7:$B$1203,I$3)) | ... K8: =IF(K$3="(empty slot)","",COUNTIFS('DAILY ENTRY'!$C$7:$C$1203,$A8,'DAILY ENTRY'!$B$7:$B$1203,K$3)) | L8: =COUNTIF('DAILY ENTRY'!$C$7:$C$1203,$A8) -> 0
A9: ='Platform Setup'!$B$9 -> Facebook Page | B9: =IF(B$3="(empty slot)","",COUNTIFS('DAILY ENTRY'!$C$7:$C$1203,$A9,'DAILY ENTRY'!$B$7:$B$1203,B$3)) -> 0 | C9: =IF(C$3="(empty slot)","",COUNTIFS('DAILY ENTRY'!$C$7:$C$1203,$A9,'DAILY ENTRY'!$B$7:$B$1203,C$3)) | D9: =IF(D$3="(empty slot)","",COUNTIFS('DAILY ENTRY'!$C$7:$C$1203,$A9,'DAILY ENTRY'!$B$7:$B$1203,D$3)) | E9: =IF(E$3="(empty slot)","",COUNTIFS('DAILY ENTRY'!$C$7:$C$1203,$A9,'DAILY ENTRY'!$B$7:$B$1203,E$3)) | F9: =IF(F$3="(empty slot)","",COUNTIFS('DAILY ENTRY'!$C$7:$C$1203,$A9,'DAILY ENTRY'!$B$7:$B$1203,F$3)) | G9: =IF(G$3="(empty slot)","",COUNTIFS('DAILY ENTRY'!$C$7:$C$1203,$A9,'DAILY ENTRY'!$B$7:$B$1203,G$3)) | H9: =IF(H$3="(empty slot)","",COUNTIFS('DAILY ENTRY'!$C$7:$C$1203,$A9,'DAILY ENTRY'!$B$7:$B$1203,H$3)) | I9: =IF(I$3="(empty slot)","",COUNTIFS('DAILY ENTRY'!$C$7:$C$1203,$A9,'DAILY ENTRY'!$B$7:$B$1203,I$3)) | ... K9: =IF(K$3="(empty slot)","",COUNTIFS('DAILY ENTRY'!$C$7:$C$1203,$A9,'DAILY ENTRY'!$B$7:$B$1203,K$3)) | L9: =COUNTIF('DAILY ENTRY'!$C$7:$C$1203,$A9) -> 0
A10: ='Platform Setup'!$B$10 -> Facebook Groups | B10: =IF(B$3="(empty slot)","",COUNTIFS('DAILY ENTRY'!$C$7:$C$1203,$A10,'DAILY ENTRY'!$B$7:$B$1203,B$3)) -> 0 | C10: =IF(C$3="(empty slot)","",COUNTIFS('DAILY ENTRY'!$C$7:$C$1203,$A10,'DAILY ENTRY'!$B$7:$B$1203,C$3)) | D10: =IF(D$3="(empty slot)","",COUNTIFS('DAILY ENTRY'!$C$7:$C$1203,$A10,'DAILY ENTRY'!$B$7:$B$1203,D$3)) | E10: =IF(E$3="(empty slot)","",COUNTIFS('DAILY ENTRY'!$C$7:$C$1203,$A10,'DAILY ENTRY'!$B$7:$B$1203,E$3)) | F10: =IF(F$3="(empty slot)","",COUNTIFS('DAILY ENTRY'!$C$7:$C$1203,$A10,'DAILY ENTRY'!$B$7:$B$1203,F$3)) | G10: =IF(G$3="(empty slot)","",COUNTIFS('DAILY ENTRY'!$C$7:$C$1203,$A10,'DAILY ENTRY'!$B$7:$B$1203,G$3)) | H10: =IF(H$3="(empty slot)","",COUNTIFS('DAILY ENTRY'!$C$7:$C$1203,$A10,'DAILY ENTRY'!$B$7:$B$1203,H$3)) | I10: =IF(I$3="(empty slot)","",COUNTIFS('DAILY ENTRY'!$C$7:$C$1203,$A10,'DAILY ENTRY'!$B$7:$B$1203,I$3)) | ... K10: =IF(K$3="(empty slot)","",COUNTIFS('DAILY ENTRY'!$C$7:$C$1203,$A10,'DAILY ENTRY'!$B$7:$B$1203,K$3)) | L10: =COUNTIF('DAILY ENTRY'!$C$7:$C$1203,$A10) -> 0
A11: ='Platform Setup'!$B$11 -> Instagram | B11: =IF(B$3="(empty slot)","",COUNTIFS('DAILY ENTRY'!$C$7:$C$1203,$A11,'DAILY ENTRY'!$B$7:$B$1203,B$3)) -> 0 | C11: =IF(C$3="(empty slot)","",COUNTIFS('DAILY ENTRY'!$C$7:$C$1203,$A11,'DAILY ENTRY'!$B$7:$B$1203,C$3)) | D11: =IF(D$3="(empty slot)","",COUNTIFS('DAILY ENTRY'!$C$7:$C$1203,$A11,'DAILY ENTRY'!$B$7:$B$1203,D$3)) | E11: =IF(E$3="(empty slot)","",COUNTIFS('DAILY ENTRY'!$C$7:$C$1203,$A11,'DAILY ENTRY'!$B$7:$B$1203,E$3)) | F11: =IF(F$3="(empty slot)","",COUNTIFS('DAILY ENTRY'!$C$7:$C$1203,$A11,'DAILY ENTRY'!$B$7:$B$1203,F$3)) | G11: =IF(G$3="(empty slot)","",COUNTIFS('DAILY ENTRY'!$C$7:$C$1203,$A11,'DAILY ENTRY'!$B$7:$B$1203,G$3)) | H11: =IF(H$3="(empty slot)","",COUNTIFS('DAILY ENTRY'!$C$7:$C$1203,$A11,'DAILY ENTRY'!$B$7:$B$1203,H$3)) | I11: =IF(I$3="(empty slot)","",COUNTIFS('DAILY ENTRY'!$C$7:$C$1203,$A11,'DAILY ENTRY'!$B$7:$B$1203,I$3)) | ... K11: =IF(K$3="(empty slot)","",COUNTIFS('DAILY ENTRY'!$C$7:$C$1203,$A11,'DAILY ENTRY'!$B$7:$B$1203,K$3)) | L11: =COUNTIF('DAILY ENTRY'!$C$7:$C$1203,$A11) -> 0
A12: ='Platform Setup'!$B$12 -> X (Twitter) | B12: =IF(B$3="(empty slot)","",COUNTIFS('DAILY ENTRY'!$C$7:$C$1203,$A12,'DAILY ENTRY'!$B$7:$B$1203,B$3)) -> 0 | C12: =IF(C$3="(empty slot)","",COUNTIFS('DAILY ENTRY'!$C$7:$C$1203,$A12,'DAILY ENTRY'!$B$7:$B$1203,C$3)) | D12: =IF(D$3="(empty slot)","",COUNTIFS('DAILY ENTRY'!$C$7:$C$1203,$A12,'DAILY ENTRY'!$B$7:$B$1203,D$3)) | E12: =IF(E$3="(empty slot)","",COUNTIFS('DAILY ENTRY'!$C$7:$C$1203,$A12,'DAILY ENTRY'!$B$7:$B$1203,E$3)) | F12: =IF(F$3="(empty slot)","",COUNTIFS('DAILY ENTRY'!$C$7:$C$1203,$A12,'DAILY ENTRY'!$B$7:$B$1203,F$3)) | G12: =IF(G$3="(empty slot)","",COUNTIFS('DAILY ENTRY'!$C$7:$C$1203,$A12,'DAILY ENTRY'!$B$7:$B$1203,G$3)) | H12: =IF(H$3="(empty slot)","",COUNTIFS('DAILY ENTRY'!$C$7:$C$1203,$A12,'DAILY ENTRY'!$B$7:$B$1203,H$3)) | I12: =IF(I$3="(empty slot)","",COUNTIFS('DAILY ENTRY'!$C$7:$C$1203,$A12,'DAILY ENTRY'!$B$7:$B$1203,I$3)) | ... K12: =IF(K$3="(empty slot)","",COUNTIFS('DAILY ENTRY'!$C$7:$C$1203,$A12,'DAILY ENTRY'!$B$7:$B$1203,K$3)) | L12: =COUNTIF('DAILY ENTRY'!$C$7:$C$1203,$A12) -> 0
A13: ='Platform Setup'!$B$13 -> Threads | B13: =IF(B$3="(empty slot)","",COUNTIFS('DAILY ENTRY'!$C$7:$C$1203,$A13,'DAILY ENTRY'!$B$7:$B$1203,B$3)) -> 0 | C13: =IF(C$3="(empty slot)","",COUNTIFS('DAILY ENTRY'!$C$7:$C$1203,$A13,'DAILY ENTRY'!$B$7:$B$1203,C$3)) | D13: =IF(D$3="(empty slot)","",COUNTIFS('DAILY ENTRY'!$C$7:$C$1203,$A13,'DAILY ENTRY'!$B$7:$B$1203,D$3)) | E13: =IF(E$3="(empty slot)","",COUNTIFS('DAILY ENTRY'!$C$7:$C$1203,$A13,'DAILY ENTRY'!$B$7:$B$1203,E$3)) | F13: =IF(F$3="(empty slot)","",COUNTIFS('DAILY ENTRY'!$C$7:$C$1203,$A13,'DAILY ENTRY'!$B$7:$B$1203,F$3)) | G13: =IF(G$3="(empty slot)","",COUNTIFS('DAILY ENTRY'!$C$7:$C$1203,$A13,'DAILY ENTRY'!$B$7:$B$1203,G$3)) | H13: =IF(H$3="(empty slot)","",COUNTIFS('DAILY ENTRY'!$C$7:$C$1203,$A13,'DAILY ENTRY'!$B$7:$B$1203,H$3)) | I13: =IF(I$3="(empty slot)","",COUNTIFS('DAILY ENTRY'!$C$7:$C$1203,$A13,'DAILY ENTRY'!$B$7:$B$1203,I$3)) | ... K13: =IF(K$3="(empty slot)","",COUNTIFS('DAILY ENTRY'!$C$7:$C$1203,$A13,'DAILY ENTRY'!$B$7:$B$1203,K$3)) | L13: =COUNTIF('DAILY ENTRY'!$C$7:$C$1203,$A13) -> 0
A14: ='Platform Setup'!$B$14 -> TikTok | B14: =IF(B$3="(empty slot)","",COUNTIFS('DAILY ENTRY'!$C$7:$C$1203,$A14,'DAILY ENTRY'!$B$7:$B$1203,B$3)) -> 0 | C14: =IF(C$3="(empty slot)","",COUNTIFS('DAILY ENTRY'!$C$7:$C$1203,$A14,'DAILY ENTRY'!$B$7:$B$1203,C$3)) | D14: =IF(D$3="(empty slot)","",COUNTIFS('DAILY ENTRY'!$C$7:$C$1203,$A14,'DAILY ENTRY'!$B$7:$B$1203,D$3)) | E14: =IF(E$3="(empty slot)","",COUNTIFS('DAILY ENTRY'!$C$7:$C$1203,$A14,'DAILY ENTRY'!$B$7:$B$1203,E$3)) | F14: =IF(F$3="(empty slot)","",COUNTIFS('DAILY ENTRY'!$C$7:$C$1203,$A14,'DAILY ENTRY'!$B$7:$B$1203,F$3)) | G14: =IF(G$3="(empty slot)","",COUNTIFS('DAILY ENTRY'!$C$7:$C$1203,$A14,'DAILY ENTRY'!$B$7:$B$1203,G$3)) | H14: =IF(H$3="(empty slot)","",COUNTIFS('DAILY ENTRY'!$C$7:$C$1203,$A14,'DAILY ENTRY'!$B$7:$B$1203,H$3)) | I14: =IF(I$3="(empty slot)","",COUNTIFS('DAILY ENTRY'!$C$7:$C$1203,$A14,'DAILY ENTRY'!$B$7:$B$1203,I$3)) | ... K14: =IF(K$3="(empty slot)","",COUNTIFS('DAILY ENTRY'!$C$7:$C$1203,$A14,'DAILY ENTRY'!$B$7:$B$1203,K$3)) | L14: =COUNTIF('DAILY ENTRY'!$C$7:$C$1203,$A14) -> 0
A15: ='Platform Setup'!$B$15 -> YouTube | B15: =IF(B$3="(empty slot)","",COUNTIFS('DAILY ENTRY'!$C$7:$C$1203,$A15,'DAILY ENTRY'!$B$7:$B$1203,B$3)) -> 0 | C15: =IF(C$3="(empty slot)","",COUNTIFS('DAILY ENTRY'!$C$7:$C$1203,$A15,'DAILY ENTRY'!$B$7:$B$1203,C$3)) | D15: =IF(D$3="(empty slot)","",COUNTIFS('DAILY ENTRY'!$C$7:$C$1203,$A15,'DAILY ENTRY'!$B$7:$B$1203,D$3)) | E15: =IF(E$3="(empty slot)","",COUNTIFS('DAILY ENTRY'!$C$7:$C$1203,$A15,'DAILY ENTRY'!$B$7:$B$1203,E$3)) | F15: =IF(F$3="(empty slot)","",COUNTIFS('DAILY ENTRY'!$C$7:$C$1203,$A15,'DAILY ENTRY'!$B$7:$B$1203,F$3)) | G15: =IF(G$3="(empty slot)","",COUNTIFS('DAILY ENTRY'!$C$7:$C$1203,$A15,'DAILY ENTRY'!$B$7:$B$1203,G$3)) | H15: =IF(H$3="(empty slot)","",COUNTIFS('DAILY ENTRY'!$C$7:$C$1203,$A15,'DAILY ENTRY'!$B$7:$B$1203,H$3)) | I15: =IF(I$3="(empty slot)","",COUNTIFS('DAILY ENTRY'!$C$7:$C$1203,$A15,'DAILY ENTRY'!$B$7:$B$1203,I$3)) | ... K15: =IF(K$3="(empty slot)","",COUNTIFS('DAILY ENTRY'!$C$7:$C$1203,$A15,'DAILY ENTRY'!$B$7:$B$1203,K$3)) | L15: =COUNTIF('DAILY ENTRY'!$C$7:$C$1203,$A15) -> 0
A16: ='Platform Setup'!$B$16 -> YouTube Shorts | B16: =IF(B$3="(empty slot)","",COUNTIFS('DAILY ENTRY'!$C$7:$C$1203,$A16,'DAILY ENTRY'!$B$7:$B$1203,B$3)) -> 0 | C16: =IF(C$3="(empty slot)","",COUNTIFS('DAILY ENTRY'!$C$7:$C$1203,$A16,'DAILY ENTRY'!$B$7:$B$1203,C$3)) | D16: =IF(D$3="(empty slot)","",COUNTIFS('DAILY ENTRY'!$C$7:$C$1203,$A16,'DAILY ENTRY'!$B$7:$B$1203,D$3)) | E16: =IF(E$3="(empty slot)","",COUNTIFS('DAILY ENTRY'!$C$7:$C$1203,$A16,'DAILY ENTRY'!$B$7:$B$1203,E$3)) | F16: =IF(F$3="(empty slot)","",COUNTIFS('DAILY ENTRY'!$C$7:$C$1203,$A16,'DAILY ENTRY'!$B$7:$B$1203,F$3)) | G16: =IF(G$3="(empty slot)","",COUNTIFS('DAILY ENTRY'!$C$7:$C$1203,$A16,'DAILY ENTRY'!$B$7:$B$1203,G$3)) | H16: =IF(H$3="(empty slot)","",COUNTIFS('DAILY ENTRY'!$C$7:$C$1203,$A16,'DAILY ENTRY'!$B$7:$B$1203,H$3)) | I16: =IF(I$3="(empty slot)","",COUNTIFS('DAILY ENTRY'!$C$7:$C$1203,$A16,'DAILY ENTRY'!$B$7:$B$1203,I$3)) | ... K16: =IF(K$3="(empty slot)","",COUNTIFS('DAILY ENTRY'!$C$7:$C$1203,$A16,'DAILY ENTRY'!$B$7:$B$1203,K$3)) | L16: =COUNTIF('DAILY ENTRY'!$C$7:$C$1203,$A16) -> 0
A17: ='Platform Setup'!$B$17 -> Pinterest | B17: =IF(B$3="(empty slot)","",COUNTIFS('DAILY ENTRY'!$C$7:$C$1203,$A17,'DAILY ENTRY'!$B$7:$B$1203,B$3)) -> 0 | C17: =IF(C$3="(empty slot)","",COUNTIFS('DAILY ENTRY'!$C$7:$C$1203,$A17,'DAILY ENTRY'!$B$7:$B$1203,C$3)) | D17: =IF(D$3="(empty slot)","",COUNTIFS('DAILY ENTRY'!$C$7:$C$1203,$A17,'DAILY ENTRY'!$B$7:$B$1203,D$3)) | E17: =IF(E$3="(empty slot)","",COUNTIFS('DAILY ENTRY'!$C$7:$C$1203,$A17,'DAILY ENTRY'!$B$7:$B$1203,E$3)) | F17: =IF(F$3="(empty slot)","",COUNTIFS('DAILY ENTRY'!$C$7:$C$1203,$A17,'DAILY ENTRY'!$B$7:$B$1203,F$3)) | G17: =IF(G$3="(empty slot)","",COUNTIFS('DAILY ENTRY'!$C$7:$C$1203,$A17,'DAILY ENTRY'!$B$7:$B$1203,G$3)) | H17: =IF(H$3="(empty slot)","",COUNTIFS('DAILY ENTRY'!$C$7:$C$1203,$A17,'DAILY ENTRY'!$B$7:$B$1203,H$3)) | I17: =IF(I$3="(empty slot)","",COUNTIFS('DAILY ENTRY'!$C$7:$C$1203,$A17,'DAILY ENTRY'!$B$7:$B$1203,I$3)) | ... K17: =IF(K$3="(empty slot)","",COUNTIFS('DAILY ENTRY'!$C$7:$C$1203,$A17,'DAILY ENTRY'!$B$7:$B$1203,K$3)) | L17: =COUNTIF('DAILY ENTRY'!$C$7:$C$1203,$A17) -> 0
A18: ='Platform Setup'!$B$18 -> Medium | B18: =IF(B$3="(empty slot)","",COUNTIFS('DAILY ENTRY'!$C$7:$C$1203,$A18,'DAILY ENTRY'!$B$7:$B$1203,B$3)) -> 0 | C18: =IF(C$3="(empty slot)","",COUNTIFS('DAILY ENTRY'!$C$7:$C$1203,$A18,'DAILY ENTRY'!$B$7:$B$1203,C$3)) | D18: =IF(D$3="(empty slot)","",COUNTIFS('DAILY ENTRY'!$C$7:$C$1203,$A18,'DAILY ENTRY'!$B$7:$B$1203,D$3)) | E18: =IF(E$3="(empty slot)","",COUNTIFS('DAILY ENTRY'!$C$7:$C$1203,$A18,'DAILY ENTRY'!$B$7:$B$1203,E$3)) | F18: =IF(F$3="(empty slot)","",COUNTIFS('DAILY ENTRY'!$C$7:$C$1203,$A18,'DAILY ENTRY'!$B$7:$B$1203,F$3)) | G18: =IF(G$3="(empty slot)","",COUNTIFS('DAILY ENTRY'!$C$7:$C$1203,$A18,'DAILY ENTRY'!$B$7:$B$1203,G$3)) | H18: =IF(H$3="(empty slot)","",COUNTIFS('DAILY ENTRY'!$C$7:$C$1203,$A18,'DAILY ENTRY'!$B$7:$B$1203,H$3)) | I18: =IF(I$3="(empty slot)","",COUNTIFS('DAILY ENTRY'!$C$7:$C$1203,$A18,'DAILY ENTRY'!$B$7:$B$1203,I$3)) | ... K18: =IF(K$3="(empty slot)","",COUNTIFS('DAILY ENTRY'!$C$7:$C$1203,$A18,'DAILY ENTRY'!$B$7:$B$1203,K$3)) | L18: =COUNTIF('DAILY ENTRY'!$C$7:$C$1203,$A18) -> 0
A19: ='Platform Setup'!$B$19 -> Substack | B19: =IF(B$3="(empty slot)","",COUNTIFS('DAILY ENTRY'!$C$7:$C$1203,$A19,'DAILY ENTRY'!$B$7:$B$1203,B$3)) -> 0 | C19: =IF(C$3="(empty slot)","",COUNTIFS('DAILY ENTRY'!$C$7:$C$1203,$A19,'DAILY ENTRY'!$B$7:$B$1203,C$3)) | D19: =IF(D$3="(empty slot)","",COUNTIFS('DAILY ENTRY'!$C$7:$C$1203,$A19,'DAILY ENTRY'!$B$7:$B$1203,D$3)) | E19: =IF(E$3="(empty slot)","",COUNTIFS('DAILY ENTRY'!$C$7:$C$1203,$A19,'DAILY ENTRY'!$B$7:$B$1203,E$3)) | F19: =IF(F$3="(empty slot)","",COUNTIFS('DAILY ENTRY'!$C$7:$C$1203,$A19,'DAILY ENTRY'!$B$7:$B$1203,F$3)) | G19: =IF(G$3="(empty slot)","",COUNTIFS('DAILY ENTRY'!$C$7:$C$1203,$A19,'DAILY ENTRY'!$B$7:$B$1203,G$3)) | H19: =IF(H$3="(empty slot)","",COUNTIFS('DAILY ENTRY'!$C$7:$C$1203,$A19,'DAILY ENTRY'!$B$7:$B$1203,H$3)) | I19: =IF(I$3="(empty slot)","",COUNTIFS('DAILY ENTRY'!$C$7:$C$1203,$A19,'DAILY ENTRY'!$B$7:$B$1203,I$3)) | ... K19: =IF(K$3="(empty slot)","",COUNTIFS('DAILY ENTRY'!$C$7:$C$1203,$A19,'DAILY ENTRY'!$B$7:$B$1203,K$3)) | L19: =COUNTIF('DAILY ENTRY'!$C$7:$C$1203,$A19) -> 0
A20: ='Platform Setup'!$B$20 -> SlideShare | B20: =IF(B$3="(empty slot)","",COUNTIFS('DAILY ENTRY'!$C$7:$C$1203,$A20,'DAILY ENTRY'!$B$7:$B$1203,B$3)) -> 0 | C20: =IF(C$3="(empty slot)","",COUNTIFS('DAILY ENTRY'!$C$7:$C$1203,$A20,'DAILY ENTRY'!$B$7:$B$1203,C$3)) | D20: =IF(D$3="(empty slot)","",COUNTIFS('DAILY ENTRY'!$C$7:$C$1203,$A20,'DAILY ENTRY'!$B$7:$B$1203,D$3)) | E20: =IF(E$3="(empty slot)","",COUNTIFS('DAILY ENTRY'!$C$7:$C$1203,$A20,'DAILY ENTRY'!$B$7:$B$1203,E$3)) | F20: =IF(F$3="(empty slot)","",COUNTIFS('DAILY ENTRY'!$C$7:$C$1203,$A20,'DAILY ENTRY'!$B$7:$B$1203,F$3)) | G20: =IF(G$3="(empty slot)","",COUNTIFS('DAILY ENTRY'!$C$7:$C$1203,$A20,'DAILY ENTRY'!$B$7:$B$1203,G$3)) | H20: =IF(H$3="(empty slot)","",COUNTIFS('DAILY ENTRY'!$C$7:$C$1203,$A20,'DAILY ENTRY'!$B$7:$B$1203,H$3)) | I20: =IF(I$3="(empty slot)","",COUNTIFS('DAILY ENTRY'!$C$7:$C$1203,$A20,'DAILY ENTRY'!$B$7:$B$1203,I$3)) | ... K20: =IF(K$3="(empty slot)","",COUNTIFS('DAILY ENTRY'!$C$7:$C$1203,$A20,'DAILY ENTRY'!$B$7:$B$1203,K$3)) | L20: =COUNTIF('DAILY ENTRY'!$C$7:$C$1203,$A20) -> 0
A21: ='Platform Setup'!$B$21 -> Tumblr | B21: =IF(B$3="(empty slot)","",COUNTIFS('DAILY ENTRY'!$C$7:$C$1203,$A21,'DAILY ENTRY'!$B$7:$B$1203,B$3)) -> 0 | C21: =IF(C$3="(empty slot)","",COUNTIFS('DAILY ENTRY'!$C$7:$C$1203,$A21,'DAILY ENTRY'!$B$7:$B$1203,C$3)) | D21: =IF(D$3="(empty slot)","",COUNTIFS('DAILY ENTRY'!$C$7:$C$1203,$A21,'DAILY ENTRY'!$B$7:$B$1203,D$3)) | E21: =IF(E$3="(empty slot)","",COUNTIFS('DAILY ENTRY'!$C$7:$C$1203,$A21,'DAILY ENTRY'!$B$7:$B$1203,E$3)) | F21: =IF(F$3="(empty slot)","",COUNTIFS('DAILY ENTRY'!$C$7:$C$1203,$A21,'DAILY ENTRY'!$B$7:$B$1203,F$3)) | G21: =IF(G$3="(empty slot)","",COUNTIFS('DAILY ENTRY'!$C$7:$C$1203,$A21,'DAILY ENTRY'!$B$7:$B$1203,G$3)) | H21: =IF(H$3="(empty slot)","",COUNTIFS('DAILY ENTRY'!$C$7:$C$1203,$A21,'DAILY ENTRY'!$B$7:$B$1203,H$3)) | I21: =IF(I$3="(empty slot)","",COUNTIFS('DAILY ENTRY'!$C$7:$C$1203,$A21,'DAILY ENTRY'!$B$7:$B$1203,I$3)) | ... K21: =IF(K$3="(empty slot)","",COUNTIFS('DAILY ENTRY'!$C$7:$C$1203,$A21,'DAILY ENTRY'!$B$7:$B$1203,K$3)) | L21: =COUNTIF('DAILY ENTRY'!$C$7:$C$1203,$A21) -> 0
A22: ='Platform Setup'!$B$22 -> Quora | B22: =IF(B$3="(empty slot)","",COUNTIFS('DAILY ENTRY'!$C$7:$C$1203,$A22,'DAILY ENTRY'!$B$7:$B$1203,B$3)) -> 0 | C22: =IF(C$3="(empty slot)","",COUNTIFS('DAILY ENTRY'!$C$7:$C$1203,$A22,'DAILY ENTRY'!$B$7:$B$1203,C$3)) | D22: =IF(D$3="(empty slot)","",COUNTIFS('DAILY ENTRY'!$C$7:$C$1203,$A22,'DAILY ENTRY'!$B$7:$B$1203,D$3)) | E22: =IF(E$3="(empty slot)","",COUNTIFS('DAILY ENTRY'!$C$7:$C$1203,$A22,'DAILY ENTRY'!$B$7:$B$1203,E$3)) | F22: =IF(F$3="(empty slot)","",COUNTIFS('DAILY ENTRY'!$C$7:$C$1203,$A22,'DAILY ENTRY'!$B$7:$B$1203,F$3)) | G22: =IF(G$3="(empty slot)","",COUNTIFS('DAILY ENTRY'!$C$7:$C$1203,$A22,'DAILY ENTRY'!$B$7:$B$1203,G$3)) | H22: =IF(H$3="(empty slot)","",COUNTIFS('DAILY ENTRY'!$C$7:$C$1203,$A22,'DAILY ENTRY'!$B$7:$B$1203,H$3)) | I22: =IF(I$3="(empty slot)","",COUNTIFS('DAILY ENTRY'!$C$7:$C$1203,$A22,'DAILY ENTRY'!$B$7:$B$1203,I$3)) | ... K22: =IF(K$3="(empty slot)","",COUNTIFS('DAILY ENTRY'!$C$7:$C$1203,$A22,'DAILY ENTRY'!$B$7:$B$1203,K$3)) | L22: =COUNTIF('DAILY ENTRY'!$C$7:$C$1203,$A22) -> 0
A23: ='Platform Setup'!$B$23 -> Reddit | B23: =IF(B$3="(empty slot)","",COUNTIFS('DAILY ENTRY'!$C$7:$C$1203,$A23,'DAILY ENTRY'!$B$7:$B$1203,B$3)) -> 0 | C23: =IF(C$3="(empty slot)","",COUNTIFS('DAILY ENTRY'!$C$7:$C$1203,$A23,'DAILY ENTRY'!$B$7:$B$1203,C$3)) | D23: =IF(D$3="(empty slot)","",COUNTIFS('DAILY ENTRY'!$C$7:$C$1203,$A23,'DAILY ENTRY'!$B$7:$B$1203,D$3)) | E23: =IF(E$3="(empty slot)","",COUNTIFS('DAILY ENTRY'!$C$7:$C$1203,$A23,'DAILY ENTRY'!$B$7:$B$1203,E$3)) | F23: =IF(F$3="(empty slot)","",COUNTIFS('DAILY ENTRY'!$C$7:$C$1203,$A23,'DAILY ENTRY'!$B$7:$B$1203,F$3)) | G23: =IF(G$3="(empty slot)","",COUNTIFS('DAILY ENTRY'!$C$7:$C$1203,$A23,'DAILY ENTRY'!$B$7:$B$1203,G$3)) | H23: =IF(H$3="(empty slot)","",COUNTIFS('DAILY ENTRY'!$C$7:$C$1203,$A23,'DAILY ENTRY'!$B$7:$B$1203,H$3)) | I23: =IF(I$3="(empty slot)","",COUNTIFS('DAILY ENTRY'!$C$7:$C$1203,$A23,'DAILY ENTRY'!$B$7:$B$1203,I$3)) | ... K23: =IF(K$3="(empty slot)","",COUNTIFS('DAILY ENTRY'!$C$7:$C$1203,$A23,'DAILY ENTRY'!$B$7:$B$1203,K$3)) | L23: =COUNTIF('DAILY ENTRY'!$C$7:$C$1203,$A23) -> 0
A24: ='Platform Setup'!$B$24 -> Discord | B24: =IF(B$3="(empty slot)","",COUNTIFS('DAILY ENTRY'!$C$7:$C$1203,$A24,'DAILY ENTRY'!$B$7:$B$1203,B$3)) -> 0 | C24: =IF(C$3="(empty slot)","",COUNTIFS('DAILY ENTRY'!$C$7:$C$1203,$A24,'DAILY ENTRY'!$B$7:$B$1203,C$3)) | D24: =IF(D$3="(empty slot)","",COUNTIFS('DAILY ENTRY'!$C$7:$C$1203,$A24,'DAILY ENTRY'!$B$7:$B$1203,D$3)) | E24: =IF(E$3="(empty slot)","",COUNTIFS('DAILY ENTRY'!$C$7:$C$1203,$A24,'DAILY ENTRY'!$B$7:$B$1203,E$3)) | F24: =IF(F$3="(empty slot)","",COUNTIFS('DAILY ENTRY'!$C$7:$C$1203,$A24,'DAILY ENTRY'!$B$7:$B$1203,F$3)) | G24: =IF(G$3="(empty slot)","",COUNTIFS('DAILY ENTRY'!$C$7:$C$1203,$A24,'DAILY ENTRY'!$B$7:$B$1203,G$3)) | H24: =IF(H$3="(empty slot)","",COUNTIFS('DAILY ENTRY'!$C$7:$C$1203,$A24,'DAILY ENTRY'!$B$7:$B$1203,H$3)) | I24: =IF(I$3="(empty slot)","",COUNTIFS('DAILY ENTRY'!$C$7:$C$1203,$A24,'DAILY ENTRY'!$B$7:$B$1203,I$3)) | ... K24: =IF(K$3="(empty slot)","",COUNTIFS('DAILY ENTRY'!$C$7:$C$1203,$A24,'DAILY ENTRY'!$B$7:$B$1203,K$3)) | L24: =COUNTIF('DAILY ENTRY'!$C$7:$C$1203,$A24) -> 0
A25: ='Platform Setup'!$B$25 -> Slack Communities | B25: =IF(B$3="(empty slot)","",COUNTIFS('DAILY ENTRY'!$C$7:$C$1203,$A25,'DAILY ENTRY'!$B$7:$B$1203,B$3)) -> 0 | C25: =IF(C$3="(empty slot)","",COUNTIFS('DAILY ENTRY'!$C$7:$C$1203,$A25,'DAILY ENTRY'!$B$7:$B$1203,C$3)) | D25: =IF(D$3="(empty slot)","",COUNTIFS('DAILY ENTRY'!$C$7:$C$1203,$A25,'DAILY ENTRY'!$B$7:$B$1203,D$3)) | E25: =IF(E$3="(empty slot)","",COUNTIFS('DAILY ENTRY'!$C$7:$C$1203,$A25,'DAILY ENTRY'!$B$7:$B$1203,E$3)) | F25: =IF(F$3="(empty slot)","",COUNTIFS('DAILY ENTRY'!$C$7:$C$1203,$A25,'DAILY ENTRY'!$B$7:$B$1203,F$3)) | G25: =IF(G$3="(empty slot)","",COUNTIFS('DAILY ENTRY'!$C$7:$C$1203,$A25,'DAILY ENTRY'!$B$7:$B$1203,G$3)) | H25: =IF(H$3="(empty slot)","",COUNTIFS('DAILY ENTRY'!$C$7:$C$1203,$A25,'DAILY ENTRY'!$B$7:$B$1203,H$3)) | I25: =IF(I$3="(empty slot)","",COUNTIFS('DAILY ENTRY'!$C$7:$C$1203,$A25,'DAILY ENTRY'!$B$7:$B$1203,I$3)) | ... K25: =IF(K$3="(empty slot)","",COUNTIFS('DAILY ENTRY'!$C$7:$C$1203,$A25,'DAILY ENTRY'!$B$7:$B$1203,K$3)) | L25: =COUNTIF('DAILY ENTRY'!$C$7:$C$1203,$A25) -> 0
A26: ='Platform Setup'!$B$26 -> WhatsApp Channel | B26: =IF(B$3="(empty slot)","",COUNTIFS('DAILY ENTRY'!$C$7:$C$1203,$A26,'DAILY ENTRY'!$B$7:$B$1203,B$3)) -> 0 | C26: =IF(C$3="(empty slot)","",COUNTIFS('DAILY ENTRY'!$C$7:$C$1203,$A26,'DAILY ENTRY'!$B$7:$B$1203,C$3)) | D26: =IF(D$3="(empty slot)","",COUNTIFS('DAILY ENTRY'!$C$7:$C$1203,$A26,'DAILY ENTRY'!$B$7:$B$1203,D$3)) | E26: =IF(E$3="(empty slot)","",COUNTIFS('DAILY ENTRY'!$C$7:$C$1203,$A26,'DAILY ENTRY'!$B$7:$B$1203,E$3)) | F26: =IF(F$3="(empty slot)","",COUNTIFS('DAILY ENTRY'!$C$7:$C$1203,$A26,'DAILY ENTRY'!$B$7:$B$1203,F$3)) | G26: =IF(G$3="(empty slot)","",COUNTIFS('DAILY ENTRY'!$C$7:$C$1203,$A26,'DAILY ENTRY'!$B$7:$B$1203,G$3)) | H26: =IF(H$3="(empty slot)","",COUNTIFS('DAILY ENTRY'!$C$7:$C$1203,$A26,'DAILY ENTRY'!$B$7:$B$1203,H$3)) | I26: =IF(I$3="(empty slot)","",COUNTIFS('DAILY ENTRY'!$C$7:$C$1203,$A26,'DAILY ENTRY'!$B$7:$B$1203,I$3)) | ... K26: =IF(K$3="(empty slot)","",COUNTIFS('DAILY ENTRY'!$C$7:$C$1203,$A26,'DAILY ENTRY'!$B$7:$B$1203,K$3)) | L26: =COUNTIF('DAILY ENTRY'!$C$7:$C$1203,$A26) -> 0
A27: ='Platform Setup'!$B$27 -> Telegram Channel | B27: =IF(B$3="(empty slot)","",COUNTIFS('DAILY ENTRY'!$C$7:$C$1203,$A27,'DAILY ENTRY'!$B$7:$B$1203,B$3)) -> 0 | C27: =IF(C$3="(empty slot)","",COUNTIFS('DAILY ENTRY'!$C$7:$C$1203,$A27,'DAILY ENTRY'!$B$7:$B$1203,C$3)) | D27: =IF(D$3="(empty slot)","",COUNTIFS('DAILY ENTRY'!$C$7:$C$1203,$A27,'DAILY ENTRY'!$B$7:$B$1203,D$3)) | E27: =IF(E$3="(empty slot)","",COUNTIFS('DAILY ENTRY'!$C$7:$C$1203,$A27,'DAILY ENTRY'!$B$7:$B$1203,E$3)) | F27: =IF(F$3="(empty slot)","",COUNTIFS('DAILY ENTRY'!$C$7:$C$1203,$A27,'DAILY ENTRY'!$B$7:$B$1203,F$3)) | G27: =IF(G$3="(empty slot)","",COUNTIFS('DAILY ENTRY'!$C$7:$C$1203,$A27,'DAILY ENTRY'!$B$7:$B$1203,G$3)) | H27: =IF(H$3="(empty slot)","",COUNTIFS('DAILY ENTRY'!$C$7:$C$1203,$A27,'DAILY ENTRY'!$B$7:$B$1203,H$3)) | I27: =IF(I$3="(empty slot)","",COUNTIFS('DAILY ENTRY'!$C$7:$C$1203,$A27,'DAILY ENTRY'!$B$7:$B$1203,I$3)) | ... K27: =IF(K$3="(empty slot)","",COUNTIFS('DAILY ENTRY'!$C$7:$C$1203,$A27,'DAILY ENTRY'!$B$7:$B$1203,K$3)) | L27: =COUNTIF('DAILY ENTRY'!$C$7:$C$1203,$A27) -> 0
A28: ='Platform Setup'!$B$28 -> Google Business Profile | B28: =IF(B$3="(empty slot)","",COUNTIFS('DAILY ENTRY'!$C$7:$C$1203,$A28,'DAILY ENTRY'!$B$7:$B$1203,B$3)) -> 0 | C28: =IF(C$3="(empty slot)","",COUNTIFS('DAILY ENTRY'!$C$7:$C$1203,$A28,'DAILY ENTRY'!$B$7:$B$1203,C$3)) | D28: =IF(D$3="(empty slot)","",COUNTIFS('DAILY ENTRY'!$C$7:$C$1203,$A28,'DAILY ENTRY'!$B$7:$B$1203,D$3)) | E28: =IF(E$3="(empty slot)","",COUNTIFS('DAILY ENTRY'!$C$7:$C$1203,$A28,'DAILY ENTRY'!$B$7:$B$1203,E$3)) | F28: =IF(F$3="(empty slot)","",COUNTIFS('DAILY ENTRY'!$C$7:$C$1203,$A28,'DAILY ENTRY'!$B$7:$B$1203,F$3)) | G28: =IF(G$3="(empty slot)","",COUNTIFS('DAILY ENTRY'!$C$7:$C$1203,$A28,'DAILY ENTRY'!$B$7:$B$1203,G$3)) | H28: =IF(H$3="(empty slot)","",COUNTIFS('DAILY ENTRY'!$C$7:$C$1203,$A28,'DAILY ENTRY'!$B$7:$B$1203,H$3)) | I28: =IF(I$3="(empty slot)","",COUNTIFS('DAILY ENTRY'!$C$7:$C$1203,$A28,'DAILY ENTRY'!$B$7:$B$1203,I$3)) | ... K28: =IF(K$3="(empty slot)","",COUNTIFS('DAILY ENTRY'!$C$7:$C$1203,$A28,'DAILY ENTRY'!$B$7:$B$1203,K$3)) | L28: =COUNTIF('DAILY ENTRY'!$C$7:$C$1203,$A28) -> 0
A29: ='Platform Setup'!$B$29 -> Bing Places | B29: =IF(B$3="(empty slot)","",COUNTIFS('DAILY ENTRY'!$C$7:$C$1203,$A29,'DAILY ENTRY'!$B$7:$B$1203,B$3)) -> 0 | C29: =IF(C$3="(empty slot)","",COUNTIFS('DAILY ENTRY'!$C$7:$C$1203,$A29,'DAILY ENTRY'!$B$7:$B$1203,C$3)) | D29: =IF(D$3="(empty slot)","",COUNTIFS('DAILY ENTRY'!$C$7:$C$1203,$A29,'DAILY ENTRY'!$B$7:$B$1203,D$3)) | E29: =IF(E$3="(empty slot)","",COUNTIFS('DAILY ENTRY'!$C$7:$C$1203,$A29,'DAILY ENTRY'!$B$7:$B$1203,E$3)) | F29: =IF(F$3="(empty slot)","",COUNTIFS('DAILY ENTRY'!$C$7:$C$1203,$A29,'DAILY ENTRY'!$B$7:$B$1203,F$3)) | G29: =IF(G$3="(empty slot)","",COUNTIFS('DAILY ENTRY'!$C$7:$C$1203,$A29,'DAILY ENTRY'!$B$7:$B$1203,G$3)) | H29: =IF(H$3="(empty slot)","",COUNTIFS('DAILY ENTRY'!$C$7:$C$1203,$A29,'DAILY ENTRY'!$B$7:$B$1203,H$3)) | I29: =IF(I$3="(empty slot)","",COUNTIFS('DAILY ENTRY'!$C$7:$C$1203,$A29,'DAILY ENTRY'!$B$7:$B$1203,I$3)) | ... K29: =IF(K$3="(empty slot)","",COUNTIFS('DAILY ENTRY'!$C$7:$C$1203,$A29,'DAILY ENTRY'!$B$7:$B$1203,K$3)) | L29: =COUNTIF('DAILY ENTRY'!$C$7:$C$1203,$A29) -> 0
A30: ='Platform Setup'!$B$30 -> Trustpilot | B30: =IF(B$3="(empty slot)","",COUNTIFS('DAILY ENTRY'!$C$7:$C$1203,$A30,'DAILY ENTRY'!$B$7:$B$1203,B$3)) -> 0 | C30: =IF(C$3="(empty slot)","",COUNTIFS('DAILY ENTRY'!$C$7:$C$1203,$A30,'DAILY ENTRY'!$B$7:$B$1203,C$3)) | D30: =IF(D$3="(empty slot)","",COUNTIFS('DAILY ENTRY'!$C$7:$C$1203,$A30,'DAILY ENTRY'!$B$7:$B$1203,D$3)) | E30: =IF(E$3="(empty slot)","",COUNTIFS('DAILY ENTRY'!$C$7:$C$1203,$A30,'DAILY ENTRY'!$B$7:$B$1203,E$3)) | F30: =IF(F$3="(empty slot)","",COUNTIFS('DAILY ENTRY'!$C$7:$C$1203,$A30,'DAILY ENTRY'!$B$7:$B$1203,F$3)) | G30: =IF(G$3="(empty slot)","",COUNTIFS('DAILY ENTRY'!$C$7:$C$1203,$A30,'DAILY ENTRY'!$B$7:$B$1203,G$3)) | H30: =IF(H$3="(empty slot)","",COUNTIFS('DAILY ENTRY'!$C$7:$C$1203,$A30,'DAILY ENTRY'!$B$7:$B$1203,H$3)) | I30: =IF(I$3="(empty slot)","",COUNTIFS('DAILY ENTRY'!$C$7:$C$1203,$A30,'DAILY ENTRY'!$B$7:$B$1203,I$3)) | ... K30: =IF(K$3="(empty slot)","",COUNTIFS('DAILY ENTRY'!$C$7:$C$1203,$A30,'DAILY ENTRY'!$B$7:$B$1203,K$3)) | L30: =COUNTIF('DAILY ENTRY'!$C$7:$C$1203,$A30) -> 0
A31: ='Platform Setup'!$B$31 -> Crunchbase | B31: =IF(B$3="(empty slot)","",COUNTIFS('DAILY ENTRY'!$C$7:$C$1203,$A31,'DAILY ENTRY'!$B$7:$B$1203,B$3)) -> 0 | C31: =IF(C$3="(empty slot)","",COUNTIFS('DAILY ENTRY'!$C$7:$C$1203,$A31,'DAILY ENTRY'!$B$7:$B$1203,C$3)) | D31: =IF(D$3="(empty slot)","",COUNTIFS('DAILY ENTRY'!$C$7:$C$1203,$A31,'DAILY ENTRY'!$B$7:$B$1203,D$3)) | E31: =IF(E$3="(empty slot)","",COUNTIFS('DAILY ENTRY'!$C$7:$C$1203,$A31,'DAILY ENTRY'!$B$7:$B$1203,E$3)) | F31: =IF(F$3="(empty slot)","",COUNTIFS('DAILY ENTRY'!$C$7:$C$1203,$A31,'DAILY ENTRY'!$B$7:$B$1203,F$3)) | G31: =IF(G$3="(empty slot)","",COUNTIFS('DAILY ENTRY'!$C$7:$C$1203,$A31,'DAILY ENTRY'!$B$7:$B$1203,G$3)) | H31: =IF(H$3="(empty slot)","",COUNTIFS('DAILY ENTRY'!$C$7:$C$1203,$A31,'DAILY ENTRY'!$B$7:$B$1203,H$3)) | I31: =IF(I$3="(empty slot)","",COUNTIFS('DAILY ENTRY'!$C$7:$C$1203,$A31,'DAILY ENTRY'!$B$7:$B$1203,I$3)) | ... K31: =IF(K$3="(empty slot)","",COUNTIFS('DAILY ENTRY'!$C$7:$C$1203,$A31,'DAILY ENTRY'!$B$7:$B$1203,K$3)) | L31: =COUNTIF('DAILY ENTRY'!$C$7:$C$1203,$A31) -> 0
A32: ='Platform Setup'!$B$32 -> G2 | B32: =IF(B$3="(empty slot)","",COUNTIFS('DAILY ENTRY'!$C$7:$C$1203,$A32,'DAILY ENTRY'!$B$7:$B$1203,B$3)) -> 0 | C32: =IF(C$3="(empty slot)","",COUNTIFS('DAILY ENTRY'!$C$7:$C$1203,$A32,'DAILY ENTRY'!$B$7:$B$1203,C$3)) | D32: =IF(D$3="(empty slot)","",COUNTIFS('DAILY ENTRY'!$C$7:$C$1203,$A32,'DAILY ENTRY'!$B$7:$B$1203,D$3)) | E32: =IF(E$3="(empty slot)","",COUNTIFS('DAILY ENTRY'!$C$7:$C$1203,$A32,'DAILY ENTRY'!$B$7:$B$1203,E$3)) | F32: =IF(F$3="(empty slot)","",COUNTIFS('DAILY ENTRY'!$C$7:$C$1203,$A32,'DAILY ENTRY'!$B$7:$B$1203,F$3)) | G32: =IF(G$3="(empty slot)","",COUNTIFS('DAILY ENTRY'!$C$7:$C$1203,$A32,'DAILY ENTRY'!$B$7:$B$1203,G$3)) | H32: =IF(H$3="(empty slot)","",COUNTIFS('DAILY ENTRY'!$C$7:$C$1203,$A32,'DAILY ENTRY'!$B$7:$B$1203,H$3)) | I32: =IF(I$3="(empty slot)","",COUNTIFS('DAILY ENTRY'!$C$7:$C$1203,$A32,'DAILY ENTRY'!$B$7:$B$1203,I$3)) | ... K32: =IF(K$3="(empty slot)","",COUNTIFS('DAILY ENTRY'!$C$7:$C$1203,$A32,'DAILY ENTRY'!$B$7:$B$1203,K$3)) | L32: =COUNTIF('DAILY ENTRY'!$C$7:$C$1203,$A32) -> 0
A33: ='Platform Setup'!$B$33 -> Capterra | B33: =IF(B$3="(empty slot)","",COUNTIFS('DAILY ENTRY'!$C$7:$C$1203,$A33,'DAILY ENTRY'!$B$7:$B$1203,B$3)) -> 0 | C33: =IF(C$3="(empty slot)","",COUNTIFS('DAILY ENTRY'!$C$7:$C$1203,$A33,'DAILY ENTRY'!$B$7:$B$1203,C$3)) | D33: =IF(D$3="(empty slot)","",COUNTIFS('DAILY ENTRY'!$C$7:$C$1203,$A33,'DAILY ENTRY'!$B$7:$B$1203,D$3)) | E33: =IF(E$3="(empty slot)","",COUNTIFS('DAILY ENTRY'!$C$7:$C$1203,$A33,'DAILY ENTRY'!$B$7:$B$1203,E$3)) | F33: =IF(F$3="(empty slot)","",COUNTIFS('DAILY ENTRY'!$C$7:$C$1203,$A33,'DAILY ENTRY'!$B$7:$B$1203,F$3)) | G33: =IF(G$3="(empty slot)","",COUNTIFS('DAILY ENTRY'!$C$7:$C$1203,$A33,'DAILY ENTRY'!$B$7:$B$1203,G$3)) | H33: =IF(H$3="(empty slot)","",COUNTIFS('DAILY ENTRY'!$C$7:$C$1203,$A33,'DAILY ENTRY'!$B$7:$B$1203,H$3)) | I33: =IF(I$3="(empty slot)","",COUNTIFS('DAILY ENTRY'!$C$7:$C$1203,$A33,'DAILY ENTRY'!$B$7:$B$1203,I$3)) | ... K33: =IF(K$3="(empty slot)","",COUNTIFS('DAILY ENTRY'!$C$7:$C$1203,$A33,'DAILY ENTRY'!$B$7:$B$1203,K$3)) | L33: =COUNTIF('DAILY ENTRY'!$C$7:$C$1203,$A33) -> 0
A34: ='Platform Setup'!$B$34 -> Clutch | B34: =IF(B$3="(empty slot)","",COUNTIFS('DAILY ENTRY'!$C$7:$C$1203,$A34,'DAILY ENTRY'!$B$7:$B$1203,B$3)) -> 0 | C34: =IF(C$3="(empty slot)","",COUNTIFS('DAILY ENTRY'!$C$7:$C$1203,$A34,'DAILY ENTRY'!$B$7:$B$1203,C$3)) | D34: =IF(D$3="(empty slot)","",COUNTIFS('DAILY ENTRY'!$C$7:$C$1203,$A34,'DAILY ENTRY'!$B$7:$B$1203,D$3)) | E34: =IF(E$3="(empty slot)","",COUNTIFS('DAILY ENTRY'!$C$7:$C$1203,$A34,'DAILY ENTRY'!$B$7:$B$1203,E$3)) | F34: =IF(F$3="(empty slot)","",COUNTIFS('DAILY ENTRY'!$C$7:$C$1203,$A34,'DAILY ENTRY'!$B$7:$B$1203,F$3)) | G34: =IF(G$3="(empty slot)","",COUNTIFS('DAILY ENTRY'!$C$7:$C$1203,$A34,'DAILY ENTRY'!$B$7:$B$1203,G$3)) | H34: =IF(H$3="(empty slot)","",COUNTIFS('DAILY ENTRY'!$C$7:$C$1203,$A34,'DAILY ENTRY'!$B$7:$B$1203,H$3)) | I34: =IF(I$3="(empty slot)","",COUNTIFS('DAILY ENTRY'!$C$7:$C$1203,$A34,'DAILY ENTRY'!$B$7:$B$1203,I$3)) | ... K34: =IF(K$3="(empty slot)","",COUNTIFS('DAILY ENTRY'!$C$7:$C$1203,$A34,'DAILY ENTRY'!$B$7:$B$1203,K$3)) | L34: =COUNTIF('DAILY ENTRY'!$C$7:$C$1203,$A34) -> 0
A35: ='Platform Setup'!$B$35 -> Eventbrite | B35: =IF(B$3="(empty slot)","",COUNTIFS('DAILY ENTRY'!$C$7:$C$1203,$A35,'DAILY ENTRY'!$B$7:$B$1203,B$3)) -> 0 | C35: =IF(C$3="(empty slot)","",COUNTIFS('DAILY ENTRY'!$C$7:$C$1203,$A35,'DAILY ENTRY'!$B$7:$B$1203,C$3)) | D35: =IF(D$3="(empty slot)","",COUNTIFS('DAILY ENTRY'!$C$7:$C$1203,$A35,'DAILY ENTRY'!$B$7:$B$1203,D$3)) | E35: =IF(E$3="(empty slot)","",COUNTIFS('DAILY ENTRY'!$C$7:$C$1203,$A35,'DAILY ENTRY'!$B$7:$B$1203,E$3)) | F35: =IF(F$3="(empty slot)","",COUNTIFS('DAILY ENTRY'!$C$7:$C$1203,$A35,'DAILY ENTRY'!$B$7:$B$1203,F$3)) | G35: =IF(G$3="(empty slot)","",COUNTIFS('DAILY ENTRY'!$C$7:$C$1203,$A35,'DAILY ENTRY'!$B$7:$B$1203,G$3)) | H35: =IF(H$3="(empty slot)","",COUNTIFS('DAILY ENTRY'!$C$7:$C$1203,$A35,'DAILY ENTRY'!$B$7:$B$1203,H$3)) | I35: =IF(I$3="(empty slot)","",COUNTIFS('DAILY ENTRY'!$C$7:$C$1203,$A35,'DAILY ENTRY'!$B$7:$B$1203,I$3)) | ... K35: =IF(K$3="(empty slot)","",COUNTIFS('DAILY ENTRY'!$C$7:$C$1203,$A35,'DAILY ENTRY'!$B$7:$B$1203,K$3)) | L35: =COUNTIF('DAILY ENTRY'!$C$7:$C$1203,$A35) -> 0
A36: ='Platform Setup'!$B$36 -> Meetup | B36: =IF(B$3="(empty slot)","",COUNTIFS('DAILY ENTRY'!$C$7:$C$1203,$A36,'DAILY ENTRY'!$B$7:$B$1203,B$3)) -> 0 | C36: =IF(C$3="(empty slot)","",COUNTIFS('DAILY ENTRY'!$C$7:$C$1203,$A36,'DAILY ENTRY'!$B$7:$B$1203,C$3)) | D36: =IF(D$3="(empty slot)","",COUNTIFS('DAILY ENTRY'!$C$7:$C$1203,$A36,'DAILY ENTRY'!$B$7:$B$1203,D$3)) | E36: =IF(E$3="(empty slot)","",COUNTIFS('DAILY ENTRY'!$C$7:$C$1203,$A36,'DAILY ENTRY'!$B$7:$B$1203,E$3)) | F36: =IF(F$3="(empty slot)","",COUNTIFS('DAILY ENTRY'!$C$7:$C$1203,$A36,'DAILY ENTRY'!$B$7:$B$1203,F$3)) | G36: =IF(G$3="(empty slot)","",COUNTIFS('DAILY ENTRY'!$C$7:$C$1203,$A36,'DAILY ENTRY'!$B$7:$B$1203,G$3)) | H36: =IF(H$3="(empty slot)","",COUNTIFS('DAILY ENTRY'!$C$7:$C$1203,$A36,'DAILY ENTRY'!$B$7:$B$1203,H$3)) | I36: =IF(I$3="(empty slot)","",COUNTIFS('DAILY ENTRY'!$C$7:$C$1203,$A36,'DAILY ENTRY'!$B$7:$B$1203,I$3)) | ... K36: =IF(K$3="(empty slot)","",COUNTIFS('DAILY ENTRY'!$C$7:$C$1203,$A36,'DAILY ENTRY'!$B$7:$B$1203,K$3)) | L36: =COUNTIF('DAILY ENTRY'!$C$7:$C$1203,$A36) -> 0
A37: ='Platform Setup'!$B$37 -> Luma | B37: =IF(B$3="(empty slot)","",COUNTIFS('DAILY ENTRY'!$C$7:$C$1203,$A37,'DAILY ENTRY'!$B$7:$B$1203,B$3)) -> 0 | C37: =IF(C$3="(empty slot)","",COUNTIFS('DAILY ENTRY'!$C$7:$C$1203,$A37,'DAILY ENTRY'!$B$7:$B$1203,C$3)) | D37: =IF(D$3="(empty slot)","",COUNTIFS('DAILY ENTRY'!$C$7:$C$1203,$A37,'DAILY ENTRY'!$B$7:$B$1203,D$3)) | E37: =IF(E$3="(empty slot)","",COUNTIFS('DAILY ENTRY'!$C$7:$C$1203,$A37,'DAILY ENTRY'!$B$7:$B$1203,E$3)) | F37: =IF(F$3="(empty slot)","",COUNTIFS('DAILY ENTRY'!$C$7:$C$1203,$A37,'DAILY ENTRY'!$B$7:$B$1203,F$3)) | G37: =IF(G$3="(empty slot)","",COUNTIFS('DAILY ENTRY'!$C$7:$C$1203,$A37,'DAILY ENTRY'!$B$7:$B$1203,G$3)) | H37: =IF(H$3="(empty slot)","",COUNTIFS('DAILY ENTRY'!$C$7:$C$1203,$A37,'DAILY ENTRY'!$B$7:$B$1203,H$3)) | I37: =IF(I$3="(empty slot)","",COUNTIFS('DAILY ENTRY'!$C$7:$C$1203,$A37,'DAILY ENTRY'!$B$7:$B$1203,I$3)) | ... K37: =IF(K$3="(empty slot)","",COUNTIFS('DAILY ENTRY'!$C$7:$C$1203,$A37,'DAILY ENTRY'!$B$7:$B$1203,K$3)) | L37: =COUNTIF('DAILY ENTRY'!$C$7:$C$1203,$A37) -> 0
A38: ='Platform Setup'!$B$38 -> Spotify for Creators | B38: =IF(B$3="(empty slot)","",COUNTIFS('DAILY ENTRY'!$C$7:$C$1203,$A38,'DAILY ENTRY'!$B$7:$B$1203,B$3)) -> 0 | C38: =IF(C$3="(empty slot)","",COUNTIFS('DAILY ENTRY'!$C$7:$C$1203,$A38,'DAILY ENTRY'!$B$7:$B$1203,C$3)) | D38: =IF(D$3="(empty slot)","",COUNTIFS('DAILY ENTRY'!$C$7:$C$1203,$A38,'DAILY ENTRY'!$B$7:$B$1203,D$3)) | E38: =IF(E$3="(empty slot)","",COUNTIFS('DAILY ENTRY'!$C$7:$C$1203,$A38,'DAILY ENTRY'!$B$7:$B$1203,E$3)) | F38: =IF(F$3="(empty slot)","",COUNTIFS('DAILY ENTRY'!$C$7:$C$1203,$A38,'DAILY ENTRY'!$B$7:$B$1203,F$3)) | G38: =IF(G$3="(empty slot)","",COUNTIFS('DAILY ENTRY'!$C$7:$C$1203,$A38,'DAILY ENTRY'!$B$7:$B$1203,G$3)) | H38: =IF(H$3="(empty slot)","",COUNTIFS('DAILY ENTRY'!$C$7:$C$1203,$A38,'DAILY ENTRY'!$B$7:$B$1203,H$3)) | I38: =IF(I$3="(empty slot)","",COUNTIFS('DAILY ENTRY'!$C$7:$C$1203,$A38,'DAILY ENTRY'!$B$7:$B$1203,I$3)) | ... K38: =IF(K$3="(empty slot)","",COUNTIFS('DAILY ENTRY'!$C$7:$C$1203,$A38,'DAILY ENTRY'!$B$7:$B$1203,K$3)) | L38: =COUNTIF('DAILY ENTRY'!$C$7:$C$1203,$A38) -> 0
A39: ='Platform Setup'!$B$39 -> Apple Podcasts | B39: =IF(B$3="(empty slot)","",COUNTIFS('DAILY ENTRY'!$C$7:$C$1203,$A39,'DAILY ENTRY'!$B$7:$B$1203,B$3)) -> 0 | C39: =IF(C$3="(empty slot)","",COUNTIFS('DAILY ENTRY'!$C$7:$C$1203,$A39,'DAILY ENTRY'!$B$7:$B$1203,C$3)) | D39: =IF(D$3="(empty slot)","",COUNTIFS('DAILY ENTRY'!$C$7:$C$1203,$A39,'DAILY ENTRY'!$B$7:$B$1203,D$3)) | E39: =IF(E$3="(empty slot)","",COUNTIFS('DAILY ENTRY'!$C$7:$C$1203,$A39,'DAILY ENTRY'!$B$7:$B$1203,E$3)) | F39: =IF(F$3="(empty slot)","",COUNTIFS('DAILY ENTRY'!$C$7:$C$1203,$A39,'DAILY ENTRY'!$B$7:$B$1203,F$3)) | G39: =IF(G$3="(empty slot)","",COUNTIFS('DAILY ENTRY'!$C$7:$C$1203,$A39,'DAILY ENTRY'!$B$7:$B$1203,G$3)) | H39: =IF(H$3="(empty slot)","",COUNTIFS('DAILY ENTRY'!$C$7:$C$1203,$A39,'DAILY ENTRY'!$B$7:$B$1203,H$3)) | I39: =IF(I$3="(empty slot)","",COUNTIFS('DAILY ENTRY'!$C$7:$C$1203,$A39,'DAILY ENTRY'!$B$7:$B$1203,I$3)) | ... K39: =IF(K$3="(empty slot)","",COUNTIFS('DAILY ENTRY'!$C$7:$C$1203,$A39,'DAILY ENTRY'!$B$7:$B$1203,K$3)) | L39: =COUNTIF('DAILY ENTRY'!$C$7:$C$1203,$A39) -> 0
A40: ='Platform Setup'!$B$40 -> LinkedIn Articles | B40: =IF(B$3="(empty slot)","",COUNTIFS('DAILY ENTRY'!$C$7:$C$1203,$A40,'DAILY ENTRY'!$B$7:$B$1203,B$3)) -> 0 | C40: =IF(C$3="(empty slot)","",COUNTIFS('DAILY ENTRY'!$C$7:$C$1203,$A40,'DAILY ENTRY'!$B$7:$B$1203,C$3)) | D40: =IF(D$3="(empty slot)","",COUNTIFS('DAILY ENTRY'!$C$7:$C$1203,$A40,'DAILY ENTRY'!$B$7:$B$1203,D$3)) | E40: =IF(E$3="(empty slot)","",COUNTIFS('DAILY ENTRY'!$C$7:$C$1203,$A40,'DAILY ENTRY'!$B$7:$B$1203,E$3)) | F40: =IF(F$3="(empty slot)","",COUNTIFS('DAILY ENTRY'!$C$7:$C$1203,$A40,'DAILY ENTRY'!$B$7:$B$1203,F$3)) | G40: =IF(G$3="(empty slot)","",COUNTIFS('DAILY ENTRY'!$C$7:$C$1203,$A40,'DAILY ENTRY'!$B$7:$B$1203,G$3)) | H40: =IF(H$3="(empty slot)","",COUNTIFS('DAILY ENTRY'!$C$7:$C$1203,$A40,'DAILY ENTRY'!$B$7:$B$1203,H$3)) | I40: =IF(I$3="(empty slot)","",COUNTIFS('DAILY ENTRY'!$C$7:$C$1203,$A40,'DAILY ENTRY'!$B$7:$B$1203,I$3)) | ... K40: =IF(K$3="(empty slot)","",COUNTIFS('DAILY ENTRY'!$C$7:$C$1203,$A40,'DAILY ENTRY'!$B$7:$B$1203,K$3)) | L40: =COUNTIF('DAILY ENTRY'!$C$7:$C$1203,$A40) -> 0
A41: ='Platform Setup'!$B$41 -> WordPress.com | B41: =IF(B$3="(empty slot)","",COUNTIFS('DAILY ENTRY'!$C$7:$C$1203,$A41,'DAILY ENTRY'!$B$7:$B$1203,B$3)) -> 0 | C41: =IF(C$3="(empty slot)","",COUNTIFS('DAILY ENTRY'!$C$7:$C$1203,$A41,'DAILY ENTRY'!$B$7:$B$1203,C$3)) | D41: =IF(D$3="(empty slot)","",COUNTIFS('DAILY ENTRY'!$C$7:$C$1203,$A41,'DAILY ENTRY'!$B$7:$B$1203,D$3)) | E41: =IF(E$3="(empty slot)","",COUNTIFS('DAILY ENTRY'!$C$7:$C$1203,$A41,'DAILY ENTRY'!$B$7:$B$1203,E$3)) | F41: =IF(F$3="(empty slot)","",COUNTIFS('DAILY ENTRY'!$C$7:$C$1203,$A41,'DAILY ENTRY'!$B$7:$B$1203,F$3)) | G41: =IF(G$3="(empty slot)","",COUNTIFS('DAILY ENTRY'!$C$7:$C$1203,$A41,'DAILY ENTRY'!$B$7:$B$1203,G$3)) | H41: =IF(H$3="(empty slot)","",COUNTIFS('DAILY ENTRY'!$C$7:$C$1203,$A41,'DAILY ENTRY'!$B$7:$B$1203,H$3)) | I41: =IF(I$3="(empty slot)","",COUNTIFS('DAILY ENTRY'!$C$7:$C$1203,$A41,'DAILY ENTRY'!$B$7:$B$1203,I$3)) | ... K41: =IF(K$3="(empty slot)","",COUNTIFS('DAILY ENTRY'!$C$7:$C$1203,$A41,'DAILY ENTRY'!$B$7:$B$1203,K$3)) | L41: =COUNTIF('DAILY ENTRY'!$C$7:$C$1203,$A41) -> 0
A42: ='Platform Setup'!$B$42 -> Blogger | B42: =IF(B$3="(empty slot)","",COUNTIFS('DAILY ENTRY'!$C$7:$C$1203,$A42,'DAILY ENTRY'!$B$7:$B$1203,B$3)) -> 0 | C42: =IF(C$3="(empty slot)","",COUNTIFS('DAILY ENTRY'!$C$7:$C$1203,$A42,'DAILY ENTRY'!$B$7:$B$1203,C$3)) | D42: =IF(D$3="(empty slot)","",COUNTIFS('DAILY ENTRY'!$C$7:$C$1203,$A42,'DAILY ENTRY'!$B$7:$B$1203,D$3)) | E42: =IF(E$3="(empty slot)","",COUNTIFS('DAILY ENTRY'!$C$7:$C$1203,$A42,'DAILY ENTRY'!$B$7:$B$1203,E$3)) | F42: =IF(F$3="(empty slot)","",COUNTIFS('DAILY ENTRY'!$C$7:$C$1203,$A42,'DAILY ENTRY'!$B$7:$B$1203,F$3)) | G42: =IF(G$3="(empty slot)","",COUNTIFS('DAILY ENTRY'!$C$7:$C$1203,$A42,'DAILY ENTRY'!$B$7:$B$1203,G$3)) | H42: =IF(H$3="(empty slot)","",COUNTIFS('DAILY ENTRY'!$C$7:$C$1203,$A42,'DAILY ENTRY'!$B$7:$B$1203,H$3)) | I42: =IF(I$3="(empty slot)","",COUNTIFS('DAILY ENTRY'!$C$7:$C$1203,$A42,'DAILY ENTRY'!$B$7:$B$1203,I$3)) | ... K42: =IF(K$3="(empty slot)","",COUNTIFS('DAILY ENTRY'!$C$7:$C$1203,$A42,'DAILY ENTRY'!$B$7:$B$1203,K$3)) | L42: =COUNTIF('DAILY ENTRY'!$C$7:$C$1203,$A42) -> 0
A43: ='Platform Setup'!$B$43 -> Quora Spaces | B43: =IF(B$3="(empty slot)","",COUNTIFS('DAILY ENTRY'!$C$7:$C$1203,$A43,'DAILY ENTRY'!$B$7:$B$1203,B$3)) -> 0 | C43: =IF(C$3="(empty slot)","",COUNTIFS('DAILY ENTRY'!$C$7:$C$1203,$A43,'DAILY ENTRY'!$B$7:$B$1203,C$3)) | D43: =IF(D$3="(empty slot)","",COUNTIFS('DAILY ENTRY'!$C$7:$C$1203,$A43,'DAILY ENTRY'!$B$7:$B$1203,D$3)) | E43: =IF(E$3="(empty slot)","",COUNTIFS('DAILY ENTRY'!$C$7:$C$1203,$A43,'DAILY ENTRY'!$B$7:$B$1203,E$3)) | F43: =IF(F$3="(empty slot)","",COUNTIFS('DAILY ENTRY'!$C$7:$C$1203,$A43,'DAILY ENTRY'!$B$7:$B$1203,F$3)) | G43: =IF(G$3="(empty slot)","",COUNTIFS('DAILY ENTRY'!$C$7:$C$1203,$A43,'DAILY ENTRY'!$B$7:$B$1203,G$3)) | H43: =IF(H$3="(empty slot)","",COUNTIFS('DAILY ENTRY'!$C$7:$C$1203,$A43,'DAILY ENTRY'!$B$7:$B$1203,H$3)) | I43: =IF(I$3="(empty slot)","",COUNTIFS('DAILY ENTRY'!$C$7:$C$1203,$A43,'DAILY ENTRY'!$B$7:$B$1203,I$3)) | ... K43: =IF(K$3="(empty slot)","",COUNTIFS('DAILY ENTRY'!$C$7:$C$1203,$A43,'DAILY ENTRY'!$B$7:$B$1203,K$3)) | L43: =COUNTIF('DAILY ENTRY'!$C$7:$C$1203,$A43) -> 0
A44: ='Platform Setup'!$B$44 -> Vocal Media | B44: =IF(B$3="(empty slot)","",COUNTIFS('DAILY ENTRY'!$C$7:$C$1203,$A44,'DAILY ENTRY'!$B$7:$B$1203,B$3)) -> 0 | C44: =IF(C$3="(empty slot)","",COUNTIFS('DAILY ENTRY'!$C$7:$C$1203,$A44,'DAILY ENTRY'!$B$7:$B$1203,C$3)) | D44: =IF(D$3="(empty slot)","",COUNTIFS('DAILY ENTRY'!$C$7:$C$1203,$A44,'DAILY ENTRY'!$B$7:$B$1203,D$3)) | E44: =IF(E$3="(empty slot)","",COUNTIFS('DAILY ENTRY'!$C$7:$C$1203,$A44,'DAILY ENTRY'!$B$7:$B$1203,E$3)) | F44: =IF(F$3="(empty slot)","",COUNTIFS('DAILY ENTRY'!$C$7:$C$1203,$A44,'DAILY ENTRY'!$B$7:$B$1203,F$3)) | G44: =IF(G$3="(empty slot)","",COUNTIFS('DAILY ENTRY'!$C$7:$C$1203,$A44,'DAILY ENTRY'!$B$7:$B$1203,G$3)) | H44: =IF(H$3="(empty slot)","",COUNTIFS('DAILY ENTRY'!$C$7:$C$1203,$A44,'DAILY ENTRY'!$B$7:$B$1203,H$3)) | I44: =IF(I$3="(empty slot)","",COUNTIFS('DAILY ENTRY'!$C$7:$C$1203,$A44,'DAILY ENTRY'!$B$7:$B$1203,I$3)) | ... K44: =IF(K$3="(empty slot)","",COUNTIFS('DAILY ENTRY'!$C$7:$C$1203,$A44,'DAILY ENTRY'!$B$7:$B$1203,K$3)) | L44: =COUNTIF('DAILY ENTRY'!$C$7:$C$1203,$A44) -> 0
A45: ='Platform Setup'!$B$45 -> DEV Community | B45: =IF(B$3="(empty slot)","",COUNTIFS('DAILY ENTRY'!$C$7:$C$1203,$A45,'DAILY ENTRY'!$B$7:$B$1203,B$3)) -> 0 | C45: =IF(C$3="(empty slot)","",COUNTIFS('DAILY ENTRY'!$C$7:$C$1203,$A45,'DAILY ENTRY'!$B$7:$B$1203,C$3)) | D45: =IF(D$3="(empty slot)","",COUNTIFS('DAILY ENTRY'!$C$7:$C$1203,$A45,'DAILY ENTRY'!$B$7:$B$1203,D$3)) | E45: =IF(E$3="(empty slot)","",COUNTIFS('DAILY ENTRY'!$C$7:$C$1203,$A45,'DAILY ENTRY'!$B$7:$B$1203,E$3)) | F45: =IF(F$3="(empty slot)","",COUNTIFS('DAILY ENTRY'!$C$7:$C$1203,$A45,'DAILY ENTRY'!$B$7:$B$1203,F$3)) | G45: =IF(G$3="(empty slot)","",COUNTIFS('DAILY ENTRY'!$C$7:$C$1203,$A45,'DAILY ENTRY'!$B$7:$B$1203,G$3)) | H45: =IF(H$3="(empty slot)","",COUNTIFS('DAILY ENTRY'!$C$7:$C$1203,$A45,'DAILY ENTRY'!$B$7:$B$1203,H$3)) | I45: =IF(I$3="(empty slot)","",COUNTIFS('DAILY ENTRY'!$C$7:$C$1203,$A45,'DAILY ENTRY'!$B$7:$B$1203,I$3)) | ... K45: =IF(K$3="(empty slot)","",COUNTIFS('DAILY ENTRY'!$C$7:$C$1203,$A45,'DAILY ENTRY'!$B$7:$B$1203,K$3)) | L45: =COUNTIF('DAILY ENTRY'!$C$7:$C$1203,$A45) -> 0
A46: ='Platform Setup'!$B$46 -> Hashnode | B46: =IF(B$3="(empty slot)","",COUNTIFS('DAILY ENTRY'!$C$7:$C$1203,$A46,'DAILY ENTRY'!$B$7:$B$1203,B$3)) -> 0 | C46: =IF(C$3="(empty slot)","",COUNTIFS('DAILY ENTRY'!$C$7:$C$1203,$A46,'DAILY ENTRY'!$B$7:$B$1203,C$3)) | D46: =IF(D$3="(empty slot)","",COUNTIFS('DAILY ENTRY'!$C$7:$C$1203,$A46,'DAILY ENTRY'!$B$7:$B$1203,D$3)) | E46: =IF(E$3="(empty slot)","",COUNTIFS('DAILY ENTRY'!$C$7:$C$1203,$A46,'DAILY ENTRY'!$B$7:$B$1203,E$3)) | F46: =IF(F$3="(empty slot)","",COUNTIFS('DAILY ENTRY'!$C$7:$C$1203,$A46,'DAILY ENTRY'!$B$7:$B$1203,F$3)) | G46: =IF(G$3="(empty slot)","",COUNTIFS('DAILY ENTRY'!$C$7:$C$1203,$A46,'DAILY ENTRY'!$B$7:$B$1203,G$3)) | H46: =IF(H$3="(empty slot)","",COUNTIFS('DAILY ENTRY'!$C$7:$C$1203,$A46,'DAILY ENTRY'!$B$7:$B$1203,H$3)) | I46: =IF(I$3="(empty slot)","",COUNTIFS('DAILY ENTRY'!$C$7:$C$1203,$A46,'DAILY ENTRY'!$B$7:$B$1203,I$3)) | ... K46: =IF(K$3="(empty slot)","",COUNTIFS('DAILY ENTRY'!$C$7:$C$1203,$A46,'DAILY ENTRY'!$B$7:$B$1203,K$3)) | L46: =COUNTIF('DAILY ENTRY'!$C$7:$C$1203,$A46) -> 0
A47: ='Platform Setup'!$B$47 -> Google Search Console | B47: =IF(B$3="(empty slot)","",COUNTIFS('DAILY ENTRY'!$C$7:$C$1203,$A47,'DAILY ENTRY'!$B$7:$B$1203,B$3)) -> 0 | C47: =IF(C$3="(empty slot)","",COUNTIFS('DAILY ENTRY'!$C$7:$C$1203,$A47,'DAILY ENTRY'!$B$7:$B$1203,C$3)) | D47: =IF(D$3="(empty slot)","",COUNTIFS('DAILY ENTRY'!$C$7:$C$1203,$A47,'DAILY ENTRY'!$B$7:$B$1203,D$3)) | E47: =IF(E$3="(empty slot)","",COUNTIFS('DAILY ENTRY'!$C$7:$C$1203,$A47,'DAILY ENTRY'!$B$7:$B$1203,E$3)) | F47: =IF(F$3="(empty slot)","",COUNTIFS('DAILY ENTRY'!$C$7:$C$1203,$A47,'DAILY ENTRY'!$B$7:$B$1203,F$3)) | G47: =IF(G$3="(empty slot)","",COUNTIFS('DAILY ENTRY'!$C$7:$C$1203,$A47,'DAILY ENTRY'!$B$7:$B$1203,G$3)) | H47: =IF(H$3="(empty slot)","",COUNTIFS('DAILY ENTRY'!$C$7:$C$1203,$A47,'DAILY ENTRY'!$B$7:$B$1203,H$3)) | I47: =IF(I$3="(empty slot)","",COUNTIFS('DAILY ENTRY'!$C$7:$C$1203,$A47,'DAILY ENTRY'!$B$7:$B$1203,I$3)) | ... K47: =IF(K$3="(empty slot)","",COUNTIFS('DAILY ENTRY'!$C$7:$C$1203,$A47,'DAILY ENTRY'!$B$7:$B$1203,K$3)) | L47: =COUNTIF('DAILY ENTRY'!$C$7:$C$1203,$A47) -> 0
A48: ='Platform Setup'!$B$48 -> Google Analytics | B48: =IF(B$3="(empty slot)","",COUNTIFS('DAILY ENTRY'!$C$7:$C$1203,$A48,'DAILY ENTRY'!$B$7:$B$1203,B$3)) -> 0 | C48: =IF(C$3="(empty slot)","",COUNTIFS('DAILY ENTRY'!$C$7:$C$1203,$A48,'DAILY ENTRY'!$B$7:$B$1203,C$3)) | D48: =IF(D$3="(empty slot)","",COUNTIFS('DAILY ENTRY'!$C$7:$C$1203,$A48,'DAILY ENTRY'!$B$7:$B$1203,D$3)) | E48: =IF(E$3="(empty slot)","",COUNTIFS('DAILY ENTRY'!$C$7:$C$1203,$A48,'DAILY ENTRY'!$B$7:$B$1203,E$3)) | F48: =IF(F$3="(empty slot)","",COUNTIFS('DAILY ENTRY'!$C$7:$C$1203,$A48,'DAILY ENTRY'!$B$7:$B$1203,F$3)) | G48: =IF(G$3="(empty slot)","",COUNTIFS('DAILY ENTRY'!$C$7:$C$1203,$A48,'DAILY ENTRY'!$B$7:$B$1203,G$3)) | H48: =IF(H$3="(empty slot)","",COUNTIFS('DAILY ENTRY'!$C$7:$C$1203,$A48,'DAILY ENTRY'!$B$7:$B$1203,H$3)) | I48: =IF(I$3="(empty slot)","",COUNTIFS('DAILY ENTRY'!$C$7:$C$1203,$A48,'DAILY ENTRY'!$B$7:$B$1203,I$3)) | ... K48: =IF(K$3="(empty slot)","",COUNTIFS('DAILY ENTRY'!$C$7:$C$1203,$A48,'DAILY ENTRY'!$B$7:$B$1203,K$3)) | L48: =COUNTIF('DAILY ENTRY'!$C$7:$C$1203,$A48) -> 0
A49: ='Platform Setup'!$B$49 -> Microsoft Clarity | B49: =IF(B$3="(empty slot)","",COUNTIFS('DAILY ENTRY'!$C$7:$C$1203,$A49,'DAILY ENTRY'!$B$7:$B$1203,B$3)) -> 0 | C49: =IF(C$3="(empty slot)","",COUNTIFS('DAILY ENTRY'!$C$7:$C$1203,$A49,'DAILY ENTRY'!$B$7:$B$1203,C$3)) | D49: =IF(D$3="(empty slot)","",COUNTIFS('DAILY ENTRY'!$C$7:$C$1203,$A49,'DAILY ENTRY'!$B$7:$B$1203,D$3)) | E49: =IF(E$3="(empty slot)","",COUNTIFS('DAILY ENTRY'!$C$7:$C$1203,$A49,'DAILY ENTRY'!$B$7:$B$1203,E$3)) | F49: =IF(F$3="(empty slot)","",COUNTIFS('DAILY ENTRY'!$C$7:$C$1203,$A49,'DAILY ENTRY'!$B$7:$B$1203,F$3)) | G49: =IF(G$3="(empty slot)","",COUNTIFS('DAILY ENTRY'!$C$7:$C$1203,$A49,'DAILY ENTRY'!$B$7:$B$1203,G$3)) | H49: =IF(H$3="(empty slot)","",COUNTIFS('DAILY ENTRY'!$C$7:$C$1203,$A49,'DAILY ENTRY'!$B$7:$B$1203,H$3)) | I49: =IF(I$3="(empty slot)","",COUNTIFS('DAILY ENTRY'!$C$7:$C$1203,$A49,'DAILY ENTRY'!$B$7:$B$1203,I$3)) | ... K49: =IF(K$3="(empty slot)","",COUNTIFS('DAILY ENTRY'!$C$7:$C$1203,$A49,'DAILY ENTRY'!$B$7:$B$1203,K$3)) | L49: =COUNTIF('DAILY ENTRY'!$C$7:$C$1203,$A49) -> 0
A50: TOTAL ENTRIES | B50: =SUM(B4:B49) -> 0 | C50: =SUM(C4:C49) -> 0 | D50: =SUM(D4:D49) -> 0 | E50: =SUM(E4:E49) -> 0 | F50: =SUM(F4:F49) -> 0 | G50: =SUM(G4:G49) -> 0 | H50: =SUM(H4:H49) -> 0 | I50: =SUM(I4:I49) -> 0 | ... L50: =SUM(L4:L49) -> 0

Sheet Summary
A1: MANAGEMENT SUMMARY — one page, read in 60 seconds
A2: All figures are calculated. For detail, open the Dashboard.
A4: THE FIVE NUMBERS THAT MATTER
A5: 1. Platform coverage (accounts live and complete) | B5: =IFERROR(COUNTIF('Platform Setup'!$J$4:$J$49,"Complete")/COUNTA('Platform Setup'!$B$4:$B$49),0) -> 0 | C5: Is PCI present everywhere it should be? Target 100% within the first 6 weeks.
A6: 2. Task completion rate | B6: =IFERROR(COUNTIF('Master Tasks'!$J$4:$J$66,"Complete")/COUNTA('Master Tasks'!$A$4:$A$66),0) -> 0 | C6: How much of the agreed plan is finished and evidenced.
A7: 3. LinkedIn acceptance rate | B7: =IFERROR(COUNTIF('LinkedIn Outreach'!$N$5:$N$1203,"Yes")/COUNTIF('LinkedIn Outreach'!$M$5:$M$1203,"Yes"),0) -> 0 | C7: Quality of targeting and of the connection note. 2026 average 27-30%; good 30-45%; below 20% needs fixing.
A8: 4. Reply rate on the honorary certification message | B8: =IFERROR((COUNTIF('LinkedIn Outreach'!$S$5:$S$1203,"Interested")+COUNTIF('LinkedIn Outreach'!$S$5:$S$1203,"Info Requested")+COUNTIF('LinkedIn Outreach'!$S$5:$S$1203,"Meeting Booked")+COUNTIF('LinkedIn Outreach'!$S$5:$S$1203,"Converted"))/COUNTIF('LinkedIn Outreach'!$R$5:$R$1203,"Yes"),0) -> 0 | C8: Quality of the 300-character message. 2026 average about 10%; 15%+ is strong.
A9: 5. Meetings and conversions produced | B9: =COUNTIF('LinkedIn Outreach'!$S$5:$S$1203,"Meeting Booked")+COUNTIF('LinkedIn Outreach'!$S$5:$S$1203,"Converted")+COUNTIF('Community & PR'!$N$5:$N$403,"Meeting Booked") -> 0 | C9: The only output that turns into members and partnerships.
A11: VOLUME DELIVERED TO DATE
A12: Days with activity logged | B12: =SUMPRODUCT(('DAILY ENTRY'!$A$7:$A$1203<>"")/COUNTIFS('DAILY ENTRY'!$A$7:$A$1203,'DAILY ENTRY'!$A$7:$A$1203&"")) -> 0 | C12: Days the employee recorded activity.
A13: Leads researched | B13: =SUMIFS('DAILY ENTRY'!$F$7:$F$1203,'DAILY ENTRY'!$D$7:$D$1203,"Lead researched (Sales Navigator)") -> 0 | C13: Sales Navigator research volume.
A14: Connection requests sent | B14: =SUMIFS('DAILY ENTRY'!$F$7:$F$1203,'DAILY ENTRY'!$D$7:$D$1203,"Connection request sent") -> 0 | C14: Personalised invitations.
A15: First messages sent | B15: =SUMIFS('DAILY ENTRY'!$F$7:$F$1203,'DAILY ENTRY'!$D$7:$D$1203,"First message sent") -> 0 | C15: 300-character honorary certification messages.
A16: Follow-ups sent | B16: =SUMIFS('DAILY ENTRY'!$F$7:$F$1203,'DAILY ENTRY'!$D$7:$D$1203,"Follow-up message sent") -> 0 | C16: Day 4 and day 10 follow-ups.
A17: Posts published | B17: =SUMIFS('DAILY ENTRY'!$F$7:$F$1203,'DAILY ENTRY'!$D$7:$D$1203,"Post / content published") -> 0 | C17: All platforms combined.
A18: Community answers | B18: =SUMIFS('DAILY ENTRY'!$F$7:$F$1203,'DAILY ENTRY'!$D$7:$D$1203,"Community answer or comment") -> 0 | C18: Quora, Reddit and groups.
A19: Partnership / PR contacts approached | B19: =SUMIFS('DAILY ENTRY'!$F$7:$F$1203,'DAILY ENTRY'!$D$7:$D$1203,"Partnership / PR contact") -> 0 | C19: Associations, universities, employers, podcasts, media.
A20: Accounts set up | B20: =SUMIFS('DAILY ENTRY'!$F$7:$F$1203,'DAILY ENTRY'!$D$7:$D$1203,"Account created / profile completed") -> 0 | C20: New PCI platform accounts created.
A22: RISKS AND THINGS NEEDING A DECISION
A23: Tasks blocked | B23: =COUNTIF('Master Tasks'!$J$4:$J$66,"Blocked") -> 0 | C23: Each one needs a decision from the manager. Filter Master Tasks by Status = Blocked to see them.
A24: Platforms still not started | B24: =COUNTIF('Platform Setup'!$J$4:$J$49,"Not Started") -> 46 | C24: No PCI presence yet on these channels.
A25: Live accounts without 2FA | B25: =COUNTIFS('Platform Setup'!$I$4:$I$49,"No",'Platform Setup'!$J$4:$J$49,"<>Not Started") -> 0 | C25: Security exposure - fix immediately.
A26: Messages sent over 300 characters | B26: =COUNTIF('LinkedIn Outreach'!$Q$5:$Q$1203,">300") -> 0 | C26: Breach of the agreed message standard.
A27: Blocked items raised by the team | B27: =COUNTIF('DAILY ENTRY'!$I$7:$I$1203,"Blocked") -> 0 | C27: Read the Daily Log Blocker column for detail.
A29: THE DAILY RHYTHM WE EXPECT
A30: 09:00 Research | B30: 30 qualified leads in Sales Navigator, each with a personal line written.
A31: 10:00 Connect | B31: 20 personalised connection requests (template M1, under 200 characters).
A32: 11:00 Message | B32: 15 honorary certification messages to new acceptances (template M2, under 300 characters).
A33: 11:30 Reply | B33: Answer every response the same day. Escalate anything uncertain.
A34: 12:00 Follow up | B34: Day 4 and day 10 follow-ups only. Two maximum, then close politely.
