Workbook

Sheet START HERE
A1: PCI AI — PROJECT CONTROLS INSTITUTE | EMPLOYEE EXECUTION TRACKER
A2: ◀ MAP | B2: Read this page first. It takes 5 minutes and explains exactly how to use every tab.
A3: NEW HERE? Read this page, then TEAM GUIDE (where to log what), then PLATFORM GUIDE (how to use each platform). · A word you do not know? The GLOSSARY tab. Lost? The MAP tab lists every sheet with one click. · Need something to write? Article Bank.
A4: 1. HOW THIS WORKS — employees fill in ONE sheet
A5: EVERY DAY -> DAILY ENTRY tab | B5: This is the only sheet you must fill in. One row for each thing you did: the date, your name, which platform, what kind of work, how many, how long it took and a link that proves it. Every row also carries the two tag columns (Objective + For (brand)); six of the twelve columns are dropdowns, so most of a row is clicking, not typing.
A6: Log as you go, not at 5pm | B6: Add the row when you finish the task. Ten rows a day is normal. If you did nothing on a platform, there is simply no row for it.
A7: ALSO, if you do LinkedIn outreach | B7: The LinkedIn Outreach tab holds one row per PERSON you contact - name, company, the message you sent, and what they replied. This cannot be collapsed into daily totals, because acceptance and reply rates need to be tracked per person.
A8: Everything else fills itself in | B8: Platform Progress, Who Did What, Team Scorecard, Weekly Review, Dashboard and Summary all calculate from what you enter. You never type a number twice. The Daily Log tab is optional.
A9: BEFORE YOU START -> Platform Setup tab | B9: Work through the account list and follow the setup steps written in each row. Mark Status = Complete only when the profile is fully filled in with logo, bio, link and 2FA.
A10: BEFORE YOU WRITE -> Publishing Plan tab | B10: The ten publishing platforms, ranked, with the rule for each one. Read the rule before you publish anywhere.
A11: BEFORE YOU MESSAGE -> Message Bank tab | B11: Never write outreach from scratch. Copy the approved message and replace every [bracket] with real details from the person's profile.
A12: EVERY FRIDAY -> Weekly Review tab | B12: Write your wins, misses and next week's focus. The numbers are already there. Use the dropdown in cell B2 to see just your own week.
A13: REFERENCE -> How-To Guides, LinkedIn Playbook, Benchmarks | B13: Read these when you start a platform for the first time or when you want to know what good looks like.
A14: FOR THE MANAGER -> Weekly Pulse, Objective Performance, Team Scorecard, Dashboard, Summary | B14: Read-only pages — nobody types in them. Monday, in this order: WEEKLY PULSE (what moved last week, green or red) → OBJECTIVE PERFORMANCE (which campaigns earned their hours: compare Value rank with Share of minutes) → TEAM SCORECARD column Q (the one-sentence verdict per person) → DASHBOARD section 9 DATA HEALTH (every number there must read zero before you quote anything to anyone). SUMMARY is the one page to forward upwards.
A15: Master Tasks tab | B15: The full workstream list with an Owner column. Update Status and Progress when a task moves.
A17: 2. TEAM SETTINGS — the manager fills these once (yellow cells)
A18: Team / department name
A19: Manager / reviewer | C19: Required — the manager runs the Monday review and signs QA.
A20: Programme start date (a Monday) | B20: 46251
A21: Working days per week | B21: 5
A22: Our week starts on (1 = Sunday, 2 = Monday) | B22: 2 | C22: Set 1 for a Sunday-Thursday working week (Saudi, Qatar, Kuwait, Bahrain) so Sunday's output lands in the right week. Weekly Pulse and Weekly Review both follow this.
A23: 3. DAILY TARGETS — per person, per working day. The Dashboard multiplies by the number of people on the roster.
A24: Activity | B24: Target per day (each person) | C24: Target per week (auto)
A25: Sales Navigator leads researched | B25: 30 | C25: =B25*'START HERE'!$B$21 -> 150
A26: Connection requests sent | B26: 20 | C26: =B26*'START HERE'!$B$21 -> 100
A27: First messages sent (accepted connections) | B27: 15 | C27: =B27*'START HERE'!$B$21 -> 75
A28: Follow-up messages sent | B28: 10 | C28: =B28*'START HERE'!$B$21 -> 50
A29: Posts published (all platforms) | B29: 2 | C29: =B29*'START HERE'!$B$21 -> 10
A30: Community answers / comments (incl. engagement; 3-5 full answers/week) | B30: 3 | C30: =B30*'START HERE'!$B$21 -> 15
A31: Partnership / PR contacts approached | B31: 5 | C31: =B31*'START HERE'!$B$21 -> 25
A32: Meaningful engagements (likes + comments on others) | B32: 15 | C32: =B32*'START HERE'!$B$21 -> 75
A34: 4. GOLDEN RULES — these protect PCI's reputation. Breaking them is a serious issue.
A35: 1. Be honest. Never tell anyone they have been awarded, approved or guaranteed an honorary certification. You are inviting them to be considered and sharing the criteria — nothing more.
A36: 2. Never invent facts about PCI — numbers of members, accreditations, recognition or partnerships. If you are unsure, ask your manager before you send.
A37: 3. Personalise every message. Read the profile first and reference something real (their role, employer, project type or years of experience).
A38: 4. Keep outreach messages under 300 characters and connection notes under 200 characters.
A39: 5. No bulk sending, no automation tools, no bots, no scraping. LinkedIn restricts accounts for this and it destroys reply rates.
A40: 6. Respect limits: stop at the daily target. If LinkedIn shows a warning, stop for the day and tell your manager.
A41: 7. If someone says no or asks you to stop, thank them politely and never contact them again. Mark Outcome = Declined.
A42: 8. Answer the question first, promote PCI second. On Quora, Reddit and groups a useful answer with no link beats a link with no value.
A43: 9. Never post PCI passwords in this file — only the reference name from the password manager. Turn on 2FA everywhere.
A44: 10. Log everything the same day. Evidence (a URL or screenshot link) is what makes the work count.
A46: 5. COLOUR LEGEND
A47: Yellow cell | B47: You type here.
A48: White cell | B48: Calculated or reference — do not type over it.
A49: Grey / blue header | B49: Structure — do not rename, the Dashboard depends on these names.
A50: Green | B50: Good / on target.
A51: Red | B51: Attention needed / over limit.
A53: 6. TEAM ROSTER — type each marketing team member's name here, exactly as they will type it in the log tabs
A54: Slot | B54: Employee name (this becomes the dropdown in every log tab)
A55: 1 | B55: Employee 1
A56: 2
A57: 3
A58: 4
A59: 5
A60: 6
A61: 7
A62: 8
A63: 9
A64: 10
A66: Names must match exactly between this list and the log tabs, otherwise the Team Scorecard will show zero for that person. Use the dropdown in the log tabs rather than typing names by hand.
A68: 7. BRANDS & PROPERTIES — every logged row says WHO it is for
A69: Primary brand (default focus) | B69: PCI AI - Institute (umbrella)
A70: Each log tab has a For (brand) column: the institute, one certification (PCL-AI / PFL-AI / PML-AI), PCI World, Certuvo, or All / shared when the work genuinely serves everything. Tag every row — the Objective Performance sheet splits results by brand as well as by campaign, so one file serves the whole estate without mixing the numbers.
A72: 8. WHERE EACH PART OF THE GROWTH PLAN LIVES
A73: Executive dashboard / management summary | B73: Dashboard, Summary
A74: Employee scorecard and grading | B74: Employee Score, Team Scorecard
A75: Master growth plan | B75: Master Tasks
A76: Daily execution | B76: DAILY ENTRY
A77: LinkedIn Sales Navigator + honorary certification pipeline | B77: LinkedIn Outreach, LinkedIn Playbook, Message Bank
A78: Enterprise / employer, university, association and influencer pipelines | B78: Partnership Pipeline
A79: Funnel and lead scoring | B79: LinkedIn Outreach (columns Y-AC), Partnership Pipeline, Dashboard section 7
A80: Social media, content factory, Medium / Quora / Reddit, YouTube | B80: Content Calendar, Publishing Plan, Platform Setup, Platform Progress
A81: SEO and content clusters | B81: SEO Clusters
A82: PR, media, podcasts, webinars and events | B82: Partnership Pipeline, Community & PR, Platform Setup
A83: Reviews and reputation | B83: Platform Setup (directory rows), QA & Compliance
A84: Platform accounts | B84: Platform Setup, Platform Progress
... A90: Lists and controls | B90: Lists, Benchmarks
A93: 9. HOW THIS FILE IS SHARED — one file, whole team. Breaking these rules corrupts everyone's numbers.
A94: 1. The file lives in ONE place — a SharePoint / OneDrive folder. Everyone opens it from that link with AutoSave on. No local copies, no email attachments, ever.
A95: FILTERING IS ALLOWED and works on every table — the sheets are locked against changing formulas, not against looking. In a file several people have open at once, use View → Sheet View → New first so your filter is yours alone; then clear it when you are done. SORTING a shared log is still a bad idea: it moves other people's rows under them.
A96: 3. To claim a row on a log sheet, click the first fully empty row and type the Date first.
A97: 4. Never paste whole rows. Type, or paste values only, into yellow columns.
A98: 5. Calculated pages and columns are protected. If you cannot type somewhere, that is deliberate — nothing is broken.
A99: 6. After the example-row purge, rows are never deleted. Corrections are edits; disputes resolve through SharePoint version history.
A100: 7. One named person owns this workbook (the manager in cell B19): they run the Monday review and the Friday QA pass, and only they edit the roster, targets, Lists, Message Bank and Master Task owners.
A101: 8. Capacity: the outreach log holds ~1,200 leads, the daily log ~1,000 rows and the other logs ~400 rows. The owner archives a dated copy monthly. At sustained full-team volume, the lead log belongs in a CRM — this file then tracks activity, not the pipeline.
A103: 10. DAY-1 CHECKLIST — every new team member | B103: Done (Yes / No — manager confirms)
A104: Read START HERE fully, including the Golden Rules and section 9
A105: Added to the team roster above by the manager — name matches exactly everywhere
A106: Password-manager access granted (passwords never go in this file)
A107: LinkedIn profile optimised per LinkedIn Playbook step A
A108: Message Bank read — copy only rows with Status = Approved
A109: Daily targets (section 3) understood and agreed
A110: First 5 logged leads reviewed by the manager BEFORE any request is sent
A111: First 3 sent messages reviewed by the manager
A112: Knows the duplicate rule: Ctrl+F the lead's URL before logging
A113: Assigned their Master Tasks rows and QA checks where relevant
A115: 11. OUR WEB DOMAINS — use these in links, UTMs, bios and releases
A116: Domain | B116: Brand / property it serves | C116: What it is for (manager edits if wrong)
...

Sheet MAP
A1: MAP — what every tab is for, and what you do on it
A2: Click a name in the first column to jump straight there; every sheet has a ◀ MAP link to come back. Read the WHO TYPES ON IT column before you touch a sheet — most of this workbook calculates itself and is not meant to be typed in. New here? START HERE, then TEAM GUIDE, then PLATFORM GUIDE.
A3: ◀ START HERE
A4: Sheet (click to open) | B4: What this sheet is | C4: Who types on it | D4: What you do here, and when
A5: READ FIRST — what a new joiner reads, in this order
A6: START HERE | B6: The rulebook. It sets out how the team works: what to log, the daily targets everyone is measured against, the golden rules that protect PCI's reputation, the team roster and the five web domains we own. | C6: Manager fills the yellow settings once | D6: Read it end to end on your first day — it takes about five minutes. Come back whenever you are unsure what a rule actually says.
A7: TEAM GUIDE | B7: The onboarding sheet. It answers the one question everyone asks — 'I just did this thing, where do I log it?' — for every kind of work, and explains how your score is calculated. | C7: Nobody — read it | D7: Read it after START HERE. Keep it open for your first week; the 'where do I log what' table settles almost every question.
A8: GROWTH PLAYBOOK | B8: The 23 growth techniques PCI actually uses, each written out in working detail: why it works, the exact steps, how often, and the number that proves it worked. | C8: Nobody — read it | D8: Read the technique before you start that kind of work. It also lists what NOT to do — tactics that get accounts penalised.
A9: PLATFORM GUIDE | B9: One row for every platform we are on, saying what to do there each week, how often, and the single number that proves it is working. Setting the account up is on Platform Setup; this is what you do once it exists. | C9: Nobody — read it | D9: Look up your platform before your first session on it. Gold rows are the highest-value platforms — if time is short, work down from the top.
A10: PR & Target Directory | B10: The named routes out: which publications accept contributed articles, which podcasts take guests, which boards and directories are worth applying to — and which ones we have deliberately decided to skip, with the reason. | C10: Manager only | D10: Check it before you approach anyone. If a route is marked as a skip, do not spend time on it.
A11: Glossary | B11: Every term this workbook uses without stopping to explain it — ICP, canonical link, dwell time, EVM, person-day — in plain English, grouped by where you meet the word. | C11: Nobody — read it | D11: Look a word up the moment it stops you. If a term is missing, say so in the Monday review.
A12: UPGRADE NOTES | B12: The changelog. Every change made to this workbook, what was tested, what was found and what was fixed. | C12: Nobody — read it | D12: Read it when the file changes, so you know what moved and why.
A14: DAILY WORK — the sheets you type on
A15: DAILY ENTRY | B15: The one sheet everybody fills in. One row for each thing you do: the date, your name, which platform, what kind of work, how many, how long it took, and a link that proves it. Every management page in the file is built from these rows. | C15: Everyone | D15: Add the row when you FINISH the task, not at 5pm. Ten rows a day is normal. Set both tags — Objective and For (brand) — on every row.
A16: LinkedIn Outreach | B16: One row per PERSON you contact on LinkedIn. It carries the lead from research through the connection request, the message, the reply and the meeting to the sale. This is the honorary-certification engine. | C16: Everyone | D16: Fill columns A-L when you research the lead, M-T when you send and hear back, AD onward only if it becomes a meeting or a sale. Column AN warns you if the person is already in the sheet.
A17: Partnership Pipeline | B17: One row per ORGANISATION rather than per person: associations, universities, employers and training partners, from first contact to a signed agreement. | C17: Everyone | D17: Open a row when you first approach them. A deal only counts as revenue once a real contract-signed date is in the sheet.
A18: Content Calendar | B18: Every piece of content, from the idea to the published URL and the numbers it produced — impressions, engagements, clicks and leads. | C18: Everyone | D18: Add a row when you plan the piece; set Status to Published AND fill the published date on the day it goes live. Missing either one breaks the reporting.
A19: Content Scheduler | B19: One row per running schedule — a platform, at a cadence, between two dates. It works out how many posts that schedule promised and how many actually went out, so you can see which schedules are slipping. | C19: Everyone | D19: Set one up when you commit to a cadence. Coverage under 100% means you are behind on that schedule. The table below the grid says which platforms can schedule natively and with what limits.
A20: Community & PR | B20: Everywhere you show up as a helpful expert rather than a seller: forum answers, community threads, press mentions, podcast appearances and journalist requests. | C20: Everyone | D20: One row per thread started or substantive answer given — never one per like or one-line comment.
A21: Job Postings | B21: Every open PCI role, on every board it is posted to. One row per platform per position, with the applicant count. | C21: Everyone | D21: Add a row each time you post a role somewhere. Update the applicant count when you check the board.
A22: Link Building | B22: Off-page SEO in one place: every site we want a link from, who we contacted, what we offered, and whether the link actually went live. | C22: Everyone | D22: One row per prospect. Fill the date-live column only when you can see the link on the page — that is what the weekly backlink number counts.
A23: Experiments | B23: A/B tests written down honestly: what you changed, what you expected, what happened, and what you will do about it. | C23: Everyone | D23: Start a row before you run the test, not after. Record the result even when it is disappointing — that is the point of the sheet.
A24: UTM Builder | B24: Builds the tracked links we share. A link without one of these tags is invisible in analytics, so nobody can tell where an enquiry came from. | C24: Everyone | D24: Build the link here first, then paste it into the post. Never share a bare URL in a campaign.
A25: SEO Clusters | B25: The seven big subjects we intend to own in Google. Each has one long pillar page and the supporting articles that link up to it, with the Search Console numbers beside them. | C25: Whoever owns SEO | D25: Use it to see how a piece of content fits the plan before you write it. Column F gives the Article Bank ID of the brief for each supporting article.
A26: Keyword Plan | B26: 76 researched search terms, graded Easy, Medium or Hard from what actually ranks today, with the ten to attack first and the reason each one was chosen. | C26: Whoever owns SEO | D26: Pick your next article from here, Easy first — a new site does not beat PMI or AACE on a hard term. Column P gives the Article Bank ID of its brief.
... A28: Daily Log | B28: An optional one-line-per-day summary. Everything on it is calculated from DAILY ENTRY, so it is a convenience, not a second place to type. | C28: Nobody — it calculates | D28: Ignore it unless you like a daily digest. Nothing depends on it.
A30: RESULTS — read-only pages. Nobody types on these
A31: Weekly Pulse | B31: This week against last week, and against the average of the four completed weeks before it. Green means up, red means down. | C31: Nobody — it calculates | D31: The manager's first stop on Monday. If a high-value effort is falling week on week, rebalance before month-end.
A32: Dashboard | B32: The cumulative record — everything achieved since the programme started, with headline KPI tiles down the right-hand side and a DATA HEALTH block at the bottom that counts logging mistakes. | C32: Nobody — it calculates | D32: Check DATA HEALTH before quoting any number on this page to anyone. Every figure in that block should read zero.
A33: Summary | B33: One page, readable in sixty seconds: the six numbers that matter, volume delivered, what needs a decision, and the daily rhythm expected of the team. | C33: Nobody — it calculates | D33: This is the page to forward upwards. Print it for a board or investor update.
A34: Objective Performance | B34: The same results split two ways: by campaign (honorary outreach, certification sales, authority building…) and by brand (the institute, each certification, PCI World, Certuvo). It also shows minutes per person per campaign. | C34: Nobody — it calculates | D34: Compare Value rank against Share of minutes. If the highest-value campaigns are getting the smallest share of the team's hours, move people.
A35: Team Scorecard | B35: Every person's outreach numbers side by side — volume, acceptance rate, reply rate, meetings — with a one-sentence verdict per person. | C35: Nobody — it calculates | D35: Read column Q first: it says in plain words what each person should fix.
A36: Employee Score | B36: The weighted score out of 100 used in reviews. Quality counts far more than volume, and no score appears until there is enough history to be fair. | C36: Nobody — it calculates | D36: Look at the 'What to fix first' column, not just the number. A blank grade means not enough data yet, not a bad result.
A37: Weekly Review | B37: The Friday page: what went well, what did not, and next week's focus, with the week's numbers already filled in beside your notes. | C37: Everyone writes their own notes | D37: Fill it in every Friday. Use the dropdown at the top right to see just your own week.
A38: Platform Progress | B38: How much has actually happened on each of the 133 platforms, how long ago, and who touched it last — set against how valuable that platform is. | C38: Nobody — it calculates | D38: Use it to find neglected high-value platforms. The Attention column tells you which ones have gone quiet.
A39: Who Did What | B39: A grid of every platform against every person, so you can see at a glance who has been carrying which channel. | C39: Nobody — it calculates | D39: Use it when reallocating platforms, or when someone is away and their channels need covering.
A40: Accounts Register | B40: Every account we hold: who owns it, whether two-factor is on, and the reference to the entry in the password manager. | C40: Manager only | D40: Passwords are NEVER stored here — only the vault reference. Check it when somebody joins or leaves.
A42: MANAGEMENT — the manager sets these up
A43: Master Tasks | B43: The full workstream list: every task needed to build the marketing function, with an owner, a due date and what 'done' looks like. | C43: Manager only | D43: Assign an owner and a due date to every row before rollout. Update Status as tasks move.
A44: Platform Setup | B44: All 133 platforms with the steps to create and finish each account, its priority and value rank, which countries it is strongest in, and which brand it serves. | C44: Manager only | D44: Work down it when setting the estate up. Mark Status = Complete only when the profile is genuinely finished — logo, bio, link and two-factor.
A45: Publishing Plan | B45: The ten publishing platforms, ranked, with the rule for each: what may be published there and what must be set (such as the canonical link). | C45: Manager only | D45: Read the rule for a platform before publishing there the first time.
A46: Channel Costs | B46: What each paid tool and channel costs per month, and the economics that fall out of it: cost per meeting and revenue per pound of channel cost. | C46: Manager only | D46: Fill the yellow cost cells. The block underneath then computes the return on its own.
A47: QA & Compliance | B47: The fifteen checks that protect PCI's reputation and keep the accounts alive — honesty of claims, message limits, data protection, platform rules — several with a live pass or fail signal. | C47: Manager only | D47: Work through it monthly and sign it off. An unowned checklist is not a control.
A48: Message Bank | B48: The approved outreach messages — connection notes, first messages and follow-ups — each with a live character count against the platform's limit, and a signed approval. Nothing that is not on this sheet may be sent. | C48: Manager only | D48: Copy the approved text and replace every [bracket] with something real from that person's profile. Never write outreach from scratch.
A50: REFERENCE — look these up when you need them
A51: LinkedIn Playbook | B51: The outreach method in order, from building the saved searches to handing a warm lead over — the detail behind what the Outreach sheet asks you to log. | C51: Nobody — read it | D51: Read it before your first day of outreach, then dip back into it when a step stops working.
A52: How-To Guides | B52: A short training manual per workstream: what you do each week on it and what good looks like. | C52: Nobody — read it | D52: Read the row for a workstream when you pick it up for the first time.
A53: Benchmarks | B53: What good numbers actually look like in 2026, with the source named for every figure and an honest note about where those figures come from. | C53: Nobody — read it | D53: Use it to judge whether a rate is genuinely poor or simply normal. Treat vendor benchmarks as a sanity check, not a law.
A54: Lists | B54: The source values behind every dropdown in the workbook, plus the rule for how each platform should be logged so the same work is never counted twice. | C54: Manager only | D54: Only the manager changes these. Renaming a value here disconnects every row already logged against it.
A56: Colour of a tab tells you the same thing: gold = read first, green = guides, blue = you type here, navy = results (read-only), purple = manager, grey = reference. If a cell will not let you type in it, it is a formula — that is the file working, not a fault.

Sheet TEAM GUIDE
A1: TEAM GUIDE — how this system works, end to end
A2: ◀ MAP | B2: For every team member, new or old. Fifteen minutes here saves the manager explaining the same thing ten times. The deeper references are How-To Guides, LinkedIn Playbook and GROWTH PLAYBOOK.
A4: THE WHOLE SYSTEM IN ONE SENTENCE
A5: You do real marketing work → you log it the same day with evidence → the Dashboard, scorecards and funnel build themselves → the manager reviews Monday morning → next week gets better. Nothing here is busywork: every cell you fill feeds a number a decision is made on.
A7: WHERE DO I LOG WHAT — the only mapping you must memorise
A8: You did this… | B8: Log it here | C8: Also here (if it applies) | D8: It shows up in… | E8: Same-day rule
A9: Researched leads in Sales Navigator | B9: DAILY ENTRY (count + minutes) | C9: LinkedIn Outreach — one row per lead | D9: Team Scorecard, Dashboard §4 | E9: Log before you finish for the day
A10: Sent a connection request / message / follow-up | B10: LinkedIn Outreach — tick the columns on that lead's row | C10: DAILY ENTRY (count for the day) | D10: Funnel, Employee Score | E10: Paste the exact message text
A11: Got a reply / booked a meeting | B11: LinkedIn Outreach — Outcome column | C11: — | D11: Funnel stages 5–6, Dashboard §3 | E11: Update the same day; add Meeting date
A12: Published a post / article / video | B12: Content Calendar — one row per item | C12: DAILY ENTRY (count) | D12: Dashboard §5, Publishing Plan | E12: Paste the published URL
A13: Answered on Quora / Reddit / a community | B13: Community & PR — one row per answer | C13: DAILY ENTRY (count) | D13: Dashboard §5 | E13: Paste the thread URL
A14: Contacted a partner / university / podcast | B14: Partnership Pipeline — one row per organisation | C14: Community & PR for individual touches | D14: Partnership Pipeline stage, Dashboard §8 | E14: Score ICP fit honestly
A15: Ran an A/B test | B15: Experiments — one row per test | C15: — | D15: Playbook improvements | E15: Conclude before starting the next
A16: Built a tracked link | B16: UTM Builder | C16: — | D16: Google Analytics campaigns | E16: Copy only the generated link
A17: Set up / improved an account | B17: Platform Setup — status + profile % | C17: DAILY ENTRY ('Account created / profile completed') | D17: Accounts Register, Dashboard §2 | E17: Record the vault entry name
A18: Reviewed analytics | B18: DAILY ENTRY (Analytics review) | C18: SEO Clusters for search data | D18: Platform Progress | E18: One row per session, primary tool
A19: Sent an email campaign / WhatsApp / Telegram / SMS broadcast | B19: DAILY ENTRY — 'Email campaign sent' or 'WhatsApp / Telegram / SMS sent', How many = messages delivered | C19: — | D19: Weekly Pulse (email / WhatsApp-SMS rows) | E19: Log the same day with the campaign report link
... A24: EVERY row, whatever it is | B24: Set BOTH tag columns: Objective (which campaign — honorary outreach, a certification's sales, authority building…) and For (brand) (who it is for — the institute, PCL-AI / PFL-AI / PML-AI, PCI World or Certuvo) | C24: — | D24: Objective Performance — results per campaign AND per brand | E24: An untagged row lands in a red '(no objective set)' / '(no brand set)' line the manager reviews Monday
A26: YOUR FIRST DAY (the manager ticks these on START HERE §10)
A27: 1) Read START HERE top to bottom — especially the Golden Rules and the sharing rules (§9).
A28: 2) Check your name is on the roster exactly as you will select it in dropdowns.
A29: 3) Get password-vault access from the manager. Open Accounts Register to see which vault entry each platform uses.
A30: 4) Optimise your own LinkedIn profile using LinkedIn Playbook step A. Do not send anything yet.
A31: 5) Read the Message Bank. You may only ever send rows marked Approved — personalised, never pasted blind.
A32: 6) Log your first 5 researched leads in LinkedIn Outreach and show the manager BEFORE sending any request.
A33: 7) After the manager reviews your first 3 sent messages, you are live. Follow the daily targets from START HERE §3.
A35: YOUR EVERY DAY — the 20-minute logging habit
A36: • Morning (5 min): open Dashboard → 'Follow-ups due today' and your red cells. Clear those first — a due follow-up beats a new lead.
A37: • During the day: work in your platforms. Keep LinkedIn Outreach open; a lead takes 30 seconds to log while the profile is in front of you.
A38: • Before you stop (15 min): fill DAILY ENTRY — one row per activity type, with counts, minutes and one evidence link. If it is not logged today, it did not happen.
... A41: HOW YOUR SCORE WORKS (Employee Score tab — quality beats volume)
A42: Lead quality (15) | B42: Are the leads you research genuinely in-profile (8+ years, right roles)?
A43: Acceptance rate (20) | B43: Do your connection requests get accepted? Benchmark: 30%+ is good. Personalisation drives this.
A44: Reply rate (20) | B44: Do your messages get replies? Fluent copying of the Message Bank with real personalisation drives this.
A45: Positive replies (10) | B45: Interested / info requested / meeting booked.
A46: Meetings & applications (20) | B46: The outcomes that matter.
A47: Downstream results (10) | B47: Conversions attributed to your leads.
A48: Compliance (5) | B48: No over-length messages, no rule breaches. Breaches zero this and flag the manager.
A49: No grade appears until you have ~20 connections of history — a blank grade means 'not enough data yet', not 'failing'.
A51: FREQUENTLY ASKED
A52: A cell went red when I typed a name/platform. | B52: Red = that exact text is not on the official list, so it would be invisible to every report. Use the dropdown, or fix the spelling.
A53: I can't type in a cell. | B53: It is protected on purpose — it is a formula or a manager-owned cell. Nothing is broken. Yellow cells are yours.
A54: The lead I found shows DUPLICATE. | B54: Someone already logged them. Ctrl+F the URL, read the earlier row, and do not re-contact — especially if they declined.
A55: Which platform value do I pick for X? | B55: Lists tab, column 'Platform logging rule' — every ambiguous case has a written rule (Shorts → YouTube, newsletter issue → LinkedIn Newsletter, etc.).
A56: I ran out of empty rows. | B56: Tell the manager — they archive a dated copy monthly and clear logged rows. Never delete rows yourself.
A57: I made a typo in a logged row. | B57: Edit the cell to correct it. Never delete rows; disputes are resolved from version history.
A58: Where do I see how the team is doing? | B58: Dashboard (whole team), Team Scorecard (per person), Weekly Review (trend). You never type on those pages.
A59: Someone asked me to promise them a certification. | B59: Never. Read the Golden Rules — no outcome promises, ever. Report the conversation to the manager.
A61: WORKED EXAMPLES — what a good row looks like on each log
A62: These used to sit on the first row of each log as an example to delete. Typing over one instead of deleting it lost the work from every report, so the logs now start empty and the examples live here, where nothing can be typed over them.
A63: DAILY ENTRY | B63: Date: 2026-08-17 00:00:00 · Your name: Employee 1 · Platform: LinkedIn Sales Navigator · What kind of work: Lead researched (Sales Navigator) · What exactly did you do?: Built a list of project controls managers in the UK rail sector · How many: 30 · Minutes spent: 60 · Link / proof: [Sales Nav list link]
A64: DAILY ENTRY | B64: Date: 2026-08-17 00:00:00 · Your name: Employee 1 · Platform: LinkedIn Personal Profile · What kind of work: Connection request sent · What exactly did you do?: Sent connection requests with a personal line from each profile · How many: 20 · Minutes spent: 45 · Link / proof: logged in LinkedIn Outreach tab
A65: DAILY ENTRY | B65: Date: 2026-08-17 00:00:00 · Your name: Employee 1 · Platform: Medium · What kind of work: Post / content published · What exactly did you do?: Published the article on cost control mistakes, canonical set to our site · How many: 1 · Minutes spent: 90 · Link / proof: [article URL]
A66: LinkedIn Outreach | B66: Date: 2026-08-17 00:00:00 · Employee: Employee 1 · Job title: Project Controls Manager · Country: United Kingdom · Lead segment: Project Controls Manager · Sales Nav list: PC Managers - UK · Years exp.: 14 · Personal line used (from their profile): Led cost control on the [X] rail upgrade - mentioned it in her post last week
A67: Content Calendar | B67: Plan date: 2026-08-17 00:00:00 · Employee: Employee 1 · Platform: LinkedIn Company Page · Content type: Carousel · Topic / title: 5 cost-control mistakes that kill a project schedule · Objective: Authority & Entity Building · Hook / first line: Most schedule slips are visible in the cost report 6 weeks before anyone admits it. · Call to action: Read the full PCI guide - link in comments
A68: Community & PR | B68: Date: 2026-08-17 00:00:00 · Employee: Employee 1 · Platform / channel: Quora · Organisation or community: Quora - Project Management topic · Type: Community / Group · Contact name: - · Contact role: - · URL of thread / profile: [question URL]
A69: Partnership Pipeline | B69: Date opened: 2026-08-17 00:00:00 · Owner: Employee 1 · Type: Employer / Enterprise · Country: United Kingdom · Contact name: A. Sample · Contact role: Head of PMO · LinkedIn / URL: [LinkedIn URL] · Why them (the fit): 300+ project controls staff, no internal credentialing route, actively hiring planners
A70: Job Postings | B70: Date posted: 2026-08-17 00:00:00 · Posted by: Employee 1 · Position title: Regional Marketing Executive (Gulf) · Position type: Marketing · For (brand): PCI AI - Institute (umbrella) · Platform: LinkedIn Company Page · Country / region: UAE + Gulf · Job post URL: [post URL]
A71: Link Building | B71: Date: 2026-08-17 00:00:00 · Employee: Employee 1 · Tactic: Unlinked mention reclaimed · Target site / domain: pmworldjournal.com · Their page URL: [article that mentions PCI] · Our target URL: https://projectcontrolsinstitute.org/ · Contact / route: editor email · Anchor text (planned): Project Controls Institute
A72: Content Scheduler | B72: Platform: LinkedIn Company Page · For (brand): PCI AI - Institute (umbrella) · Objective: Content & SEO Growth · Cadence: 3x Weekly · Posts per cycle: 1 · Content format: Single image · Scheduling tool: Native scheduler · Start date: 2026-08-17 00:00:00
A73: Experiments | B73: Start date: 2026-08-17 00:00:00 · Owner: Employee 1 · Channel / platform: LinkedIn Personal Profile · Variant A: Generic note: role and company mentioned · Variant B: Specific note: their project type mentioned · Metric being judged: Acceptance rate · Sample A: 100 · Result A: 24
A74: UTM Builder | B74: Landing page URL: https://projectcontrolsinstitute.org/honorary-certification · Source: linkedin · Medium: social · Campaign: honorary-aug26 · Content: connection-message · Date: 2026-08-17 00:00:00

Sheet GROWTH PLAYBOOK
A1: GROWTH PLAYBOOK — the techniques, in working detail
A2: ◀ MAP | B2: Each technique: why it works, the exact steps, cadence, the number that proves it is working, and the mistake that gets accounts banned or rankings burned. Every step logs into the sheet named in the last column.
A4: Technique | B4: Why it works | C4: Exactly how — numbered steps | D4: Cadence | E4: KPI that proves it | F4: Logs into
A5: 1. SEO content clusters (pillar + spokes) | B5: Google ranks depth, not scattered posts. One pillar page per money topic ('project controls certification', 'earned value management') with 6-10 supporting articles all linking back to it makes PCI the topical authority. | C5: 1) Pick the cluster in SEO Clusters — pillar phrase + 8 supporting questions people search. 2) Write the pillar (2,500+ words, answers the whole topic, cites standards). 3) One supporting article per week answering ONE question, linking UP to the pillar with exact-phrase anchor. 4) Interlink siblings. 5) Add FAQ blocks with the literal question as a heading. 6) Track impressions/clicks/position monthly from Search Console into SEO Clusters. | D5: 1 pillar / month; 1-2 spokes / week | E5: Search Console: position for the pillar phrase; clicks/month | F5: SEO Clusters
A6: 2. E-E-A-T authority signals | B6: Google's quality systems reward demonstrated Experience, Expertise, Authority, Trust — critical for an education brand ranked among established bodies. | C6: 1) Every article carries a named author with credentials and a bio page. 2) Author bios link to their LinkedIn and publications. 3) Cite primary sources (standards, published data) — never invent numbers. 4) Keep an About/Governance page path from every article. 5) Get authors quoted elsewhere (see technique 4) and link those mentions back to the bio. | D6: Continuous — a rule, not a task | E6: Branded-search volume; author-name searches | F6: Content Calendar
A7: 3. Answer-engine optimisation (AEO) — being the cited answer | B7: AI answers (Google AI Overviews, ChatGPT, Perplexity) are a fast-growing discovery surface, and the traffic they send arrives with the question already framed — treat published conversion multiples as vendor marketing until you measure your own in GA4. The pipelines differ: ChatGPT retrieves from Bing's index, Perplexity crawls itself, AI Overviews uses Google — each needs its own work. The pattern that repeats across cited pages is a 2-3 sentence direct answer in the opening. | C7: 1) robots.txt: explicitly allow GPTBot, OAI-SearchBot, PerplexityBot, ClaudeBot, Google-Extended (check the CDN/WAF is not blocking them). 2) Verify the domain in Bing Webmaster Tools + enable IndexNow — that is the ChatGPT pipeline. 3) Restructure the top 30 pages: question-form H2s with a 2-3 sentence answer capsule directly under each, then depth; add FAQ blocks and comparison tables. 4) Put one cited statistic in every major section — and publish original data so PCI becomes the source others cite. 5) Off-page is most of the battle: get PCI named in the pages the engines already cite (certification listicles, Reddit/Quora threads, trade-press roundups) — pitch inclusion into existing ranking articles before writing new ones. 6) Keep entity facts identical across the site, Wikidata, Crunchbase, LinkedIn, GBP. 7) Monthly: run the 20-prompt audit; log which domains get cited; target them. | D7: 5 pages restructured / month + monthly audit | E7: Brand mention rate across 20 prompts; AI-referral sessions in GA4 | F7: SEO Clusters / Experiments
A8: 4. Digital PR & backlink earning (post-HARO stack) | B8: Links and mentions from real publications remain the strongest ranking and AI-citation input. HARO is dead (shut Dec 2024); the working 2026 stack is journalist-request services + contributed articles + podcast guesting + one quarterly data study. | C8: 1) Build a one-page expert kit per spokesperson (bio, credentials, 5 angles, headshot). 2) Subscribe: Source of Sources + Help a B2B Writer (free), Qwoted / Featured, ResponseSource for UK press; monitor #journorequest on X and Bluesky twice daily. 3) Answer only on-expertise queries within 2 hours: 80-120 words, data-led, quote-ready. 4) Publish one original data study per quarter (salary survey, AI-adoption survey) — the single best link magnet — and pitch it to the trade press on the PR & Target Directory tab. 5) One contributed article and one podcast pitch per month from the same tab. 6) Every placement goes on an 'As featured in' page (E-E-A-T + AI-citation asset). 7) Never pay for links; never mass-pitch off-topic — accounts get deprioritised. | D8: 3-5 responses / week; monthly article + podcast; quarterly study | E8: Linked placements / month; referring domains; AI-answer brand mentions | F8: Community & PR
A9: 5. LinkedIn organic engine (2026 mechanics) | B9: The decision-makers are here, but the algorithm has changed: personal profiles reach several times what company pages do on identical content (published estimates cluster around 5-10x; measure your own), document/carousel posts lead engagement, dwell time (15+ seconds of reading) is the top ranking signal, and external links in the post body still suppress reach. | C9: 1) Put 70% of effort behind 2-3 named staff profiles; the company page is the archive/credibility layer that reshares people. 2) Weekly per profile: one document/carousel (exam tips, salary data), one short native video (under 90s), one text story — written for dwell: strong first two lines, line-broken body, a chart screenshot. 3) Comment meaningfully on 15 target-audience posts daily BEFORE posting. 4) Links go in the first comment or profile — never the post body. 5) Reply to every comment within 60 minutes of posting (first-hour velocity gates reach). 6) Reshares from colleagues staggered, not simultaneous — identical simultaneous reposts suppress all copies. 7) Outreach only through the approved message system; never automate — engagement pods and AI-comment tools are detected and reach-penalised. | D9: Daily comments; 3 posts / week / profile; fortnightly newsletter | E9: Member reach per post; acceptance %; reply %; newsletter subscribers | F9: Content Calendar + LinkedIn Outreach
A10: 6. Community-led growth (answer first, never spam) | B10: Quora, Reddit, Planning Planet, PMI Community, Stack Exchange rank in Google for years and reach practitioners directly. One good answer works forever; one spammy answer burns the account and the brand. | C10: 1) Pick 2 communities per person, build real profiles (disclose PCI affiliation). 2) Answer the question COMPLETELY first; PCI gets one contextual mention only where genuinely relevant — max 1 link per 5 answers on Reddit, none on Stack Exchange. 3) Target questions that already rank in Google (search the question first). 4) 3-5 quality answers/week per person beats 20 thin ones. 5) Log every answer in Community & PR with the thread URL. 6) Read each community's self-promotion rules before the first post — bans are permanent. | D10: 3-5 answers / person / week | E10: Answer views, upvotes, referral sessions in GA4 | F10: Community & PR
A11: 7. Syndication waterfall (one asset, many surfaces — canonicals verified) | B11: Every original article can reach several extra audiences without duplicate-content damage — IF each platform's canonical reality is respected. Verified 2026: Medium, DEV and Hashnode support canonicals; Substack and LinkedIn Articles do NOT. | C11: 1) Publish the original on the website first; allow 2-10 days and verify it is indexed before syndicating. 2) Medium: use the Import tool — it sets the canonical to the original automatically. 3) LinkedIn Articles: 300-word excerpt + 'read the full analysis' link — never the full piece (no canonical support). 4) Substack: native newsletter framing + link only — never paste the full post (no canonical; the copy can outrank your site). 5) Slides to SlideShare; a 60-second summary to Shorts; an audio take to the podcast. 6) Each copy = its own Content Calendar row, status Repurposed, linking the original; plan the waterfall in the 'Repurpose to' column at writing time. 7) If a syndicated copy outranks the original, strengthen internal links to the original or request removal. | D11: Top 2 posts / month | E11: Referral sessions per surface; original URL keeps the ranking | F11: Content Calendar / Publishing Plan
A12: 8. Webinar → content engine | B12: One monthly webinar produces the month's best content and the warmest leads: registrants are self-qualified by topic. | C12: 1) Monthly topic from the best-performing cluster. 2) Deliver on Zoom Webinars; list on Eventbrite/Luma/Meetup + LinkedIn Event. 3) UTM every registration link. 4) Replay to YouTube; cut 3-5 Shorts; write the recap article (technique 7 waterfall). 5) Registrants enter the ESP nurture sequence; attendees get the certification next-step email within 24h. 6) Every speaker invitation logged in Partnership Pipeline. | D12: Monthly | E12: Registrants, attendance %, replay views, applications started | F12: Partnership Pipeline + Content Calendar
A13: 9. Email nurture (the owned list) | B13: The only audience no algorithm can take away, and the highest-converting surface for a considered purchase like certification. | C13: 1) One lead magnet per certification (syllabus PDF, formula sheet, salary guide) behind a form. 2) Welcome sequence: 5 emails over 2 weeks — value, value, story, proof, ask. 3) Fortnightly newsletter after that: one insight, one resource, one next step. 4) Every send is one Email Marketing (ESP) row in DAILY ENTRY. 5) Consent only — record lawful basis at capture; unsubscribe honoured same day. | D13: Fortnightly sends; sequences always-on | E13: List growth/month, open %, click %, applications from email | F13: DAILY ENTRY + UTM Builder
A14: 10. Digital badge loop (Credly) | B14: Every certified professional who shares a verifiable badge markets to their whole network with third-party credibility — near-zero cost, compounds with every cohort. | C14: 1) Issue every credential as a Credly badge automatically on conferral. 2) Prompt shares to LinkedIn in the conferral email (one click). 3) Repost great badge-shares from the company page (with permission). 4) Track share-rate; a shared badge is a logged Engagement. | D14: Automatic per conferral; monthly share-rate review | E14: Badge share rate; referral traffic from credly.com | F14: Platform Setup + DAILY ENTRY
A15: 11. Directories, citations & reviews | B15: Consistent entity citations (name-address-site) across credible directories underpin the knowledge panel and AI-engine trust; course directories add referral leads directly. | C15: 1) Complete Google Business Profile + Bing Places with identical details. 2) List courses on findcourses/coursetakers-type aggregators (UK/US/Gulf). 3) CPD directories where factually eligible — never claim accreditation that does not exist. 4) Invite genuinely satisfied certified professionals to Trustpilot — never incentivised, never gated. 5) Keep Crunchbase/Wikidata facts current. | D15: One-time setup + quarterly verification | E15: Citation consistency; referral sessions from directories | F15: Platform Setup + QA & Compliance
... A27: 23. Off-page SEO — the link engine (guardrailed) | B27: Referring domains are the strongest off-page ranking signal a new domain can earn, and for AI engines every credible link is one more corroborating source. This technique turns the linkable assets (research report, tools, guides) into a systematic weekly link programme instead of hoping. | C27: 1) Quarterly competitor backlink gap: list who links to AACE, Project Control Academy, EVMi and projectcontrolsinstitute.com but not to us (free: their public mention SERPs + Ahrefs/Semrush free webmaster tiers on our own domain) — every gap is a prospect row in Link Building. 2) Monthly unlinked-mention reclaim: search the brand names in quotes; every mention without a link gets a polite ask — the easiest links that exist. 3) Resource-page + broken-link outreach: university careers pages, PM resource lists, association link pages — pitch the research report, calculators and guides as the replacement or addition. 4) Every guest post, journalist quote, podcast appearance and directory listing from the other techniques gets its own Link Building row — one system of record for off-page. 5) Anchors natural: brand or bare URL for most links; exact-match keywords sparingly. 6) NEVER: paid links, PBNs, bulk reciprocal swaps, comment/forum spam, fiverr link gigs — that is the link spam Google's SpamBrain demotes, and it burns the domain permanently. 7) Weekly rhythm: 10 new prospects logged, 5 outreach emails, follow-ups cleared; log the day's work in DAILY ENTRY as 'Link building / outreach (off-page)'. | D27: Weekly: 10 prospects, 5 outreach; monthly mention-reclaim; quarterly gap analysis | E27: Referring domains trend (Search Console links report + 'Earned - live' rows) | F27: Link Building

Sheet PLATFORM GUIDE
A1: PLATFORM GUIDE — how to use every platform, step by step
A2: ◀ MAP | B2: One row per platform, the whole estate. Account setup lives on Platform Setup (column E); this sheet is the WEEKLY PLAY once the account exists — what to do, how often, and the number that proves it is working. Identity columns update from Platform Setup automatically. Gold rows are the top-10 value platforms: if time is short, work this sheet top rank first.
A3: Platform | B3: Area | C3: Priority | D3: Value rank | E3: Strongest in (countries) | F3: What it's for (logging rule) | G3: How to use it — step by step | H3: KPI that proves it | I3: Time / week
A4: ='Platform Setup'!$B$4 -> LinkedIn Company Page | B4: ='Platform Setup'!$C$4 -> LinkedIn | C4: ='Platform Setup'!$D$4 -> Critical | D4: ='Platform Setup'!$P$4 -> 1 | E4: ='Platform Setup'!$Q$4 -> Global — the professional default | F4: One row per PAGE post. A reshare from a personal profile is logged on LinkedIn Personal Profile, not here. | G4: 1) 3 posts/week from Content Calendar (carousel, credential story, poll). 2) Reply to every comment within 60 minutes of posting (first-hour velocity gates reach). 3) Reshare each post from personal profiles next morning. 4) Log each post in Content Calendar with URL. | H4: Follower growth + engagement rate per post | I4: 3 h
A5: ='Platform Setup'!$B$5 -> LinkedIn Personal Profile | B5: ='Platform Setup'!$C$5 -> LinkedIn | C5: ='Platform Setup'!$D$5 -> Critical | D5: ='Platform Setup'!$P$5 -> 2 | E5: ='Platform Setup'!$Q$5 -> Global — the professional default | F5: All outreach (connect / message / follow-up) logs here. There is no plain 'LinkedIn'. | G5: 1) Work the daily targets: research leads, send personalised connects, message accepted ones (Message Bank approved text only). A FREE LinkedIn account allows only a handful of personalised connection notes per month — check the current cap on the account before planning the week; Premium/Sales Navigator seats are what make the note-led targets reachable. 2) Work the daily engagement target from START HERE §3 (15 likes + comments on other people's posts), of which at least 5 are substantive comments on prospect posts. 3) Log every touch in LinkedIn Outreach same day. | H5: Acceptance % and reply % (Dashboard §3) | I5: 5 h/day team-wide
A6: ='Platform Setup'!$B$6 -> LinkedIn Sales Navigator | B6: ='Platform Setup'!$C$6 -> LinkedIn | C6: ='Platform Setup'!$D$6 -> Critical | D6: ='Platform Setup'!$P$6 -> 3 | E6: ='Platform Setup'!$Q$6 -> Global — the professional default | F6: Lead research only. | G6: 1) Build one saved search per segment (Lead Segment list). 2) Pull 30 qualified leads/day per person into LinkedIn Outreach with the why-them note. 3) Refresh saved-search alerts each Monday. | H6: Qualified leads logged/day vs target | I6: 1 h/day
A7: ='Platform Setup'!$B$7 -> LinkedIn Articles | B7: ='Platform Setup'!$C$7 -> LinkedIn | C7: ='Platform Setup'!$D$7 -> Critical | D7: ='Platform Setup'!$P$7 -> 4 | E7: ='Platform Setup'!$Q$7 -> Global | F7: Only items made in the Write-article editor. Newsletter issues go to LinkedIn Newsletter. | G7: 1) One article/month per named leader (repurpose a Website/Blog original, canonical to site). 2) 1,200+ words, credential CTA at the end. 3) Log in Content Calendar as Repurposed. | H7: Article views + profile visits | I7: 2 h/month
A8: ='Platform Setup'!$B$8 -> LinkedIn Newsletter | B8: ='Platform Setup'!$C$8 -> LinkedIn | C8: ='Platform Setup'!$D$8 -> High | D8: ='Platform Setup'!$P$8 -> 19 | E8: ='Platform Setup'!$Q$8 -> Global | F8: Newsletter issues win over LinkedIn Articles. | G8: 1) One issue every fortnight from the Company Page. 2) Subject = a question practitioners ask (steal from Keyword Plan Easy queries). 3) End every issue with one credential CTA. | H8: Subscriber growth per issue | I8: 2 h/fortnight
A9: ='Platform Setup'!$B$9 -> LinkedIn Groups | B9: ='Platform Setup'!$C$9 -> LinkedIn | C9: ='Platform Setup'!$D$9 -> High | D9: ='Platform Setup'!$P$9 -> 20 | E9: ='Platform Setup'!$Q$9 -> Global | F9: One row per group discussion started or answered — not per like. | G9: 1) 3 useful answers/week in the 10 joined groups — answer, never pitch. 2) Note engaged members as leads in LinkedIn Outreach. 3) Log in Community & PR. | H9: Answers logged + leads sourced from groups | I9: 1.5 h
A10: ='Platform Setup'!$B$10 -> LinkedIn Live | B10: ='Platform Setup'!$C$10 -> LinkedIn | C10: ='Platform Setup'!$D$10 -> High | D10: ='Platform Setup'!$P$10 -> 21 | E10: ='Platform Setup'!$Q$10 -> Global | F10: Native live video; repurpose to YouTube after. | G10: 1) One live/month: expert interview or exam-prep clinic, promoted 10 days ahead. 2) Multistream via StreamYard to YouTube. 3) Clip 3 shorts from the recording within 48h. | H10: Live viewers + replay views | I10: 4 h/month
A11: ='Platform Setup'!$B$11 -> YouTube | B11: ='Platform Setup'!$C$11 -> Social Media | C11: ='Platform Setup'!$D$11 -> Critical | D11: ='Platform Setup'!$P$11 -> 5 | E11: ='Platform Setup'!$Q$11 -> Global | F11: Shorts are YouTube + Content Type = Short Video. Structure exam-prep playlists as YouTube Courses for the EDU shelf. Vimeo retired. | G11: 1) One long-form/week (webinar cut, expert interview, how-to) + 3 Shorts clipped from it. 2) Titles from Keyword Plan questions; chapters + description links with UTMs. 3) Playlists per certification; exam-prep playlist as a YouTube Course. | H11: Watch time + subscribers; clicks to site (UTM) | I11: 4 h
A12: ='Platform Setup'!$B$12 -> Facebook Page | B12: ='Platform Setup'!$C$12 -> Social Media | C12: ='Platform Setup'!$D$12 -> High | D12: ='Platform Setup'!$P$12 -> 22 | E12: ='Platform Setup'!$Q$12 -> India, SE Asia, MENA — weak for UK/US professionals | F12: One row per page post. Boosting a post is paid media, logged separately. | G12: 1) 3 posts/week mirrored from LinkedIn (reformat, don't cross-post links only). 2) Boost nothing organically weak. 3) Reply to comments/DMs daily — India/MENA audience is active here. | H12: Reach + profile actions | I12: 1 h
A13: ='Platform Setup'!$B$13 -> Instagram | B13: ='Platform Setup'!$C$13 -> Social Media | C13: ='Platform Setup'!$D$13 -> High | D13: ='Platform Setup'!$P$13 -> 23 | E13: ='Platform Setup'!$Q$13 -> Gulf-strong global (KSA 77% penetration) | F13: One row per feed post or Reel. A day's Stories are one row, not one per frame. | G13: 1) 3 posts/week: carousel tips, credential stories, reels from YouTube Shorts. 2) Stories on exam dates/webinars. 3) Bio link via UTM to the current campaign page. Gulf audience is here — use Arabic captions where relevant. | H13: Reach + link taps | I13: 1.5 h
A14: ='Platform Setup'!$B$14 -> X (Twitter) | B14: ='Platform Setup'!$C$14 -> Social Media | C14: ='Platform Setup'!$D$14 -> Medium | D14: ='Platform Setup'!$P$14 -> 48 | E14: ='Platform Setup'!$Q$14 -> US, Japan, KSA (top Arab market) | F14: One row per post or thread — a thread is ONE row, not one per tweet. | G14: 1) One insight post/day + replies in industry conversations. 2) Thread each new article into 5-7 tweets ending with the link. 3) Watch #journorequest daily (technique 4). | H14: Impressions + profile clicks | I14: 1 h
A15: ='Platform Setup'!$B$15 -> Threads | B15: ='Platform Setup'!$C$15 -> Social Media | C15: ='Platform Setup'!$D$15 -> Medium | D15: ='Platform Setup'!$P$15 -> 49 | E15: ='Platform Setup'!$Q$15 -> India, Brazil, US | F15: One row per post. Replies to other people are engagement, logged as 'Engagement (commented on someone else)'. | G15: 1) Mirror the X cadence (1 post/day) — India + US audience. 2) Native text, no link-dumping; link in reply. 3) Engage 5 PM-adjacent threads daily. | H15: Followers + engagement | I15: 30 min
A16: ='Platform Setup'!$B$16 -> TikTok | B16: ='Platform Setup'!$C$16 -> Social Media | C16: ='Platform Setup'!$D$16 -> Medium | D16: ='Platform Setup'!$P$16 -> 50 | E16: ='Platform Setup'!$Q$16 -> KSA + Gulf strongest; global | F16: One row per video published. | G16: 1) 3 educational shorts/week (reuse YouTube Shorts, native captions). 2) Hook in the first 2 seconds: a mistake, a number, a question. 3) KSA/Gulf hashtags — this is a Gulf reach channel. | H16: Views + follows from KSA/Gulf | I16: 1.5 h
A17: ='Platform Setup'!$B$17 -> Pinterest | B17: ='Platform Setup'!$C$17 -> Social Media | C17: ='Platform Setup'!$D$17 -> Low | D17: ='Platform Setup'!$P$17 -> 96 | E17: ='Platform Setup'!$Q$17 -> Global | F17: One row per batch session, not per Pin — record how many Pins in 'How many'. | G17: 1) Pin every infographic/carousel to topic boards monthly (Idea Pins were retired in 2023 — use standard image or video Pins). 2) One checklist Pin per published article. 3) UTM every destination link. | H17: Outbound clicks | I17: 30 min/month
A18: ='Platform Setup'!$B$18 -> Bluesky | B18: ='Platform Setup'!$C$18 -> Social Media | C18: ='Platform Setup'!$D$18 -> Low | D18: ='Platform Setup'!$P$18 -> 97 | E18: ='Platform Setup'!$Q$18 -> US + UK niche | F18: Watching brief; thin project-controls density today. | G18: 1) Watching brief: mirror 2 posts/week. 2) Revisit quarterly — move up only if PM community density appears. | H18: Follower trend (quarterly review) | I18: 15 min
A19: ='Platform Setup'!$B$19 -> Website / Blog | B19: ='Platform Setup'!$C$19 -> Publishing | C19: ='Platform Setup'!$D$19 -> Critical | D19: ='Platform Setup'!$P$19 -> 6 | E19: ='Platform Setup'!$Q$19 -> Global | F19: Originals publish here. Each syndicated copy = own row, Content Status Repurposed. | G19: 1) Publish per Keyword Plan: one spoke/week, Easy difficulty first, mapped in SEO Clusters. 2) Every post: named author, sources, FAQ block, credential CTA, internal links to pillar. 3) Originals here FIRST; syndicate once indexed (2-10 days) with canonical. | H19: Search Console clicks + positions on target keywords | I19: 4 h
A20: ='Platform Setup'!$B$20 -> Medium | B20: ='Platform Setup'!$C$20 -> Publishing | C20: ='Platform Setup'!$D$20 -> High | D20: ='Platform Setup'!$P$20 -> 24 | E20: ='Platform Setup'!$Q$20 -> Global | F20: Syndication surface — set the canonical link. | G20: 1) Republish site originals once indexed (2-10 days) via the Import tool — canonical set automatically. 2) Submit to 1-2 relevant publications. 3) One native answer-style piece/month targeting an Easy question keyword. | H20: Referral visits + follows | I20: 1 h
A21: ='Platform Setup'!$B$21 -> Substack | B21: ='Platform Setup'!$C$21 -> Publishing | C21: ='Platform Setup'!$D$21 -> Medium | D21: ='Platform Setup'!$P$21 -> 51 | E21: ='Platform Setup'!$Q$21 -> Global | F21: Only issues natively published on Substack. | G21: 1) Only if the newsletter lives natively here — otherwise skip (ESP owns email). 2) If used: fortnightly issue, cross-recommend via beehiiv-style recommendations. | H21: Subscriber growth | I21: 2 h/fortnight
A22: ='Platform Setup'!$B$22 -> SlideShare | B22: ='Platform Setup'!$C$22 -> Publishing | C22: ='Platform Setup'!$D$22 -> Medium | D22: ='Platform Setup'!$P$22 -> 52 | E22: ='Platform Setup'!$Q$22 -> Global | F22: One row per deck uploaded. | G22: 1) Upload each deck/one-pager monthly with keyword-rich title + description. 2) Link back to the source page. 3) No bulk dumping. | H22: Views + clickthroughs | I22: 30 min/month
A23: ='Platform Setup'!$B$23 -> WordPress.com | B23: ='Platform Setup'!$C$23 -> Publishing | C23: ='Platform Setup'!$D$23 -> Medium | D23: ='Platform Setup'!$P$23 -> 53 | E23: ='Platform Setup'!$Q$23 -> Global | F23: One row per article published or syndicated. | G23: 1) Satellite blog: one repurposed article/month with canonical. 2) Never let it outrank the main site — always canonical + link home. | H23: Referral visits | I23: 30 min/month
A24: ='Platform Setup'!$B$24 -> Blogger | B24: ='Platform Setup'!$C$24 -> Publishing | C24: ='Platform Setup'!$D$24 -> Low | D24: ='Platform Setup'!$P$24 -> 98 | E24: ='Platform Setup'!$Q$24 -> Global | F24: One row per article published or syndicated. | G24: 1) Same satellite rules as WordPress.com — one repurpose/month, canonical set, link home. | H24: Referral visits | I24: 20 min/month
A25: ='Platform Setup'!$B$25 -> Tumblr | B25: ='Platform Setup'!$C$25 -> Publishing | C25: ='Platform Setup'!$D$25 -> Low | D25: ='Platform Setup'!$P$25 -> 99 | E25: ='Platform Setup'!$Q$25 -> Global | F25: One row per post published. | G25: 1) Low priority: reblog visual content monthly. 2) Tag by topic; skip if time-pressed. | H25: Referral visits | I25: 15 min/month
A26: ='Platform Setup'!$B$26 -> Vocal Media | B26: ='Platform Setup'!$C$26 -> Publishing | C26: ='Platform Setup'!$D$26 -> Low | D26: ='Platform Setup'!$P$26 -> 100 | E26: ='Platform Setup'!$Q$26 -> Global | F26: One row per story published. | G26: 1) One career-story piece/quarter (human angle, credential mention). 2) Link to author page. | H26: Reads + referrals | I26: 1 h/quarter
A27: ='Platform Setup'!$B$27 -> DEV Community | B27: ='Platform Setup'!$C$27 -> Publishing | C27: ='Platform Setup'!$D$27 -> Low | D27: ='Platform Setup'!$P$27 -> 101 | E27: ='Platform Setup'!$Q$27 -> Global | F27: One row per article. Comments on other people's posts are engagement. | G27: 1) Only for Certuvo engineering content (if tooling ships). 2) One technical post/quarter max. | H27: Followers + referrals | I27: 1 h/quarter
A28: ='Platform Setup'!$B$28 -> Hashnode | B28: ='Platform Setup'!$C$28 -> Publishing | C28: ='Platform Setup'!$D$28 -> Low | D28: ='Platform Setup'!$P$28 -> 102 | E28: ='Platform Setup'!$Q$28 -> Global | F28: One row per article published. | G28: 1) Mirror of DEV Community play — Certuvo technical content only, quarterly. | H28: Referrals | I28: 1 h/quarter
A29: ='Platform Setup'!$B$29 -> Quora | B29: ='Platform Setup'!$C$29 -> Community | C29: ='Platform Setup'!$D$29 -> High | D29: ='Platform Setup'!$P$29 -> 25 | E29: ='Platform Setup'!$Q$29 -> US + India | F29: One Quora value. Space vs answer is the Activity type, not the platform. | G29: 1) Answer 3 high-traffic questions/week from saved topic feeds (project controls, planning, EVM). 2) Genuine answer first, one relevant link max. 3) Log answers in Community & PR with URL. | H29: Answer views + upvotes; referral visits | I29: 1.5 h
A30: ='Platform Setup'!$B$30 -> Reddit | B30: ='Platform Setup'!$C$30 -> Community | C30: ='Platform Setup'!$D$30 -> High | D30: ='Platform Setup'!$P$30 -> 26 | E30: ='Platform Setup'!$Q$30 -> US, UK, anglosphere | F30: One row per thread started or substantive answer given — never per upvote or one-line comment. | G30: 1) Contribute helpfully in the subreddits named on Platform Setup — r/projectmanagement, r/construction, r/civilengineering, r/PMP, r/artificial — value first, weeks before any link. 2) Never paste identical answers. 3) AMA once credibility exists. Reddit is the #1 AI-cited domain — presence here feeds AI answers. | H30: Karma trend + non-penalised mentions | I30: 1.5 h
A31: ='Platform Setup'!$B$31 -> Planning Planet | B31: ='Platform Setup'!$C$31 -> Community | C31: ='Platform Setup'!$D$31 -> High | D31: ='Platform Setup'!$P$31 -> 27 | E31: ='Platform Setup'!$Q$31 -> Global (UK-run; heavy Gulf / oil & gas) | F31: The project controls forum (incl. Guild of Project Controls). Exactly our audience. | G31: 1) 3 forum answers/week — this is EXACTLY our audience. 2) Build named-expert reputation; signature link once established. 3) Note active senior practitioners as honorary-outreach candidates. | H31: Answers + honorary leads sourced | I31: 1.5 h
A32: ='Platform Setup'!$B$32 -> PMI Community (ProjectManagement.com) | B32: ='Platform Setup'!$C$32 -> Community | C32: ='Platform Setup'!$D$32 -> High | D32: ='Platform Setup'!$P$32 -> 28 | E32: ='Platform Setup'!$Q$32 -> Global | F32: Largest adjacent professional audience. | G32: 1) 2 discussion contributions/week. 2) Respect house rules — no direct promotion; expertise only. 3) Watch for content-contribution openings (they take articles). | H32: Contributions + profile views | I32: 1 h
A33: ='Platform Setup'!$B$33 -> Facebook Groups | B33: ='Platform Setup'!$C$33 -> Community | C33: ='Platform Setup'!$D$33 -> Medium | D33: ='Platform Setup'!$P$33 -> 54 | E33: ='Platform Setup'!$Q$33 -> India, SE Asia, MENA — weak for UK/US professionals | F33: One row per discussion started or substantive answer given. | G33: 1) 3 useful answers/week across the 10 joined groups (Gulf/India planner groups). 2) Value first; link only when asked or clearly helpful. 3) Log in Community & PR. | H33: Answers + leads sourced | I33: 1 h
A34: ='Platform Setup'!$B$34 -> Discord | B34: ='Platform Setup'!$C$34 -> Community | C34: ='Platform Setup'!$D$34 -> Medium | D34: ='Platform Setup'!$P$34 -> 55 | E34: ='Platform Setup'!$Q$34 -> Global | F34: One row per session of helping, not per message. Record minutes honestly. | G34: 1) Be present in 2-3 PM/engineering servers; answer when pinged-relevant. 2) No drive-by promo — servers ban fast. | H34: Helpful answers logged | I34: 45 min
A35: ='Platform Setup'!$B$35 -> Slack Communities | B35: ='Platform Setup'!$C$35 -> Community | C35: ='Platform Setup'!$D$35 -> Medium | D35: ='Platform Setup'!$P$35 -> 56 | E35: ='Platform Setup'!$Q$35 -> Global | F35: One row per session of helping, not per message. | G35: 1) Same as Discord: 2-3 communities, answer genuinely, DM only when invited. | H35: Answers + DMs earned | I35: 45 min
A36: ='Platform Setup'!$B$36 -> WhatsApp Channel | B36: ='Platform Setup'!$C$36 -> Community | C36: ='Platform Setup'!$D$36 -> Medium | D36: ='Platform Setup'!$P$36 -> 57 | E36: ='Platform Setup'!$Q$36 -> India + Gulf; near-universal outside the US | F36: Broadcast channel. The 1:1 reminder tool is WhatsApp Business API / SMS. | G36: 1) One value broadcast/week max (exam tip, deadline reminder, new resource). 2) Grow the channel via site + email footers. 3) Log sends in DAILY ENTRY ('WhatsApp / Telegram / SMS sent'). | H36: Subscribers + view rate | I36: 30 min
A37: ='Platform Setup'!$B$37 -> AACE Communities | B37: ='Platform Setup'!$C$37 -> Community | C37: ='Platform Setup'!$D$37 -> Medium | D37: ='Platform Setup'!$P$37 -> 58 | E37: ='Platform Setup'!$Q$37 -> Global | F37: Cost-engineering overlap; engage respectfully — peer body. | G37: 1) Respectful peer-body presence: answer technically, never conquest inside their house. 2) Note engaged members for individual outreach OUTSIDE the community. | H37: Reputation (no complaints) + leads noted | I37: 45 min
A38: ='Platform Setup'!$B$38 -> Telegram Channel | B38: ='Platform Setup'!$C$38 -> Community | C38: ='Platform Setup'!$D$38 -> Low | D38: ='Platform Setup'!$P$38 -> 103 | E38: ='Platform Setup'!$Q$38 -> India, Russia, MENA | F38: One row per broadcast sent — put the subscriber count in 'How many'. | G38: 1) Mirror WhatsApp Channel content (India/MENA audience). 2) One value post/week; pin the current campaign. 3) Log sends in DAILY ENTRY. | H38: Subscribers + views per post | I38: 20 min
A39: ='Platform Setup'!$B$39 -> Project Management Stack Exchange | B39: ='Platform Setup'!$C$39 -> Community | C39: ='Platform Setup'!$D$39 -> Low | D39: ='Platform Setup'!$P$39 -> 104 | E39: ='Platform Setup'!$Q$39 -> Global | F39: Small but evergreen Q&A footprint. | G39: 1) One thorough answer/week on scheduling/EVM questions. 2) Evergreen answers rank in Google for years — pick questions matching Keyword Plan terms. | H39: Answer score + cumulative views | I39: 45 min
A40: ='Platform Setup'!$B$40 -> GitHub | B40: ='Platform Setup'!$C$40 -> Community | C40: ='Platform Setup'!$D$40 -> Low | D40: ='Platform Setup'!$P$40 -> 105 | E40: ='Platform Setup'!$Q$40 -> Global | F40: Only if Certuvo open-sources tooling. | G40: 1) Only if Certuvo open-sources tooling: keep README + examples current, answer issues weekly. | H40: Stars + issue response time | I40: 1 h (if active)
A41: ='Platform Setup'!$B$41 -> Credly / Digital Badges | B41: ='Platform Setup'!$C$41 -> Directory/Review | C41: ='Platform Setup'!$D$41 -> High | D41: ='Platform Setup'!$P$41 -> 29 | E41: ='Platform Setup'!$Q$41 -> Global | F41: Badge shares on LinkedIn are organic reach — core channel for a credentialing body. Issue as Open Badges 3.0 (verify the issuer is on the 1EdTech certified list). | G41: 1) Issue a badge with every credential same-day. 2) Prompt every earner to share to LinkedIn (template in Message Bank). 3) Track share rate monthly. | H41: Badge share rate (target 40%+) | I41: 30 min
A42: ='Platform Setup'!$B$42 -> Google Business Profile | B42: ='Platform Setup'!$C$42 -> Directory/Review | C42: ='Platform Setup'!$D$42 -> Medium | D42: ='Platform Setup'!$P$42 -> 59 | E42: ='Platform Setup'!$Q$42 -> Global | F42: One row per post, or one row per review-answering session. | G42: 1) Weekly: one post (update/event). 2) Answer every review + question within 48h. 3) Keep NAP identical to site footer. | H42: Profile actions + review score | I42: 30 min
A43: ='Platform Setup'!$B$43 -> Trustpilot | B43: ='Platform Setup'!$C$43 -> Directory/Review | C43: ='Platform Setup'!$D$43 -> Medium | D43: ='Platform Setup'!$P$43 -> 60 | E43: ='Platform Setup'!$Q$43 -> Global | F43: One row per review-answering session — never one per review invitation sent. | G43: 1) Invite every certified candidate to review (email in the completion flow). 2) Reply to every review within 48h — negatives first. 3) Never gate or incentivise. | H43: Review count + rating trend | I43: 30 min
A44: ='Platform Setup'!$B$44 -> Course Aggregators (findcourses etc.) | B44: ='Platform Setup'!$C$44 -> Directory/Review | C44: ='Platform Setup'!$D$44 -> Medium | D44: ='Platform Setup'!$P$44 -> 61 | E44: ='Platform Setup'!$Q$44 -> UK + global | F44: Course directories send qualified lead-gen traffic. | G44: 1) Keep listings current (dates, prices, UTM links). 2) Compare cost-per-lead across directories quarterly in Channel Costs; cut the losers. | H44: Leads per directory per month | I44: 1 h/month
A45: ='Platform Setup'!$B$45 -> CPD Directory Listings | B45: ='Platform Setup'!$C$45 -> Directory/Review | C45: ='Platform Setup'!$D$45 -> Medium | D45: ='Platform Setup'!$P$45 -> 62 | E45: ='Platform Setup'!$Q$45 -> UK | F45: Legitimacy checkpoints for this exact buyer. | G45: 1) Keep the accreditation listing current. 2) Cite 'CPD-accredited' on every course page + campaign. 3) Renew on time. | H45: Referrals from directory | I45: 30 min/month
A46: ='Platform Setup'!$B$46 -> Bing Places | B46: ='Platform Setup'!$C$46 -> Directory/Review | C46: ='Platform Setup'!$D$46 -> Low | D46: ='Platform Setup'!$P$46 -> 106 | E46: ='Platform Setup'!$Q$46 -> US + UK | F46: Setup and maintenance work only. There is nothing to publish here weekly. | G46: 1) Quarterly: verify listing matches GBP exactly. | H46: Listing live + consistent | I46: 10 min/quarter
A47: ='Platform Setup'!$B$47 -> Crunchbase | B47: ='Platform Setup'!$C$47 -> Directory/Review | C47: ='Platform Setup'!$D$47 -> Low | D47: ='Platform Setup'!$P$47 -> 107 | E47: ='Platform Setup'!$Q$47 -> Global | F47: Profile setup and update work only — one row per update session. | G47: 1) Quarterly: refresh both profiles (funding, headcount, news links). | H47: Profile completeness | I47: 20 min/quarter
A48: ='Platform Setup'!$B$48 -> G2 | B48: ='Platform Setup'!$C$48 -> Directory/Review | C48: ='Platform Setup'!$D$48 -> Low | D48: ='Platform Setup'!$P$48 -> 108 | E48: ='Platform Setup'!$Q$48 -> Global | F48: Certuvo brand only — PCI has no genuine category here. | G48: 1) Certuvo: ask every active user cohort for a review each quarter. 2) Respond to all reviews. 3) Keep the profile's screenshots current. | H48: Review count + category rank | I48: 1 h/month
A49: ='Platform Setup'!$B$49 -> Capterra | B49: ='Platform Setup'!$C$49 -> Directory/Review | C49: ='Platform Setup'!$D$49 -> Low | D49: ='Platform Setup'!$P$49 -> 109 | E49: ='Platform Setup'!$Q$49 -> Global | F49: Certuvo brand only. | G49: 1) Certuvo: mirror the G2 play — quarterly review asks, respond to all. | H49: Reviews + referrals | I49: 30 min/month
A50: ='Platform Setup'!$B$50 -> Clutch | B50: ='Platform Setup'!$C$50 -> Directory/Review | C50: ='Platform Setup'!$D$50 -> Low | D50: ='Platform Setup'!$P$50 -> 110 | E50: ='Platform Setup'!$Q$50 -> Global | F50: Certuvo brand only. | G50: 1) Certuvo: maintain profile; request 2 client reviews/quarter. | H50: Reviews | I50: 30 min/quarter
A51: ='Platform Setup'!$B$51 -> Wikipedia / Wikidata | B51: ='Platform Setup'!$C$51 -> Directory/Review | C51: ='Platform Setup'!$D$51 -> Low | D51: ='Platform Setup'!$P$51 -> 111 | E51: ='Platform Setup'!$Q$51 -> Global | F51: Never self-edit; notability-dependent. | G51: 1) NEVER self-edit articles. 2) Keep the Wikidata item accurate (identifiers, sameAs, ISNI) — that IS allowed. 3) Build notability via press until an independent editor writes the article. | H51: Wikidata item completeness | I51: 30 min/quarter
A52: ='Platform Setup'!$B$52 -> Product Hunt | B52: ='Platform Setup'!$C$52 -> Directory/Review | C52: ='Platform Setup'!$D$52 -> Low | D52: ='Platform Setup'!$P$52 -> 112 | E52: ='Platform Setup'!$Q$52 -> Global | F52: One-off Certuvo launch venue. | G52: 1) One-off Certuvo launch: prepare 3 weeks (teaser page, hunter, launch-day comment plan). 2) Launch Tuesday-Thursday; all-hands replies on the day. | H52: Upvotes + signups on launch day | I52: one-off
A53: ='Platform Setup'!$B$53 -> Zoom Webinars | B53: ='Platform Setup'!$C$53 -> Events | C53: ='Platform Setup'!$D$53 -> Critical | D53: ='Platform Setup'!$P$53 -> 7 | E53: ='Platform Setup'!$Q$53 -> Global | F53: The event lives here; Eventbrite/Luma/Meetup rows are listings only. | G53: 1) One webinar/month: topic from Keyword Plan questions; registration page with UTM. 2) Reminder sequence via ESP + WhatsApp. 3) Recording to YouTube within 48h; leads into LinkedIn Outreach. | H53: Registrations, attendance rate, leads | I53: 4 h/month
A54: ='Platform Setup'!$B$54 -> Eventbrite | B54: ='Platform Setup'!$C$54 -> Events | C54: ='Platform Setup'!$D$54 -> Medium | D54: ='Platform Setup'!$P$54 -> 63 | E54: ='Platform Setup'!$Q$54 -> Global | F54: Listing/distribution row for an event delivered on Zoom Webinars. | G54: 1) List every webinar here for discovery reach. 2) Use Eventbrite's reminder emails. 3) One row per event in Content Calendar. | H54: Registrations sourced from listing | I54: 30 min/event
A55: ='Platform Setup'!$B$55 -> Luma | B55: ='Platform Setup'!$C$55 -> Events | C55: ='Platform Setup'!$D$55 -> Medium | D55: ='Platform Setup'!$P$55 -> 64 | E55: ='Platform Setup'!$Q$55 -> Global | F55: Listing/distribution row. | G55: 1) Mirror the Eventbrite listing play; Luma's calendar-subscribe builds a repeat audience. | H55: Calendar subscribers | I55: 20 min/event
A56: ='Platform Setup'!$B$56 -> Meetup | B56: ='Platform Setup'!$C$56 -> Events | C56: ='Platform Setup'!$D$56 -> Low | D56: ='Platform Setup'!$P$56 -> 113 | E56: ='Platform Setup'!$Q$56 -> Global | F56: Listing/distribution row. | G56: 1) List events only if a recurring local/online group exists; otherwise skip. | H56: RSVPs | I56: 20 min/event
A57: ='Platform Setup'!$B$57 -> StreamYard | B57: ='Platform Setup'!$C$57 -> Events | C57: ='Platform Setup'!$D$57 -> Low | D57: ='Platform Setup'!$P$57 -> 114 | E57: ='Platform Setup'!$Q$57 -> Global | F57: Multistream studio (LinkedIn Live + YouTube at once). | G57: 1) Use for every live: brand the overlay, multistream LinkedIn Live + YouTube simultaneously. 2) Save ISO recordings for clipping. | H57: Concurrent viewers across streams | I57: included in event time
A58: ='Platform Setup'!$B$58 -> Podcast Guesting | B58: ='Platform Setup'!$C$58 -> Podcast | C58: ='Platform Setup'!$D$58 -> High | D58: ='Platform Setup'!$P$58 -> 30 | E58: ='Platform Setup'!$Q$58 -> Global | F58: Guest appearances on others' shows. Own show = Spotify for Creators. | G58: 1) 2 bookings/month via PodMatch + direct pitches (PR & Target Directory list). 2) Prep 3 stories + 1 offer (free resource) per show. 3) Log each appearance in Community & PR with episode URL. | H58: Appearances + referral visits | I58: 3 h/month
A59: ='Platform Setup'!$B$59 -> Spotify for Creators | B59: ='Platform Setup'!$C$59 -> Podcast | C59: ='Platform Setup'!$D$59 -> Medium | D59: ='Platform Setup'!$P$59 -> 65 | E59: ='Platform Setup'!$Q$59 -> Global | F59: Log each episode once, here. Apple = directory admin only. | G59: 1) If/when PCI runs its own show: fortnightly episode, guest-led. 2) Log each episode here once; Apple is directory admin only. | H59: Listens + follows | I59: 4 h/fortnight
A60: ='Platform Setup'!$B$60 -> Apple Podcasts | B60: ='Platform Setup'!$C$60 -> Podcast | C60: ='Platform Setup'!$D$60 -> Low | D60: ='Platform Setup'!$P$60 -> 115 | E60: ='Platform Setup'!$Q$60 -> Global | F60: Directory setup/maintenance work only — never episode rows. | G60: 1) Directory upkeep only: artwork, categories, description quarterly. | H60: Directory listing healthy | I60: 10 min/quarter
A61: ='Platform Setup'!$B$61 -> YouTube Podcasts | B61: ='Platform Setup'!$C$61 -> Podcast | C61: ='Platform Setup'!$D$61 -> Low | D61: ='Platform Setup'!$P$61 -> 116 | E61: ='Platform Setup'!$Q$61 -> Global | F61: Free RSS syndication once the show exists. | G61: 1) Connect the RSS once the show exists; verify episodes appear. | H61: YouTube podcast plays | I61: 10 min/month
A62: ='Platform Setup'!$B$62 -> Partnership / PR Outreach | B62: ='Platform Setup'!$C$62 -> Partnership/PR | C62: ='Platform Setup'!$D$62 -> Critical | D62: ='Platform Setup'!$P$62 -> 8 | E62: ='Platform Setup'!$Q$62 -> Global | F62: All partnership work. Who it targets = Org Type column, never the Platform. | G62: 1) 5 association + 3 university + 5 employer approaches/week (Partnership Pipeline rows). 2) Lead with what THEY get (member discount, guest content, data). 3) Move stages honestly; managers join at Meeting stage. | H62: Meetings booked + agreements signed | I62: 3 h
A63: ='Platform Setup'!$B$63 -> Journalist Requests (Qwoted / Featured) | B63: ='Platform Setup'!$C$63 -> Partnership/PR | C63: ='Platform Setup'!$D$63 -> Medium | D63: ='Platform Setup'!$P$63 -> 66 | E63: ='Platform Setup'!$Q$63 -> Global | F63: Expert-source services; authority backlinks + press mentions. | G63: 1) Check daily; answer only on-expertise requests within 2h. 2) 80-120 words, data-led, quotable. 3) Log placements in Community & PR. | H63: Placements + backlinks earned | I63: 45 min/day scan
A64: ='Platform Setup'!$B$64 -> Press Release Distribution | B64: ='Platform Setup'!$C$64 -> Partnership/PR | C64: ='Platform Setup'!$D$64 -> Medium | D64: ='Platform Setup'!$P$64 -> 67 | E64: ='Platform Setup'!$Q$64 -> Global | F64: Credential-launch news only. Verified free stack (Aug 2026): PRLog (unlimited, fast Google indexing) + openPR (1 per 30 days, Google News). Value = indexed third-party references AI engines read — journalists do not browse free wires; links are nofollow by Google policy. Own newsroom + NewsArticle schema first, wires second. | G64: 1) Real news only: newsroom post first (NewsArticle schema), then PRLog (free), then openPR (1/30 days). 2) Facts, quotes, numbers — no keyword stuffing (links are nofollow). 3) Search the headline after a week; log indexed pickups. | H64: Indexed pickups on non-PCI domains | I64: 1 h/release
A65: ='Platform Setup'!$B$65 -> LinkedIn Ads | B65: ='Platform Setup'!$C$65 -> Paid Media | C65: ='Platform Setup'!$D$65 -> High | D65: ='Platform Setup'!$P$65 -> 31 | E65: ='Platform Setup'!$Q$65 -> Global | F65: Event promotion + retargeting engaged followers. | G65: 1) Only: event promotion + retargeting engaged followers. 2) $20/day test budgets; kill anything above target CPL in 2 weeks. 3) Log spend in Channel Costs weekly. | H65: Cost per lead vs organic benchmark | I65: 1 h
A66: ='Platform Setup'!$B$66 -> Google Ads | B66: ='Platform Setup'!$C$66 -> Paid Media | C66: ='Platform Setup'!$D$66 -> High | D66: ='Platform Setup'!$P$66 -> 32 | E66: ='Platform Setup'!$Q$66 -> Global | F66: High-intent certification queries + brand-term protection. | G66: 1) Brand-term protection + 2-3 high-intent exact keywords from Keyword Plan (certification cost, courses in Dubai). 2) Landing pages must match query intent. 3) Weekly search-term negatives. | H66: CPL + brand impression share | I66: 1.5 h
A67: ='Platform Setup'!$B$67 -> Meta Ads | B67: ='Platform Setup'!$C$67 -> Paid Media | C67: ='Platform Setup'!$D$67 -> Medium | D67: ='Platform Setup'!$P$67 -> 68 | E67: ='Platform Setup'!$Q$67 -> Global | F67: Retargeting + early-career B2C (Certuvo). | G67: 1) Retargeting site visitors + Certuvo B2C tests only. 2) Creative from top organic posts. 3) Weekly spend log in Channel Costs. | H67: CPL / ROAS | I67: 1 h
A68: ='Platform Setup'!$B$68 -> Microsoft Ads | B68: ='Platform Setup'!$C$68 -> Paid Media | C68: ='Platform Setup'!$D$68 -> Low | D68: ='Platform Setup'!$P$68 -> 117 | E68: ='Platform Setup'!$Q$68 -> Global | F68: Cheap B2B desktop-search overflow. | G68: 1) Import the Google Ads brand + high-intent campaigns monthly. 2) Cheap B2B desktop overflow — cap budgets low. | H68: CPL vs Google | I68: 30 min/month
A69: ='Platform Setup'!$B$69 -> Email Marketing (ESP) | B69: ='Platform Setup'!$C$69 -> Email & CRM | C69: ='Platform Setup'!$D$69 -> Critical | D69: ='Platform Setup'!$P$69 -> 9 | E69: ='Platform Setup'!$Q$69 -> Global | F69: The owned list. ESP sends always log here, whatever the newsletter surface. | G69: 1) Newsletter every fortnight; automated nurture sequences always-on (playbook technique 9). 2) Every lead magnet feeds the welcome automation. 3) Log every campaign in DAILY ENTRY ('Email campaign sent', How many = delivered). 4) Prune non-openers quarterly. | H69: Open >35%, click >2.5%, list growth | I69: 3 h
A70: ='Platform Setup'!$B$70 -> WhatsApp Business API / SMS | B70: ='Platform Setup'!$C$70 -> Email & CRM | C70: ='Platform Setup'!$D$70 -> Medium | D70: ='Platform Setup'!$P$70 -> 69 | E70: ='Platform Setup'!$Q$70 -> India + Gulf; near-universal outside the US | F70: Exam, webinar and application reminders (Gulf-heavy audience). | G70: 1) Reminders only: exam dates, webinar starts, application deadlines — consented contacts. 2) Log sends in DAILY ENTRY. 3) Review opt-outs monthly (<1%). | H70: Delivery + opt-out rate | I70: 45 min
A71: ='Platform Setup'!$B$71 -> Affiliate / Referral Programme | B71: ='Platform Setup'!$C$71 -> Email & CRM | C71: ='Platform Setup'!$D$71 -> Medium | D71: ='Platform Setup'!$P$71 -> 70 | E71: ='Platform Setup'!$Q$71 -> Global | F71: Alumni referrals; influencer codes for Certuvo. | G71: 1) Every certified alumnus gets a referral code at completion. 2) Monthly leaderboard email to active referrers. 3) Pay out on schedule, publicly thank top referrers. | H71: Referred applications/month | I71: 1 h/month
A72: ='Platform Setup'!$B$72 -> Bing Webmaster Tools + IndexNow | B72: ='Platform Setup'!$C$72 -> Analytics | C72: ='Platform Setup'!$D$72 -> Critical | D72: ='Platform Setup'!$P$72 -> 10 | E72: ='Platform Setup'!$Q$72 -> Global | F72: ChatGPT retrieves from Bing's index — unindexed on Bing means invisible in ChatGPT answers. Verify domain, submit sitemap, enable IndexNow. | G72: 1) Weekly: check indexation of new pages; submit any missing URL. 2) IndexNow fires on publish — verify monthly. ChatGPT retrieves from Bing's index; unindexed = invisible there. | H72: Pages indexed in Bing vs published | I72: 20 min
A73: ='Platform Setup'!$B$73 -> AI Answer Engines (ChatGPT / Perplexity / AI Overviews) | B73: ='Platform Setup'!$C$73 -> SEO & Syndication | C73: ='Platform Setup'!$D$73 -> Critical | D73: ='Platform Setup'!$P$73 -> 11 | E73: ='Platform Setup'!$Q$73 -> Global | F73: Run the monthly 20-prompt citation audit; log which sources the engines cite and target those exact pages. | G73: 1) Monthly: run the 20-prompt citation audit (who do engines cite for our Keyword Plan queries?). 2) Target the exact cited pages/domains with our content + entity work. 3) Log movement in SEO Clusters notes. | H73: PCI citations in the monthly audit | I73: 2 h/month
A74: ='Platform Setup'!$B$74 -> PM World Journal | B74: ='Platform Setup'!$C$74 -> Publishing | C74: ='Platform Setup'!$D$74 -> Critical | D74: ='Platform Setup'!$P$74 -> 12 | E74: ='Platform Setup'!$Q$74 -> Global | F74: The project-management journal that accepts practitioner papers; pitch a named-author series via pmworldjournal.com/authors. | G74: 1) One named-author practitioner paper per quarter (pitch the editor first). 2) Cite PCI frameworks with their Zenodo DOIs. 3) Share each published paper across LinkedIn + email. | H74: Papers published + citations | I74: 4 h/quarter
A75: ='Platform Setup'!$B$75 -> Project Controls Expo (UK / USA / AUS) | B75: ='Platform Setup'!$C$75 -> Events | C75: ='Platform Setup'!$D$75 -> Critical | D75: ='Platform Setup'!$P$75 -> 13 | E75: ='Platform Setup'!$Q$75 -> UK, US, Australia | F75: The niche's flagship events (London Nov, DC Oct, Melbourne Nov 2026) + Awards. Apply to speak, enter the Awards. | G75: 1) Apply to speak at each 2026 edition NOW (deadlines pass). 2) Enter the Awards. 3) If attending: book 10 meetings ahead via LinkedIn Outreach; log all in Partnership Pipeline. | H75: Speaking slots + meetings booked | I75: seasonal
A76: ='Platform Setup'!$B$76 -> Source of Sources (SOS) | B76: ='Platform Setup'!$C$76 -> Partnership/PR | C76: ='Platform Setup'!$D$76 -> High | D76: ='Platform Setup'!$P$76 -> 33 | E76: ='Platform Setup'!$Q$76 -> Global | F76: Free highest-volume journalist-request service post-HARO. 3 on-expertise answers weekly. | G76: 1) Scan daily; answer 3 on-expertise requests/week. 2) Same-day, 80-120 words, credential in the bio line. | H76: Placements | I76: 45 min
A77: ='Platform Setup'!$B$77 -> Help a B2B Writer | B77: ='Platform Setup'!$C$77 -> Partnership/PR | C77: ='Platform Setup'!$D$77 -> High | D77: ='Platform Setup'!$P$77 -> 34 | E77: ='Platform Setup'!$Q$77 -> Global | F77: Free, B2B-only writer requests; respond same day. | G77: 1) Same-day answers to B2B writer requests matching our expertise; 2/week target. | H77: Placements | I77: 30 min
A78: ='Platform Setup'!$B$78 -> ResponseSource (UK) | B78: ='Platform Setup'!$C$78 -> Partnership/PR | C78: ='Platform Setup'!$D$78 -> High | D78: ='Platform Setup'!$P$78 -> 35 | E78: ='Platform Setup'!$Q$78 -> UK | F78: UK journalist enquiry service (national + trade press); paid; 2-hour response rule. | G78: 1) Paid — answer UK trade/national requests within 2h. 2) Only keep if it lands 1+ placement/quarter (review in Channel Costs). | H78: UK placements/quarter | I78: 45 min
A79: ='Platform Setup'!$B$79 -> Project Times | B79: ='Platform Setup'!$C$79 -> Publishing | C79: ='Platform Setup'!$D$79 -> High | D79: ='Platform Setup'!$P$79 -> 36 | E79: ='Platform Setup'!$Q$79 -> Global | F79: Contributed PM articles via projecttimes.com/contribute. | G79: 1) One contributed article/quarter (evergreen career/methodology angle). 2) Author bio links to the PCI author page. | H79: Published articles + referrals | I79: 3 h/quarter
A80: ='Platform Setup'!$B$80 -> eLearning Industry | B80: ='Platform Setup'!$C$80 -> Publishing | C80: ='Platform Setup'!$D$80 -> High | D80: ='Platform Setup'!$P$80 -> 37 | E80: ='Platform Setup'!$Q$80 -> Global | F80: High-authority education portal, guest articles + author profile via /post-here. | G80: 1) One L&D-angle article/quarter via the author profile. 2) No HR content — L&D/education angle only. | H80: Published articles + referrals | I80: 3 h/quarter
A81: ='Platform Setup'!$B$81 -> Training Industry | B81: ='Platform Setup'!$C$81 -> Publishing | C81: ='Platform Setup'!$D$81 -> High | D81: ='Platform Setup'!$P$81 -> 38 | E81: ='Platform Setup'!$Q$81 -> Global | F81: Corporate L&D readership; self-service article submission; Top Training Companies lists. | G81: 1) One bylined piece/quarter; track the Top Training Companies list criteria annually and apply when eligible. | H81: Articles + list inclusion | I81: 3 h/quarter
A82: ='Platform Setup'!$B$82 -> Coursecheck | B82: ='Platform Setup'!$C$82 -> Directory/Review | C82: ='Platform Setup'!$D$82 -> High | D82: ='Platform Setup'!$P$82 -> 39 | E82: ='Platform Setup'!$Q$82 -> UK | F82: UK training-specific verified reviews; more credible to course buyers than generic review sites. | G82: 1) Capture reviews at the end of every cohort (link in completion email). 2) Respond to each; showcase the widget on course pages. | H82: Review volume + score | I82: 30 min/month
A83: ='Platform Setup'!$B$83 -> Project Control Summit | B83: ='Platform Setup'!$C$83 -> Events | C83: ='Platform Setup'!$D$83 -> High | D83: ='Platform Setup'!$P$83 -> 40 | E83: ='Platform Setup'!$Q$83 -> Global | F83: Dedicated summit for planners/cost controllers/risk. Apply to present. | G83: 1) Submit a talk each cycle. 2) If speaking: repurpose the talk into article + clips within 2 weeks. | H83: Accepted talks | I83: seasonal
A84: ='Platform Setup'!$B$84 -> Google Publisher Center (News / Discover) | B84: ='Platform Setup'!$C$84 -> SEO & Syndication | C84: ='Platform Setup'!$D$84 -> Medium | D84: ='Platform Setup'!$P$84 -> 71 | E84: ='Platform Setup'!$Q$84 -> Global | F84: News inclusion is algorithmic now; consistent cadence + NewsArticle schema earns Top Stories/Discover eligibility. | G84: 1) Keep the newsroom cadence (2+ dated NewsArticle posts/month). 2) Check Discover/News traffic monthly in Search Console. | H84: News/Discover impressions | I84: 20 min/month
A85: ='Platform Setup'!$B$85 -> The Digital Project Manager | B85: ='Platform Setup'!$C$85 -> Publishing | C85: ='Platform Setup'!$D$85 -> Medium | D85: ='Platform Setup'!$P$85 -> 72 | E85: ='Platform Setup'!$Q$85 -> Global | F85: Large PM media brand; expert contributions + podcast; target their certification roundups. | G85: 1) Pitch one expert contribution/quarter; target their certification roundup pages for PCL-AI inclusion. | H85: Placement + roundup inclusion | I85: 2 h/quarter
A86: ='Platform Setup'!$B$86 -> PBC Today (UK construction) | B86: ='Platform Setup'!$C$86 -> Publishing | C86: ='Platform Setup'!$D$86 -> Medium | D86: ='Platform Setup'!$P$86 -> 73 | E86: ='Platform Setup'!$Q$86 -> UK | F86: UK construction publication taking stakeholder opinion pieces. | G86: 1) One 700-word UK opinion piece/quarter (skills gap, AI in controls). | H86: Published pieces | I86: 2 h/quarter
A87: ='Platform Setup'!$B$87 -> Construction Week ME + CBNME | B87: ='Platform Setup'!$C$87 -> Partnership/PR | C87: ='Platform Setup'!$D$87 -> Medium | D87: ='Platform Setup'!$P$87 -> 74 | E87: ='Platform Setup'!$Q$87 -> Gulf | F87: Gulf construction trade press; build the 10-name journalist list, offer expert commentary. | G87: 1) Maintain the 10-name Gulf journalist list; offer expert comment monthly. 2) Pitch one feature/quarter (Gulf giga-projects + controls skills). | H87: Gulf press mentions | I87: 1 h/month
A88: ='Platform Setup'!$B$88 -> Amazon KDP (authority book) | B88: ='Platform Setup'!$C$88 -> Publishing | C88: ='Platform Setup'!$D$88 -> Medium | D88: ='Platform Setup'!$P$88 -> 75 | E88: ='Platform Setup'!$Q$88 -> Global | F88: A niche handbook is a compounding authority asset; Amazon is its own search engine. | G88: 1) Ship the niche handbook once; update annually. 2) Every author bio + talk cites it. 3) Run free-promo days around campaigns. | H88: Copies + reviews | I88: project, then 1 h/quarter
A89: ='Platform Setup'!$B$89 -> ResearchGate / SSRN / Academia.edu | B89: ='Platform Setup'!$C$89 -> Publishing | C89: ='Platform Setup'!$D$89 -> Medium | D89: ='Platform Setup'!$P$89 -> 76 | E89: ='Platform Setup'!$Q$89 -> Global | F89: Preprints of PCI frameworks under named authors; the direct channel to the university audience. | G89: 1) Upload each PCI framework/paper under named authors with institute affiliation. 2) Answer questions on your papers monthly. | H89: Reads + citations | I89: 1 h/month
A90: ='Platform Setup'!$B$90 -> BrightTALK | B90: ='Platform Setup'!$C$90 -> Events | C90: ='Platform Setup'!$D$90 -> Medium | D90: ='Platform Setup'!$P$90 -> 77 | E90: ='Platform Setup'!$Q$90 -> Global | F90: B2B webinar network with built-in audience discovery; test one quarter against Zoom-only baseline. | G90: 1) Run one quarter's webinars here in parallel with Zoom; compare audience quality, then decide. | H90: Registrations vs Zoom baseline | I90: 1 h/event
A91: ='Platform Setup'!$B$91 -> Sessionize + SpeakerHub | B91: ='Platform Setup'!$C$91 -> Events | C91: ='Platform Setup'!$D$91 -> Medium | D91: ='Platform Setup'!$P$91 -> 78 | E91: ='Platform Setup'!$Q$91 -> Global | F91: Speaker directories + open CFP boards; 3 applications per quarter. | G91: 1) Keep 2 leader profiles current. 2) 3 CFP applications/quarter from the open boards. | H91: CFP acceptances | I91: 1 h/quarter
A92: ='Platform Setup'!$B$92 -> PodMatch + MatchMaker.fm | B92: ='Platform Setup'!$C$92 -> Podcast | C92: ='Platform Setup'!$D$92 -> Medium | D92: ='Platform Setup'!$P$92 -> 79 | E92: ='Platform Setup'!$Q$92 -> Global | F92: Host-guest matching tools that operationalise Podcast Guesting; 2 bookings/month. | G92: 1) Weekly: accept/decline matches within 48h; pitch 3 shows/week until 2 bookings/month is steady. | H92: Bookings/month | I92: 45 min
A93: ='Platform Setup'!$B$93 -> Skool | B93: ='Platform Setup'!$C$93 -> Community | C93: ='Platform Setup'!$D$93 -> Medium | D93: ='Platform Setup'!$P$93 -> 80 | E93: ='Platform Setup'!$Q$93 -> Global | F93: Community platform WITH discovery marketplace (unlike Discord/Slack); free exam-prep group. | G93: 1) Free exam-prep group: one discussion prompt/week + weekly office-hours thread. 2) Promote inside content CTAs. 3) Graduates funnel to Certuvo. | H93: Members + weekly active % | I93: 2 h
A94: ='Platform Setup'!$B$94 -> Digg (2026 relaunch) | B94: ='Platform Setup'!$C$94 -> Community | C94: ='Platform Setup'!$D$94 -> Low | D94: ='Platform Setup'!$P$94 -> 118 | E94: ='Platform Setup'!$Q$94 -> Global | F94: Open beta closed Mar 2026 pending rebuild - watching brief only; re-verify before spending any effort. | G94: 1) Watching brief only — re-verify status at the 6-monthly review before ANY effort. | H94: n/a (watch) | I94: 0
A95: ='Platform Setup'!$B$95 -> Apple Business Connect | B95: ='Platform Setup'!$C$95 -> Directory/Review | C95: ='Platform Setup'!$D$95 -> Medium | D95: ='Platform Setup'!$P$95 -> 81 | E95: ='Platform Setup'!$Q$95 -> US-lean global | F95: Feeds Apple Maps/Siri and AI entity verification; free; critical only if physical exam centres exist. | G95: 1) Quarterly: verify the listing (only critical if physical exam centres exist). | H95: Listing accurate | I95: 10 min/quarter
A96: ='Platform Setup'!$B$96 -> beehiiv Recommendations | B96: ='Platform Setup'!$C$96 -> Email & CRM | C96: ='Platform Setup'!$D$96 -> Medium | D96: ='Platform Setup'!$P$96 -> 82 | E96: ='Platform Setup'!$Q$96 -> Global | F96: Cross-newsletter recommendations marketplace as a subscriber-acquisition surface. | G96: 1) Recommend 3-5 adjacent newsletters; request reciprocal recommendations quarterly. | H96: Subscribers from recommendations | I96: 30 min/quarter
A97: ='Platform Setup'!$B$97 -> Eng-Tips Forums | B97: ='Platform Setup'!$C$97 -> Community | C97: ='Platform Setup'!$D$97 -> Low | D97: ='Platform Setup'!$P$97 -> 119 | E97: ='Platform Setup'!$Q$97 -> US-lean global | F97: Alive in 2026; engineering-heavy rather than controls; occasional answers only. | G97: 1) Occasional expert answers (2/month) on controls-adjacent engineering threads. | H97: Answers + profile views | I97: 30 min/month
A98: ='Platform Setup'!$B$98 -> Scribd + Issuu | B98: ='Platform Setup'!$C$98 -> SEO & Syndication | C98: ='Platform Setup'!$D$98 -> Low | D98: ='Platform Setup'!$P$98 -> 120 | E98: ='Platform Setup'!$Q$98 -> Global | F98: Still Google-indexed for reports/brochures; nofollow links; visibility only, never bulk submission. | G98: 1) Upload each public report/brochure once (nofollow links; visibility only). 2) Never bulk-submit. | H98: Document views | I98: 15 min/month
A99: ='Platform Setup'!$B$99 -> Flipboard / Surf | B99: ='Platform Setup'!$C$99 -> Social Media | C99: ='Platform Setup'!$D$99 -> Low | D99: ='Platform Setup'!$P$99 -> 121 | E99: ='Platform Setup'!$Q$99 -> Global | F99: Federated 'social websites' launched Apr 2026; connect the blog RSS, revisit in 6 months. | G99: 1) RSS connected — verify it flows monthly; revisit value at the 6-monthly review. | H99: Referral visits | I99: 10 min/month
A100: ='Platform Setup'!$B$100 -> GPT Store (custom GPT) | B100: ='Platform Setup'!$C$100 -> SEO & Syndication | C100: ='Platform Setup'!$D$100 -> Low | D100: ='Platform Setup'!$P$100 -> 122 | E100: ='Platform Setup'!$Q$100 -> Global | F100: Exam-coach GPT linking to Certuvo; brand experiment, measure clicks before investing. | G100: 1) Keep the exam-coach GPT's knowledge current each quarter. 2) Measure clicks to Certuvo before investing more. | H100: Sessions + clicks out | I100: 1 h/quarter
...

Sheet PR & Target Directory
A1: PR & TARGET DIRECTORY — named routes, verified August 2026
A2: ◀ MAP | B2: The actual places, people and submission routes behind the generic platform rows — researched and verified live. Yellow columns are the team's tracker. Re-verify a route before relying on it if more than 6 months have passed.
A4: Category | B4: Target | C4: Route / where | D4: What to do | E4: Owner | F4: Status | G4: Notes / result
A5: UK course directories | B5: Reed Courses | C5: reed.co.uk/courses/providers | D5: Apply as provider; commercial terms on application
B6: findcourses.co.uk | C6: via their sales team | D6: List PCL-AI / PFL-AI / PML-AI with UTM links
B7: Emagister UK | C7: emagister.co.uk | D7: Lead-gen listing; compare cost per lead after 90 days
B8: Coursecheck | C8: coursecheck.com/training-providers | D8: Provider signup + review capture at end of each cohort
A9: Gulf directories | B9: Laimoon | C9: providers.laimoon.com | D9: Free provider listing (UAE + Saudi)
B10: Coursetakers.ae | C10: coursetakers.ae | D10: Provider signup; UAE course aggregator
B11: Edarabia | C11: edarabia.com | D11: Submit institution listing + reviews
A12: Global directories | B12: Class Central | C12: classcentral.com | D12: Request provider indexing AND pitch a free intro certificate into their editorial lists
A13: CPD accreditation | B13: The CPD Certification Service | C13: cpduk.co.uk/become-accredited | D13: Largest/oldest UK accreditor — start here
B14: CPD Standards Office | C14: cpdstandards.com/become-accredited | D14: Research-based accreditor; alternative quote
B15: The CPD Group | C15: thecpd.group | D15: 9,900+ providers; certified by The CPD Register
A16: Podcasts (guesting) | B16: Project Chatter | C16: projectchatter.com/be-a-guest | D16: TOP TARGET — the project controls podcast; direct guest form; 45-60 min remote
B17: Beyond Deadlines | C17: beyond-deadlines.com | D17: Construction planning/scheduling audience
B18: PM Happy Hour | C18: pmhappyhour.com | D18: Practitioner-guest format
B19: People and Projects | C19: peopleandprojectspodcast.com | D19: Long-running interview format
B20: Manage This (Velociteach) | C20: velociteach.com | D20: 1st/3rd Tuesdays; pitch via contact form
A21: Publications | B21: PM World Journal | C21: pmworldjournal.com/authors | D21: PRIORITY — pitch a named-author monthly series to the editor
B22: Project Times | C22: projecttimes.com/contribute | D22: Word-doc submission; evergreen career articles
B23: Training Industry | C23: trainingindustry.com/collaborate-with-us + editor@trainingindustry.com | D23: Bylined article + research Top Training Companies criteria
B24: eLearning Industry | C24: elearningindustry.com/post-here | D24: Author profile + L&D-angle articles (no HR content)
B25: PBC Today | C25: pbctoday.co.uk | D25: 700-word UK construction opinion pieces
B26: The Digital Project Manager | C26: thedigitalprojectmanager.com | D26: Expert contribution + their podcast + certification roundups
A27: Publications (Gulf) | B27: Construction Week ME | C27: constructionweekonline.com | D27: Journalist roster on Muck Rack; offer expert commentary
B28: CBNME | C28: cbnme.com | D28: Gulf construction business news; pitch editors
A29: Publications (academic) | B29: Journal of Project Management | C29: growingscience.com/jpm | D29: Open access, covers project controls, no submission charge
A30: Journalist requests | B30: Source of Sources (SOS) | C30: free subscription | D30: 3 on-expertise answers weekly, 80-120 words, data-led
B31: Help a B2B Writer | C31: free, B2B-only | D31: Respond same day
B32: ResponseSource (UK) | C32: responsesource.com | D32: Paid; Business/Education/Construction categories; 2-hour answers
B33: #journorequest | C33: X and Bluesky, twice daily | D33: Fastest channel; search saved daily
A34: Events & awards | B34: Project Controls Expo UK | C34: projectcontrolexpo.com/uk | D34: London (Wembley) 2-4 Nov 2026, 2,000+ delegates — speaker application + Awards entry
B35: Project Controls Expo USA | C35: projectcontrolexpo.com | D35: Washington DC 5-7 Oct 2026
B36: Project Controls Expo Australia | C36: projectcontrolexpo.com | D36: Melbourne (MCG) 23-25 Nov 2026
B37: Project Control Summit | C37: projectcontrolsummit.com | D37: Apply to present
B38: Advancing Project Controls | C38: advancing-project-controls.com | D38: US conference; speaking/sponsor slots
A39: Speaker directories | B39: Sessionize | C39: sessionize.com — free | D39: Profiles for 2 PCI leaders + 3 CFP applications/quarter
B40: SpeakerHub | C40: speakerhub.com | D40: Directory + CFP board
A41: Podcast booking tools | B41: PodMatch | C41: podmatch.com | D41: Guest profile; 2 bookings/month
B42: MatchMaker.fm | C42: matchmaker.fm | D42: Freemium alternative
A43: Partnership targets | B43: APM (Assoc. for Project Management) | C43: apm.org.uk/membership | D43: Explore Corporate Partner programme — 42,000+ members
B44: ACostE | C44: acoste.org.uk | D44: Cost engineers association; natural collaboration partner
A45: Authority registries | B45: Credential Engine Registry | C45: credentialengine.org · accounts@credentialengine.org | D45: FREE — publish PCL-AI/PFL-AI/PML-AI in CTDL; auto-creates the credentialfinder.org listing; consumed by ~21 US state systems
B46: CareerOneStop Certification Finder | C46: info@careeronestop.org | D46: US DoL-sponsored directory that syndicates via public API — email the certification details
B47: D&B D-U-N-S | C47: dnb.com/en-us/smb/duns/get-a-duns.html | D47: Free, ~30 business days; one per legal entity
B48: ISNI via Bowker | C48: myidentifiers.com | D48: ~$5 one-time; add the ISNI to Wikidata + schema
B49: OpenCorporates | C49: opencorporates.com/companies/us_de/ | D49: Verify the Delaware record exists and matches the canonical name — 10 minutes, once
B50: Google Knowledge Panel | C50: search the brand → 'Claim this knowledge panel' | D50: Claim once it appears; built by the entity-graph work, not by application
A51: Startup listings | B51: Tracxn | C51: tracxn.com/listyourstartup | D51: Free, analyst-reviewed; Perplexity observed citing it — list PCI and Certuvo
B52: Dealroom | C52: dealroom.co/for-builders | D52: Free self-serve add + claim
B53: Magnitt (Gulf) | C53: magnitt.com → Create/Claim company | D53: The MENA startup dataset governments cite
B54: F6S | C54: f6s.com | D54: Free profile; watch grants/accelerators quarterly
B55: AlternativeTo (Certuvo) | C55: alternativeto.net | D55: Free dofollow; alternatives pages get AI-cited
B56: SaaSHub (Certuvo) | C56: saashub.com | D56: Free listing with dofollow
B57: There's An AI For That (Certuvo) | C57: theresanaiforthat.com | D57: Only if genuine AI features ship
A58: Gulf job boards | B58: Bayt.com | C58: bayt.com employer registration | D58: Free employer profile; largest Arab-world job platform
B59: Naukrigulf | C59: naukrigulf.com employer zone | D59: India-to-Gulf pipeline; light presence
B60: GulfTalent | C60: gulftalent.com | D60: Only after Bayt shows demand
A61: Institution authority (strategic) | B61: ISO/IEC 17024 accreditation | C61: ANAB (anab.ansi.org, form PCAC-FR-503) / UKAS / IAS | D61: THE endgame authority move for a certification body — workshop → eligibility → application → assessment; realistic 12-24 months, five-figure annual cost. A leadership programme, not a marketing task; PCI already states 'developed with reference to 17024'
B62: Regulatory recognition — honest read | C62: Ofqual / Dubai KHDA / Abu Dhabi ACTVET / Saudi TVTC | D62: Ofqual needs an England-operating awarding organisation with governance + reserves; KHDA permit is for Dubai training institutes (AED 15-25k/yr + premises); TVTC licenses foreign providers in-Kingdom. Realistic route today: partner institutes that already hold the local licence deliver PCI prep — log them in Partnership Pipeline
B63: buildingSMART International | C63: buildingsmart.org member directory | D63: Paid membership with a public member-directory listing; consider when the BIM/data-standards angle goes live
B64: UNESCO Global Skills Academy / ILO skills partnerships | C64: unesco.org/en/global-education-coalition | D64: Partnership application, big-brand halo (IBM, Microsoft, Coursera are partners); long shot — one well-prepared approach, then park
B65: The Conversation | C65: theconversation.com/become-an-author | D65: Only university-affiliated authors (adjunct/honorary roles and PhD candidates qualify; independent orgs excluded). Route: PCI leaders holding visiting/adjunct roles, or honorary fellows in academia writing on project controls + AI
B66: UK construction awards (CN Awards, NFB Awards of Excellence, NCE) | C66: constructionnews.co.uk / builders.org.uk / nceawards.newcivilengineer.com | D66: Entries with published, indexed shortlist pages — authority mentions on trade-press domains; enter the training/skills categories
A67: Guest publications (PM) | B67: PM Column | C67: pmcolumn.com/contribution-guidelines | D67: Live guest-blogging guidelines; practical PM audience
B68: Projectcubicle | C68: projectcubicle.com (guest post) | D68: ~900-word guest posts with byline + link; running since 2007
B69: IAPM 'Write for IAPM' | C69: iapm.net/en/service/write-for-iapm | D69: Structured guest-article process; European PM body audience
B70: ProProfs PM articles | C70: proprofs.com/c/submit-project-management-article | D70: Simple submission; leadership/PM topics
B71: Rebel's Guide to PM | C71: rebelsguidetopm.com — pitch directly | D71: Award-winning PM blog; accepts guest posts, no formal page — personalised pitch to Elizabeth Harrin
B72: Vendor blogs: Deltek Project Nation + Plan Academy | C72: deltek.com Project Nation guest author; planacademy.com | D72: PM-software vendor blogs that publish expert contributions — exactly the project-controls buyer; pitch P6/EVM how-tos
A73: News distribution (verified) | B73: PRLog | C73: prlog.org — free | D73: Best free wire: unlimited cadence, images/video, fast Google indexing via RSS. Every credential/programme announcement goes here after the own-site newsroom post
B74: openPR | C74: openpr.com — free | D74: 1 free release per 30 days; Google News indexed; strongest EU reach of the free wires
B75: IssueWire | C75: issuewire.com | D75: Free tier = first release only, NO Google News (that needs the $21-45 tiers); use paid only when a specific spread matters
B76: EIN Presswire | C76: einpresswire.com | D76: No free tier; $149/release transparent pricing — the paid option when a launch justifies it
B77: The rule for every release | C77: own newsroom first | D77: Google treats distributed press-release links as nofollow (link-scheme policy) — the value is indexed corroboration AI engines read, never link equity. Newsworthy facts, quotes, numbers; no keyword stuffing
A78: Job posting boards (verified) | B78: Careers page + Google for Jobs | C78: JobPosting JSON-LD per role page | D78: FREE and fully live 2026 — do this before paying any board; surfaces in Google's job box
B79: LinkedIn Jobs | C79: Company page → post free | D79: 1 free job at a time (pauses day 14, expires day 30); promote only if stalled (~$300/30 days typical)
B80: Indeed | C80: post directly in the dashboard | D80: Free organic degraded by the 31 Mar 2026 policy (feed-posted jobs need Indeed Apply); direct posts keep residual visibility — sponsor small amounts only when needed
B81: Wellfound | C81: wellfound.com — free unlimited + ATS | D81: Free core forever; remote marketing/growth roles
B82: Bayt / Naukrigulf / Naukri.com | C82: employer accounts | D82: Bayt ~$158/post (the Gulf board); Naukrigulf 5 free posts for new employers; Naukri.com from ~Rs 400 — the India pipeline
B83: jobs.ac.uk / HigherEdJobs | C83: recruiter products | D83: GBP 250+ / $325 per post — only for UK/US academic SMEs, examiners and item writers
B84: Internshala | C84: employer dashboard — 1 free post/month | D84: India marketing interns and junior ambassadors; free tier only
A85: Verified SKIPs — do not spend time | B85: Golden.com | C85: — | D85: DEAD — acquired by ComplyAdvantage 2024; public wiki gone
B86: BBB accreditation | C86: — | D86: $500-1,000+/yr pay-to-play seal; reviews have replaced it
B87: Futurepedia Verified | C87: — | D87: $497 — pay only after free directories prove qualified traffic
B88: UKRLP / UKPRN | C88: — | D88: Requires a UK legal entity; becomes a KEEP the day a UK Ltd exists
B89: ROR | C89: — | D89: Eligible only once PCI appears as affiliation in published research
B90: CPD Register 'free listing' | C90: — | D90: Does not exist — listing is bundled with paid accreditation only
B91: Coursera / edX partnership | C91: — | D91: Selective BD partnerships; unrealistic at current scale — revisit later
B92: llms.txt | C92: — | D92: Re-verified evidence-negative: 97% of files never fetched; no provider parses it
B93: ESCO qualification listing | C93: — | D93: EU database fed only by Member-State national qualification registers referenced to EQF — no route for a non-EU private credential
B94: Wikibooks / Wikiversity | C94: — | D94: Same conflict-of-interest rules as Wikipedia — organisational self-contribution is treated as promotional; never self-edit
B95: BusinessBalls | C95: — | D95: Content library (Accipio-owned), no contributor route found
B96: engineering.com contributor route | C96: — | D96: No verified 2026 submission page — do not chase until the 6-monthly re-verify finds one
B97: PR.com / 24-7PressRelease / PRFree / PRUnderground | C97: — | D97: Unverified this round — stick to the verified PRLog + openPR stack; re-check at the 6-monthly review
... B102: We Work Remotely / RemoteOK | C102: — | D102: $299+/post with a tech-lean audience — wrong cost/audience for a small institute

Sheet UPGRADE NOTES
A1: UPGRADE NOTES — what was tested, what was missing, what changed
A2: ◀ MAP | B2: Three independent audit passes ran end to end — every formula, every platform list, and the whole system as a product a team runs daily — then three judges verified the rebuild. Type: PLATFORM = a capability the workbook lacked; PROCESS = a workflow rule no spreadsheet can enforce alone.
A4: # | B4: Finding | C4: Type | D4: Severity | E4: What this workbook does | F4: What the team must still do
A5: 1 | B5: Why the file showed one employee | C5: Process | D5: — | E5: The team roster (START HERE rows 55-64) has ten slots and only slot 1 was ever filled, with the placeholder 'Employee 1'. Every scorecard, dropdown and column is driven from those cells — the design was always multi-employee; the roster was never populated. | F5: Manager replaces 'Employee 1' with a real name and fills a slot per team member. Names must match exactly everywhere.
A6: 2 | B6: UTM links were malformed | C6: Platform | D6: Blocker | E6: The link formula used SEARCH('?'), which treats ? as a wildcard, so every URL was joined with '&' instead of '?' — GA4 could never read a single campaign parameter. Fixed with FIND; campaign/content segments un-nested. | F6: Regenerate and re-paste any UTM link created from V6.
A7: 3 | B7: Team targets compared to one person | C7: Platform | D7: Blocker | E7: Dashboard 'Expected to date' never multiplied by headcount, so five people were measured against one person's target. Now multiplied by the count of filled roster slots. | F7: Keep the roster accurate — an unfilled slot lowers the expectation.
A8: 4 | B8: No duplicate-lead defence | C8: Platform | D8: Blocker | E8: Nothing stopped two employees logging or re-contacting the same person — including someone who had declined. This version adds a live Duplicate? column and red highlighting on the lead URL and organisation columns. | F8: Rule: Ctrl+F the lead's URL before logging. A red cell means stop and check the earlier row.
A9: 5 | B9: Platform lists disagreed with each other | C9: Platform | D9: Blocker | E9: 3 platforms were selectable but invisible to every rollup; 'Quora / Quora Spaces' in the Publishing Plan could never match a count; generic 'LinkedIn' in examples/tasks counted nowhere. All lists come from one canonical platform list (71 at that round; the estate has since grown — see later entries); every stray string remapped. | F9: Log only with dropdown values. The dedup rule for each platform is beside it on the Lists tab.
A10: 6 | B10: 25 platforms were missing | C10: Platform | D10: Major | E10: No paid channels, no email marketing, no webinar delivery, no digital badges (Credly), no profession-specific communities (Planning Planet, PMI), no podcast guesting, no partnership/PR platform value. All added with areas, priorities and setup steps. | F10: Work the new Critical/High rows in Platform Setup: Zoom Webinars, Email Marketing (ESP), Credly, Partnership / PR Outreach, LinkedIn Live, Planning Planet, PMI Community.
A11: 7 | B11: Funnel stopped before money | C11: Platform | D11: Major | E11: Tracking ended at 'Application Started'. This version adds per-lead columns: meeting date, PCI closer, application date, certification, purchase date, revenue and the PCI order reference, plus deal value / contract date on partnerships and a Dashboard revenue block. | F11: Rule: a lead may be marked Converted only when its PCI order/application reference is in the row. The PCI platform stays the ledger; this file reconciles to it.
A12: 8 | B12: Follow-ups fired from the wrong date | C12: Platform | D12: Major | E12: Follow-up due = date logged + 4, not date messaged — due before the first message went out. Now driven by the new 'Message sent date' (+4 and +10), and the Dashboard due-count includes blank/no-response outcomes. | F12: Fill 'Message sent date' when the first message goes out.
A13: 9 | B13: Formula sheets were unprotected | C13: Process | D13: Blocker | E13: Any employee could type over the Dashboard or a score formula with no warning. All computed sheets and formula columns are now protected (no password); entry columns stay open. | F13: If you cannot type somewhere, that is the protection working — do not remove it.
A14: 10 | B14: No operating model for a shared file | C14: Process | D14: Blocker | E14: Nothing said where the file lives or how ten people use it at once. START HERE section 9 now carries the eight sharing rules (one location, AutoSave, no sorting shared logs, claim rows by date, never paste whole rows, no deletions, one owner, monthly archive). | F14: Manager adopts the rules verbatim and names the owner in cell B19.
A15: 11 | B15: No onboarding checklist | C15: Process | D15: Major | E15: Rules existed as prose; nothing was tickable. START HERE section 10 is a ten-point Day-1 checklist with a manager sign-off column. | F15: Run it for every joiner; first 5 leads and first 3 messages get manager review before sending.
A16: 12 | B16: Message approval was undefined | C16: Process | D16: Major | E16: The rule said 'approved messages only' but nothing recorded approval. Message Bank now has Status / Approved by / Approved date; M1-M15 are grandfathered as Approved pending the manager's initials. | F16: Manager initials and dates every row; new messages enter as Draft.
... A20: 16 | B20: Weekly Review trend depended on the person selector | C20: Platform | D20: Major | E20: The Dashboard trend charts read selector-filtered cells, so the 'team trend' was whoever was last selected. Three selector-independent all-team columns added for trend reporting. | F20: Chart team trend from the All-team columns (T:V); use the selector for 1:1s only.
A21: 17 | B21: Fresh-file noise | C21: Platform | D21: Minor | E21: 'Days since last worked: 46251' on every platform before any logging. Guarded — blank until real activity exists.
A22: 18 | B22: Capacity ceilings | C22: Platform | D22: Major | E22: The outreach log holds ~1,200 leads (a 5-person team at target fills it in ~8 working days); logs hold ~400 rows; week list ends at 26. Validation ranges now match counted ranges so nothing silently drops out inside those limits. | F22: Monthly archive by the owner. At sustained full-team volume, move the lead log to a CRM and keep this file for activity and content tracking.
A23: 19 | B23: Channel costs were untracked | C23: Platform | D23: Minor | E23: Hours were logged but money was not — cost per meeting was uncomputable. New Channel Costs sheet feeds the Dashboard. | F23: Owner fills monthly costs; review cost-per-meeting monthly.
A24: 20 | B24: Two-brand ambiguity (Certuvo) | C24: Process | D24: Minor | E24: SUPERSEDED by the brand dimension: every log tab now carries a For (brand) column, so Certuvo work is logged in this file and tagged 'Certuvo (exam prep)' — results split cleanly on Objective Performance. | F24: Tag Certuvo rows with the brand dropdown; no separate copy of the file is needed.
A25: 21 | B25: Workbook recalculates slowly | C25: Platform | D25: Minor | E25: The array formulas on Platform Progress and the Daily Log make full recalculation slow in some spreadsheet engines. Guards added in V7 reduce it; expect a pause on open with large data. | F25: Prefer Excel desktop/web; avoid opening in unrelated tools.
A26: 22 | B26: Dropdowns did not actually enforce anything | C26: Platform | D26: Blocker | E26: Every one of V6's 54 validation rules had error alerts switched off — Excel showed the list but silently accepted anything typed, and mistyped names then vanished from every report. All rules rebuilt with hard errors on, plus red tripwire highlighting on any name or platform that will not count. | F26: If a cell turns red, fix the spelling — red means invisible to every report.
A27: 23 | B27: Example rows sat inside a dead zone | C27: Platform | D27: Major | E27: Reports read from row 7 (DAILY ENTRY) / row 5 (logs); the example rows above that carried live yellow cells and dropdowns, so typing over them (instead of deleting them) put real work where no report could see it. Examples are now grey, the notes say exactly where data starts, and the instruction is explicit: delete the rows, never clear them. | F27: Manager deletes all grey example rows in one pass on day 1 and confirms the Dashboard reads zero.
A28: 24 | B28: Date and number columns accepted text | C28: Platform | D28: Major | E28: Dates and counts had no validation, and a text date silently drops the row from weekly buckets. Date and whole-number validation added on every date/quantity column.
A29: 25 | B29: Hidden helper columns added | C29: Platform | D29: Minor | E29: DAILY ENTRY columns K and L are hidden calculation flags (first entry per day, and per day per person) that drive the days-logged counts efficiently. | F29: Do not unhide, edit or delete DAILY ENTRY columns K and L.
A30: 26 | B30: Single-employee residue removed | C30: Process | D30: Major | E30: START HERE section 2 asked for one 'Employee name' — a leftover from a single-user draft that made the whole file read as one person's tracker. It is now Team Settings (team name + manager); people exist only on the roster, targets are explicitly per person, and the Dashboard multiplies by headcount. | F30: Manager fills Team Settings and the roster; nothing else defines who is on the team.
A31: 27 | B31: Platform coverage doubled on live research | C31: Platform | D31: Major | E31: Web research (August 2026, 26 searches) added 29 vetted organic-growth platforms — the ChatGPT-visibility pipeline (Bing Webmaster Tools + IndexNow), AI answer-engine auditing, PM World Journal, Project Controls Expo, the post-HARO journalist stack, UK/Gulf course directories, CPD accreditors, podcast booking tools and more — bringing the estate at that round to 100 platforms across 12 areas (later rounds grew it to 133 across 13), each with setup steps. | F31: Work Platform Setup by priority; the named routes live on PR & Target Directory.
A32: 28 | B32: Dead tactics documented so nobody wastes time | C32: Process | D32: Minor | E32: The research also verified what NOT to do: HARO is dead, article directories and bulk PDF submission are link spam, llms.txt is evidence-negative, engagement pods and automated LinkedIn tools get accounts penalised. GROWTH PLAYBOOK technique 15 carries the full list. | F32: Read playbook technique 15 before acting on any 'SEO tips' list from the internet. Note: the original HARO shut Dec 2024; the brand was relaunched under Featured.com in 2025 — treat it as part of the Featured stack.
A33: 29 | B33: GROWTH PLAYBOOK added — now 22 techniques in working detail | C33: Process | D33: Major | E33: Numbered steps, cadence, KPI and pitfalls for every technique: SEO clusters, E-E-A-T, answer-engine optimisation, digital PR, the 2026 LinkedIn engine, community growth, syndication with verified canonical rules (Substack and LinkedIn have none), webinars, email, the Credly badge loop, directories, YouTube Shorts-first, measurement, the dead-tactics guardrail — plus, from later rounds: entity authority (14), the free publishing & news pipeline (16), and six world-class additions: original research & data studies, free tools & calculators, Arabic/Gulf localisation, internal linking architecture, employee advocacy & social proof, and guarded programmatic geo×role pages (17-22). | F33: Each technique names the sheet it logs into; the manager assigns owners per technique.
A34: 30 | B34: TEAM GUIDE added — the end-to-end explainer | C34: Process | D34: Major | E34: A team that does not know how to run the system now has the answer in one tab: where to log what, first day, every day, how scoring works, and an FAQ. | F34: Every new joiner reads TEAM GUIDE before anything else (Day-1 Checklist item 1).
A35: 31 | B35: Accounts Register added — and why it holds no passwords | C35: Process | D35: Major | E35: Every marketing account on one page: URL, login, vault entry name, 2FA, owner, status — built by formula from Platform Setup so there is one source of truth. Passwords stay in the team password manager: a shared, synced, version-historied workbook can never hold credentials safely, and the register names the exact vault entry instead. | F35: Manager fills the vault location cell and grants vault access on day 1.
A36: 32 | B36: PR & Target Directory added — named, verified routes | C36: Platform | D36: Major | E36: 40 researched targets with live routes at that round — course directories (UK/Gulf/global), CPD accreditors, five PM podcasts that take guests, seven publications with submission pages, the journalist-request stack, 2026 expo dates, speaker directories and partnership targets; later research rounds grew the directory to ~100 rows including the verified skip list. | F36: Assign an owner per category; statuses tracked in the yellow columns.
A37: 33 | B37: Authority & AI-visibility research round | C37: Platform | D37: Major | E37: A second deep-research pass (34 verified searches) added 26 authority and listing platforms under a new Authority & Listings area: the Credential Engine Registry (free, consumed by US state systems), CareerOneStop, the Knowledge Panel entity-graph stack, D-U-N-S, ISNI, Tracxn/Dealroom/Magnitt startup databases, Gulf job boards and Certuvo tool directories — plus corrected education schema (the Course Info rich result was retired in 2025; Course List remains). GROWTH PLAYBOOK technique 14 carries the evidence-ranked top-10 AI-visibility actions; the verified skip-list (Golden dead, BBB pay-to-play, UKRLP needs a UK entity) is on PR & Target Directory so nobody re-litigates it. | F37: Work the Critical rows first: Credential Engine, the entity graph, education schema. The 20-prompt AI citation audit runs monthly.
A38: 34 | B38: Institution authority + free publishing + free news research round | C38: Platform | D38: Major | E38: A third research pass (33 verified searches) covered three lanes. (1) Institution authority: the ISO/IEC 17024 accreditation path (ANAB/UKAS/IAS) and an honest read on Ofqual/KHDA/ACTVET/TVTC regulatory recognition — partner-institute route today; The Conversation's academic-affiliation rule; buildingSMART; UNESCO Global Skills Academy; UK award shortlists. (2) Free educational publishing: Zenodo DOIs, OER Commons + MERLOT (non-university contributors verified), TrainingZone/HRZone, six PM guest-post routes. (3) Free news: PRLog + openPR verified as the free stack (IssueWire free tier has no Google News; EIN has no free tier); press-release links are nofollow — value is AI-readable corroboration. Dead ends recorded on the skip list (ESCO, Wikibooks/Wikiversity COI, BusinessBalls, unverified PR wires). | F38: Playbook technique 16 is the pipeline; the strategic 17024 row is leadership's call, not marketing's.
A39: 35 | B39: Objective dimension added — performance is now testable per campaign | C39: Platform | D39: Major | E39: Every log tab carries an Objective dropdown (11 effort categories: honorary certification outreach, per-credential certification sales, authority & entity building, content & SEO, community, partnerships & PR, events, Certuvo, brand). The Content Calendar's existing Objective column became the dropdown — no duplicate column. The new Objective Performance sheet totals activities, minutes, content, community actions, leads, meetings and revenue per category, plus a person × objective minutes matrix, so each campaign is judged on its own numbers. | F39: Tag every row; the red '(no objective set)' line must be zero by each Monday review.
A40: 36 | B40: Brand / property dimension + the web domain map | C40: Platform | D40: Major | E40: Every log tab (and Platform Setup and Master Tasks) now carries a For (brand) column: PCI AI - Institute, PCL-AI, PFL-AI or PML-AI certification, PCI World, Certuvo, or All/shared — so results are testable per property as well as per campaign. The Content Calendar's old 3-value Brand column became this dropdown; Certuvo-only platforms (G2, Capterra, AlternativeTo, Udemy…) come pre-tagged on Platform Setup. Objective Performance gained a RESULTS BY BRAND table. START HERE §11 now maps the five web domains — projectcontrolsinstitute.org, pciai.org, pciglobal.ai, pciworld.org, mypci.org — to the brand each serves, and every UTM/press link must land on one of them. | F40: Tag both columns on every row; the manager corrects the domain map if a purpose is wrong.
... A50: 46 | B50: Independent critical re-audit — treated as if built by someone else | C50: Process | D50: Major | E50: A fresh adversarial audit assumed nothing and trusted nothing: an independent numerical oracle, a static 'silent-zero' analysis of all 2,078 conditional criteria (a SUMIFS whose criteria text no longer exists returns 0 forever with no error — none found), Excel-integrity checks for repair-prompt triggers (none), a cached-error sweep (none), and cadence maths proved across every scheduling frequency. Real defects found and fixed: (1) 'Content published' meant different things on Weekly Pulse (by published date) and the Dashboard (by status) — now both mean status Published/Repurposed, so the two pages can never disagree; (2) 'Connection requests sent' appeared twice on the Dashboard from two different sources with the same label — now each names its source; (3) a schedule row with the end date before the start date produced NEGATIVE planned posts and poisoned coverage — now blank, with the dates flagged red; (4) formula cells on Message Bank and Lists were editable; (5) 24 sheets still showed raw gridlines while the rest did not — the whole workbook now shares one look; (6) a first-run screen of zeros looked broken — Dashboard and Weekly Pulse now explain themselves until data arrives. | F50: The release gate is now 66 structural checks + a 51-assertion live simulation + the static and integrity analyses — all must pass.
A51: 47 | B51: Premium formatting pass | C51: Process | D51: Minor | E51: Everything now matches the workbook's own design system (Arial, navy titles, banded headers), tabs are colour-grouped and reordered by workflow, panes freeze on every long sheet, and every sheet prints one page wide with repeating headers.

Sheet DAILY ENTRY
A1: DAILY ENTRY — this is the only sheet you need to fill in
A2: ◀ MAP | B2: One row for each thing you do, logged the same day. Start typing on row 4 — the sheet ships empty, and a worked example for this log is on TEAM GUIDE. YOUR DATA STARTS ON ROW 7 — the grey rows above it are examples.
A3: Date | B3: Your name | C3: Platform | D3: What kind of work | E3: What exactly did you do? | F3: How many (optional) | G3: Minutes spent | H3: Link / proof (optional) | I3: Result (optional) | J3: Notes or blocker (optional) | K3: First entry of day (auto — leave) | L3: First of day for this person (auto — leave) | M3: Objective | N3: For (brand)
K4: =IF($A4="",0,IF(COUNTIF($A$4:$A4,$A4)=1,1,0)) -> 0 | L4: =IF($A4="",0,IF(COUNTIFS($A$4:$A4,$A4,$B$4:$B4,$B4)=1,1,0)) -> 0
K5: =IF($A5="",0,IF(COUNTIF($A$4:$A5,$A5)=1,1,0)) -> 0 | L5: =IF($A5="",0,IF(COUNTIFS($A$4:$A5,$A5,$B$4:$B5,$B5)=1,1,0)) -> 0
K6: =IF($A6="",0,IF(COUNTIF($A$4:$A6,$A6)=1,1,0)) -> 0 | L6: =IF($A6="",0,IF(COUNTIFS($A$4:$A6,$A6,$B$4:$B6,$B6)=1,1,0)) -> 0
K7: =IF($A7="",0,IF(COUNTIF($A$4:$A7,$A7)=1,1,0)) -> 0 | L7: =IF($A7="",0,IF(COUNTIFS($A$4:$A7,$A7,$B$4:$B7,$B7)=1,1,0)) -> 0
K8: =IF($A8="",0,IF(COUNTIF($A$4:$A8,$A8)=1,1,0)) -> 0 | L8: =IF($A8="",0,IF(COUNTIFS($A$4:$A8,$A8,$B$4:$B8,$B8)=1,1,0)) -> 0
K9: =IF($A9="",0,IF(COUNTIF($A$4:$A9,$A9)=1,1,0)) -> 0 | L9: =IF($A9="",0,IF(COUNTIFS($A$4:$A9,$A9,$B$4:$B9,$B9)=1,1,0)) -> 0
K10: =IF($A10="",0,IF(COUNTIF($A$4:$A10,$A10)=1,1,0)) -> 0 | L10: =IF($A10="",0,IF(COUNTIFS($A$4:$A10,$A10,$B$4:$B10,$B10)=1,1,0)) -> 0
K11: =IF($A11="",0,IF(COUNTIF($A$4:$A11,$A11)=1,1,0)) -> 0 | L11: =IF($A11="",0,IF(COUNTIFS($A$4:$A11,$A11,$B$4:$B11,$B11)=1,1,0)) -> 0
K12: =IF($A12="",0,IF(COUNTIF($A$4:$A12,$A12)=1,1,0)) -> 0 | L12: =IF($A12="",0,IF(COUNTIFS($A$4:$A12,$A12,$B$4:$B12,$B12)=1,1,0)) -> 0
K13: =IF($A13="",0,IF(COUNTIF($A$4:$A13,$A13)=1,1,0)) -> 0 | L13: =IF($A13="",0,IF(COUNTIFS($A$4:$A13,$A13,$B$4:$B13,$B13)=1,1,0)) -> 0
K14: =IF($A14="",0,IF(COUNTIF($A$4:$A14,$A14)=1,1,0)) -> 0 | L14: =IF($A14="",0,IF(COUNTIFS($A$4:$A14,$A14,$B$4:$B14,$B14)=1,1,0)) -> 0
K15: =IF($A15="",0,IF(COUNTIF($A$4:$A15,$A15)=1,1,0)) -> 0 | L15: =IF($A15="",0,IF(COUNTIFS($A$4:$A15,$A15,$B$4:$B15,$B15)=1,1,0)) -> 0
... K1006: =IF($A1006="",0,IF(COUNTIF($A$4:$A1006,$A1006)=1,1,0)) -> 0 | L1006: =IF($A1006="",0,IF(COUNTIFS($A$4:$A1006,$A1006,$B$4:$B1006,$B1006)=1,1,0)) -> 0
A1007: LAST ROW — anything typed below this line is invisible to every report. Archive a dated copy and start a new file.

Sheet LinkedIn Outreach
A1: LINKEDIN + SALES NAVIGATOR OUTREACH LOG — one row per person
A2: ◀ MAP | B2: Log every lead the same day. Fill A-L when you research the lead; M-T when you send and hear back; Y-Z when you score it; AD onward only if it becomes a meeting or a sale; AO-AP (Objective and For (brand)) always. Column AN flags a duplicate the moment you paste a URL that is already in the sheet — check it before you write anything else.
A3: Date | B3: Employee | C3: Lead name | D3: LinkedIn / Sales Nav URL | E3: Company | F3: Job title | G3: Country | H3: Lead segment | I3: Sales Nav list | J3: Years exp. | K3: Qualified? | L3: Personal line used (from their profile) | M3: Connection sent? | N3: Accepted? | O3: Template used | P3: Message sent (paste the final text) | Q3: Chars | R3: Message sent? | S3: Outcome | T3: Reply summary | U3: Follow-up due | V3: Follow-ups sent | W3: Next action | X3: Notes | Y3: ICP fit (1-5) | Z3: Intent signals (1-5) | AA3: Lead score (auto) | AB3: Priority band | AC3: Funnel stage (auto) | AD3: Accepted date | AE3: Message sent date | AF3: Follow-up 2 due (auto) | AG3: Meeting date | AH3: Handed to (PCI closer) | AI3: Application date | AJ3: Certification | AK3: Purchase date | AL3: Revenue | AM3: PCI order / application ref | AN3: Duplicate? (auto) | AO3: Objective | AP3: For (brand)
K4: =IF(J4="","",IF(J4>=8,"Yes","Check")) | Q4: =IF(P4="","",LEN(P4)) | U4: =IF($AE4<>"",$AE4+4,IF(OR(R4<>"Yes",A4=""),"",A4+4)) | AA4: =IF(AND($Y4="",$Z4=""),"",ROUND(IFERROR(VALUE(LEFT($Y4,1)),0)*12+IFERROR(VALUE(LEFT($Z4,1)),0)*8,0)) | AB4: =IF($AA4="","",IF($AA4>=80,"A - call first",IF($AA4>=60,"B - worth pursuing",IF($AA4>=40,"C - nurture","D - do not spend time here")))) | AC4: =IF($C4="","",IF($S4="Converted","8 Won / Certified",IF($S4="Application Started","7 Certification / Enterprise opportunity",IF($S4="Meeting Booked","6 Meeting / Application",IF(OR($S4="Interested",$S4="Info Requested"),"5 Interested",IF(OR($S4="Declined",$S4="Not Relevant",$S4="Do Not Contact / Unsubscribed"),"9 Closed - Lost",IF($R4="Yes","4 Contacted",IF($N4="Yes","2 Engaged",IF($M4="Yes","1 Awareness",IF($AA4>=60,"3 Qualified","1 Awareness")))))))))) | AF4: =IF($AE4="","",$AE4+10) | AN4: =IF($D4="","",IF(COUNTIF($D$4:$D$1203,$D4)>1,"DUPLICATE — check earlier row",""))
K5: =IF(J5="","",IF(J5>=8,"Yes","Check")) | Q5: =IF(P5="","",LEN(P5)) | U5: =IF($AE5<>"",$AE5+4,IF(OR(R5<>"Yes",A5=""),"",A5+4)) | AA5: =IF(AND($Y5="",$Z5=""),"",ROUND(IFERROR(VALUE(LEFT($Y5,1)),0)*12+IFERROR(VALUE(LEFT($Z5,1)),0)*8,0)) | AB5: =IF($AA5="","",IF($AA5>=80,"A - call first",IF($AA5>=60,"B - worth pursuing",IF($AA5>=40,"C - nurture","D - do not spend time here")))) | AC5: =IF($C5="","",IF($S5="Converted","8 Won / Certified",IF($S5="Application Started","7 Certification / Enterprise opportunity",IF($S5="Meeting Booked","6 Meeting / Application",IF(OR($S5="Interested",$S5="Info Requested"),"5 Interested",IF(OR($S5="Declined",$S5="Not Relevant",$S5="Do Not Contact / Unsubscribed"),"9 Closed - Lost",IF($R5="Yes","4 Contacted",IF($N5="Yes","2 Engaged",IF($M5="Yes","1 Awareness",IF($AA5>=60,"3 Qualified","1 Awareness")))))))))) | AF5: =IF($AE5="","",$AE5+10) | AN5: =IF($D5="","",IF(COUNTIF($D$4:$D$1203,$D5)>1,"DUPLICATE — check earlier row",""))
K6: =IF(J6="","",IF(J6>=8,"Yes","Check")) | Q6: =IF(P6="","",LEN(P6)) | U6: =IF($AE6<>"",$AE6+4,IF(OR(R6<>"Yes",A6=""),"",A6+4)) | AA6: =IF(AND($Y6="",$Z6=""),"",ROUND(IFERROR(VALUE(LEFT($Y6,1)),0)*12+IFERROR(VALUE(LEFT($Z6,1)),0)*8,0)) | AB6: =IF($AA6="","",IF($AA6>=80,"A - call first",IF($AA6>=60,"B - worth pursuing",IF($AA6>=40,"C - nurture","D - do not spend time here")))) | AC6: =IF($C6="","",IF($S6="Converted","8 Won / Certified",IF($S6="Application Started","7 Certification / Enterprise opportunity",IF($S6="Meeting Booked","6 Meeting / Application",IF(OR($S6="Interested",$S6="Info Requested"),"5 Interested",IF(OR($S6="Declined",$S6="Not Relevant",$S6="Do Not Contact / Unsubscribed"),"9 Closed - Lost",IF($R6="Yes","4 Contacted",IF($N6="Yes","2 Engaged",IF($M6="Yes","1 Awareness",IF($AA6>=60,"3 Qualified","1 Awareness")))))))))) | AF6: =IF($AE6="","",$AE6+10) | AN6: =IF($D6="","",IF(COUNTIF($D$4:$D$1203,$D6)>1,"DUPLICATE — check earlier row",""))
K7: =IF(J7="","",IF(J7>=8,"Yes","Check")) | Q7: =IF(P7="","",LEN(P7)) | U7: =IF($AE7<>"",$AE7+4,IF(OR(R7<>"Yes",A7=""),"",A7+4)) | AA7: =IF(AND($Y7="",$Z7=""),"",ROUND(IFERROR(VALUE(LEFT($Y7,1)),0)*12+IFERROR(VALUE(LEFT($Z7,1)),0)*8,0)) | AB7: =IF($AA7="","",IF($AA7>=80,"A - call first",IF($AA7>=60,"B - worth pursuing",IF($AA7>=40,"C - nurture","D - do not spend time here")))) | AC7: =IF($C7="","",IF($S7="Converted","8 Won / Certified",IF($S7="Application Started","7 Certification / Enterprise opportunity",IF($S7="Meeting Booked","6 Meeting / Application",IF(OR($S7="Interested",$S7="Info Requested"),"5 Interested",IF(OR($S7="Declined",$S7="Not Relevant",$S7="Do Not Contact / Unsubscribed"),"9 Closed - Lost",IF($R7="Yes","4 Contacted",IF($N7="Yes","2 Engaged",IF($M7="Yes","1 Awareness",IF($AA7>=60,"3 Qualified","1 Awareness")))))))))) | AF7: =IF($AE7="","",$AE7+10) | AN7: =IF($D7="","",IF(COUNTIF($D$4:$D$1203,$D7)>1,"DUPLICATE — check earlier row",""))
K8: =IF(J8="","",IF(J8>=8,"Yes","Check")) | Q8: =IF(P8="","",LEN(P8)) | U8: =IF($AE8<>"",$AE8+4,IF(OR(R8<>"Yes",A8=""),"",A8+4)) | AA8: =IF(AND($Y8="",$Z8=""),"",ROUND(IFERROR(VALUE(LEFT($Y8,1)),0)*12+IFERROR(VALUE(LEFT($Z8,1)),0)*8,0)) | AB8: =IF($AA8="","",IF($AA8>=80,"A - call first",IF($AA8>=60,"B - worth pursuing",IF($AA8>=40,"C - nurture","D - do not spend time here")))) | AC8: =IF($C8="","",IF($S8="Converted","8 Won / Certified",IF($S8="Application Started","7 Certification / Enterprise opportunity",IF($S8="Meeting Booked","6 Meeting / Application",IF(OR($S8="Interested",$S8="Info Requested"),"5 Interested",IF(OR($S8="Declined",$S8="Not Relevant",$S8="Do Not Contact / Unsubscribed"),"9 Closed - Lost",IF($R8="Yes","4 Contacted",IF($N8="Yes","2 Engaged",IF($M8="Yes","1 Awareness",IF($AA8>=60,"3 Qualified","1 Awareness")))))))))) | AF8: =IF($AE8="","",$AE8+10) | AN8: =IF($D8="","",IF(COUNTIF($D$4:$D$1203,$D8)>1,"DUPLICATE — check earlier row",""))
K9: =IF(J9="","",IF(J9>=8,"Yes","Check")) | Q9: =IF(P9="","",LEN(P9)) | U9: =IF($AE9<>"",$AE9+4,IF(OR(R9<>"Yes",A9=""),"",A9+4)) | AA9: =IF(AND($Y9="",$Z9=""),"",ROUND(IFERROR(VALUE(LEFT($Y9,1)),0)*12+IFERROR(VALUE(LEFT($Z9,1)),0)*8,0)) | AB9: =IF($AA9="","",IF($AA9>=80,"A - call first",IF($AA9>=60,"B - worth pursuing",IF($AA9>=40,"C - nurture","D - do not spend time here")))) | AC9: =IF($C9="","",IF($S9="Converted","8 Won / Certified",IF($S9="Application Started","7 Certification / Enterprise opportunity",IF($S9="Meeting Booked","6 Meeting / Application",IF(OR($S9="Interested",$S9="Info Requested"),"5 Interested",IF(OR($S9="Declined",$S9="Not Relevant",$S9="Do Not Contact / Unsubscribed"),"9 Closed - Lost",IF($R9="Yes","4 Contacted",IF($N9="Yes","2 Engaged",IF($M9="Yes","1 Awareness",IF($AA9>=60,"3 Qualified","1 Awareness")))))))))) | AF9: =IF($AE9="","",$AE9+10) | AN9: =IF($D9="","",IF(COUNTIF($D$4:$D$1203,$D9)>1,"DUPLICATE — check earlier row",""))
K10: =IF(J10="","",IF(J10>=8,"Yes","Check")) | Q10: =IF(P10="","",LEN(P10)) | U10: =IF($AE10<>"",$AE10+4,IF(OR(R10<>"Yes",A10=""),"",A10+4)) | AA10: =IF(AND($Y10="",$Z10=""),"",ROUND(IFERROR(VALUE(LEFT($Y10,1)),0)*12+IFERROR(VALUE(LEFT($Z10,1)),0)*8,0)) | AB10: =IF($AA10="","",IF($AA10>=80,"A - call first",IF($AA10>=60,"B - worth pursuing",IF($AA10>=40,"C - nurture","D - do not spend time here")))) | AC10: =IF($C10="","",IF($S10="Converted","8 Won / Certified",IF($S10="Application Started","7 Certification / Enterprise opportunity",IF($S10="Meeting Booked","6 Meeting / Application",IF(OR($S10="Interested",$S10="Info Requested"),"5 Interested",IF(OR($S10="Declined",$S10="Not Relevant",$S10="Do Not Contact / Unsubscribed"),"9 Closed - Lost",IF($R10="Yes","4 Contacted",IF($N10="Yes","2 Engaged",IF($M10="Yes","1 Awareness",IF($AA10>=60,"3 Qualified","1 Awareness")))))))))) | AF10: =IF($AE10="","",$AE10+10) | AN10: =IF($D10="","",IF(COUNTIF($D$4:$D$1203,$D10)>1,"DUPLICATE — check earlier row",""))
K11: =IF(J11="","",IF(J11>=8,"Yes","Check")) | Q11: =IF(P11="","",LEN(P11)) | U11: =IF($AE11<>"",$AE11+4,IF(OR(R11<>"Yes",A11=""),"",A11+4)) | AA11: =IF(AND($Y11="",$Z11=""),"",ROUND(IFERROR(VALUE(LEFT($Y11,1)),0)*12+IFERROR(VALUE(LEFT($Z11,1)),0)*8,0)) | AB11: =IF($AA11="","",IF($AA11>=80,"A - call first",IF($AA11>=60,"B - worth pursuing",IF($AA11>=40,"C - nurture","D - do not spend time here")))) | AC11: =IF($C11="","",IF($S11="Converted","8 Won / Certified",IF($S11="Application Started","7 Certification / Enterprise opportunity",IF($S11="Meeting Booked","6 Meeting / Application",IF(OR($S11="Interested",$S11="Info Requested"),"5 Interested",IF(OR($S11="Declined",$S11="Not Relevant",$S11="Do Not Contact / Unsubscribed"),"9 Closed - Lost",IF($R11="Yes","4 Contacted",IF($N11="Yes","2 Engaged",IF($M11="Yes","1 Awareness",IF($AA11>=60,"3 Qualified","1 Awareness")))))))))) | AF11: =IF($AE11="","",$AE11+10) | AN11: =IF($D11="","",IF(COUNTIF($D$4:$D$1203,$D11)>1,"DUPLICATE — check earlier row",""))
K12: =IF(J12="","",IF(J12>=8,"Yes","Check")) | Q12: =IF(P12="","",LEN(P12)) | U12: =IF($AE12<>"",$AE12+4,IF(OR(R12<>"Yes",A12=""),"",A12+4)) | AA12: =IF(AND($Y12="",$Z12=""),"",ROUND(IFERROR(VALUE(LEFT($Y12,1)),0)*12+IFERROR(VALUE(LEFT($Z12,1)),0)*8,0)) | AB12: =IF($AA12="","",IF($AA12>=80,"A - call first",IF($AA12>=60,"B - worth pursuing",IF($AA12>=40,"C - nurture","D - do not spend time here")))) | AC12: =IF($C12="","",IF($S12="Converted","8 Won / Certified",IF($S12="Application Started","7 Certification / Enterprise opportunity",IF($S12="Meeting Booked","6 Meeting / Application",IF(OR($S12="Interested",$S12="Info Requested"),"5 Interested",IF(OR($S12="Declined",$S12="Not Relevant",$S12="Do Not Contact / Unsubscribed"),"9 Closed - Lost",IF($R12="Yes","4 Contacted",IF($N12="Yes","2 Engaged",IF($M12="Yes","1 Awareness",IF($AA12>=60,"3 Qualified","1 Awareness")))))))))) | AF12: =IF($AE12="","",$AE12+10) | AN12: =IF($D12="","",IF(COUNTIF($D$4:$D$1203,$D12)>1,"DUPLICATE — check earlier row",""))
K13: =IF(J13="","",IF(J13>=8,"Yes","Check")) | Q13: =IF(P13="","",LEN(P13)) | U13: =IF($AE13<>"",$AE13+4,IF(OR(R13<>"Yes",A13=""),"",A13+4)) | AA13: =IF(AND($Y13="",$Z13=""),"",ROUND(IFERROR(VALUE(LEFT($Y13,1)),0)*12+IFERROR(VALUE(LEFT($Z13,1)),0)*8,0)) | AB13: =IF($AA13="","",IF($AA13>=80,"A - call first",IF($AA13>=60,"B - worth pursuing",IF($AA13>=40,"C - nurture","D - do not spend time here")))) | AC13: =IF($C13="","",IF($S13="Converted","8 Won / Certified",IF($S13="Application Started","7 Certification / Enterprise opportunity",IF($S13="Meeting Booked","6 Meeting / Application",IF(OR($S13="Interested",$S13="Info Requested"),"5 Interested",IF(OR($S13="Declined",$S13="Not Relevant",$S13="Do Not Contact / Unsubscribed"),"9 Closed - Lost",IF($R13="Yes","4 Contacted",IF($N13="Yes","2 Engaged",IF($M13="Yes","1 Awareness",IF($AA13>=60,"3 Qualified","1 Awareness")))))))))) | AF13: =IF($AE13="","",$AE13+10) | AN13: =IF($D13="","",IF(COUNTIF($D$4:$D$1203,$D13)>1,"DUPLICATE — check earlier row",""))
K14: =IF(J14="","",IF(J14>=8,"Yes","Check")) | Q14: =IF(P14="","",LEN(P14)) | U14: =IF($AE14<>"",$AE14+4,IF(OR(R14<>"Yes",A14=""),"",A14+4)) | AA14: =IF(AND($Y14="",$Z14=""),"",ROUND(IFERROR(VALUE(LEFT($Y14,1)),0)*12+IFERROR(VALUE(LEFT($Z14,1)),0)*8,0)) | AB14: =IF($AA14="","",IF($AA14>=80,"A - call first",IF($AA14>=60,"B - worth pursuing",IF($AA14>=40,"C - nurture","D - do not spend time here")))) | AC14: =IF($C14="","",IF($S14="Converted","8 Won / Certified",IF($S14="Application Started","7 Certification / Enterprise opportunity",IF($S14="Meeting Booked","6 Meeting / Application",IF(OR($S14="Interested",$S14="Info Requested"),"5 Interested",IF(OR($S14="Declined",$S14="Not Relevant",$S14="Do Not Contact / Unsubscribed"),"9 Closed - Lost",IF($R14="Yes","4 Contacted",IF($N14="Yes","2 Engaged",IF($M14="Yes","1 Awareness",IF($AA14>=60,"3 Qualified","1 Awareness")))))))))) | AF14: =IF($AE14="","",$AE14+10) | AN14: =IF($D14="","",IF(COUNTIF($D$4:$D$1203,$D14)>1,"DUPLICATE — check earlier row",""))
K15: =IF(J15="","",IF(J15>=8,"Yes","Check")) | Q15: =IF(P15="","",LEN(P15)) | U15: =IF($AE15<>"",$AE15+4,IF(OR(R15<>"Yes",A15=""),"",A15+4)) | AA15: =IF(AND($Y15="",$Z15=""),"",ROUND(IFERROR(VALUE(LEFT($Y15,1)),0)*12+IFERROR(VALUE(LEFT($Z15,1)),0)*8,0)) | AB15: =IF($AA15="","",IF($AA15>=80,"A - call first",IF($AA15>=60,"B - worth pursuing",IF($AA15>=40,"C - nurture","D - do not spend time here")))) | AC15: =IF($C15="","",IF($S15="Converted","8 Won / Certified",IF($S15="Application Started","7 Certification / Enterprise opportunity",IF($S15="Meeting Booked","6 Meeting / Application",IF(OR($S15="Interested",$S15="Info Requested"),"5 Interested",IF(OR($S15="Declined",$S15="Not Relevant",$S15="Do Not Contact / Unsubscribed"),"9 Closed - Lost",IF($R15="Yes","4 Contacted",IF($N15="Yes","2 Engaged",IF($M15="Yes","1 Awareness",IF($AA15>=60,"3 Qualified","1 Awareness")))))))))) | AF15: =IF($AE15="","",$AE15+10) | AN15: =IF($D15="","",IF(COUNTIF($D$4:$D$1203,$D15)>1,"DUPLICATE — check earlier row",""))
... K1203: =IF(J1203="","",IF(J1203>=8,"Yes","Check")) | Q1203: =IF(P1203="","",LEN(P1203)) | U1203: =IF($AE1203<>"",$AE1203+4,IF(OR(R1203<>"Yes",A1203=""),"",A1203+4)) | AA1203: =IF(AND($Y1203="",$Z1203=""),"",ROUND(IFERROR(VALUE(LEFT($Y1203,1)),0)*12+IFERROR(VALUE(LEFT($Z1203,1)),0)*8,0)) | AB1203: =IF($AA1203="","",IF($AA1203>=80,"A - call first",IF($AA1203>=60,"B - worth pursuing",IF($AA1203>=40,"C - nurture","D - do not spend time here")))) | AC1203: =IF($C1203="","",IF($S1203="Converted","8 Won / Certified",IF($S1203="Application Started","7 Certification / Enterprise opportunity",IF($S1203="Meeting Booked","6 Meeting / Application",IF(OR($S1203="Interested",$S1203="Info Requested"),"5 Interested",IF(OR($S1203="Declined",$S1203="Not Relevant",$S1203="Do Not Contact / Unsubscribed"),"9 Closed - Lost",IF($R1203="Yes","4 Contacted",IF($N1203="Yes","2 Engaged",IF($M1203="Yes","1 Awareness",IF($AA1203>=60,"3 Qualified","1 Awareness")))))))))) | AF1203: =IF($AE1203="","",$AE1203+10) | AN1203: =IF($D1203="","",IF(COUNTIF($D$4:$D$1203,$D1203)>1,"DUPLICATE — check earlier row",""))
A1204: LAST ROW — anything typed below this line is invisible to every report. Archive a dated copy and start a new file.

Sheet Partnership Pipeline
A1: PARTNERSHIP PIPELINE — employers, universities, associations, influencers, media
A2: ◀ MAP | B2: One row per organisation. The grey row below the headers is an EXAMPLE — right-click its row number and Delete row before live use. Your data starts on the first white row.
A3: Date opened | B3: Owner | C3: Organisation | D3: Type | E3: Country | F3: Contact name | G3: Contact role | H3: LinkedIn / URL | I3: Why them (the fit) | J3: ICP fit (1-5) | K3: Intent signals (1-5) | L3: Score (auto) | M3: Band (auto) | N3: Stage | O3: Potential value | P3: What they get | Q3: Last contact | R3: Next step | S3: Next step due | T3: Status | U3: Notes | V3: Deal value (number) | W3: Contract signed date | X3: Objective | Y3: For (brand)
L4: =IF(AND($J4="",$K4=""),"",ROUND(IFERROR(VALUE(LEFT($J4,1)),0)*12+IFERROR(VALUE(LEFT($K4,1)),0)*8,0)) | M4: =IF($L4="","",IF($L4>=80,"A - pursue now",IF($L4>=60,"B - worth pursuing",IF($L4>=40,"C - nurture","D - park it"))))
L5: =IF(AND($J5="",$K5=""),"",ROUND(IFERROR(VALUE(LEFT($J5,1)),0)*12+IFERROR(VALUE(LEFT($K5,1)),0)*8,0)) | M5: =IF($L5="","",IF($L5>=80,"A - pursue now",IF($L5>=60,"B - worth pursuing",IF($L5>=40,"C - nurture","D - park it"))))
L6: =IF(AND($J6="",$K6=""),"",ROUND(IFERROR(VALUE(LEFT($J6,1)),0)*12+IFERROR(VALUE(LEFT($K6,1)),0)*8,0)) | M6: =IF($L6="","",IF($L6>=80,"A - pursue now",IF($L6>=60,"B - worth pursuing",IF($L6>=40,"C - nurture","D - park it"))))
L7: =IF(AND($J7="",$K7=""),"",ROUND(IFERROR(VALUE(LEFT($J7,1)),0)*12+IFERROR(VALUE(LEFT($K7,1)),0)*8,0)) | M7: =IF($L7="","",IF($L7>=80,"A - pursue now",IF($L7>=60,"B - worth pursuing",IF($L7>=40,"C - nurture","D - park it"))))
L8: =IF(AND($J8="",$K8=""),"",ROUND(IFERROR(VALUE(LEFT($J8,1)),0)*12+IFERROR(VALUE(LEFT($K8,1)),0)*8,0)) | M8: =IF($L8="","",IF($L8>=80,"A - pursue now",IF($L8>=60,"B - worth pursuing",IF($L8>=40,"C - nurture","D - park it"))))
L9: =IF(AND($J9="",$K9=""),"",ROUND(IFERROR(VALUE(LEFT($J9,1)),0)*12+IFERROR(VALUE(LEFT($K9,1)),0)*8,0)) | M9: =IF($L9="","",IF($L9>=80,"A - pursue now",IF($L9>=60,"B - worth pursuing",IF($L9>=40,"C - nurture","D - park it"))))
L10: =IF(AND($J10="",$K10=""),"",ROUND(IFERROR(VALUE(LEFT($J10,1)),0)*12+IFERROR(VALUE(LEFT($K10,1)),0)*8,0)) | M10: =IF($L10="","",IF($L10>=80,"A - pursue now",IF($L10>=60,"B - worth pursuing",IF($L10>=40,"C - nurture","D - park it"))))
L11: =IF(AND($J11="",$K11=""),"",ROUND(IFERROR(VALUE(LEFT($J11,1)),0)*12+IFERROR(VALUE(LEFT($K11,1)),0)*8,0)) | M11: =IF($L11="","",IF($L11>=80,"A - pursue now",IF($L11>=60,"B - worth pursuing",IF($L11>=40,"C - nurture","D - park it"))))
L12: =IF(AND($J12="",$K12=""),"",ROUND(IFERROR(VALUE(LEFT($J12,1)),0)*12+IFERROR(VALUE(LEFT($K12,1)),0)*8,0)) | M12: =IF($L12="","",IF($L12>=80,"A - pursue now",IF($L12>=60,"B - worth pursuing",IF($L12>=40,"C - nurture","D - park it"))))
L13: =IF(AND($J13="",$K13=""),"",ROUND(IFERROR(VALUE(LEFT($J13,1)),0)*12+IFERROR(VALUE(LEFT($K13,1)),0)*8,0)) | M13: =IF($L13="","",IF($L13>=80,"A - pursue now",IF($L13>=60,"B - worth pursuing",IF($L13>=40,"C - nurture","D - park it"))))
L14: =IF(AND($J14="",$K14=""),"",ROUND(IFERROR(VALUE(LEFT($J14,1)),0)*12+IFERROR(VALUE(LEFT($K14,1)),0)*8,0)) | M14: =IF($L14="","",IF($L14>=80,"A - pursue now",IF($L14>=60,"B - worth pursuing",IF($L14>=40,"C - nurture","D - park it"))))
L15: =IF(AND($J15="",$K15=""),"",ROUND(IFERROR(VALUE(LEFT($J15,1)),0)*12+IFERROR(VALUE(LEFT($K15,1)),0)*8,0)) | M15: =IF($L15="","",IF($L15>=80,"A - pursue now",IF($L15>=60,"B - worth pursuing",IF($L15>=40,"C - nurture","D - park it"))))
... L403: =IF(AND($J403="",$K403=""),"",ROUND(IFERROR(VALUE(LEFT($J403,1)),0)*12+IFERROR(VALUE(LEFT($K403,1)),0)*8,0)) | M403: =IF($L403="","",IF($L403>=80,"A - pursue now",IF($L403>=60,"B - worth pursuing",IF($L403>=40,"C - nurture","D - park it"))))
A404: LAST ROW — anything typed below this line is invisible to every report. Archive a dated copy and start a new file.

Sheet Content Calendar
A1: CONTENT CALENDAR — plan, publish and measure every post on every platform
A2: ◀ MAP | B2: Plan the week ahead every Monday. Row 4 is a worked example - your data starts on row 5. Fill in the results columns 7 days after publishing.
A3: Plan date | B3: Employee | C3: Platform | D3: Content type | E3: Topic / title | F3: Objective | G3: Hook / first line | H3: Call to action | I3: Asset link (Canva / Drive) | J3: Status | K3: Published date | L3: Published URL | M3: Impressions | N3: Engagements | O3: Clicks | P3: Leads | Q3: Repurpose to | R3: Notes | S3: For (brand)
A404: LAST ROW — anything typed below this line is invisible to every report. Archive a dated copy and start a new file.

Sheet Content Scheduler
A1: CONTENT SCHEDULER — what runs where, at what cadence, fully tracked
A2: ◀ MAP | B2: One row per running schedule (platform × cadence × window). Planned posts and published-in-window compute live from this row and the Content Calendar — coverage below 100% means the schedule is slipping. The reference table under the grid says which platforms support scheduling, where, and with what limits (researched Aug 2026). Dashboard shows active schedules and coverage.
A3: Platform | B3: For (brand) | C3: Objective | D3: Cadence | E3: Posts per cycle | F3: Content format | G3: Scheduling tool | H3: Start date | I3: End date | J3: Planned posts (auto) | K3: Published in window (auto) | L3: Coverage (auto) | M3: Owner | N3: Status | O3: Notes
J4: =IF(OR($H4="",$I4="",$D4="",$I4<$H4),"",ROUND((($I4-$H4)+1)/IF($D4="Daily",1,IF($D4="3x Weekly",7/3,IF($D4="Weekly",7,IF($D4="Fortnightly",14,IF($D4="Monthly",30.44,1000000)))))*IF($E4="",1,$E4),0)) | K4: =IF(OR($A4="",$H4="",$I4="",$I4<$H4),"",SUMPRODUCT(('Content Calendar'!$C$4:$C$403=$A4)*ISNUMBER('Content Calendar'!$K$4:$K$403)*('Content Calendar'!$K$4:$K$403>=$H4)*('Content Calendar'!$K$4:$K$403<=$I4)*((($B4="")+('Content Calendar'!$S$4:$S$403=$B4))>0)*((($C4="")+('Content Calendar'!$F$4:$F$403=$C4))>0))) | L4: =IF(OR($J4="",$K4="",N($J4)<=0),"",$K4/$J4)
J5: =IF(OR($H5="",$I5="",$D5="",$I5<$H5),"",ROUND((($I5-$H5)+1)/IF($D5="Daily",1,IF($D5="3x Weekly",7/3,IF($D5="Weekly",7,IF($D5="Fortnightly",14,IF($D5="Monthly",30.44,1000000)))))*IF($E5="",1,$E5),0)) | K5: =IF(OR($A5="",$H5="",$I5="",$I5<$H5),"",SUMPRODUCT(('Content Calendar'!$C$4:$C$403=$A5)*ISNUMBER('Content Calendar'!$K$4:$K$403)*('Content Calendar'!$K$4:$K$403>=$H5)*('Content Calendar'!$K$4:$K$403<=$I5)*((($B5="")+('Content Calendar'!$S$4:$S$403=$B5))>0)*((($C5="")+('Content Calendar'!$F$4:$F$403=$C5))>0))) | L5: =IF(OR($J5="",$K5="",N($J5)<=0),"",$K5/$J5)
J6: =IF(OR($H6="",$I6="",$D6="",$I6<$H6),"",ROUND((($I6-$H6)+1)/IF($D6="Daily",1,IF($D6="3x Weekly",7/3,IF($D6="Weekly",7,IF($D6="Fortnightly",14,IF($D6="Monthly",30.44,1000000)))))*IF($E6="",1,$E6),0)) | K6: =IF(OR($A6="",$H6="",$I6="",$I6<$H6),"",SUMPRODUCT(('Content Calendar'!$C$4:$C$403=$A6)*ISNUMBER('Content Calendar'!$K$4:$K$403)*('Content Calendar'!$K$4:$K$403>=$H6)*('Content Calendar'!$K$4:$K$403<=$I6)*((($B6="")+('Content Calendar'!$S$4:$S$403=$B6))>0)*((($C6="")+('Content Calendar'!$F$4:$F$403=$C6))>0))) | L6: =IF(OR($J6="",$K6="",N($J6)<=0),"",$K6/$J6)
J7: =IF(OR($H7="",$I7="",$D7="",$I7<$H7),"",ROUND((($I7-$H7)+1)/IF($D7="Daily",1,IF($D7="3x Weekly",7/3,IF($D7="Weekly",7,IF($D7="Fortnightly",14,IF($D7="Monthly",30.44,1000000)))))*IF($E7="",1,$E7),0)) | K7: =IF(OR($A7="",$H7="",$I7="",$I7<$H7),"",SUMPRODUCT(('Content Calendar'!$C$4:$C$403=$A7)*ISNUMBER('Content Calendar'!$K$4:$K$403)*('Content Calendar'!$K$4:$K$403>=$H7)*('Content Calendar'!$K$4:$K$403<=$I7)*((($B7="")+('Content Calendar'!$S$4:$S$403=$B7))>0)*((($C7="")+('Content Calendar'!$F$4:$F$403=$C7))>0))) | L7: =IF(OR($J7="",$K7="",N($J7)<=0),"",$K7/$J7)
J8: =IF(OR($H8="",$I8="",$D8="",$I8<$H8),"",ROUND((($I8-$H8)+1)/IF($D8="Daily",1,IF($D8="3x Weekly",7/3,IF($D8="Weekly",7,IF($D8="Fortnightly",14,IF($D8="Monthly",30.44,1000000)))))*IF($E8="",1,$E8),0)) | K8: =IF(OR($A8="",$H8="",$I8="",$I8<$H8),"",SUMPRODUCT(('Content Calendar'!$C$4:$C$403=$A8)*ISNUMBER('Content Calendar'!$K$4:$K$403)*('Content Calendar'!$K$4:$K$403>=$H8)*('Content Calendar'!$K$4:$K$403<=$I8)*((($B8="")+('Content Calendar'!$S$4:$S$403=$B8))>0)*((($C8="")+('Content Calendar'!$F$4:$F$403=$C8))>0))) | L8: =IF(OR($J8="",$K8="",N($J8)<=0),"",$K8/$J8)
J9: =IF(OR($H9="",$I9="",$D9="",$I9<$H9),"",ROUND((($I9-$H9)+1)/IF($D9="Daily",1,IF($D9="3x Weekly",7/3,IF($D9="Weekly",7,IF($D9="Fortnightly",14,IF($D9="Monthly",30.44,1000000)))))*IF($E9="",1,$E9),0)) | K9: =IF(OR($A9="",$H9="",$I9="",$I9<$H9),"",SUMPRODUCT(('Content Calendar'!$C$4:$C$403=$A9)*ISNUMBER('Content Calendar'!$K$4:$K$403)*('Content Calendar'!$K$4:$K$403>=$H9)*('Content Calendar'!$K$4:$K$403<=$I9)*((($B9="")+('Content Calendar'!$S$4:$S$403=$B9))>0)*((($C9="")+('Content Calendar'!$F$4:$F$403=$C9))>0))) | L9: =IF(OR($J9="",$K9="",N($J9)<=0),"",$K9/$J9)
J10: =IF(OR($H10="",$I10="",$D10="",$I10<$H10),"",ROUND((($I10-$H10)+1)/IF($D10="Daily",1,IF($D10="3x Weekly",7/3,IF($D10="Weekly",7,IF($D10="Fortnightly",14,IF($D10="Monthly",30.44,1000000)))))*IF($E10="",1,$E10),0)) | K10: =IF(OR($A10="",$H10="",$I10="",$I10<$H10),"",SUMPRODUCT(('Content Calendar'!$C$4:$C$403=$A10)*ISNUMBER('Content Calendar'!$K$4:$K$403)*('Content Calendar'!$K$4:$K$403>=$H10)*('Content Calendar'!$K$4:$K$403<=$I10)*((($B10="")+('Content Calendar'!$S$4:$S$403=$B10))>0)*((($C10="")+('Content Calendar'!$F$4:$F$403=$C10))>0))) | L10: =IF(OR($J10="",$K10="",N($J10)<=0),"",$K10/$J10)
J11: =IF(OR($H11="",$I11="",$D11="",$I11<$H11),"",ROUND((($I11-$H11)+1)/IF($D11="Daily",1,IF($D11="3x Weekly",7/3,IF($D11="Weekly",7,IF($D11="Fortnightly",14,IF($D11="Monthly",30.44,1000000)))))*IF($E11="",1,$E11),0)) | K11: =IF(OR($A11="",$H11="",$I11="",$I11<$H11),"",SUMPRODUCT(('Content Calendar'!$C$4:$C$403=$A11)*ISNUMBER('Content Calendar'!$K$4:$K$403)*('Content Calendar'!$K$4:$K$403>=$H11)*('Content Calendar'!$K$4:$K$403<=$I11)*((($B11="")+('Content Calendar'!$S$4:$S$403=$B11))>0)*((($C11="")+('Content Calendar'!$F$4:$F$403=$C11))>0))) | L11: =IF(OR($J11="",$K11="",N($J11)<=0),"",$K11/$J11)
J12: =IF(OR($H12="",$I12="",$D12="",$I12<$H12),"",ROUND((($I12-$H12)+1)/IF($D12="Daily",1,IF($D12="3x Weekly",7/3,IF($D12="Weekly",7,IF($D12="Fortnightly",14,IF($D12="Monthly",30.44,1000000)))))*IF($E12="",1,$E12),0)) | K12: =IF(OR($A12="",$H12="",$I12="",$I12<$H12),"",SUMPRODUCT(('Content Calendar'!$C$4:$C$403=$A12)*ISNUMBER('Content Calendar'!$K$4:$K$403)*('Content Calendar'!$K$4:$K$403>=$H12)*('Content Calendar'!$K$4:$K$403<=$I12)*((($B12="")+('Content Calendar'!$S$4:$S$403=$B12))>0)*((($C12="")+('Content Calendar'!$F$4:$F$403=$C12))>0))) | L12: =IF(OR($J12="",$K12="",N($J12)<=0),"",$K12/$J12)
J13: =IF(OR($H13="",$I13="",$D13="",$I13<$H13),"",ROUND((($I13-$H13)+1)/IF($D13="Daily",1,IF($D13="3x Weekly",7/3,IF($D13="Weekly",7,IF($D13="Fortnightly",14,IF($D13="Monthly",30.44,1000000)))))*IF($E13="",1,$E13),0)) | K13: =IF(OR($A13="",$H13="",$I13="",$I13<$H13),"",SUMPRODUCT(('Content Calendar'!$C$4:$C$403=$A13)*ISNUMBER('Content Calendar'!$K$4:$K$403)*('Content Calendar'!$K$4:$K$403>=$H13)*('Content Calendar'!$K$4:$K$403<=$I13)*((($B13="")+('Content Calendar'!$S$4:$S$403=$B13))>0)*((($C13="")+('Content Calendar'!$F$4:$F$403=$C13))>0))) | L13: =IF(OR($J13="",$K13="",N($J13)<=0),"",$K13/$J13)
J14: =IF(OR($H14="",$I14="",$D14="",$I14<$H14),"",ROUND((($I14-$H14)+1)/IF($D14="Daily",1,IF($D14="3x Weekly",7/3,IF($D14="Weekly",7,IF($D14="Fortnightly",14,IF($D14="Monthly",30.44,1000000)))))*IF($E14="",1,$E14),0)) | K14: =IF(OR($A14="",$H14="",$I14="",$I14<$H14),"",SUMPRODUCT(('Content Calendar'!$C$4:$C$403=$A14)*ISNUMBER('Content Calendar'!$K$4:$K$403)*('Content Calendar'!$K$4:$K$403>=$H14)*('Content Calendar'!$K$4:$K$403<=$I14)*((($B14="")+('Content Calendar'!$S$4:$S$403=$B14))>0)*((($C14="")+('Content Calendar'!$F$4:$F$403=$C14))>0))) | L14: =IF(OR($J14="",$K14="",N($J14)<=0),"",$K14/$J14)
J15: =IF(OR($H15="",$I15="",$D15="",$I15<$H15),"",ROUND((($I15-$H15)+1)/IF($D15="Daily",1,IF($D15="3x Weekly",7/3,IF($D15="Weekly",7,IF($D15="Fortnightly",14,IF($D15="Monthly",30.44,1000000)))))*IF($E15="",1,$E15),0)) | K15: =IF(OR($A15="",$H15="",$I15="",$I15<$H15),"",SUMPRODUCT(('Content Calendar'!$C$4:$C$403=$A15)*ISNUMBER('Content Calendar'!$K$4:$K$403)*('Content Calendar'!$K$4:$K$403>=$H15)*('Content Calendar'!$K$4:$K$403<=$I15)*((($B15="")+('Content Calendar'!$S$4:$S$403=$B15))>0)*((($C15="")+('Content Calendar'!$F$4:$F$403=$C15))>0))) | L15: =IF(OR($J15="",$K15="",N($J15)<=0),"",$K15/$J15)
... J103: =IF(OR($H103="",$I103="",$D103="",$I103<$H103),"",ROUND((($I103-$H103)+1)/IF($D103="Daily",1,IF($D103="3x Weekly",7/3,IF($D103="Weekly",7,IF($D103="Fortnightly",14,IF($D103="Monthly",30.44,1000000)))))*IF($E103="",1,$E103),0)) | K103: =IF(OR($A103="",$H103="",$I103="",$I103<$H103),"",SUMPRODUCT(('Content Calendar'!$C$4:$C$403=$A103)*ISNUMBER('Content Calendar'!$K$4:$K$403)*('Content Calendar'!$K$4:$K$403>=$H103)*('Content Calendar'!$K$4:$K$403<=$I103)*((($B103="")+('Content Calendar'!$S$4:$S$403=$B103))>0)*((($C103="")+('Content Calendar'!$F$4:$F$403=$C103))>0))) | L103: =IF(OR($J103="",$K103="",N($J103)<=0),"",$K103/$J103)
A104: LAST ROW — anything typed below this line is invisible to every report. Archive a dated copy and start a new file.
A106: WHERE SCHEDULING WORKS — researched Aug 2026, re-verify 6-monthly
A107: Platform | B107: Native scheduler | C107: Window / limits | D107: Schedulable | E107: Not schedulable / third-party route | F107: PCI cadence (same figure as PLATFORM GUIDE)
A108: LinkedIn (Page + personal) | B108: YES — built into the composer, free | C108: 10 min to 3 months ahead | D108: Text, single image, single video, link | E108: No polls, documents/carousels or multi-image; Pages cannot schedule reshares | F108: Page 3 posts/wk; personal daily
A109: Facebook Page | B109: YES — Meta Business Suite Planner | C109: 75 days; 25 posts/day Meta family cap | D109: Posts, Reels, Stories, bulk | E109: Live video | F109: 3-5 quality posts/wk
A110: Instagram | B110: YES — in-app (Business/Creator) + Meta Business Suite | C110: 25/day, 75 days ahead | D110: Feed, carousels, Reels; STORIES via Business Suite only | E110: Stories from the IG app itself; Live | F110: 3-5 feed/wk + Stories near-daily
A111: X (Twitter) | B111: YES — x.com desktop, free tier | C111: Up to 18 months | D111: Single posts (text, image, video, link) | E111: Threads (multi-post) not schedulable natively — use Buffer/Publer; no mobile; no polls | F111: 1-2 posts/day; 1-2 threads/wk
A112: Threads | B112: YES — native since Jan 2025 (three-dot menu) | C112: 75 days | D112: Standard posts (text, image, video) | E112: Replies cannot be scheduled | F112: 1 post/day, mirroring X
A113: TikTok | B113: YES — TikTok Studio, desktop, Business/Creator accounts | C113: 15 min to 10 DAYS only; scheduled posts cannot be edited | D113: Videos | E113: Anything from the mobile app; personal accounts | F113: 1-3 videos/wk
A114: YouTube | B114: YES — Studio scheduled publish + Premieres | C114: About a year ahead | D114: Long-form, Shorts (scheduled individually), Premieres | E114: Batch-scheduling Shorts | F114: 1 long-form/wk + Shorts more often
A115: Pinterest | B115: YES — native Pin scheduler (Business) | C115: 30 days max; 10 pins queued max | D115: Standard image or video Pins, one at a time (Idea Pins were retired in 2023) | E115: Bulk scheduling | F115: Monthly batch — one Pin per published article
A116: Bluesky | B116: NO native scheduler (open feature request) | C116: — | D116: Third-party only: Buffer (approved partner), Fedica — threads schedulable there | E116: Everything natively | F116: Watching brief — mirror 2 posts/wk
A117: Snapchat | B117: PARTIAL — Public Story posts schedulable in-app | C117: Window undocumented | D117: Public Story snaps | E117: Spotlight has no native scheduling (Later via official API) | F117: Regular Story presence on posting days
A118: Telegram Channel | B118: YES — long-press send, then Schedule | C118: 365 days ahead; 100 queued per channel | D118: All message types | E118: Recurring posts (needs bots) | F118: 1 value post/wk, pin the campaign
... A123: Newsletter / ESP | B123: YES — every modern ESP, with send-time optimisation | C123: Effectively unlimited | D123: Campaigns / broadcasts | E123: — | F123: Weekly or fortnightly
A125: RECOMMENDED $0 STACK (researched): Metricool Free — 1 brand, 9 networks free including Threads, Bluesky, Google Business Profile, TikTok, Pinterest and YouTube — plus the NATIVE schedulers for LinkedIn (3 months), X (18 months), Telegram (365 days), Medium and the ESP. LinkedIn and X sit outside Metricool's free tier but have the strongest native schedulers, so the gap costs nothing. Nothing mainstream schedules WhatsApp Channels or ordinary Reddit posts — those stay manual. Flags: the GBP scheduler is newly rolled out (confirm in your own dashboard before relying on it); Metricool's free monthly post cap is reported inconsistently (20 vs 50) — check in-app.

Sheet Community & PR
A1: COMMUNITY, PARTNERSHIPS & PR — Quora, Reddit, groups, associations, universities, employers, media
A2: ◀ MAP | B2: One row per answer, per contact, per pitch. Row 4 is a worked example - your data starts on row 5.
A3: Date | B3: Employee | C3: Platform / channel | D3: Organisation or community | E3: Type | F3: Contact name | G3: Contact role | H3: URL of thread / profile | I3: Why we targeted them | J3: Action taken | K3: Template used | L3: What you said (summary) | M3: Status | N3: Outcome | O3: Follow-up due | P3: Meeting date | Q3: Evidence URL | R3: Next action | S3: Notes | T3: Objective | U3: For (brand)
A404: LAST ROW — anything typed below this line is invisible to every report. Archive a dated copy and start a new file.

Sheet Job Postings
A1: JOB POSTINGS — every open position, on every platform that matters
A2: ◀ MAP | B2: One row per position per platform. Log the day's posting work in DAILY ENTRY as 'Job post published' too, so it counts in activity. Close filled roles the same day — a stale listing reads as an unprofessional institute.
A3: Date posted | B3: Posted by | C3: Position title | D3: Position type | E3: For (brand) | F3: Platform | G3: Country / region | H3: Job post URL | I3: Status | J3: Applicants | K3: Shortlisted | L3: Hired | M3: Notes
A204: LAST ROW — anything typed below this line is invisible to every report. Archive a dated copy and start a new file.

Sheet Link Building
A1: LINK BUILDING — the off-page SEO engine, link by link
A2: ◀ MAP | B2: One row per link prospect, from first contact to live. Referring domains are the currency of off-page SEO — but only earned ones: NEVER buy links, join link farms or swap bulk reciprocals (that is the link spam Google penalises). Tactics and weekly cadence live in GROWTH PLAYBOOK technique 23. Our target URL must be on an estate domain (START HERE §11). Cross-check earned links against Search Console monthly.
A3: Date | B3: Employee | C3: Tactic | D3: Target site / domain | E3: Their page URL | F3: Our target URL | G3: Contact / route | H3: Anchor text (planned) | I3: Status | J3: Link type | K3: Date live | L3: Objective | M3: For (brand) | N3: Notes
A404: LAST ROW — anything typed below this line is invisible to every report. Archive a dated copy and start a new file.

Sheet Experiments
A1: CAMPAIGN EXPERIMENTS — change one thing at a time and measure it
A2: ◀ MAP | B2: Run one experiment per channel at a time. If two things change at once you learn nothing. Rates and a size guard are calculated for you.
A3: ID | B3: Start date | C3: Owner | D3: Channel / platform | E3: What we believe (hypothesis) | F3: Variant A | G3: Variant B | H3: Metric being judged | I3: Sample A | J3: Result A | K3: Rate A | L3: Sample B | M3: Result B | N3: Rate B | O3: Difference | P3: Big enough to act on? | Q3: Status | R3: Decision taken | S3: Rolled into the playbook?
A4: ="EXP-"&TEXT(ROW()-3,"000") -> EXP-001 | K4: =IFERROR(J4/I4,"") | N4: =IFERROR(M4/L4,"") | O4: =IFERROR(N4-K4,"") | P4: =IF(OR($I4="",$L4=""),"",IF(MIN($I4,$L4)<30,"No - fewer than 30 in a group, this is noise",IF(ABS($O4)<0.05,"No - the gap is too small to trust",IF(MIN($I4,$L4)<100,"Maybe - directional only, keep running","Yes - act on it"))))
A5: ="EXP-"&TEXT(ROW()-3,"000") -> EXP-002 | K5: =IFERROR(J5/I5,"") | N5: =IFERROR(M5/L5,"") | O5: =IFERROR(N5-K5,"") | P5: =IF(OR($I5="",$L5=""),"",IF(MIN($I5,$L5)<30,"No - fewer than 30 in a group, this is noise",IF(ABS($O5)<0.05,"No - the gap is too small to trust",IF(MIN($I5,$L5)<100,"Maybe - directional only, keep running","Yes - act on it"))))
A6: =IF($E6="","","EXP-"&TEXT(3,"000")) | K6: =IFERROR(J6/I6,"") | N6: =IFERROR(M6/L6,"") | O6: =IFERROR(N6-K6,"") | P6: =IF(OR($I6="",$L6=""),"",IF(MIN($I6,$L6)<30,"No - fewer than 30 in a group, this is noise",IF(ABS($O6)<0.05,"No - the gap is too small to trust",IF(MIN($I6,$L6)<100,"Maybe - directional only, keep running","Yes - act on it"))))
A7: =IF($E7="","","EXP-"&TEXT(4,"000")) | K7: =IFERROR(J7/I7,"") | N7: =IFERROR(M7/L7,"") | O7: =IFERROR(N7-K7,"") | P7: =IF(OR($I7="",$L7=""),"",IF(MIN($I7,$L7)<30,"No - fewer than 30 in a group, this is noise",IF(ABS($O7)<0.05,"No - the gap is too small to trust",IF(MIN($I7,$L7)<100,"Maybe - directional only, keep running","Yes - act on it"))))
A8: =IF($E8="","","EXP-"&TEXT(5,"000")) | K8: =IFERROR(J8/I8,"") | N8: =IFERROR(M8/L8,"") | O8: =IFERROR(N8-K8,"") | P8: =IF(OR($I8="",$L8=""),"",IF(MIN($I8,$L8)<30,"No - fewer than 30 in a group, this is noise",IF(ABS($O8)<0.05,"No - the gap is too small to trust",IF(MIN($I8,$L8)<100,"Maybe - directional only, keep running","Yes - act on it"))))
A9: =IF($E9="","","EXP-"&TEXT(6,"000")) | K9: =IFERROR(J9/I9,"") | N9: =IFERROR(M9/L9,"") | O9: =IFERROR(N9-K9,"") | P9: =IF(OR($I9="",$L9=""),"",IF(MIN($I9,$L9)<30,"No - fewer than 30 in a group, this is noise",IF(ABS($O9)<0.05,"No - the gap is too small to trust",IF(MIN($I9,$L9)<100,"Maybe - directional only, keep running","Yes - act on it"))))
A10: =IF($E10="","","EXP-"&TEXT(7,"000")) | K10: =IFERROR(J10/I10,"") | N10: =IFERROR(M10/L10,"") | O10: =IFERROR(N10-K10,"") | P10: =IF(OR($I10="",$L10=""),"",IF(MIN($I10,$L10)<30,"No - fewer than 30 in a group, this is noise",IF(ABS($O10)<0.05,"No - the gap is too small to trust",IF(MIN($I10,$L10)<100,"Maybe - directional only, keep running","Yes - act on it"))))
A11: =IF($E11="","","EXP-"&TEXT(8,"000")) | K11: =IFERROR(J11/I11,"") | N11: =IFERROR(M11/L11,"") | O11: =IFERROR(N11-K11,"") | P11: =IF(OR($I11="",$L11=""),"",IF(MIN($I11,$L11)<30,"No - fewer than 30 in a group, this is noise",IF(ABS($O11)<0.05,"No - the gap is too small to trust",IF(MIN($I11,$L11)<100,"Maybe - directional only, keep running","Yes - act on it"))))
A12: =IF($E12="","","EXP-"&TEXT(9,"000")) | K12: =IFERROR(J12/I12,"") | N12: =IFERROR(M12/L12,"") | O12: =IFERROR(N12-K12,"") | P12: =IF(OR($I12="",$L12=""),"",IF(MIN($I12,$L12)<30,"No - fewer than 30 in a group, this is noise",IF(ABS($O12)<0.05,"No - the gap is too small to trust",IF(MIN($I12,$L12)<100,"Maybe - directional only, keep running","Yes - act on it"))))
A13: =IF($E13="","","EXP-"&TEXT(10,"000")) | K13: =IFERROR(J13/I13,"") | N13: =IFERROR(M13/L13,"") | O13: =IFERROR(N13-K13,"") | P13: =IF(OR($I13="",$L13=""),"",IF(MIN($I13,$L13)<30,"No - fewer than 30 in a group, this is noise",IF(ABS($O13)<0.05,"No - the gap is too small to trust",IF(MIN($I13,$L13)<100,"Maybe - directional only, keep running","Yes - act on it"))))
A14: =IF($E14="","","EXP-"&TEXT(11,"000")) | K14: =IFERROR(J14/I14,"") | N14: =IFERROR(M14/L14,"") | O14: =IFERROR(N14-K14,"") | P14: =IF(OR($I14="",$L14=""),"",IF(MIN($I14,$L14)<30,"No - fewer than 30 in a group, this is noise",IF(ABS($O14)<0.05,"No - the gap is too small to trust",IF(MIN($I14,$L14)<100,"Maybe - directional only, keep running","Yes - act on it"))))
A15: =IF($E15="","","EXP-"&TEXT(12,"000")) | K15: =IFERROR(J15/I15,"") | N15: =IFERROR(M15/L15,"") | O15: =IFERROR(N15-K15,"") | P15: =IF(OR($I15="",$L15=""),"",IF(MIN($I15,$L15)<30,"No - fewer than 30 in a group, this is noise",IF(ABS($O15)<0.05,"No - the gap is too small to trust",IF(MIN($I15,$L15)<100,"Maybe - directional only, keep running","Yes - act on it"))))
A16: =IF($E16="","","EXP-"&TEXT(13,"000")) | K16: =IFERROR(J16/I16,"") | N16: =IFERROR(M16/L16,"") | O16: =IFERROR(N16-K16,"") | P16: =IF(OR($I16="",$L16=""),"",IF(MIN($I16,$L16)<30,"No - fewer than 30 in a group, this is noise",IF(ABS($O16)<0.05,"No - the gap is too small to trust",IF(MIN($I16,$L16)<100,"Maybe - directional only, keep running","Yes - act on it"))))
A17: =IF($E17="","","EXP-"&TEXT(14,"000")) | K17: =IFERROR(J17/I17,"") | N17: =IFERROR(M17/L17,"") | O17: =IFERROR(N17-K17,"") | P17: =IF(OR($I17="",$L17=""),"",IF(MIN($I17,$L17)<30,"No - fewer than 30 in a group, this is noise",IF(ABS($O17)<0.05,"No - the gap is too small to trust",IF(MIN($I17,$L17)<100,"Maybe - directional only, keep running","Yes - act on it"))))
A18: =IF($E18="","","EXP-"&TEXT(15,"000")) | K18: =IFERROR(J18/I18,"") | N18: =IFERROR(M18/L18,"") | O18: =IFERROR(N18-K18,"") | P18: =IF(OR($I18="",$L18=""),"",IF(MIN($I18,$L18)<30,"No - fewer than 30 in a group, this is noise",IF(ABS($O18)<0.05,"No - the gap is too small to trust",IF(MIN($I18,$L18)<100,"Maybe - directional only, keep running","Yes - act on it"))))
A19: =IF($E19="","","EXP-"&TEXT(16,"000")) | K19: =IFERROR(J19/I19,"") | N19: =IFERROR(M19/L19,"") | O19: =IFERROR(N19-K19,"") | P19: =IF(OR($I19="",$L19=""),"",IF(MIN($I19,$L19)<30,"No - fewer than 30 in a group, this is noise",IF(ABS($O19)<0.05,"No - the gap is too small to trust",IF(MIN($I19,$L19)<100,"Maybe - directional only, keep running","Yes - act on it"))))
A20: =IF($E20="","","EXP-"&TEXT(17,"000")) | K20: =IFERROR(J20/I20,"") | N20: =IFERROR(M20/L20,"") | O20: =IFERROR(N20-K20,"") | P20: =IF(OR($I20="",$L20=""),"",IF(MIN($I20,$L20)<30,"No - fewer than 30 in a group, this is noise",IF(ABS($O20)<0.05,"No - the gap is too small to trust",IF(MIN($I20,$L20)<100,"Maybe - directional only, keep running","Yes - act on it"))))
A21: =IF($E21="","","EXP-"&TEXT(18,"000")) | K21: =IFERROR(J21/I21,"") | N21: =IFERROR(M21/L21,"") | O21: =IFERROR(N21-K21,"") | P21: =IF(OR($I21="",$L21=""),"",IF(MIN($I21,$L21)<30,"No - fewer than 30 in a group, this is noise",IF(ABS($O21)<0.05,"No - the gap is too small to trust",IF(MIN($I21,$L21)<100,"Maybe - directional only, keep running","Yes - act on it"))))
A22: =IF($E22="","","EXP-"&TEXT(19,"000")) | K22: =IFERROR(J22/I22,"") | N22: =IFERROR(M22/L22,"") | O22: =IFERROR(N22-K22,"") | P22: =IF(OR($I22="",$L22=""),"",IF(MIN($I22,$L22)<30,"No - fewer than 30 in a group, this is noise",IF(ABS($O22)<0.05,"No - the gap is too small to trust",IF(MIN($I22,$L22)<100,"Maybe - directional only, keep running","Yes - act on it"))))
A23: =IF($E23="","","EXP-"&TEXT(20,"000")) | K23: =IFERROR(J23/I23,"") | N23: =IFERROR(M23/L23,"") | O23: =IFERROR(N23-K23,"") | P23: =IF(OR($I23="",$L23=""),"",IF(MIN($I23,$L23)<30,"No - fewer than 30 in a group, this is noise",IF(ABS($O23)<0.05,"No - the gap is too small to trust",IF(MIN($I23,$L23)<100,"Maybe - directional only, keep running","Yes - act on it"))))
A24: =IF($E24="","","EXP-"&TEXT(21,"000")) | K24: =IFERROR(J24/I24,"") | N24: =IFERROR(M24/L24,"") | O24: =IFERROR(N24-K24,"") | P24: =IF(OR($I24="",$L24=""),"",IF(MIN($I24,$L24)<30,"No - fewer than 30 in a group, this is noise",IF(ABS($O24)<0.05,"No - the gap is too small to trust",IF(MIN($I24,$L24)<100,"Maybe - directional only, keep running","Yes - act on it"))))
A25: =IF($E25="","","EXP-"&TEXT(22,"000")) | K25: =IFERROR(J25/I25,"") | N25: =IFERROR(M25/L25,"") | O25: =IFERROR(N25-K25,"") | P25: =IF(OR($I25="",$L25=""),"",IF(MIN($I25,$L25)<30,"No - fewer than 30 in a group, this is noise",IF(ABS($O25)<0.05,"No - the gap is too small to trust",IF(MIN($I25,$L25)<100,"Maybe - directional only, keep running","Yes - act on it"))))
A26: =IF($E26="","","EXP-"&TEXT(23,"000")) | K26: =IFERROR(J26/I26,"") | N26: =IFERROR(M26/L26,"") | O26: =IFERROR(N26-K26,"") | P26: =IF(OR($I26="",$L26=""),"",IF(MIN($I26,$L26)<30,"No - fewer than 30 in a group, this is noise",IF(ABS($O26)<0.05,"No - the gap is too small to trust",IF(MIN($I26,$L26)<100,"Maybe - directional only, keep running","Yes - act on it"))))
A27: =IF($E27="","","EXP-"&TEXT(24,"000")) | K27: =IFERROR(J27/I27,"") | N27: =IFERROR(M27/L27,"") | O27: =IFERROR(N27-K27,"") | P27: =IF(OR($I27="",$L27=""),"",IF(MIN($I27,$L27)<30,"No - fewer than 30 in a group, this is noise",IF(ABS($O27)<0.05,"No - the gap is too small to trust",IF(MIN($I27,$L27)<100,"Maybe - directional only, keep running","Yes - act on it"))))
A28: =IF($E28="","","EXP-"&TEXT(25,"000")) | K28: =IFERROR(J28/I28,"") | N28: =IFERROR(M28/L28,"") | O28: =IFERROR(N28-K28,"") | P28: =IF(OR($I28="",$L28=""),"",IF(MIN($I28,$L28)<30,"No - fewer than 30 in a group, this is noise",IF(ABS($O28)<0.05,"No - the gap is too small to trust",IF(MIN($I28,$L28)<100,"Maybe - directional only, keep running","Yes - act on it"))))
A29: =IF($E29="","","EXP-"&TEXT(26,"000")) | K29: =IFERROR(J29/I29,"") | N29: =IFERROR(M29/L29,"") | O29: =IFERROR(N29-K29,"") | P29: =IF(OR($I29="",$L29=""),"",IF(MIN($I29,$L29)<30,"No - fewer than 30 in a group, this is noise",IF(ABS($O29)<0.05,"No - the gap is too small to trust",IF(MIN($I29,$L29)<100,"Maybe - directional only, keep running","Yes - act on it"))))
A30: =IF($E30="","","EXP-"&TEXT(27,"000")) | K30: =IFERROR(J30/I30,"") | N30: =IFERROR(M30/L30,"") | O30: =IFERROR(N30-K30,"") | P30: =IF(OR($I30="",$L30=""),"",IF(MIN($I30,$L30)<30,"No - fewer than 30 in a group, this is noise",IF(ABS($O30)<0.05,"No - the gap is too small to trust",IF(MIN($I30,$L30)<100,"Maybe - directional only, keep running","Yes - act on it"))))
A31: =IF($E31="","","EXP-"&TEXT(28,"000")) | K31: =IFERROR(J31/I31,"") | N31: =IFERROR(M31/L31,"") | O31: =IFERROR(N31-K31,"") | P31: =IF(OR($I31="",$L31=""),"",IF(MIN($I31,$L31)<30,"No - fewer than 30 in a group, this is noise",IF(ABS($O31)<0.05,"No - the gap is too small to trust",IF(MIN($I31,$L31)<100,"Maybe - directional only, keep running","Yes - act on it"))))
A32: =IF($E32="","","EXP-"&TEXT(29,"000")) | K32: =IFERROR(J32/I32,"") | N32: =IFERROR(M32/L32,"") | O32: =IFERROR(N32-K32,"") | P32: =IF(OR($I32="",$L32=""),"",IF(MIN($I32,$L32)<30,"No - fewer than 30 in a group, this is noise",IF(ABS($O32)<0.05,"No - the gap is too small to trust",IF(MIN($I32,$L32)<100,"Maybe - directional only, keep running","Yes - act on it"))))
A33: =IF($E33="","","EXP-"&TEXT(30,"000")) | K33: =IFERROR(J33/I33,"") | N33: =IFERROR(M33/L33,"") | O33: =IFERROR(N33-K33,"") | P33: =IF(OR($I33="",$L33=""),"",IF(MIN($I33,$L33)<30,"No - fewer than 30 in a group, this is noise",IF(ABS($O33)<0.05,"No - the gap is too small to trust",IF(MIN($I33,$L33)<100,"Maybe - directional only, keep running","Yes - act on it"))))
A34: =IF($E34="","","EXP-"&TEXT(31,"000")) | K34: =IFERROR(J34/I34,"") | N34: =IFERROR(M34/L34,"") | O34: =IFERROR(N34-K34,"") | P34: =IF(OR($I34="",$L34=""),"",IF(MIN($I34,$L34)<30,"No - fewer than 30 in a group, this is noise",IF(ABS($O34)<0.05,"No - the gap is too small to trust",IF(MIN($I34,$L34)<100,"Maybe - directional only, keep running","Yes - act on it"))))
A35: =IF($E35="","","EXP-"&TEXT(32,"000")) | K35: =IFERROR(J35/I35,"") | N35: =IFERROR(M35/L35,"") | O35: =IFERROR(N35-K35,"") | P35: =IF(OR($I35="",$L35=""),"",IF(MIN($I35,$L35)<30,"No - fewer than 30 in a group, this is noise",IF(ABS($O35)<0.05,"No - the gap is too small to trust",IF(MIN($I35,$L35)<100,"Maybe - directional only, keep running","Yes - act on it"))))
A36: =IF($E36="","","EXP-"&TEXT(33,"000")) | K36: =IFERROR(J36/I36,"") | N36: =IFERROR(M36/L36,"") | O36: =IFERROR(N36-K36,"") | P36: =IF(OR($I36="",$L36=""),"",IF(MIN($I36,$L36)<30,"No - fewer than 30 in a group, this is noise",IF(ABS($O36)<0.05,"No - the gap is too small to trust",IF(MIN($I36,$L36)<100,"Maybe - directional only, keep running","Yes - act on it"))))
A37: =IF($E37="","","EXP-"&TEXT(34,"000")) | K37: =IFERROR(J37/I37,"") | N37: =IFERROR(M37/L37,"") | O37: =IFERROR(N37-K37,"") | P37: =IF(OR($I37="",$L37=""),"",IF(MIN($I37,$L37)<30,"No - fewer than 30 in a group, this is noise",IF(ABS($O37)<0.05,"No - the gap is too small to trust",IF(MIN($I37,$L37)<100,"Maybe - directional only, keep running","Yes - act on it"))))
A38: =IF($E38="","","EXP-"&TEXT(35,"000")) | K38: =IFERROR(J38/I38,"") | N38: =IFERROR(M38/L38,"") | O38: =IFERROR(N38-K38,"") | P38: =IF(OR($I38="",$L38=""),"",IF(MIN($I38,$L38)<30,"No - fewer than 30 in a group, this is noise",IF(ABS($O38)<0.05,"No - the gap is too small to trust",IF(MIN($I38,$L38)<100,"Maybe - directional only, keep running","Yes - act on it"))))
A39: =IF($E39="","","EXP-"&TEXT(36,"000")) | K39: =IFERROR(J39/I39,"") | N39: =IFERROR(M39/L39,"") | O39: =IFERROR(N39-K39,"") | P39: =IF(OR($I39="",$L39=""),"",IF(MIN($I39,$L39)<30,"No - fewer than 30 in a group, this is noise",IF(ABS($O39)<0.05,"No - the gap is too small to trust",IF(MIN($I39,$L39)<100,"Maybe - directional only, keep running","Yes - act on it"))))
A40: =IF($E40="","","EXP-"&TEXT(37,"000")) | K40: =IFERROR(J40/I40,"") | N40: =IFERROR(M40/L40,"") | O40: =IFERROR(N40-K40,"") | P40: =IF(OR($I40="",$L40=""),"",IF(MIN($I40,$L40)<30,"No - fewer than 30 in a group, this is noise",IF(ABS($O40)<0.05,"No - the gap is too small to trust",IF(MIN($I40,$L40)<100,"Maybe - directional only, keep running","Yes - act on it"))))
A41: =IF($E41="","","EXP-"&TEXT(38,"000")) | K41: =IFERROR(J41/I41,"") | N41: =IFERROR(M41/L41,"") | O41: =IFERROR(N41-K41,"") | P41: =IF(OR($I41="",$L41=""),"",IF(MIN($I41,$L41)<30,"No - fewer than 30 in a group, this is noise",IF(ABS($O41)<0.05,"No - the gap is too small to trust",IF(MIN($I41,$L41)<100,"Maybe - directional only, keep running","Yes - act on it"))))
A42: =IF($E42="","","EXP-"&TEXT(39,"000")) | K42: =IFERROR(J42/I42,"") | N42: =IFERROR(M42/L42,"") | O42: =IFERROR(N42-K42,"") | P42: =IF(OR($I42="",$L42=""),"",IF(MIN($I42,$L42)<30,"No - fewer than 30 in a group, this is noise",IF(ABS($O42)<0.05,"No - the gap is too small to trust",IF(MIN($I42,$L42)<100,"Maybe - directional only, keep running","Yes - act on it"))))
A43: =IF($E43="","","EXP-"&TEXT(40,"000")) | K43: =IFERROR(J43/I43,"") | N43: =IFERROR(M43/L43,"") | O43: =IFERROR(N43-K43,"") | P43: =IF(OR($I43="",$L43=""),"",IF(MIN($I43,$L43)<30,"No - fewer than 30 in a group, this is noise",IF(ABS($O43)<0.05,"No - the gap is too small to trust",IF(MIN($I43,$L43)<100,"Maybe - directional only, keep running","Yes - act on it"))))
A44: =IF($E44="","","EXP-"&TEXT(41,"000")) | K44: =IFERROR(J44/I44,"") | N44: =IFERROR(M44/L44,"") | O44: =IFERROR(N44-K44,"") | P44: =IF(OR($I44="",$L44=""),"",IF(MIN($I44,$L44)<30,"No - fewer than 30 in a group, this is noise",IF(ABS($O44)<0.05,"No - the gap is too small to trust",IF(MIN($I44,$L44)<100,"Maybe - directional only, keep running","Yes - act on it"))))
A45: =IF($E45="","","EXP-"&TEXT(42,"000")) | K45: =IFERROR(J45/I45,"") | N45: =IFERROR(M45/L45,"") | O45: =IFERROR(N45-K45,"") | P45: =IF(OR($I45="",$L45=""),"",IF(MIN($I45,$L45)<30,"No - fewer than 30 in a group, this is noise",IF(ABS($O45)<0.05,"No - the gap is too small to trust",IF(MIN($I45,$L45)<100,"Maybe - directional only, keep running","Yes - act on it"))))
A46: =IF($E46="","","EXP-"&TEXT(43,"000")) | K46: =IFERROR(J46/I46,"") | N46: =IFERROR(M46/L46,"") | O46: =IFERROR(N46-K46,"") | P46: =IF(OR($I46="",$L46=""),"",IF(MIN($I46,$L46)<30,"No - fewer than 30 in a group, this is noise",IF(ABS($O46)<0.05,"No - the gap is too small to trust",IF(MIN($I46,$L46)<100,"Maybe - directional only, keep running","Yes - act on it"))))
A47: =IF($E47="","","EXP-"&TEXT(44,"000")) | K47: =IFERROR(J47/I47,"") | N47: =IFERROR(M47/L47,"") | O47: =IFERROR(N47-K47,"") | P47: =IF(OR($I47="",$L47=""),"",IF(MIN($I47,$L47)<30,"No - fewer than 30 in a group, this is noise",IF(ABS($O47)<0.05,"No - the gap is too small to trust",IF(MIN($I47,$L47)<100,"Maybe - directional only, keep running","Yes - act on it"))))
A48: =IF($E48="","","EXP-"&TEXT(45,"000")) | K48: =IFERROR(J48/I48,"") | N48: =IFERROR(M48/L48,"") | O48: =IFERROR(N48-K48,"") | P48: =IF(OR($I48="",$L48=""),"",IF(MIN($I48,$L48)<30,"No - fewer than 30 in a group, this is noise",IF(ABS($O48)<0.05,"No - the gap is too small to trust",IF(MIN($I48,$L48)<100,"Maybe - directional only, keep running","Yes - act on it"))))
A49: =IF($E49="","","EXP-"&TEXT(46,"000")) | K49: =IFERROR(J49/I49,"") | N49: =IFERROR(M49/L49,"") | O49: =IFERROR(N49-K49,"") | P49: =IF(OR($I49="",$L49=""),"",IF(MIN($I49,$L49)<30,"No - fewer than 30 in a group, this is noise",IF(ABS($O49)<0.05,"No - the gap is too small to trust",IF(MIN($I49,$L49)<100,"Maybe - directional only, keep running","Yes - act on it"))))
A50: =IF($E50="","","EXP-"&TEXT(47,"000")) | K50: =IFERROR(J50/I50,"") | N50: =IFERROR(M50/L50,"") | O50: =IFERROR(N50-K50,"") | P50: =IF(OR($I50="",$L50=""),"",IF(MIN($I50,$L50)<30,"No - fewer than 30 in a group, this is noise",IF(ABS($O50)<0.05,"No - the gap is too small to trust",IF(MIN($I50,$L50)<100,"Maybe - directional only, keep running","Yes - act on it"))))
A51: =IF($E51="","","EXP-"&TEXT(48,"000")) | K51: =IFERROR(J51/I51,"") | N51: =IFERROR(M51/L51,"") | O51: =IFERROR(N51-K51,"") | P51: =IF(OR($I51="",$L51=""),"",IF(MIN($I51,$L51)<30,"No - fewer than 30 in a group, this is noise",IF(ABS($O51)<0.05,"No - the gap is too small to trust",IF(MIN($I51,$L51)<100,"Maybe - directional only, keep running","Yes - act on it"))))
A52: =IF($E52="","","EXP-"&TEXT(49,"000")) | K52: =IFERROR(J52/I52,"") | N52: =IFERROR(M52/L52,"") | O52: =IFERROR(N52-K52,"") | P52: =IF(OR($I52="",$L52=""),"",IF(MIN($I52,$L52)<30,"No - fewer than 30 in a group, this is noise",IF(ABS($O52)<0.05,"No - the gap is too small to trust",IF(MIN($I52,$L52)<100,"Maybe - directional only, keep running","Yes - act on it"))))
A53: =IF($E53="","","EXP-"&TEXT(50,"000")) | K53: =IFERROR(J53/I53,"") | N53: =IFERROR(M53/L53,"") | O53: =IFERROR(N53-K53,"") | P53: =IF(OR($I53="",$L53=""),"",IF(MIN($I53,$L53)<30,"No - fewer than 30 in a group, this is noise",IF(ABS($O53)<0.05,"No - the gap is too small to trust",IF(MIN($I53,$L53)<100,"Maybe - directional only, keep running","Yes - act on it"))))
A55: READ THIS BEFORE ACTING ON A RESULT. The 'big enough to act on' column is a rough guard, not a statistical test: it requires at least 30 in each group and a gap of at least 5 percentage points before it will say yes, and it calls anything under 100 per group directional only. Most marketing A/B tests are called far too early on far too little data, which is how teams end up confidently adopting a change that did nothing.

Sheet UTM Builder
A1: UTM BUILDER — so you can prove which platform actually produced enquiries
A2: ◀ MAP | B2: Fill in the yellow columns and copy the tracked link from column F. Any link posted without one of these is untraceable, and the work behind it cannot be credited to anyone.
A3: Landing page URL | B3: Source | C3: Medium | D3: Campaign | E3: Content | F3: Tracked link (copy this) | G3: Used where | H3: Date
F4: =IF(OR($A4="",$B4="",$C4=""),"",$A4&IF(ISNUMBER(FIND("?",$A4)),"&","?")&"utm_source="&LOWER(SUBSTITUTE(TRIM($B4)," ","-"))&"&utm_medium="&LOWER(SUBSTITUTE(TRIM($C4)," ","-"))&IF($D4="","","&utm_campaign="&LOWER(SUBSTITUTE(TRIM($D4)," ","-")))&IF($E4="","","&utm_content="&LOWER(SUBSTITUTE(TRIM($E4)," ","-"))))
F5: =IF(OR($A5="",$B5="",$C5=""),"",$A5&IF(ISNUMBER(FIND("?",$A5)),"&","?")&"utm_source="&LOWER(SUBSTITUTE(TRIM($B5)," ","-"))&"&utm_medium="&LOWER(SUBSTITUTE(TRIM($C5)," ","-"))&IF($D5="","","&utm_campaign="&LOWER(SUBSTITUTE(TRIM($D5)," ","-")))&IF($E5="","","&utm_content="&LOWER(SUBSTITUTE(TRIM($E5)," ","-"))))
F6: =IF(OR($A6="",$B6="",$C6=""),"",$A6&IF(ISNUMBER(FIND("?",$A6)),"&","?")&"utm_source="&LOWER(SUBSTITUTE(TRIM($B6)," ","-"))&"&utm_medium="&LOWER(SUBSTITUTE(TRIM($C6)," ","-"))&IF($D6="","","&utm_campaign="&LOWER(SUBSTITUTE(TRIM($D6)," ","-")))&IF($E6="","","&utm_content="&LOWER(SUBSTITUTE(TRIM($E6)," ","-"))))
F7: =IF(OR($A7="",$B7="",$C7=""),"",$A7&IF(ISNUMBER(FIND("?",$A7)),"&","?")&"utm_source="&LOWER(SUBSTITUTE(TRIM($B7)," ","-"))&"&utm_medium="&LOWER(SUBSTITUTE(TRIM($C7)," ","-"))&IF($D7="","","&utm_campaign="&LOWER(SUBSTITUTE(TRIM($D7)," ","-")))&IF($E7="","","&utm_content="&LOWER(SUBSTITUTE(TRIM($E7)," ","-"))))
F8: =IF(OR($A8="",$B8="",$C8=""),"",$A8&IF(ISNUMBER(FIND("?",$A8)),"&","?")&"utm_source="&LOWER(SUBSTITUTE(TRIM($B8)," ","-"))&"&utm_medium="&LOWER(SUBSTITUTE(TRIM($C8)," ","-"))&IF($D8="","","&utm_campaign="&LOWER(SUBSTITUTE(TRIM($D8)," ","-")))&IF($E8="","","&utm_content="&LOWER(SUBSTITUTE(TRIM($E8)," ","-"))))
F9: =IF(OR($A9="",$B9="",$C9=""),"",$A9&IF(ISNUMBER(FIND("?",$A9)),"&","?")&"utm_source="&LOWER(SUBSTITUTE(TRIM($B9)," ","-"))&"&utm_medium="&LOWER(SUBSTITUTE(TRIM($C9)," ","-"))&IF($D9="","","&utm_campaign="&LOWER(SUBSTITUTE(TRIM($D9)," ","-")))&IF($E9="","","&utm_content="&LOWER(SUBSTITUTE(TRIM($E9)," ","-"))))
F10: =IF(OR($A10="",$B10="",$C10=""),"",$A10&IF(ISNUMBER(FIND("?",$A10)),"&","?")&"utm_source="&LOWER(SUBSTITUTE(TRIM($B10)," ","-"))&"&utm_medium="&LOWER(SUBSTITUTE(TRIM($C10)," ","-"))&IF($D10="","","&utm_campaign="&LOWER(SUBSTITUTE(TRIM($D10)," ","-")))&IF($E10="","","&utm_content="&LOWER(SUBSTITUTE(TRIM($E10)," ","-"))))
F11: =IF(OR($A11="",$B11="",$C11=""),"",$A11&IF(ISNUMBER(FIND("?",$A11)),"&","?")&"utm_source="&LOWER(SUBSTITUTE(TRIM($B11)," ","-"))&"&utm_medium="&LOWER(SUBSTITUTE(TRIM($C11)," ","-"))&IF($D11="","","&utm_campaign="&LOWER(SUBSTITUTE(TRIM($D11)," ","-")))&IF($E11="","","&utm_content="&LOWER(SUBSTITUTE(TRIM($E11)," ","-"))))
F12: =IF(OR($A12="",$B12="",$C12=""),"",$A12&IF(ISNUMBER(FIND("?",$A12)),"&","?")&"utm_source="&LOWER(SUBSTITUTE(TRIM($B12)," ","-"))&"&utm_medium="&LOWER(SUBSTITUTE(TRIM($C12)," ","-"))&IF($D12="","","&utm_campaign="&LOWER(SUBSTITUTE(TRIM($D12)," ","-")))&IF($E12="","","&utm_content="&LOWER(SUBSTITUTE(TRIM($E12)," ","-"))))
F13: =IF(OR($A13="",$B13="",$C13=""),"",$A13&IF(ISNUMBER(FIND("?",$A13)),"&","?")&"utm_source="&LOWER(SUBSTITUTE(TRIM($B13)," ","-"))&"&utm_medium="&LOWER(SUBSTITUTE(TRIM($C13)," ","-"))&IF($D13="","","&utm_campaign="&LOWER(SUBSTITUTE(TRIM($D13)," ","-")))&IF($E13="","","&utm_content="&LOWER(SUBSTITUTE(TRIM($E13)," ","-"))))
F14: =IF(OR($A14="",$B14="",$C14=""),"",$A14&IF(ISNUMBER(FIND("?",$A14)),"&","?")&"utm_source="&LOWER(SUBSTITUTE(TRIM($B14)," ","-"))&"&utm_medium="&LOWER(SUBSTITUTE(TRIM($C14)," ","-"))&IF($D14="","","&utm_campaign="&LOWER(SUBSTITUTE(TRIM($D14)," ","-")))&IF($E14="","","&utm_content="&LOWER(SUBSTITUTE(TRIM($E14)," ","-"))))
F15: =IF(OR($A15="",$B15="",$C15=""),"",$A15&IF(ISNUMBER(FIND("?",$A15)),"&","?")&"utm_source="&LOWER(SUBSTITUTE(TRIM($B15)," ","-"))&"&utm_medium="&LOWER(SUBSTITUTE(TRIM($C15)," ","-"))&IF($D15="","","&utm_campaign="&LOWER(SUBSTITUTE(TRIM($D15)," ","-")))&IF($E15="","","&utm_content="&LOWER(SUBSTITUTE(TRIM($E15)," ","-"))))
... F103: =IF(OR($A103="",$B103="",$C103=""),"",$A103&IF(ISNUMBER(FIND("?",$A103)),"&","?")&"utm_source="&LOWER(SUBSTITUTE(TRIM($B103)," ","-"))&"&utm_medium="&LOWER(SUBSTITUTE(TRIM($C103)," ","-"))&IF($D103="","","&utm_campaign="&LOWER(SUBSTITUTE(TRIM($D103)," ","-")))&IF($E103="","","&utm_content="&LOWER(SUBSTITUTE(TRIM($E103)," ","-"))))
A105: NAMING CONVENTION - agree it once and never deviate, because Google Analytics treats LinkedIn, linkedin and Linkedin as three different sources. source = the platform (linkedin, medium, quora, youtube). medium = the type (social, email, referral, organic). campaign = purpose and month (honorary-aug26). content = which specific asset or message. Everything is forced to lower case by the formula.

Sheet SEO Clusters
A1: SEO CONTENT CLUSTERS — build authority on a topic, not a pile of unrelated posts
A2: ◀ MAP | B2: One pillar page per subject, with supporting articles that all link back to it. Fill in the search-console columns monthly.
A3: Cluster (pillar topic) | B3: Pillar page URL | C3: Supporting article | D3: Target search phrase | E3: What the searcher wants | F3: Article Bank ID (the brief) | G3: Status | H3: Published URL | I3: Links to pillar? | J3: Republished to | K3: Canonical set? | L3: Impressions (GSC) | M3: Clicks (GSC) | N3: Position | O3: Notes
A4: Project controls fundamentals | C4: What is project controls and what does a project controls engineer do | F4: AB-00077 | G4: Idea
A5: Planning and scheduling | C5: How to build a realistic project schedule in Primavera P6 | F5: AB-00078 | G5: Idea
A6: Cost control and estimating | C6: Cost control methods that catch overruns early | F6: AB-00079 | G6: Idea
A7: Earned value management | C7: Earned value management explained with a worked example | F7: AB-00080 | G7: Idea
A8: Risk management | C8: Quantitative schedule risk analysis for beginners | F8: AB-00081 | G8: Idea
A9: AI in project controls | C9: How AI is changing forecasting in project controls | F9: AB-00082 | G9: Idea
A10: Certification and careers | C10: Project controls certification routes compared | F10: AB-00083 | G10: Idea
A12: Pillar names here, on Keyword Plan column O and in Article Bank column C are the SAME seven — filter any of the three by the same word. Column F is the brief for the supporting article: find that ID on Article Bank, claim it with your name, and the prompt is ready to use.

Sheet Keyword Plan
A1: KEYWORD PLAN — where the SEO effort wins (researched Aug 2026)
A2: ◀ MAP | B2: 76 keywords, difficulty graded from live SERP sampling (sampled rows marked ✓): EASY = thin/forum/programmatic pages rank — attack now. MEDIUM = mid-authority mix — winnable with a genuinely better page. HARD = PMI / AACE / RICS / big-vendor territory — pillar pages only, patience. Volume bands are honest editorial estimates, not tool metrics. CRITICAL: projectcontrolsinstitute.com (a competitor training provider) owns PCI's exact name in Google today — the brand-defense row is attack keyword #1. Re-verify quarterly in Search Console; re-check the P1 SERPs monthly.
A3: Keyword | B3: Cluster | C3: Intent | D3: Funnel | E3: Volume band | F3: Difficulty | G3: Who ranks today (Aug 2026) | H3: Asset to build | I3: Priority | J3: SERP ✓ | K3: Owner | L3: Status | M3: Published URL | N3: Notes | O3: Pillar (same 7 as SEO Clusters) | P3: Article Bank ID (the brief)
A4: project controls institute | B4: Brand | C4: Navigational | D4: BOFU | E4: Medium | F4: Hard | G4: projectcontrolsinstitute.com (the .com competitor) owns this SERP today | H4: Homepage + About + Organization schema — brand defense | I4: P1 | J4: ✓ | O4: Certification and careers | P4: AB-00001
A5: PCL-AI certification | B5: Brand | C5: Navigational | D5: BOFU | E5: Low | F5: Easy | G5: Nobody — undefined SERP | H5: Landing page (define the product SERP before others do) | I5: P2 | O5: Certification and careers | P5: AB-00002
A6: Certuvo | B6: Brand | C6: Navigational | D6: BOFU | E6: Low | F6: Easy | G6: Nobody — undefined SERP | H6: Certuvo homepage + cross-links | I6: P2 | O6: Certification and careers | P6: AB-00003
A7: project controls certification | B7: Core | C7: Commercial | D7: MOFU | E7: High | F7: Hard | G7: APMG, Project Control Academy, EVMi (CPCP), projectcontrolsinstitute.com, SmartPM | H7: Pillar page (certification hub) | I7: P2 | J7: ✓ | O7: Certification and careers | P7: AB-00004
A8: project controls training | B8: Core | C8: Commercial | D8: MOFU | E8: High | F8: Hard | G8: Project Control Academy, Plan Academy, GLOMACS, projectcontrolsinstitute.com | H8: Pillar page (training hub) | I8: P2 | J8: ✓ | O8: Certification and careers | P8: AB-00005
A9: project controls course | B9: Core | C9: Commercial | D9: MOFU | E9: Medium | F9: Hard | G9: Same set as 'training' (PCA, Plan Academy, Class Central) | H9: Fold into training pillar | I9: P3 | O9: Certification and careers | P9: AB-00006
A10: project controls certification online | B10: Core | C10: Transactional | D10: BOFU | E10: Medium | F10: Medium | G10: Class Central, APMG, PCA, EVMi, projectcontrolsinstitute.com | H10: Landing page (online delivery USP) | I10: P2 | J10: ✓ | O10: Certification and careers | P10: AB-00007
A11: project controls course online | B11: Core | C11: Transactional | D11: BOFU | E11: Medium | F11: Medium | G11: Class Central, PCA, Plan Academy | H11: Same landing page | I11: P2 | O11: Certification and careers | P11: AB-00008
A12: certified project controls professional | B12: Core | C12: Commercial | D12: BOFU | E12: Medium | F12: Medium | G12: EVMi (CPCP trademark), PCA, AACE | H12: Landing page (PCL-AI positioned against CPCP) | I12: P2 | O12: Certification and careers | P12: AB-00009
A13: project controls certification cost | B13: Core | C13: Commercial | D13: BOFU | E13: Low | F13: Easy | G13: ccpstudy.com, AACE, scattered blogs | H13: FAQ block + pricing table on cert pages | I13: P2 | O13: Certification and careers | P13: AB-00010
A14: project controls qualifications | B14: Core | C14: Commercial | D14: MOFU | E14: Low | F14: Medium | G14: ECITB, APM, Zippia, University of Cumbria | H14: Spoke article (UK-flavoured) | I14: P2 | O14: Certification and careers | P14: AB-00011
A15: planning engineer certification | B15: Role | C15: Commercial | D15: BOFU | E15: Medium | F15: Medium | G15: O*NET, GAFM, apeng.org, gipmc.org, planningengineer.net — weak low-authority SERP | H15: Landing page (PCL-AI for planning engineers) | I15: P1 | J15: ✓ | O15: Certification and careers | P15: AB-00012
A16: certified planning engineer | B16: Role | C16: Commercial | D16: BOFU | E16: Medium | F16: Medium | G16: GAFM, APEng, GIPMC, International Certification Centre | H16: Same landing page + FAQ block | I16: P2 | O16: Certification and careers | P16: AB-00013
A17: how to become a planning engineer | B17: Role | C17: Informational | D17: TOFU | E17: Medium | F17: Medium | G17: Indeed, Zippia, ZipRecruiter, planningengineer.net | H17: Spoke article (career guide, cert CTA) | I17: P2 | J17: ✓ | O17: Certification and careers | P17: AB-00014
A18: senior planning engineer career path | B18: Role | C18: Informational | D18: TOFU | E18: Medium | F18: Medium | G18: Job boards, Zippia | H18: Spoke article (progression ladder to PML-AI) | I18: P3 | O18: Certification and careers | P18: AB-00015
A19: planning engineer salary | B19: Role | C19: Informational | D19: TOFU | E19: High | F19: Hard | G19: Glassdoor, Indeed, PayScale, GulfTalent | H19: Spoke / salary-by-region tool | I19: P3 | O19: Certification and careers | P19: AB-00016
A20: cost controller certification | B20: Role | C20: Commercial | D20: BOFU | E20: Medium | F20: Easy | G20: ResumeCat, LinkedIn Pulse, Intl Certification Centre, AAIFM, PCA — thin SERP | H20: Landing page (cost-controller track) | I20: P1 | J20: ✓ | O20: Certification and careers | P20: AB-00017
A21: cost engineer certification | B21: Role | C21: Commercial | D21: BOFU | E21: Medium | F21: Medium | G21: AACE (CCP/CCT), universeestimating.com, IMF Academy | H21: Landing page + AACE comparison link | I21: P2 | O21: Certification and careers | P21: AB-00018
A22: project scheduler certification | B22: Role | C22: Commercial | D22: BOFU | E22: Medium | F22: Medium | G22: PMI (PMI-SP), AACE (PSP), Project Management Academy | H22: Landing page (scheduler track) | I22: P2 | O22: Certification and careers | P22: AB-00019
A23: AACE PSP certification guide | B23: Conquest | C23: Commercial | D23: MOFU | E23: Medium | F23: Medium | G23: AACE, planningengineer.net, projectcontrolsinstitute.com | H23: Spoke guide (conquest, PCL-AI alternative) | I23: P2 | O23: Certification and careers | P23: AB-00020
A24: quantity surveyor certification | B24: Role | C24: Commercial | D24: MOFU | E24: Medium | F24: Hard | G24: RICS, Novatr, Class Central, Alison | H24: Spoke ('QS to project controls' angle) | I24: P3 | O24: Certification and careers | P24: AB-00021
A25: quantity surveyor certification online | B25: Role | C25: Commercial | D25: MOFU | E25: Medium | F25: Medium | G25: Novatr, Coursesity, Alison, quantitysurveyingcoach.com | H25: Spoke + cert CTA | I25: P3 | J25: ✓ | O25: Certification and careers | P25: AB-00022
A26: PMO certification | B26: Role | C26: Commercial | D26: MOFU | E26: High | F26: Hard | G26: PMI (PMI-PMOCP), GSDC, The Digital PM, PMO Global Institute | H26: Spoke article (PMO leads angle) | I26: P3 | J26: ✓ | O26: Certification and careers | P26: AB-00023
A27: what does a project controls engineer do | B27: Role | C27: Informational | D27: TOFU | E27: Medium | F27: Medium | G27: Zippia, Indeed, research.com | H27: Spoke article | I27: P3 | O27: Certification and careers | P27: AB-00024
A28: how to become a project controls manager | B28: Role | C28: Informational | D28: TOFU | E28: Low | F28: Easy | G28: Thin — no dedicated authority page found | H28: Spoke article (to PML-AI) | I28: P2 | O28: Certification and careers | P28: AB-00025
A29: project controls salary | B29: Role | C29: Informational | D29: TOFU | E29: Medium | F29: Medium | G29: Zippia, Glassdoor, Ladders | H29: Spoke / salary tool | I29: P3 | O29: Certification and careers | P29: AB-00026
